Workbook

Sheet 표지
B3: 14일이면 확실하게 끝낸다
B5: =SUM(목차!F6:F187)&"제" -> 1648제
B7: 공공조달관리사 2주 완성
B9: =" 실전 문제 "&SUM(목차!F6:F187)&"개로 꿰뚫는 공공조달 실무." -> 실전 문제 1648개로 꿰뚫는 공공조달 실무.
B10: 엑셀 하나로 끝내는, 무한회독 트레이닝.
B13: ▶ 지금 바로 풀어보기

Sheet 목차
A2: 공공조달관리사 필기 출제기준 (2026.03.01~2028.12.31 적용)
A3: 검정방법: 객관식 / 문제수: 80 / 시험시간: 2시간 | 과목: ① 공공조달과 법제도 이해(30) ② 공공조달계획 수립 및 분석(20) ③ 공공계약관리(30)
A5: 필기과목 | B5: 주요항목 | C5: 세부항목 | D5: 세세항목 | E5: 시트명 | F5: 생성 문제 수
A6: 1. 공공조달과 법제도 이해 | B6: 1. 공공조달 개요 | C6: 1. 공공조달의 정의 및 목적 | D6: 1. 공공조달의 정의 | E6: 1-1_공공조달개요 | F6: =COUNTIF('1-1_공공조달개요'!A:L,목차!D6) -> 16 | L6: 1-1_공공조달개요
D7: 2. 공공조달의 목적 | F7: =COUNTIF('1-1_공공조달개요'!A:L,목차!D7) -> 17 | L7: 1-2_원칙및방법
D8: 3. 공공조달의 범위 | F8: =COUNTIF('1-1_공공조달개요'!A:L,목차!D8) -> 11 | L8: 1-3_전자조달시스템
C9: 2. 공공조달 참여자, 이해관계자 | D9: 1. 공공조달 수요자 | F9: =COUNTIF('1-1_공공조달개요'!A:L,목차!D9) -> 5 | L9: 1-4_전략적공공조달
D10: 2. 공공조달 공급자 | F10: =COUNTIF('1-1_공공조달개요'!A:L,목차!D10) -> 5 | L10: 1-5_공공조달법률이해
D11: 3. 공공조달 이해관계자 | F11: =COUNTIF('1-1_공공조달개요'!A:L,목차!D11) -> 12 | L11: 1-6_공정조달관리
C12: 3. 공공조달의 특성 | D12: 1. 상업적 구매행위 특성 | F12: =COUNTIF('1-1_공공조달개요'!A:L,목차!D12) -> 7 | L12: 2-1_공공조달계획
D13: 2. 공공조달의 조달행위 특성 | F13: =COUNTIF('1-1_공공조달개요'!A:L,목차!D13) -> 23 | L13: 2-2_조달요구응대및제안
C14: 4. 공공조달의 구성체계 | D14: 1. 조직적 구성체계 | F14: =COUNTIF('1-1_공공조달개요'!A:L,목차!D14) -> 13 | L14: 2-3_입찰제안평가및계약체결
D15: 2. 감독 및 기능적 책임 | F15: =COUNTIF('1-1_공공조달개요'!A:L,목차!D15) -> 10 | L15: 3-1_계약관리일반절차
B16: 2. 공공조달 원칙 및 방법 | C16: 1. 공공조달 원칙 | D16: 1. 공공조달 기본 원칙 | E16: 1-2_원칙및방법 | F16: =COUNTIF('1-2_원칙및방법'!A:L,목차!D16) -> 26 | L16: 3-2_물품계약관리
D17: 2. 공공조달 실행 원칙 | F17: =COUNTIF('1-2_원칙및방법'!A:L,목차!D17) -> 6 | L17: 3-3_용역다수공급자계약관리
C18: 2. 공공조달 유형 | D18: 1. 중앙집중형 공공조달 | F18: =COUNTIF('1-2_원칙및방법'!A:L,목차!D18) -> 12 | L18: 3-4_공사계약관리
D19: 2. 분산형 공공조달 | F19: =COUNTIF('1-2_원칙및방법'!A:L,목차!D19) -> 6 | L19: Temp
C20: 3. 경쟁적 공공조달 방법 | D20: 1. 일반경쟁 | F20: =COUNTIF('1-2_원칙및방법'!A:L,목차!D20) -> 20
D21: 2. 제한경쟁 | F21: =COUNTIF('1-2_원칙및방법'!A:L,목차!D21) -> 9
D22: 3. 지명경쟁 | F22: =COUNTIF('1-2_원칙및방법'!A:L,목차!D22) -> 6
C23: 4. 비경쟁적 공공조달 방법 | D23: 1. 수의계약 | F23: =COUNTIF('1-2_원칙및방법'!A:L,목차!D23) -> 27
D24: 2. 소액구매 | F24: =COUNTIF('1-2_원칙및방법'!A:L,목차!D24) -> 9
B25: 3. 전자조달시스템 | C25: 1. 전자조달시스템 개요 | D25: 1. 전자조달시스템 개념 | E25: 1-3_전자조달시스템 | F25: =COUNTIF('1-3_전자조달시스템'!A:L,목차!D25) -> 7
D26: 2. 전자조달시스템 유형 | F26: =COUNTIF('1-3_전자조달시스템'!A:L,목차!D26) -> 3
D27: 3. 전자조달시스템 운영환경 | F27: =COUNTIF('1-3_전자조달시스템'!A:L,목차!D27) -> 5
D28: 4. 전자조달시스템 구성요소 | F28: =COUNTIF('1-3_전자조달시스템'!A:L,목차!D28) -> 3
D29: 5. 전자조달시스템 기능 | F29: =COUNTIF('1-3_전자조달시스템'!A:L,목차!D29) -> 6
D30: 6. 전자조달시스템 도입 성과 | F30: =COUNTIF('1-3_전자조달시스템'!A:L,목차!D30) -> 7
C31: 2. 국가종합전자조달시스템(나라장터) 연계 계약 관리 지원시스템 개요 | D31: 1. 종합쇼핑몰 이용절차 | F31: =COUNTIF('1-3_전자조달시스템'!A:L,목차!D31) -> 16
D32: 2. 혁신장터 활용 계약 | F32: =COUNTIF('1-3_전자조달시스템'!A:L,목차!D32) -> 3
D33: 3. 벤처나라 활용 계약 | F33: =COUNTIF('1-3_전자조달시스템'!A:L,목차!D33) -> 8
D34: 4. 디지털서비스몰 활용 계약 | F34: =COUNTIF('1-3_전자조달시스템'!A:L,목차!D34) -> 1
D35: 5. 이음장터 활용 계약 | F35: =COUNTIF('1-3_전자조달시스템'!A:L,목차!D35) -> 2
C36: 3. 목록정보시스템 개요 | D36: 1. 물품목록법령의 개요 | F36: =COUNTIF('1-3_전자조달시스템'!A:L,목차!D36) -> 7
D37: 2. 목록정보시스템 이용 일반절차 | F37: =COUNTIF('1-3_전자조달시스템'!A:L,목차!D37) -> 7
D38: 3. 목록정보시스템 활용 목록화 절차 | F38: =COUNTIF('1-3_전자조달시스템'!A:L,목차!D38) -> 4
D39: 4. 목록정보시스템 활용 분류·품명·품목 관리 절차 | F39: =COUNTIF('1-3_전자조달시스템'!A:L,목차!D39) -> 9
D40: 5. 목록정보시스템 활용 최신화 및 분류 정비 | F40: =COUNTIF('1-3_전자조달시스템'!A:L,목차!D40) -> 2
D41: 6. 목록정보시스템 활용 분류체계 국제 표준화 | F41: =COUNTIF('1-3_전자조달시스템'!A:L,목차!D41) -> 1
B42: 4. 전략적 공공조달 | C42: 1. 중소기업지원 조달 | D42: 1. 중소기업과 공공구매제도 이해 | E42: 1-4_전략적공공조달 | F42: =COUNTIF('1-4_전략적공공조달'!A:L,목차!D42) -> 8
D43: 2. 중소기업자간 경쟁제도 이해 | F43: =COUNTIF('1-4_전략적공공조달'!A:L,목차!D43) -> 9
D44: 3. 공사용자재 직접구매제도 이해 | F44: =COUNTIF('1-4_전략적공공조달'!A:L,목차!D44) -> 4
C45: 2. 녹색조달 | D45: 1. 공공조달의 환경적 지속가능성 개요 | F45: =COUNTIF('1-4_전략적공공조달'!A:L,목차!D45) -> 7
D46: 2. 녹색제품 우선구매제도 이해 | F46: =COUNTIF('1-4_전략적공공조달'!A:L,목차!D46) -> 10
D47: 3. 생애주기비용을 고려한 공공조달 제도 이해 | F47: =COUNTIF('1-4_전략적공공조달'!A:L,목차!D47) -> 5
C48: 3. 혁신·기술개발 촉진조달 | D48: 1. 중소기업 기술개발제품 우선구매제도 이해 | F48: =COUNTIF('1-4_전략적공공조달'!A:L,목차!D48) -> 6
D49: 2. 우수조달물품 지정제도의 이해 | F49: =COUNTIF('1-4_전략적공공조달'!A:L,목차!D49) -> 5
D50: 3. 혁신제품 지정제도의 이해 | F50: =COUNTIF('1-4_전략적공공조달'!A:L,목차!D50) -> 17
C51: 4. 사회적가치 지원 조달 | D51: 1. 장애인기업 우선구매제도 이해 | F51: =COUNTIF('1-4_전략적공공조달'!A:L,목차!D51) -> 2
D52: 2. 중증장애인생산품 우선구매제도 이해 | F52: =COUNTIF('1-4_전략적공공조달'!A:L,목차!D52) -> 4
D53: 3. 여성기업 우선구매제도 이해 | F53: =COUNTIF('1-4_전략적공공조달'!A:L,목차!D53) -> 4
D54: 4. 사회적기업제품 우선구매제도 이해 | F54: =COUNTIF('1-4_전략적공공조달'!A:L,목차!D54) -> 4
D55: 5. 공공조달과 사회적가치 및 이에스지(ESG) | F55: =COUNTIF('1-4_전략적공공조달'!A:L,목차!D55) -> 14
B56: 5. 공공조달법률 이해 | C56: 1. 공공계약 관련 민법 규정의 이해 | D56: 1. 계약의 성립 관련 규정 | E56: 1-5_공공조달법률이해 | F56: =COUNTIF('1-5_공공조달법률이해'!A:L,목차!D56) -> 10
D57: 2. 계약의 효력 관련 규정 | F57: =COUNTIF('1-5_공공조달법률이해'!A:L,목차!D57) -> 5
D58: 3. 계약의 해제·해지에 관한 규정 | F58: =COUNTIF('1-5_공공조달법률이해'!A:L,목차!D58) -> 3
D59: 4. 도급·위임에 관한 규정 | F59: =COUNTIF('1-5_공공조달법률이해'!A:L,목차!D59) -> 2
D60: 5. 화해에 관한 규정 | F60: =COUNTIF('1-5_공공조달법률이해'!A:L,목차!D60) -> 4
C61: 2. 공공계약(국가 및 지방) 법령의 이해 | D61: 1. 추정가격 및 예정가격 결정 | F61: =COUNTIF('1-5_공공조달법률이해'!A:L,목차!D61) -> 26
D62: 2. 계약의 방법에 관한 규정 | F62: =COUNTIF('1-5_공공조달법률이해'!A:L,목차!D62) -> 16
D63: 3. 입찰 및 낙찰 절차 규정 | F63: =COUNTIF('1-5_공공조달법률이해'!A:L,목차!D63) -> 4
D64: 4. 계약의 체결 및 이행 규정 | F64: =COUNTIF('1-5_공공조달법률이해'!A:L,목차!D64) -> 9
D65: 5. 이의신청과 분쟁조정 | F65: =COUNTIF('1-5_공공조달법률이해'!A:L,목차!D65) -> 3
C66: 3. 조달사업법령의 이해 | D66: 1. 공공조달의 정책기반 | F66: =COUNTIF('1-5_공공조달법률이해'!A:L,목차!D66) -> 7
D67: 2. 계약체결의 요청 및 방법 | F67: =COUNTIF('1-5_공공조달법률이해'!A:L,목차!D67) -> 6
D68: 3. 대금지급 규정 | F68: =COUNTIF('1-5_공공조달법률이해'!A:L,목차!D68) -> 5
D69: 4. 조달사업의 공정성 | F69: =COUNTIF('1-5_공공조달법률이해'!A:L,목차!D69) -> 6
D70: 5. 수요기관 및 조달사업의 지원 | F70: =COUNTIF('1-5_공공조달법률이해'!A:L,목차!D70) -> 5
C71: 4. 전자조달법령의 이해 | D71: 1. 전자적 공고의 방법 및 시기 | F71: =COUNTIF('1-5_공공조달법률이해'!A:L,목차!D71) -> 9
D72: 2. 전자적 형태의 입찰서 제출 | F72: =COUNTIF('1-5_공공조달법률이해'!A:L,목차!D72) -> 5
D73: 3. 전자공개수의계약 | F73: =COUNTIF('1-5_공공조달법률이해'!A:L,목차!D73) -> 5
D74: 4. 하도급 관리의 전자적 처리 | F74: =COUNTIF('1-5_공공조달법률이해'!A:L,목차!D74) -> 5
D75: 5. 전자조달시스템 이용·활용 제한 | F75: =COUNTIF('1-5_공공조달법률이해'!A:L,목차!D75) -> 3
C76: 5. 공기업·준정부기관 계약사무규칙 | D76: 1. 국제입찰 대상 공공조달계약 범위 | F76: =COUNTIF('1-5_공공조달법률이해'!A:L,목차!D76) -> 9
D77: 2. 중소기업자간 경쟁제품 구매위탁 의무 예외 | F77: =COUNTIF('1-5_공공조달법률이해'!A:L,목차!D77) -> 4
D78: 3. 수의계약 규정 | F78: =COUNTIF('1-5_공공조달법률이해'!A:L,목차!D78) -> 3
D79: 4. 의견 청취 및 심의절차 | F79: =COUNTIF('1-5_공공조달법률이해'!A:L,목차!D79) -> 2
D80: 5. 이의신청 규정 | F80: =COUNTIF('1-5_공공조달법률이해'!A:L,목차!D80) -> 1
B81: 6. 공정조달 관리 | C81: 1. 공공조달 법규 분쟁 및 해석 | D81: 1. 공공조달 분쟁조정 | E81: 1-6_공정조달관리 | F81: =COUNTIF('1-6_공정조달관리'!A:L,목차!D81) -> 16
D82: 2. 유권해석 및 감사사례 | F82: =COUNTIF('1-6_공정조달관리'!A:L,목차!D82) -> 6
D83: 3. 계약보증금 쟁점 | F83: =COUNTIF('1-6_공정조달관리'!A:L,목차!D83) -> 4
D84: 4. 부정당제재 처분 법리 | F84: =COUNTIF('1-6_공정조달관리'!A:L,목차!D84) -> 4
D85: 5. 허위서류 관련 쟁점 | F85: =COUNTIF('1-6_공정조달관리'!A:L,목차!D85) -> 3
C86: 2. 법규 위반시 제재 | D86: 1. 계약의 해제 및 해지 | F86: =COUNTIF('1-6_공정조달관리'!A:L,목차!D86) -> 5
D87: 2. 부정당업자 제재 | F87: =COUNTIF('1-6_공정조달관리'!A:L,목차!D87) -> 15
D88: 3. 불공정조달행위 제재 | F88: =COUNTIF('1-6_공정조달관리'!A:L,목차!D88) -> 7
D89: 4. 부당이득금 환수 | F89: =COUNTIF('1-6_공정조달관리'!A:L,목차!D89) -> 4
A90: 2. 공공조달계획 수립 및 분석 | B90: 1. 공공조달계획 | C90: 1. 공공조달 수요 분석 및 계획 | D90: 1. 공급 대상물 수요정보 식별 | E90: 2-1_공공조달계획 | F90: =COUNTIF('2-1_공공조달계획'!A:L,목차!D90) -> 7
D91: 2. 수요정보 평가와 요구사항 분석 | F91: =COUNTIF('2-1_공공조달계획'!A:L,목차!D91) -> 2
D92: 3. 공급계획 및 일정 수립 | F92: =COUNTIF('2-1_공공조달계획'!A:L,목차!D92) -> 6
D93: 4. 비상 공급계획 수립 | F93: =COUNTIF('2-1_공공조달계획'!A:L,목차!D93) -> 1
C94: 2. 공공조달 적정성 분석 | D94: 1. 공급방법 적정성 분석 | F94: =COUNTIF('2-1_공공조달계획'!A:L,목차!D94) -> 13
D95: 2. 공급정보 적정성 분석 | F95: =COUNTIF('2-1_공공조달계획'!A:L,목차!D95) -> 2
D96: 3. 공급 대상물 조달시장 분석 | F96: =COUNTIF('2-1_공공조달계획'!A:L,목차!D96) -> 8
D97: 4. 공급역량분석 | F97: =COUNTIF('2-1_공공조달계획'!A:L,목차!D97) -> 1
C98: 3. 공공조달 비용 적정성 분석 | D98: 1. 공급 의사결정을 위한 비용분석 | F98: =COUNTIF('2-1_공공조달계획'!A:L,목차!D98) -> 6
D99: 2. 적정 공급비용 산정 | F99: =COUNTIF('2-1_공공조달계획'!A:L,목차!D99) -> 15
C100: 4. 기타 적정성 분석 | D100: 1. 공공조달 동향 모니터링을 통한 수요예측 | F100: =COUNTIF('2-1_공공조달계획'!A:L,목차!D100) -> 3
D101: 2. 다양한 공급방법의 장단점 분석 | F101: =COUNTIF('2-1_공공조달계획'!A:L,목차!D101) -> 2
D102: 3. 공급관리 및 위험분석 | F102: =COUNTIF('2-1_공공조달계획'!A:L,목차!D102) -> 12
...

Sheet 1-6_공정조달관리
A2: 공공조달과 법제도 이해 - 6. 공정조달 관리
A3: 번호 | B3: 세부항목 | C3: 세세항목 | D3: 문제 내용 | E3: 보기① | F3: 보기② | G3: 보기③ | H3: 보기④ | I3: 정답 번호 | J3: 해설 및 오답노트 | K3: 출처 | L3: 구분
A4: 1 | B4: 1. 공공조달 법규 분쟁 및 해석 | C4: 1. 공공조달 분쟁조정 | D4: 공공조달 계약 분쟁에서 국가계약분쟁조정위원회의 조정을 거쳐 당사자가 조정안을 수락했을 때 발생하는 법적 효력은? | E4: 법원의 별도 확인 없이는 효력이 없다 | F4: 재판상 화해와 동일한 효력을 갖는다 | G4: 단순한 민사상 합의에 불과하다 | H4: 행정청 내부 참고자료로만 활용된다 | I4: 2 | J4: * 정답 (②): 조정안을 당사자가 수락하면 재판상 화해와 동일한 효력을 가져, 소송 없이도 확정판결과 같은 효력이 부여됨. | K4: 국가계약법 제29조
A5: 2 | B5: 1. 공공조달 법규 분쟁 및 해석 | C5: 1. 공공조달 분쟁조정 | D5: [상황] A사는 낙찰자 결정에 불만이 있어 국가계약분쟁조정위원회에 조정을 신청하려 한다. 이 위원회에 조정을 신청할 수 있는 사안으로 가장 적절한 것은? | E5: 타 회사 간의 순수한 상거래 채권 분쟁 | F5: 계약과 무관한 친족 간 재산 상속 분쟁 | G5: 국가계약법의 적용을 받는 계약 과정에서 발생한 입찰·낙찰 관련 분쟁 | H5: 직원 개인의 이직 관련 근로계약 분쟁 | I5: 3 | J5: * 정답 (③): 국가계약분쟁조정위원회는 국가계약법 적용을 받는 계약 과정에서 발생한 분쟁(낙찰자결정, 계약금액조정, 제재처분 이의 등)을 조정 대상으로 하며, 계약과 무관한 사적 분쟁은 대상이 아님. | K5: 국가계약법 제28조·제29조
A6: 3 | B6: 1. 공공조달 법규 분쟁 및 해석 | C6: 2. 유권해석 및 감사사례 | D6: 국가계약법과 조달사업법 각각에 대한 유권해석 소관을 비교한 설명으로 가장 옳은 것은? | E6: 국가계약법은 소관 부처인 재정경제부가, 조달사업법은 소관 부처인 조달청이 각각 유권해석을 담당한다 | F6: 두 법 모두 조달청이 유권해석 권한을 가진다 | G6: 유권해석 권한은 법원에만 있고 행정부처에는 없다 | H6: 두 법 모두 감사원이 유권해석 권한을 가진다 | I6: 1 | J6: * 정답 (①): 각 법령의 유권해석은 해당 법령의 소관 부처가 담당하는 것이 원칙이며, 국가계약법은 재정경제부, 조달사업법은 조달청이 소관 부처임.
A7: 4 | B7: 1. 공공조달 법규 분쟁 및 해석 | C7: 2. 유권해석 및 감사사례 | D7: [상황] 한 공공기관의 계약 업무 처리 과정에서 법규 위반 소지가 있다는 민원이 제기되어, 헌법기관인 감사기구가 직권으로 조사에 착수했다. 이 조사를 담당하는 기관으로 가장 적절한 것은? | E7: 국무조정실 | F7: 국회 예산정책처 | G7: 감사원 | H7: 공정거래위원회 | I7: 3 | J7: * 정답 (③): 헌법기관인 감사원은 국가 및 법률이 정한 단체의 회계검사와 행정기관·공무원의 직무감찰을 담당하며, 계약업무의 위법·부당 여부를 조사해 시정을 요구할 수 있음.
A8: 5 | B8: 1. 공공조달 법규 분쟁 및 해석 | C8: 3. 계약보증금 쟁점 | D8: [상황] 계약상대자의 귀책사유로 계약이 해제되었다. 이때 뒤따르는 계약보증금 관련 조치로 가장 적절한 것은? | E8: 납부된 계약보증금이 국고에 귀속될 수 있다 | F8: 납부된 계약보증금이 즉시 반환된다 | G8: 계약보증금은 자동으로 하자보수보증금으로 전환된다 | H8: 계약보증금 관련 규정은 적용되지 않는다 | I8: 1 | J8: * 정답 (①): 계약상대자의 귀책사유로 계약이 해제·해지되면, 계약이행 담보를 위해 납부한 계약보증금은 국고에 귀속될 수 있음. | K8: 국가계약법 시행령 제52조
A9: 6 | B9: 1. 공공조달 법규 분쟁 및 해석 | C9: 3. 계약보증금 쟁점 | D9: 계약보증금과 관련한 쟁점 중, 계약이 정상적으로 이행 완료된 경우의 처리로 가장 적절한 것은? | E9: 국고에 귀속되는 것이 원칙이다 | F9: 계약상대자에게 반환되는 것이 원칙이다 | G9: 발주기관이 임의로 사용할 수 있다 | H9: 차기 계약의 입찰보증금으로 자동 전환된다 | I9: 2 | J9: * 정답 (②): 계약이 정상적으로 이행·완료되면 담보 목적이 소멸하므로 계약보증금은 계약상대자에게 반환되는 것이 원칙임. | K9: 국가계약법 시행령 제52조
A10: 7 | B10: 1. 공공조달 법규 분쟁 및 해석 | C10: 4. 부정당제재 처분 법리 | D10: [상황] 계약담당공무원이 특정 업체에 대해 법령상 상한에 가까운 최장 기간의 부정당업자 제재를 부과하면서, 그 업체에게 사전에 의견을 제출할 기회를 전혀 주지 않았다. 이 처분에 대한 법원의 판단으로 가장 타당한 것은? | E10: 처분청의 재량이므로 법원은 심사할 수 없어 그대로 유효하다 | F10: 의견 제출 기회는 법적으로 요구되지 않으므로 문제되지 않는다 | G10: 절차적 정당성이 결여되었거나 재량권 일탈·남용이 인정되면 위법하다고 판단해 취소될 수 있다 | H10: 제재 기간의 장단과 무관하게 항상 적법하다 | I10: 3 | J10: * 정답 (③): 부정당업자 제재는 국민의 권리를 제한하는 행정처분이므로, 의견 제출 기회 등 절차적 정당성이 결여되거나 재량권 일탈·남용이 인정되면 법원이 위법하다고 판단해 취소할 수 있음.
A11: 8 | B11: 1. 공공조달 법규 분쟁 및 해석 | C11: 4. 부정당제재 처분 법리 | D11: 부정당업자 제재 처분의 요건·절차에 대한 법원의 심사 태도로 가장 적절한 것은? | E11: 제재 사유의 존부만 확인하고 절차는 심사하지 않는다 | F11: 처분청의 판단을 그대로 존중해 사실상 심사하지 않는다 | G11: 제재의 정도는 심사 대상에서 완전히 제외한다 | H11: 요건 해당 여부, 절차적 정당성, 제재 정도의 적정성을 종합적으로 심사한다 | I11: 4 | J11: * 정답 (④): 법원은 부정당업자 제재가 권리를 제한하는 행정처분이므로 요건·절차·비례원칙 등을 종합적으로 심사함.
A12: 9 | B12: 1. 공공조달 법규 분쟁 및 해석 | C12: 5. 허위서류 관련 쟁점 | D12: [상황] 낙찰자로 결정된 업체가 제출한 실적증명서가 허위로 작성된 사실이 계약체결 이후에 확인되었다. 이 경우 발주기관이 취할 수 있는 조치로 가장 적절한 것은? | E12: 형사처벌만 가능하고 계약상 조치는 불가능하다 | F12: 계약의 해제·해지, 손해배상 청구, 부정당업자 제재 등의 조치를 검토할 수 있다 | G12: 허위서류 여부와 무관하게 계약을 그대로 유지해야 한다 | H12: 이미 계약이 체결되었으므로 아무 조치도 할 수 없다 | I12: 2 | J12: * 정답 (②): 허위서류로 낙찰·계약체결한 사실이 확인되면 계약의 해제·해지, 손해배상 청구, 부정당업자 제재 등이 함께 검토될 수 있음. | K12: 국가계약법 시행령 제75조·제76조 등 관련 규정
A13: 10 | B13: 1. 공공조달 법규 분쟁 및 해석 | C13: 5. 허위서류 관련 쟁점 | D13: 입찰참가자격 서류나 실적증명서 등을 허위로 작성해 제출하는 행위가 공공조달 계약질서에 미치는 영향으로 가장 적절한 것은? | E13: 행정절차를 단순화하는 긍정적 효과가 있다 | F13: 허위서류라도 결과만 좋으면 문제되지 않는다 | G13: 다른 입찰참가자에게 아무런 영향을 주지 않는다 | H13: 공정한 경쟁을 저해하고 계약이행능력 심사의 신뢰성을 훼손한다 | I13: 4 | J13: * 정답 (④): 허위서류 제출은 계약이행능력 심사의 전제 자체를 왜곡해 공정한 경쟁을 저해하므로 엄격히 다뤄짐.
A14: 11 | B14: 2. 법규 위반시 제재 | C14: 1. 계약의 해제 및 해지 | D14: 계약상대자의 귀책사유로 계약이 해제되는 경우와 발주기관 사정으로 계약이 해지되는 경우를 비교한 설명으로 가장 적절한 것은? | E14: 귀책사유와 무관하게 처리 결과는 동일하다 | F14: 전자는 부정당업자 제재 등 불이익 조치가 뒤따를 수 있으나, 후자는 계약상대자에게 불이익이 가지 않는 방향으로 처리된다 | G14: 두 경우 모두 계약상대자에게 동일한 불이익이 발생한다 | H14: 발주기관 사정으로 인한 해지 시에도 항상 부정당업자로 제재된다 | I14: 2 | J14: * 정답 (②): 계약상대자 귀책사유로 인한 해제는 보증금 국고귀속·부정당업자 제재 등 불이익이 따르지만, 발주기관 사정으로 인한 해지는 계약상대자에게 불이익이 가지 않도록 처리되는 것이 원칙임. | K14: 국가계약법 시행령 제75조·제76조
A15: 12 | B15: 2. 법규 위반시 제재 | C15: 1. 계약의 해제 및 해지 | D15: 계약 해제·해지 시 이미 이행된 부분에 대한 처리로 가장 적절한 것은? | E15: 이미 이행된 부분에 대해서는 정산해 대가를 지급하는 것이 원칙이다 | F15: 이미 이행된 부분도 전부 무효로 처리한다 | G15: 발주기관이 임의로 지급 여부를 정한다 | H15: 귀책사유와 무관하게 대가를 전혀 지급하지 않는다 | I15: 1 | J15: * 정답 (①): 계약이 해제·해지되더라도 이미 이행된 부분에 대해서는 정산 절차를 거쳐 대가를 지급하는 것이 원칙임.
A16: 13 | B16: 2. 법규 위반시 제재 | C16: 2. 부정당업자 제재 | D16: [상황] B사는 X기관과의 계약에서 부정당업자로 제재를 받았다. 이후 B사가 Y기관이 발주하는 별도의 입찰에 참가하려 할 때의 효력으로 가장 적절한 것은? | E16: 제재 효력은 같은 지역의 기관에만 미친다 | F16: X기관 발주 입찰에서만 제한되고 Y기관 입찰 참가에는 영향이 없다 | G16: 국가계약법 적용을 받는 공공기관이라면 Y기관의 입찰 참가도 제한될 수 있다 | H16: 제재 효력은 발주기관이 명시적으로 통보한 기관에만 미친다 | I16: 3 | J16: * 정답 (③): 부정당업자 제재는 특정 발주기관에 한정되지 않고, 국가계약법의 적용을 받는 모든 공공기관의 입찰 참가를 제한하는 효력을 가짐. | K16: 국가계약법 제27조
A17: 14 | B17: 2. 법규 위반시 제재 | C17: 2. 부정당업자 제재 | D17: 다음 조치 중 성격이 나머지 셋과 가장 다른 하나는? | E17: 불공정 조달행위에 대해 과징금을 부과하는 것 | F17: 계약 위반에 따른 손해를 배상받기 위해 민사소송을 제기하는 것 | G17: 계약보증금을 국고에 귀속시키는 것 | H17: 부정당업자로 지정해 향후 입찰참가자격을 제한하는 것 | I17: 2 | J17: * 정답 (②): 손해배상을 구하는 민사소송은 계약당사자 간 채무불이행에 대한 사법적 구제절차이고, 나머지는 조달질서 유지를 위해 행정적으로 부과되는 제재의 성격을 가짐.
A18: 15 | B18: 2. 법규 위반시 제재 | C18: 3. 불공정조달행위 제재 | D18: [상황] 계약담당공무원 C는 다음 네 가지 행위 중 하나만 실제로 계약관리 업무에서 정당하게 허용되는 행위임을 알고 있다. 허용되는 행위로 가장 적절한 것은? | E18: 특정 업체만 충족 가능하도록 규격을 좁게 설정하는 행위 | F18: 법령을 위반해 특정인에게만 입찰참가자격을 부여하는 행위 | G18: 조달사업의 공정성을 해치는 것으로 대통령령이 정하는 그 밖의 행위를 하는 행위 | H18: 계약조건에 명시된 기준에 따라 이행지체에 대한 지체상금을 부과하는 행위 | I18: 4 | J18: * 정답 (④): 계약조건에 따른 지체상금 부과는 정당한 계약관리 행위이며, 나머지는 조달사업법상 금지되는 불공정 조달행위의 예시에 해당함. | K18: 조달사업에 관한 법률 제22조
A19: 16 | B19: 2. 법규 위반시 제재 | C19: 3. 불공정조달행위 제재 | D19: 불공정 조달행위 신고에 따른 조달청장의 조사 결과, 위반 사실이 확인된 경우 취할 수 있는 조치로 가장 거리가 먼 것은? | E19: 관계 기관에 관련 공무원의 징계를 요구하는 것 | F19: 수사기관에 고발하거나 수사를 의뢰하는 것 | G19: 위반 사실에 대한 시정조치를 명하는 것 | H19: 조달청장이 직접 재판을 진행해 형을 선고하는 것 | I19: 4 | J19: * 정답 (④): 조달청장은 시정조치 명령, 징계 요구, 필요시 수사기관에 고발·수사의뢰는 할 수 있으나, 재판을 직접 진행해 형을 선고하는 사법권은 없음.
A20: 17 | B20: 2. 법규 위반시 제재 | C20: 3. 불공정조달행위 제재 | D20: [상황] D사가 다른 업체와 담합해 입찰에 참여한 사실이 적발되었다. D사가 받게 될 결과로 가장 거리가 먼 것은? | E20: 그 공로를 인정받아 우수조달물품으로 신규 지정된다 | F20: 공정거래위원회로부터 과징금을 부과받을 수 있다 | G20: 부정당업자로 지정되어 입찰참가자격이 제한된다 | H20: 관련 임직원이 형사처벌을 받을 수 있다 | I20: 1 | J20: * 정답 (①): 담합은 불법행위로 각종 제재의 대상이 될 뿐, 오히려 이를 이유로 우수조달물품으로 신규 지정되는 일은 있을 수 없으며 기존 지정도 취소·제한될 수 있음.
A21: 18 | B21: 2. 법규 위반시 제재 | C21: 4. 부당이득금 환수 | D21: [상황] 계약상대자가 관계 법령을 위반해 부당한 방법으로 계약금액을 초과 지급받은 사실이 확인되었다. 이 경우 발주기관이 취할 수 있는 조치로 가장 적절한 것은? | E21: 부당이득에 해당하는 금액을 환수하는 절차를 진행할 수 있다 | F21: 계약상대자의 향후 실적으로만 반영한다 | G21: 초과 지급된 금액을 그대로 인정하고 넘어간다 | H21: 다음 계약에서 자동으로 상계 처리된다 | I21: 1 | J21: * 정답 (①): 부당한 방법으로 초과 지급받은 금액이 확인되면, 발주기관은 이를 부당이득으로 보아 환수하는 절차를 진행할 수 있음.
A22: 19 | B22: 2. 법규 위반시 제재 | C22: 4. 부당이득금 환수 | D22: 부당이득금 환수 제도의 취지로 가장 적절한 것은? | E22: 계약상대자에게 최대한의 이익을 보장하기 위해 | F22: 행정절차를 신속하게 종결하기 위해 | G22: 법령을 위반해 부당하게 얻은 이익을 원상회복시켜 조달질서의 공정성을 확보하기 위해 | H22: 발주기관의 예산을 늘리기 위해 | I22: 3 | J22: * 정답 (③): 부당이득금 환수는 위법·부당한 방법으로 얻은 이익을 원상회복시켜 조달질서의 공정성을 확보하려는 취지임.
A23: 20 | B23: 2. 법규 위반시 제재 | C23: 2. 부정당업자 제재 | D23: 정부계약 이행 과정에서 뇌물수수나 조세포탈 등으로 유죄 판결이 확정된 자에 대하여 입찰참가자격을 제한하는 경우, 판결 확정일로부터 몇 년이 경과해야 참가가 허용되는가? | E23: 유죄 판결 확정일로부터 2년 경과 | F23: 유죄 판결 확정일로부터 3년 경과 | G23: 유죄 판결 확정일로부터 5년 경과 | H23: 유죄 판결 확정일로부터 10년 경과 | I23: 1 | J23: * 정답 (①): 조세포탈 등으로 형벌을 받은 자는 해당 유죄 판결이 확정된 날부터 '2년'이 지나야만 공공기관 입찰에 다시 참여할 수 있는 자격을 회복합니다. | K23: 국가계약법 제27조의5
A24: 21 | B24: 2. 법규 위반시 제재 | C24: 1. 계약의 해제 및 해지 | D24: 계약상대자의 귀책사유로 인한 계약의 해제·해지에 대한 설명으로 가장 올바른 것은? | E24: 청렴서약서 내용을 중대하게 위반한 사실이 확인되더라도, 계약이 이미 이행 중이라면 해당 계약을 도중에 해제하거나 해지할 법적 근거는 없다. | F24: 지체상금이 계약금액의 10% 이상 발생했음에도 발주기관이 계약을 해제하지 않을 경우, 기존 계약보증금은 즉시 전액 환급 처리해야 한다. | G24: 입찰 과정에서 거짓 서류를 제출하여 낙찰받은 사실이 적발되더라도 이미 정상적으로 계약이 체결되었다면 이를 소급하여 해제할 수 없다. | H24: 계약 해제 또는 해지 조치가 선행되지 않고서는 단지 정부가 필요하다는 이유만으로 계약상대자의 계약보증금을 단독으로 국고에 귀속시킬 수 없다. | I24: 4 | J24: * 정답 (④): 계약보증금의 국고 귀속은 '계약 해제/해지' 사유가 발생하여 해당 행정 조치를 취할 때 수반되는 것이므로, 원인이 되는 해제·해지 조치 없이는 보증금만 따로 귀속시킬 수 없습니다. (오답 노트: ① 법 제5조의3에 따라 청렴서약서 위반 시 계약 해제·해지 가능, ② 시행령 제51조에 따라 계약보증금을 '추가로 납부'하게 해야 함, ③ 재경부 계약예규 및 지방계약법 제30조의2 제1항 제3호에 따라 거짓 서류 제출 시 계약 체결 후라도 명백한 해제·해지 사유임) | K24: 「국가계약법」 제5조의3 및 동법 시행령 제51조, 제75조, 지방계약법 제30조의2
A25: 22 | B25: 2. 법규 위반시 제재 | C25: 2. 부정당업자 제재 | D25: 공정경쟁 질서 확립을 위한 부정당업자의 입찰참가자격 제한 제도에 대한 설명으로 가장 올바른 것은? | E25: 사용인(직원)이 부정행위를 저지른 경우, 대표자가 위반행위를 방지하기 위해 상당한 주의와 감독을 기울였음을 입증하더라도 대표자의 자격을 무조건 제한해야 한다. | F25: 부정당업자 제재 처분을 받아 입찰참가자격이 제한된 업체는 경쟁입찰뿐만 아니라 예외적인 수의계약 체결 대상에서도 원천적으로 배제된다. | G25: 국가기관이 부정당업자의 입찰참가자격을 제한할 때는 신속한 행정 처리를 위해 계약심의위원회의 자문 절차를 전면 생략하는 것이 원칙이다. | H25: 담합이나 뇌물 제공 등 중대한 부정행위라도 처분 시효 규정에 따라 해당 행위 종료 후 3년만 경과하면 입찰 참가자격을 제한할 수 없다. | I25: 2 | J25: * 정답 (②): 부정당업자로 지정되어 제재 기간 중에 있는 업체는 경쟁입찰 참가 자격이 박탈될 뿐만 아니라, 국가계약법령상 예외적인 '수의계약' 대상자에서도 제외되어 공공조달 시장 진입이 전면 차단됩니다. (오답 노트: ① 법 제27조 제1항 단서에 따라 상당한 주의와 감독을 게을리하지 않은 경우 양벌규정에서 면책됨, ③ 자문(심의)을 생략하는 것이 아니라 원칙적으로 계약심의위원회의 심의를 거쳐야 함, ④ 처분 제척기간은 원칙적으로 5년이며 담합 및 뇌물 제공 등은 7년임) | K25: 「국가계약법」 제27조 및 동법 시행령 제76조
A26: 23 | B26: 2. 법규 위반시 제재 | C26: 2. 부정당업자 제재 | D26: 부정당업자 제재 처분의 효력 범위 및 절차에 대한 설명으로 가장 올바른 것은? | E26: 부정당업자 제재 처분은 처분청의 관할과 무관하게 통합되어, 다른 모든 중앙관서 및 지방자치단체 등 공공부문 전체에 그 효력이 미친다. | F26: 발주기관이 특정 업체의 입찰참가자격을 제한한 경우, 해당 제한 내용은 별도 전산망이 아닌 기관 내부 게시판에만 15일간 공지하면 된다. | G26: 공동계약에 참여한 공동수급체 중 1인이 제재 사유를 유발한 경우, 연대책임을 물어 원인 제공 여부와 무관하게 구성원 전원의 자격을 즉시 제한해야 한다. | H26: 법인이 공공조달 입찰 과정에서 부정당업자 제재를 받은 경우, 그 처분의 법적 효력은 법인에만 미치며 해당 행위를 직접 지시한 대표자 개인에게는 적용되지 않는다. | I26: 1 | J26: * 정답 (①): A라는 중앙관서나 지자체에서 부정당업자 제재를 내리더라도 그 처분은 통합시스템을 통해 연계되어, 전국 모든 공공기관, 지자체, 공기업 및 준정부기관의 입찰에 참여할 수 없게 됩니다. | K26: 「국가계약법 시행령」 제76조
A27: 24 | B27: 2. 법규 위반시 제재 | C27: 2. 부정당업자 제재 | D27: 입찰참가자격 제한 처분에 갈음하여 부과되는 과징금 제도에 대한 설명으로 가장 올바른 것은? | E27: 부과된 과징금을 납부 기한까지 미납할 경우, 발주기관의 장은 국세징수법이 아닌 별도의 민사소송을 통해서만 체납액을 강제 회수할 수 있다. | F27: 입찰참가자격 제한에 갈음하여 부과된 과징금은 업체의 자금 경색 등 어떠한 사유로도 납부 기한을 연장하거나 분할하여 납부할 수 없다. | G27: 과징금은 단순히 계약금액의 10%로 일괄 부과되는 것이 아니라, 위반 행위의 경중에 따라 계약금액의 100분의 30 이내에서 세부 기준에 맞추어 산정된다. | H27: 부정당업자가 대체 부과된 과징금을 성실히 전액 납부하더라도, 원래 부과받은 입찰참가자격 제한 기간은 취소되지 않고 중복 적용된다. | I27: 3 | J27: * 정답 (③): 과징금은 위반 행위의 종류와 경중에 따라 계약금액의 10% 단위로 고정되는 것이 아니라, 법정 산정 기준에 따라 계약금액의 100분의 30 이하(최대 한도) 내에서 차등 산정하여 부과됩니다. (오답 노트: ① 과징금 미납 시 별도 민사소송이 아닌 '국세 체납처분의 예'에 따라 강제 징수함(법 제27조의2), ② 재해나 자금 경색 등 일정 요건 충족 시 납부기한 연장 및 분할납부가 가능함(시행령 제76조의2), ④ 과징금은 입찰참가자격 제한 처분에 '갈음하여(대신하여)' 부과하는 것이므로 자격 제한과 중복 적용되지 않음) | K27: 「국가계약법」 제27조의2 및 동법 시행령 제76조의2
A28: 25 | B28: 1. 공공조달 법규 분쟁 및 해석 | C28: 1. 공공조달 분쟁조정 | D28: 국가계약분쟁조정위원회에 대한 설명으로 옳지 않은 것은? | E28: 「국가계약법」 제29조에 근거하여 설치된다. | F28: 각 중앙관서에 설치되어 계약 관련 분쟁을 조정한다. | G28: 조정 성립 시 재판상 화해와 동일한 효력을 가진다. | H28: 이미 소송이 진행 중인 사안에 대해서도 조정 신청이 가능하다. | I28: 4 | J28: * 정답 (④): 「국가계약법 시행령」 제101조에 따라 이미 소송이 계속 중이거나 분쟁조정이 성립된 사항에 대해서는 조정 신청이 제한된다.
A29: 26 | B29: 1. 공공조달 법규 분쟁 및 해석 | C29: 2. 유권해석 및 감사사례 | D29: 법령 해석의 효력 순위가 올바르게 나열된 것은? | E29: 행정해석 > 정부유권해석 > 사법해석 | F29: 정부유권해석 > 사법해석 > 행정해석 | G29: 사법해석 > 정부유권해석 > 행정해석 | H29: 사법해석 = 정부유권해석 > 행정해석 | I29: 3 | J29: * 정답 (③): 법원의 사법해석이 가장 우선하며, 법제처의 정부유권해석이 개별 행정기관의 행정해석보다 상위의 효력을 가진다.
A30: 27 | B30: 1. 공공조달 법규 분쟁 및 해석 | C30: 3. 계약보증금 쟁점 | D30: 지체상금이 계약보증금 상당액에 달한 경우의 처리로 옳은 것은? | E30: 지체상금이 계약보증금에 도달하면 자동으로 계약이 해제된다. | F30: 이행 가능성이 있으면 추가 계약보증금을 징수하여 계약을 유지할 수 있다. | G30: 발주기관이 별도의 판단 없이 반드시 해제·해지해야 한다. | H30: 지체상금이 계약보증금에 도달해도 계약 해제·해지 사유에 해당하지 않는다. | I30: 2 | J30: * 정답 (②): 「국가계약법 시행령」 제75조에 따라 지체상금이 계약보증금 상당액에 달하더라도, 이행 가능성과 유지 필요성이 있으면 추가 계약보증금 징수 후 계약 유지가 가능하다.
A31: 28 | B31: 1. 공공조달 법규 분쟁 및 해석 | C31: 4. 부정당제재 처분 법리 | D31: 부정당업자 제재와 적격심사의 관계에 대한 설명으로 옳은 것은? | E31: 부정당업자 제재 사유에 해당하면 적격심사 대상에서 즉시 배제한다. | F31: 적격심사와 부정당업자 제재는 별개 제도이므로 제재 확정 전 임의 배제 불가 | G31: 부정당업자 제재 처분이 확정되면 소급하여 적격심사 결과를 무효로 한다. | H31: 적격심사 과정에서 부정당업자 제재 사유 발견 시 제제가 자동 확정된다. | I31: 2 | J31: * 정답 (②): 적격심사는 낙찰자를 결정하기 위한 별도의 평가절차이고, 부정당업자 제재는 입찰 참가 자격을 제한하는 행정처분으로서 양자는 별개의 제도이다. 따라서 제재 확정 전 임의 배제는 불가하다.
A32: 29 | B32: 1. 공공조달 법규 분쟁 및 해석 | C32: 5. 허위서류 관련 쟁점 | D32: 허위실적 서류를 제출하여 낙찰받은 자에 대한 조치로 옳은 것은? | E32: 허위 실적을 제외해도 적격심사 기준을 충족하면 제재 없이 계약 유지 | F32: 허위서류 제출 자체가 계약 해제 사유이며 부정당업자 제재도 가능하나, 계약보증금 국고 귀속은 불가 | G32: 계약 해제, 부정당업자 제재, 계약보증금 국고 귀속이 모두 가능 | H32: 허위서류 제출이 고의가 아닌 단순 실수인 경우 시정 기회를 부여한다. | I32: 3 | J32: * 정답 (③): 허위서류 제출 자체가 계약 해제 및 부정당업자 제재 사유에 해당하며(심사 결과 영향·고의 여부 불문), 이는 계약상대자의 귀책사유(거짓이나 그 밖의 부정한 방법으로 계약 체결)에 따른 계약 해제이므로 계약보증금 역시 국고에 귀속된다.
A33: 30 | B33: 1. 공공조달 법규 분쟁 및 해석 | C33: 1. 공공조달 분쟁조정 | D33: 공공조달 법규 분쟁 및 해석의 기본 개념/원칙으로 가장 적절한 것은? | E33: 기준·절차를 사전에 명확히 하고 동일하게 적용하여 공정성과 투명성을 확보한다. | F33: 구두 합의가 문서보다 우선한다. | G33: 상황에 따라 사후에 기준을 바꾸어도 무방하다. | H33: 담당자 편의에 따라 공개·기록을 생략할 수 있다. | I33: 1 | J33: * 정답 (①): 원칙(사전확정·공개·기록·동일적용)은 감사·분쟁 리스크를 줄이는 핵심이다.
A34: 31 | B34: 1. 공공조달 법규 분쟁 및 해석 | C34: 1. 공공조달 분쟁조정 | D34: 다음 중 공공조달 법규 분쟁 및 해석 관련 실무통제(리스크 관리)로 가장 적절한 것은? | E34: 요구사항·평가기준·검수기준·변경절차를 문서화하고 이해관계자에게 사전 공유한다. | F34: 검수는 생략하고 하자 발생 시 추후 협의한다. | G34: 계약조건은 낙찰자와 구두로만 정한다. | H34: 평가기준은 입찰 마감 후 필요에 따라 조정한다. | I34: 1 | J34: * 정답 (①): 문서화+사전공유는 분쟁 예방, 성과관리, 책임소재 명확화에 가장 효과적이다.
A35: 32 | B35: 1. 공공조달 법규 분쟁 및 해석 | C35: 1. 공공조달 분쟁조정 | D35: 다음 중 공공조달 법규 분쟁 및 해석에 관한 설명으로 옳은 것은? | E35: 특정 업체를 지명하고 동등 이상 허용 여부는 사후 결정한다. | F35: 평가위원이 아닌 담당자 1인이 임의로 점수를 결정한다. | G35: 긴급을 이유로 공고·기록 없이 구두로 진행한다. | H35: 요구사항·평가기준·검수기준을 명확히 하고, 변경 발생 시 기록 기반으로 절차에 따라 처리한다. | I35: 4 | J35: * 정답 (④): 절차 준수와 기록(근거)은 공공조달에서 필수 요건이다.
A36: 33 | B36: 1. 공공조달 법규 분쟁 및 해석 | C36: 1. 공공조달 분쟁조정 | D36: 행정심판과 행정소송의 관계에 대한 설명으로 옳은 것은? | E36: 행정심판은 행정소송의 필수 전치절차이다. | F36: 행정심판과 행정소송은 독립적인 구제수단이다. | G36: 행정소송 제기 후 행정심판을 청구할 수 있다. | H36: 행정심판 인용 결정은 법원 판결과 동일하다. | I36: 2 | J36: * 정답 (②): 원칙적으로 행정심판과 행정소송은 독립적 구제수단이나, 법령에서 전치절차로 규정하는 경우도 있다.
A37: 34 | B37: 1. 공공조달 법규 분쟁 및 해석 | C37: 2. 유권해석 및 감사사례 | D37: 재정경제부 예규·고시의 법적 성격으로 옳은 것은? | E37: 법률과 동일한 효력을 가진다. | F37: 하위 행정규칙으로 법률에 위반할 수 없다. | G37: 법원 판결보다 우선한다. | H37: 지방자치단체에 강제력이 없다. | I37: 2 | J37: * 정답 (②): 예규·고시는 행정규칙으로 법률·시행령보다 하위에 있으며 법률에 위반되는 내용을 정할 수 없다.
A38: 35 | B38: 1. 공공조달 법규 분쟁 및 해석 | C38: 1. 공공조달 분쟁조정 | D38: 국가계약분쟁조정위원회에 분쟁조정을 신청할 수 있는 자로 옳은 것은? | E38: 발주기관만 신청 가능 | F38: 조달기업만 신청 가능 | G38: 발주기관과 조달기업 모두 신청 가능 | H38: 감사원이 신청한다. | I38: 3 | J38: * 정답 (③): 「국가계약법」 제29조에 따라 계약의 당사자인 발주기관과 계약 상대방 모두 조정을 신청할 수 있다.
A39: 36 | B39: 1. 공공조달 법규 분쟁 및 해석 | C39: 2. 유권해석 및 감사사례 | D39: 공공조달에서 '유권해석'의 의미로 가장 적절한 것은? | E39: 법원이 내리는 판결 | F39: 법령 해석 권한이 있는 기관이 내리는 공식 법령 해석 | G39: 감사원의 감사 결과 | H39: 계약 당사자 간의 합의 | I39: 2 | J39: * 정답 (②): 유권해석은 주무부처(재정경제부 등)가 법령의 의미·적용 범위에 대해 내리는 공식적 해석이다.
... A67: 64 | B67: 2. 법규 위반시 제재 | C67: 3. 불공정조달행위 제재 | D67: 「조달사업법」상 불공정조달행위의 유형으로 옳지 않은 것은? | E67: 입찰·계약서류 위·변조, 허위서류 제출 | F67: 직접생산기준 위반 납품 | G67: 원산지 거짓 표시 납품 | H67: 정상적인 가격 경쟁을 통한 낙찰 | I67: 4 | J67: * 정답 (④): 불공정조달행위는 「조달사업법」 제21조 제1항에 따라 ① 서류 위·변조, ② 직접생산기준 위반, ③ 원산지 거짓 표시, ④ 사전 승인 없이 계약규격과 다른 제품 납품, ⑤ 다수공급자계약 관련 위반, ⑥ 우수조달물품 등 부정 지정 등 6가지 유형으로 분류된다. 정상적인 가격 경쟁을 통한 낙찰은 불공정조달행위가 아니라 공공조달의 본래 운영 방식이다.

Sheet 퀴즈 모드
B2: ⚡ 계약관리 퀴즈
B3: 드롭다운에서 단어장을 선택하면 해당 시트의 문제를 즉시 불러옵니다.
B4: ▶ 단어장 선택 (시트명) | C4: 2-2_조달요구응대및제안
B5: ① 현재 문제 번호 | C5: 24 | D5: =IF($C$4="","","/ 총 "&COUNTA(INDIRECT("'"&$C$4&"'!A4:A500"))&" 문항") -> / 총 151 문항
B6: ② 내 정답 입력 (1~4)
B8: =IF($C$4="","단어장을 선택해주세요.",IFERROR(INDEX(INDIRECT("'"&$C$4&"'!D:D"),$C$5+3),"해당 번호의 문제를 찾을 수 없습니다.")) -> 조달 요구사항(Procurement Requirement) 정의 및 과업명세서 작성 시 고려하는 항목과 세부 질문의 연결로 가장 옳지 않은 것은? | I8: =IF(OR($C$4="",ISBLANK(C6)),"💡 정답 번호를 입력하면 자동으로 채점됩니다.",IF(C6=INDEX(INDIRECT("'"&$C$4&"'!I:I"),C5+3),"⭕ 정답입니다!","❌ 오답입니다! 다시 풀어보세요.")) -> 💡 정답 번호를 입력하면 자동으로 채점됩니다.
I9: =IF(OR($C$4="",ISBLANK(C6)),"","📖 [해설] "&INDEX(INDIRECT("'"&$C$4&"'!J:J"),C5+3))
B12: =IF($C$4="","","① "&IFERROR(INDEX(INDIRECT("'"&$C$4&"'!E:E"),$C$5+3),"")) -> ① 조달 배경 및 목표 - 상품, 서비스 및 공사가 필요한 이유는 무엇인가?
B13: =IF($C$4="","","② "&IFERROR(INDEX(INDIRECT("'"&$C$4&"'!F:F"),$C$5+3),"")) -> ② 이행 장소 및 방법 - 배송지(수행/시공장소)는 어디이며 어떻게 수행되는가?
B14: =IF($C$4="","","③ "&IFERROR(INDEX(INDIRECT("'"&$C$4&"'!G:G"),$C$5+3),"")) -> ③ 의사결정 체계 - 제안서 평가위원회의 개별 평가위원 명단은 누구인가?
B15: =IF($C$4="","","④ "&IFERROR(INDEX(INDIRECT("'"&$C$4&"'!H:H"),$C$5+3),"")) -> ④ 스펙 및 요구량 - 어떤 구체적인 품질 또는 수량 요구 사항을 고려해야 하는가? | I15: =IF(OR($C$4="",ISBLANK(C6)),"","§ [출처] "&INDEX(INDIRECT("'"&$C$4&"'!K:K"),C5+3))

Sheet 매크로
A1: ' 108키(풀배열) 전용 고속 퀴즈 모드 켜기
A2: Sub StartQuizMode()
A3: ' 숫자키 (상단 가로줄 & 우측 키패드 모두 적용됨. ※ Num Lock 켜짐 필수)
A4: Application.OnKey "1", "Answer1"
A5: Application.OnKey "2", "Answer2"
A6: Application.OnKey "3", "Answer3"
A7: Application.OnKey "4", "Answer4"
A9: ' 엔터키 (일반 엔터 & 우측 키패드 엔터 모두 적용)
A10: Application.OnKey "~", "NextQuestion" ' 일반 Enter
A11: Application.OnKey "{ENTER}", "NextQuestion" ' 키패드 Enter
A13: ' Page Up / Page Down (문제 앞뒤 이동)
A14: Application.OnKey "{PGUP}", "NextQuestion" ' PgUp: 다음 문제
... A65: End Sub

Sheet 매크로 사용법
B2: 1. 매크로 시트의 전체 내용 복사(ctrl + C)
B3: 2. Alt + F11
B4: 3. 삽입 > 모듈 > 붙여넣기(ctrl + V) > 닫기
B5: 4. Alt + F8
B6: 5. StartQuizMode 실행 | Q6: 매크로 동작
Q7: Enter | R7: 다음 문제
Q8: PgUp | R8: 다음 문제
Q9: PgDn | R9: 이전 문제

Sheet 1-1_공공조달개요
A2: 공공조달과 법제도 이해 - 1. 공공조달 개요
A3: 번호 | B3: 세부항목 | C3: 세세항목 | D3: 문제 내용 | E3: 보기① | F3: 보기② | G3: 보기③ | H3: 보기④ | I3: 정답 번호 | J3: 해설 및 오답노트 | K3: 출처 | L3: 개정일자 | M3: 숫자문제
A4: 1 | B4: 1. 공공조달의 정의 및 목적 | C4: 1. 공공조달의 정의 | D4: [상황] A기관은 청소용품을 가장 저렴한 가격의 업체에서 구매했고, B공사는 사회적기업이 만든 친환경 재생용지를 정책적으로 우선 구매했다. 두 사례를 공공조달의 정의 관점에서 비교한 설명으로 가장 적절한 것은? | E4: A는 전통적(협의) 관점에, B는 사회적 가치 실현 등 정책 목표를 담은 현대적(광의) 관점에 가깝다 | F4: A, B 모두 전통적(협의) 관점의 전형적 사례이다 | G4: A는 현대적 관점, B는 전통적 관점에 해당한다 | H4: 두 사례 모두 공공조달의 정의와 무관하다 | I4: 1 | J4: * 정답 (①): 단순 최저가 구매는 전통적(협의) 관점에 가깝고, 사회적 가치 실현을 목적으로 한 우선구매는 정책 수단으로서의 현대적(광의) 관점을 보여줌.
A5: 2 | B5: 1. 공공조달의 정의 및 목적 | C5: 1. 공공조달의 정의 | D5: 우리나라 조달행정이 임시외자총국 설립과 원조물자 관리를 주된 임무로 삼았던 시기로 가장 적절한 것은? | E5: 광복 이후~1960년대(전후 복구·원조물자 관리 중심) | F5: 1997년 전후(시장개방기) | G5: 2000년대 이후(전자조달 확산기) | H5: 1980년대(내자조달 확대기) | I5: 1 | J5: * 정답 (①): 광복 이후부터 1960년대까지는 6·25 전쟁 복구와 경제개발을 위한 원조물자 도입·관리가 조달행정의 중심이었고, 이 시기 임시외자총국이 설립된 뒤 조달청이 개청됨.
A6: 3 | B6: 1. 공공조달의 정의 및 목적 | C6: 1. 공공조달의 정의 | D6: 국가 및 지방자치단체가 주체가 되는 공공조달(Public Procurement)의 본질적 개념을 설명한 것으로 가장 거리가 먼 것은? | E6: 중앙관서의 장 또는 계약담당공무원이 공익 달성을 위해 민간으로부터 필요한 재화를 획득하는 일련의 과정이다. | F6: 공공기관이 자체적인 예산을 재원으로 삼아 외부의 적격한 공급자로부터 물품 및 용역을 조달받는 경제 활동이다. | G6: 수요기관이 발주한 사업에 대해 입찰 참가 자격을 갖춘 민간 기업을 평가하고 최종 계약상대자로 선정하는 절차이다. | H6: 특정 행정 기관이 자체적인 행정 수요를 충족시키기 위하여 타 국가 기관이나 지자체로부터 자산을 매입하는 행위이다. | I6: 4 | J6: * 정답 (④): 공공조달은 '공공기관(수요자)'이 자격을 갖춘 민간 '기업(공급자)'으로부터 물자나 용역을 획득하는 행위이며, 행정 기관 간의 내부 거래나 이관을 의미하지 않습니다.
A7: 4 | B7: 1. 공공조달의 정의 및 목적 | C7: 1. 공공조달의 정의 | D7: 법률적·행정적 관점에서 '공공조달(Public Procurement)'의 본질적인 정의를 가장 명확하고 오해 없이 서술한 것은? | E7: 조달청이 정부를 대표하여 단독 전담하는 제도로서, 전국의 영세한 중소기업 및 벤처기업에게 정부의 막대한 지원금을 공평하게 분배하고 기업의 성장을 돕는 일종의 재정적 복지 사업이다. | F7: 국가가 자체적인 기술로 생산하기 어려운 방산 물자나 첨단 산업 기술 제품을 외교 경로를 통해 우방국 정부로부터 직접 수입하여 국방력과 국부를 창출하는 대외 무역 상업 활동이다. | G7: 국가, 지방자치단체, 공공기관 등 공공부문이 대국민 공공서비스 제공 및 기관 운영을 위해 필수적으로 요구되는 물품, 용역, 건설공사 등을 시장의 외부 자원으로부터 획득하는 구매 절차 전반이다. | H7: 정부나 지자체가 독점적 권력을 바탕으로 민간 시장에 강제로 개입하여 주요 생필품 및 산업 원자재의 가격을 직접 통제하고 거시적인 물가를 안정화하는 일련의 직접적 시장 규제 행위이다. | I7: 3 | J7: * 정답 (③): 공공조달은 정부 등 공공부문이 자체 수요 및 공공서비스 제공에 필요한 물품, 용역, 공사를 적법한 절차에 따라 외부(민간)로부터 획득(구매)하는 행위 전반을 뜻합니다. 복지 사업이나 물가 통제 수단이 아닙니다.
A8: 5 | B8: 1. 공공조달의 정의 및 목적 | C8: 2. 공공조달의 목적 | D8: 공공조달 지출 규모가 상당한 비중을 차지한다는 점이 강조되는 이유로 가장 적절한 것은? | E8: 공공조달 지출은 절감의 여지가 전혀 없기 때문이다 | F8: 공공조달 지출의 효율성을 조금만 높여도 상당한 규모의 예산 절감·부가가치 창출 효과를 기대할 수 있기 때문이다 | G8: 공공조달은 국가 경제에서 차지하는 비중이 미미하기 때문이다 | H8: 공공조달은 민간구매보다 항상 비효율적이기 때문이다 | I8: 2 | J8: * 정답 (②): 공공조달 지출 규모가 크기 때문에 비효율성을 소폭만 제거해도 상당한 재정 절감·부가가치 창출 효과를 거둘 수 있어, 재정 운영 효율성 측면에서 그 중요성이 강조됨.
A9: 6 | B9: 1. 공공조달의 정의 및 목적 | C9: 2. 공공조달의 목적 | D9: 정부의 막대한 구매력을 지렛대 삼아 국가의 거시적 경제 성장과 사회적 가치를 견인하는 '전략적 공공조달'의 실행 방안이 아닌 것은? | E9: 자원의 재활용을 돕고 온실가스 배출을 최소화하는 친환경 제품의 구매를 의무화하는 녹색조달 제도의 적극적인 운용 | F9: 혁신적인 아이디어와 신기술을 적용한 시제품을 정부가 선도적으로 구매하여 공공서비스를 개선하는 혁신조달의 확대 | G9: 특정 대기업이나 독점적 기술을 보유한 우수 기업의 이윤을 보장하고 시장 지배력을 강화해 주기 위한 우수조달의 도입 | H9: 취약계층 일자리 창출 및 지역사회 공헌 등 경제적 이익 외의 공익적 요소를 평가에 반영하는 사회적 책임조달의 강화 | I9: 3 | J9: * 정답 (③): 전략적 공공조달의 핵심 실행 방안은 녹색조달, 혁신조달, 사회적 책임조달이며, 특정 기업의 시장 지배력을 강화하는 것은 공공조달의 목적에 위배됩니다.
A10: 7 | B10: 1. 공공조달의 정의 및 목적 | C10: 2. 공공조달의 목적 | D10: 국가 조달 제도의 역사적 발전 단계를 고찰할 때, 제도가 태동하던 '초기 단계'에서 가장 중점적으로 추구했던 정책적 목표는? | E10: 여성 기업 및 장애인 기업 등 사회적 약자를 보호하고 포용적 경제 성장을 달성하기 위한 조달 시장 진입 장벽의 완화 | F10: 친환경 자재 사용을 의무화하고 노동자의 인권을 보호하는 등 조달 과정 전반에 걸친 다양한 사회적 가치의 적극적 실현 | G10: 자국 내 유망 중소기업의 기술 경쟁력을 강화하여 글로벌 공공조달 시장(GPA)에서의 주도권과 수출 판로를 확보하는 것 | H10: 국가의 생존과 행정 운영에 필수불가결한 군수품 및 대규모 토목 자재 등의 기초 물자를 차질 없이 적시 적소에 확보하는 것 | I10: 4 | J10: * 정답 (④): 제도의 초기 형태(단순 구매 단계)는 국가 방위 및 기반 시설 구축 등 체제 유지에 필수적인 물자를 확보하는 것에 집중되었습니다.
A11: 8 | B11: 1. 공공조달의 정의 및 목적 | C11: 2. 공공조달의 목적 | D11: 현대 국가 운영에 있어 공공조달 시스템이 지니는 본질적 중요성을 가장 정확하게 짚어낸 설명은? | E11: 민간 시장 내에서 발생하는 불공정 거래 행위를 국가가 직접 규제하고 자국 산업의 피해를 구제하기 위한 법적 장치이다. | F11: 조달청을 비롯한 중앙행정기관의 업무 부담을 경감하고 행정 처리의 편의성과 효율성을 제고하기 위한 내부적 수단이다. | G11: 국가의 예산을 시장에 투입하여 정부의 정책 의지를 실물 경제 단위에서 구체적으로 집행하는 가장 핵심적인 정책 수단이다. | H11: 세계무역기구(WTO) 체제하에서 체결된 자유무역협정(FTA)을 이행하고 국제 사회와의 교역 규모를 확대하기 위한 외교 채널이다. | I11: 3 | J11: * 정답 (③): 공공조달은 단순한 물품 구매를 넘어, 세금을 재원으로 국가 정책을 실현하고 재정을 집행하는 중추적 역할을 수행합니다.
A12: 9 | B12: 1. 공공조달의 정의 및 목적 | C12: 2. 공공조달의 목적 | D12: 공공조달이 지향하는 다면적 목표 중, '정책적 측면(거시적 측면)'의 목표와 거리가 먼 것은? | E12: 공공 사업에 참여하는 공급자 간의 기회 균등을 보장하고 절차적 투명성을 엄격히 유지하는 시스템 운영상의 공정성 확보 | F12: 사회적 약자 기업에 대한 배려와 지역 경제 활성화를 도모하여 양극화를 해소하고자 하는 사회적 책임성(Social Responsibility) 강화 | G12: 민간 부문의 신기술 및 신제품 개발 투자를 유도하고 궁극적으로 대국민 공공서비스의 질적 수준을 끌어올리는 혁신(Innovation) 촉진 | H12: 제한된 자원의 효율적 사용과 탄소 중립 실현 등 미래 세대의 환경 보호를 종합적으로 고려하는 지속 가능성(Sustainability)의 유지 | I12: 1 | J12: * 정답 (①): 공정성, 투명성, 경쟁성, 비용대비 가치 등은 조달 시스템 자체를 굴러가게 하는 '운영적(미시적) 측면'의 목표입니다.
A13: 10 | B13: 1. 공공조달의 정의 및 목적 | C13: 2. 공공조달의 목적 | D13: 조달 행정이 국가 체계에서 지니는 '개념적 중요성'에 대한 철학적·행정적 설명으로 적절하지 않은 것은? | E13: 조달 과정에서 획득된 공공서비스 및 인프라의 질적 수준은 국가 정책 목표의 최종 달성 여부와 국민 삶의 질 향상에 절대적이고 직접적인 영향을 미친다. | F13: 비효율적이고 방만한 조달 운영은 단순한 행정 절차의 지연을 넘어 심각한 국가 예산의 낭비 및 거시적인 재정적 손실로 직결되는 중대한 문제를 낳는다. | G13: 현대 국가에서 공공조달은 정부의 본질적 기능을 단순히 보조하는 후선 업무가 아니라, 국가의 존립과 원활한 운영을 뒷받침하는 핵심 기능으로 격상되었다. | H13: 공공조달은 단순히 필요한 물건을 시장에서 사 오는 행위를 넘어, 국민의 세금을 재원으로 국가의 거시적 정책을 실물 경제에 투입하는 고도의 행정 수단이다. | I13: 2 | J13: * 정답 (②): 예산 낭비나 금전적 손실에 대한 설명은 조달의 '개념적 중요성'이라기보다는 '재정적 중요성'을 구체적으로 설명한 것입니다.
A14: 11 | B14: 1. 공공조달의 정의 및 목적 | C14: 2. 공공조달의 목적 | D14: 복잡다단한 법령과 규제에도 불구하고 국가 단위의 공공조달 제도가 지속적으로 존재해야 하는 가장 일차적이고 본질적인 목적은 무엇인가? | E14: 대규모 공공 발주 사업에 참여하는 다수의 민간 조달기업들에게 안정적인 일감을 제공하여 그들의 매출 및 영업 이익 극대화를 지원하기 위함이다. | F14: 국가가 국민에게 마땅히 제공해야 할 헌법적 의무인 대국민 공공서비스 유지에 필수적인 각종 자원과 인프라를 적시 적소에 안정적으로 확보하기 위함이다. | G14: 입찰 시 발생하는 업체 간의 과도한 경쟁을 억제하고 효율적인 예산 집행을 달성하여 궁극적으로 국민이 부담하는 조세부담률을 대폭 경감하기 위함이다. | H14: 국내 시장에서 검증된 우수 조달기업의 해외 진출을 국가 차원에서 적극 장려하고, 글로벌 국제 조달 시장에서의 K-조달 무역량을 확대하기 위함이다. | I14: 2 | J14: * 정답 (②): 공공조달 시스템의 제1목적은 도로, 국방, 보건, 교육 등 정부의 정상적인 기능 유지와 공공서비스 창출에 필요한 물자(공급품)를 끊김 없이 획득하는 것입니다.
A15: 12 | B15: 1. 공공조달의 정의 및 목적 | C15: 2. 공공조달의 목적 | D15: 과거 단순한 물자 획득에 치중했던 '전통적 공공조달'의 패러다임과 오늘날 거시적 목표를 지향하는 '전략적 공공조달'의 패러다임을 구분 짓는 가장 큰 핵심적 차이는 무엇인가? | E15: 조달 시장에 참여할 수 있는 대상 조달기업의 자격 요건과 진입 장벽의 완화 정도 | F15: 계약 체결부터 완료까지 소요되는 행정적 리드타임(Lead Time)의 획기적인 단축 여부 | G15: 전자조달 시스템 도입을 통해 절감된 입찰 공고 및 서류 심사 등 물리적 행정 비용 | H15: 단순 구매를 넘어 환경 보호나 일자리 창출 등 국가의 거시적 정책 목표와의 연계성 | I15: 4 | J15: * 정답 (④): 현대적 조달 체계는 물자 획득 그 자체에 머물지 않고, 막대한 조달 예산을 지렛대 삼아 국가 정책(혁신 성장 지원, 중소기업 보호, 친환경 등)을 견인하는 강력한 전략적 수단으로 진화했습니다.
... A20: 17 | B20: 1. 공공조달의 정의 및 목적 | C20: 3. 공공조달의 범위 | D20: [상황] 발주기관이 특정 조달대상물을 물품·용역·공사 중 하나로 분류하려 하는데, 담당자가 '이건 어디에도 안 들어가니 별도 범주가 필요하다'고 주장한다. 이 주장에 대한 평가로 가장 적절한 것은? | E20: 물품·용역·공사 3가지가 가장 기본적인 분류이므로, 대부분의 대상물은 이 안에서 분류할 수 있다 | F20: 모든 조달대상물은 반드시 새로운 범주를 만들어야 한다 | G20: 조달대상물은 애초에 분류 체계 자체가 없다 | H20: 물품·공사 2가지만 존재하며 용역은 별도 개념이 아니다 | I20: 1 | J20: * 정답 (①): 조달대상물의 가장 기본적인 분류는 물품·용역·공사 3가지이며, 양허권 등 특수 유형은 이보다 확장된 범주로 별도 다뤄짐.
A21: 18 | B21: 1. 공공조달의 정의 및 목적 | C21: 3. 공공조달의 범위 | D21: 조달사업에 관한 법률에서 정의하는 '조달사업'의 범위에 포함되지 않는 것은? | E21: 시설공사의 계약에 관한 사업 | F21: 물자의 공급 및 관리 | G21: 수요기관이 필요로 하는 물자의 구매 | H21: 민간기업 간의 순수한 사적 물품 거래 중개 | I21: 4 | J21: * 정답 (④): 조달사업은 수요기관의 물자 구매·공급·관리 및 시설공사 계약에 관한 사업을 의미하며, 민간기업 간 사적 거래 중개는 이에 해당하지 않음. | K21: 조달사업에 관한 법률 제2조
A22: 19 | B22: 1. 공공조달의 정의 및 목적 | C22: 3. 공공조달의 범위 | D22: 공공조달과 관련한 통계 자료를 인용할 때 확인할 사항으로 가장 적절한 것은? | E22: 오래된 자료일수록 신뢰도가 높으므로 그대로 인용한다 | F22: 구체적인 등록업체 수·비율 등의 통계는 발표 시점에 따라 달라질 수 있으므로 최신 공식 자료로 재확인하는 것이 바람직하다 | G22: 통계는 조달 실무에서 활용 가치가 없다 | H22: 통계는 한 번 발표되면 이후 변경되지 않는다 | I22: 2 | J22: * 정답 (②): 등록업체 수·비율 등 구체적 통계는 시점에 따라 변동되므로, 시험이나 실무에서 활용할 때는 최신 공식 자료(조달청 등)로 재확인하는 것이 바람직함.
A23: 20 | B23: 1. 공공조달의 정의 및 목적 | C23: 3. 공공조달의 범위 | D23: 현대적 의미의 공공조달 업무가 포괄하는 행정적·실무적 활동 범위에 대한 설명으로 가장 타당한 것은? | E23: 수요기관이 필요로 하는 유형의 물품 및 건설 자재를 민간 시장에서 단발성으로 획득하는 단순한 구매 행위 자체만을 의미한다. | F23: 입찰 공고를 게시하고 참여 업체의 적격성을 평가하여 최종적으로 가장 유리한 계약상대자를 선정하는 단계에만 엄격히 국한된다. | G23: 다수의 경쟁자 중 가장 낮은 투찰 금액을 제시한 업체를 찾아내어 국가 예산의 지출을 최소화하는 원가 절감 절차를 뜻한다. | H23: 조달 수요의 발생 및 계획 수립부터 입찰, 계약 체결, 계약 이행(납품) 관리, 그리고 사후 평가에 이르는 전체 수명 주기를 포괄한다. | I23: 4 | J23: * 정답 (④): 오늘날의 공공조달은 단순 구매(Purchasing)를 넘어 계획부터 사후관리까지의 라이프사이클 전체를 아우르는 조달(Procurement) 개념입니다.
A24: 21 | B24: 1. 공공조달의 정의 및 목적 | C24: 3. 공공조달의 범위 | D24: 국가계약법 및 관련 법령상 규정된 공공조달의 대표적인 '대상물(목적물)' 범주에 속하지 않는 것은? | E24: 교량, 도로, 항만 등 국가 기반 시설을 새롭게 조성하거나 기존의 공공 건축물을 개축 및 보수하는 대규모 건설 공사 | F24: 전문적인 지식, 기술, 노하우 등을 활용하여 국가기관에 무형의 부가가치를 제공하는 소프트웨어 개발 등의 각종 용역 | G24: 국가가 국민의 기본적인 복지와 생활 편익을 증진하기 위해 최종적인 결과물로서 대국민에게 제공하는 무상의 공공서비스 | H24: 공공기관의 원활한 행정 업무 수행과 국가 운영 인프라 유지에 필수적으로 요구되는 각종 유형의 상업적 상품 및 물품 | I24: 3 | J24: * 정답 (③): 조달의 3대 객체(대상물)는 물품, 용역, 공사입니다. 공공서비스는 이러한 조달 행위를 통해 최종적으로 달성하려는 행정적 '목적'입니다.
A25: 22 | B25: 1. 공공조달의 정의 및 목적 | C25: 3. 공공조달의 범위 | D25: 최근 수년간 공공조달 시장에서 정부가 획득하고자 하는 대상물의 범위가 단순한 규격 물품에서 시스템 통합 등 복합적이고 난해한 사업으로 크게 확대되고 있는 가장 주된 사회적 원인은? | E25: 국민의 권리 의식과 행정 기대 수준이 지속적으로 향상되고 사회 구조가 융복합됨에 따라 정부가 선제적으로 제공해야 할 공공서비스의 형태가 매우 고도화되고 다양해졌기 때문이다. | F25: 글로벌 경기 침체 및 민간 소비 시장의 장기적 위축으로 인해 새로운 캐시카우(Cash Cow)를 공공 시장에서 찾으려는 다양한 산업군의 조달기업들이 급격히 진입했기 때문이다. | G25: 부정당업자 제재 등 조달 법령상의 엄격한 진입 규제로 인해 공공조달에 상시 참여할 수 있는 역량 있는 유효 공급자의 수가 과거에 비해 절대적으로 감소하고 있기 때문이다. | H25: 복지 지출 증가에 따른 국가 재정 악화로 부처별 공공조달 예산이 매년 삭감됨에 따라, 단 한 번의 조달 발주로 여러 개의 중복된 행정 목적을 동시에 달성해야만 하기 때문이다. | I25: 1 | J25: * 정답 (①): 스마트 시티 구축, 지능형 전자정부 서비스 도입 등 정부가 해결해야 할 사회 문제(공공서비스)가 융복합화됨에 따라 조달 대상 역시 고도화된 패키지 형태로 진화하고 있습니다.
A26: 23 | B26: 1. 공공조달의 정의 및 목적 | C26: 3. 공공조달의 범위 | D26: 단순한 물자 비축에 불과했던 과거에 비해, 현대 공공조달 시장에서 국가가 획득해야 하는 대상물의 범위와 종류가 인공지능(AI), 클라우드 시스템 등으로 갈수록 비대해지고 고도화되는 가장 근본적인 이유는? | E26: 국가 세수 펑크 등 심각한 재정 부족으로 부처별 공공조달 예산이 무자비하게 삭감됨에 따라, 최소한의 한정된 비용으로 최대한의 다목적 물자를 비축해야 할 행정적 필요성 때문이다. | F26: 국민의 권리 의식 및 공공서비스에 대한 기대 수준이 크게 향상되고 사회 문제가 다변화됨에 따라 정부가 디지털 혁신 등 제공해야 할 공공서비스 자체가 고도로 복잡해지고 다양해졌기 때문이다. | G26: 글로벌 경제 위기 및 민간 시장의 고질적 소비 위축으로 인해 회사의 새로운 현금창출원(Cash Cow)을 비교적 안정적인 공공 시장에서 찾으려는 중견기업 및 대기업들이 크게 늘어났기 때문이다. | H26: 입찰 참여 자격 기준과 요구되는 재무 상태가 갈수록 엄격해짐에 따라 공공 시장 내에서 살아남은 소수의 공급자 간에만 독점적인 유효 경쟁이 심각하게 제한적으로 이루어지고 있기 때문이다. | I26: 2 | J26: * 정답 (②): 디지털 플랫폼 정부 구현 등 국가가 당면한 행정적 과제와 공공서비스의 난이도가 과거와 비할 수 없이 복잡해졌기 때문에, 조달 발주 대상 역시 단순 규격품에서 고도화된 융복합 솔루션으로 진화하는 것입니다.
A27: 24 | B27: 1. 공공조달의 정의 및 목적 | C27: 1. 공공조달의 정의 | D27: [상황] 우리나라 조달제도의 발전 과정을 시대순으로 살펴보려 한다. 다음 중 옳은 설명을 모두 고르면? (ㄱ. 1997년 WTO 정부조달협정(GPA) 가입으로 국내 조달시장이 대외에 개방되었다 ㄴ. 차세대 나라장터는 인공지능·빅데이터 등 최신 기술 기반으로 개발되었다 ㄷ. 조선시대 대동법은 현물 공납을 쌀 등으로 통일한 제도 변화였다) | E27: ㄱ만 옳다 | F27: ㄴ, ㄷ만 옳다 | G27: ㄱ, ㄴ만 옳다 | H27: ㄱ, ㄴ, ㄷ 모두 옳다 | I27: 4 | J27: * 정답 (④): GPA 가입에 따른 시장개방, 차세대 나라장터의 AI·빅데이터 기반 개발, 대동법의 현물 공납 통일이라는 세 설명 모두 옳음.
A28: 25 | B28: 2. 공공조달 참여자, 이해관계자 | C28: 1. 공공조달 수요자 | D28: [상황] 공공조달의 수요기관 유형(국가기관, 지방자치단체, 공기업, 기타 공공기관 등)별 등록 현황을 살펴볼 때 일반적으로 나타나는 경향으로 가장 적절한 것은? | E28: 전체 수요기관 중에서 국가기관이 압도적으로 높은 비중을 차지한다. | F28: 다양한 공공기관이 포함되며, 유형별 비중은 조사 시점마다 달라진다. | G28: 공공조달 수요기관으로 등록할 수 있는 자격은 공기업으로만 제한된다. | H28: 공공조달에 참여할 수 있는 수요기관의 유형은 국가기관으로 한정된다. | I28: 2 | J28: * 정답 (②): 수요기관에는 국가기관·지방자치단체·공기업·기타 공공기관 등 다양한 유형이 포함되며, 유형별 정확한 등록 비중은 조사 시점의 통계에 따라 달라질 수 있어 최신 자료 확인이 필요함.
A29: 26 | B29: 2. 공공조달 참여자, 이해관계자 | C29: 2. 공공조달 공급자 | D29: [상황] 나라장터에 등록된 조달기업 전체 중 상당수가 중소기업이라는 통계가 발표되었다. 이 통계가 시사하는 바로 가장 적절한 것은? | E29: 해당 통계는 공공조달시장 내 실제 공급자의 기업 규모별 구성 비율과는 전혀 무관한 정보이다. | F29: 중소기업이 조달시장의 대다수를 차지하여, 공공조달이 중소기업 판로 지원에 실질적으로 기여하고 있다. | G29: 현재 공공조달시장의 주요 공급망과 계약은 대부분 대기업을 위주로 집중되어 편향적으로 운영되고 있다. | H29: 자본력 등의 현실적 한계로 인하여 일반 중소기업은 공공조달시장에 원천적으로 참여할 수 없다. | I29: 2 | J29: * 정답 (②): 나라장터 등록기업의 상당수가 중소기업이라는 점은 공공조달이 중소기업 판로 지원 수단으로 실질적으로 기능할 수 있음을 보여줌(정확한 등록업체 수·비율은 조달청 최신 통계로 확인 필요).
A30: 27 | B30: 2. 공공조달 참여자, 이해관계자 | C30: 2. 공공조달 공급자 | D30: 공공조달 계약에 참여하여 사업을 수행하는 '계약상대자(조달기업)'가 지켜야 할 권리와 의무에 대한 법리적 설명으로 명백히 틀린 것은? | E30: 입찰 담합을 모의하거나 허위 서류 위변조 등 중대한 부정행위 발생 시, 국가계약법 등 관련 법령에 따라 최장 2년까지 향후 모든 공공 입찰 참가 자격이 제한(부정당업자 제재)될 수 있다. | F30: 적법한 절차를 거쳐 낙찰자로 선정되어 정식 계약을 체결한 이후에는, 천재지변 등 불가항력의 사유가 없는 한 계약서 및 과업지시서에 명시된 납품 조건과 기한을 엄격히 준수할 책임을 진다. | G30: 국가 조달 계약에서는 예산 집행 주체인 수요기관이 절대적인 우월적 지위를 가지므로, 계약상대자는 설령 부당한 과업 지시나 설계 변경 요구라 할지라도 이에 무조건적으로 복종할 법적 의무가 있다. | H30: 납품하는 재화나 제공하는 용역이 사전에 약정된 규격과 품질 기준을 완벽히 충족해야 하며, 납품 이후 일정 기간 내에 계약 목적물에 하자가 발생할 경우 법령이 정한 바에 따라 사후관리(A/S) 책임을 진다. | I30: 3 | J30: * 정답 (③): 국가계약법의 대원칙(제5조)에 따라 국가와 계약상대자는 '서로 대등한 입장에서 합의에 따라' 계약을 체결하고 신의성실의 원칙에 따라 이를 이행해야 하므로 무조건 복종할 의무는 없습니다.
A31: 28 | B31: 2. 공공조달 참여자, 이해관계자 | C31: 2. 공공조달 공급자 | D31: 공공조달 시장에 진입하여 국가기관과 지속적인 파트너십을 맺고자 하는 공급자(조달기업)에게 가장 기본적이자 최우선적으로 요구되는 핵심 윤리 요소는? | E31: 단발성 수익을 극대화하기 위해 경쟁 관계에 있는 타 업체들과 사전에 교감하여 투찰 가격을 은밀하게 모의하고 시장 질서를 교란하는 가격담합 행위 | F31: 입찰 공고문, 수요기관의 과업지시서, 국가계약법 및 하도급법 등 조달과 관련된 제반 법령과 규정을 철저히 숙지하고 한 치의 오차 없이 지키는 법규준수 행위 | G31: 입찰 적격심사 시 자사의 치명적인 결함이나 불리한 재무 상태가 감점 요소로 평가에 반영되지 않도록 신용평가 서류 조작에 적극 가담하는 정보은폐 행위 | H31: 박빙의 경쟁 상황에서 최종 낙찰 확률을 극적으로 높이기 위해 발주기관의 계약담당자나 평가위원에게 뇌물을 제공하거나 사적으로 접근하는 부정청탁 행위 | I31: 2 | J31: * 정답 (②): 입찰 담합, 부정청탁, 정보은폐 등은 모두 조달 질서를 심각하게 파괴하는 불법 행위이며, 조달 시장 참여의 대전제는 기업의 엄격한 윤리 경영과 청렴한 '법규 준수'입니다.
A32: 29 | B32: 2. 공공조달 참여자, 이해관계자 | C32: 3. 공공조달 이해관계자 | D32: [상황] 어느 위원회가 조달 행정이 법규에 맞게 집행되었는지 외부에서 점검하고 시정을 요구하는 역할을 한다고 하자. 이러한 감시·감독 기능에 가장 부합하는 기관 조합은? | E32: 나라장터 운영기관과 조달업체 협의체 | F32: 지방자치단체와 조달업체 컨소시엄 | G32: 국회와 감사원 | H32: 수요기관과 공급업체 | I32: 3 | J32: * 정답 (③): 국회와 감사원은 조달 행정 전반을 외부에서 감시·감독하고 시정을 요구하는 대표적 기관임.
A33: 30 | B33: 2. 공공조달 참여자, 이해관계자 | C33: 3. 공공조달 이해관계자 | D33: 공공조달 생태계를 구성하는 다양한 주체 중, 좁은 의미(협의)의 직접적 이해관계자로 분류하기 어려운 주체는? | E33: 수요기관의 발주 조건과 과업지시서에 맞추어 실제 재화나 용역을 납품할 의무를 지는 조달기업(공급자) | F33: 국가 예산 및 재정 집행의 적법성을 포괄적으로 감독하고 공공기관에 대한 회계 감사를 수행하는 감사원 | G33: 계약 법령과 지정된 행정 절차에 따라 상호 간에 구체적인 권리와 의무의 법률관계를 형성하는 계약 당사자 | H33: 대국민 공공서비스를 원활하게 제공하기 위해 필요 예산을 확보하고 조달 사업을 직접 발주하는 수요기관 | I33: 2 | J33: * 정답 (②): 조달을 직접 수행하는 수요기관과 기업은 '협의'의 이해관계자이며, 이를 감시하는 감사원, 국회, 일반 국민은 '광의'의 이해관계자입니다.
... A42: 39 | B42: 3. 공공조달의 특성 | C42: 2. 공공조달의 조달행위 특성 | D42: [상황] 한 담당자가 '공공조달은 원래 수의계약이 기본이고 경쟁입찰은 예외적으로만 쓰인다'고 설명했다. 이 설명에 대한 평가로 가장 적절한 것은? | E42: 틀린 설명이다. 공공조달에서 경쟁입찰과 수의계약 중 어느 것을 원칙으로 삼아야 하는지 법적으로 명확히 정해져 있지 않다. | F42: 틀린 설명이다. 공공조달 업무에서는 공급자 선정 및 계약 방법에 대해 사전에 규정된 명확한 원칙 자체가 존재하지 않는다. | G42: 틀린 설명이다. 공급자 선정은 경쟁입찰이 원칙이며, 수의계약은 관련 법령에서 정한 예외적인 사유가 있을 때만 허용된다. | H42: 옳은 설명이다. 공공조달에서는 신속한 행정 처리와 효율성 확보를 위해 수의계약을 기본적인 계약 원칙으로 채택하고 있다. | I42: 3 | J42: * 정답 (③): 공공조달의 공급자 선정은 경쟁입찰이 원칙이며, 수의계약은 법령이 정한 예외적 사유가 있을 때만 허용됨.
A43: 40 | B43: 3. 공공조달의 특성 | C43: 2. 공공조달의 조달행위 특성 | D43: [상황] 한 조달청 주무관이 신규 담당자들에게 공공계약 체결 시 준수해야 할 기본 원칙을 설명하고 있다. 이 중 적절하지 않은 발언은? | E43: 발주기관과 조달업체는 어느 한쪽으로 치우침 없이 상호 동등하고 평등한 지위에서 공정하게 계약을 맺어야 합니다. | F43: 계약 관계가 성립된 이후 양 당사자는 굳건한 신뢰를 바탕으로 합의된 내용을 성실하고 투명하게 이행해야 합니다. | G43: 공공사업의 원활한 추진을 위해 불가피한 상황이라면 업체의 정당한 이익을 일부 제한하는 특약을 설정해도 무방합니다. | H43: 계약의 성립과 세부 조건의 결정은 우월적 지위를 이용한 강요가 아닌 양측의 자율적이고 충분한 합의를 거쳐야 합니다. | I43: 3 | J43: * 정답 (③): 국가계약법상 발주기관은 어떠한 경우라도 계약상대자의 정당한 이익을 부당하게 제한하거나 침해하는 부당한 특약 및 조건을 설정할 수 없음. | K43: 국가계약법 제5조
A44: 41 | B44: 3. 공공조달의 특성 | C44: 2. 공공조달의 조달행위 특성 | D44: [상황] 한 발표자가 공공조달의 핵심원칙을 나열하며 '경쟁, 공정성, 지속가능성'을 언급했다. 다음 중 이 핵심원칙 목록에 함께 포함되기 어려운 것은? | E44: 수익성(Profitability) | F44: 책임성(Accountability) | G44: 투명성(Transparency) | H44: 효율성(Efficiency) | I44: 1 | J44: * 정답 (①): 수익성은 민간기업의 목표이며, 공공조달의 핵심원칙(경쟁·투명성·공정성·효율성·책임성·윤리성·VFM·지속가능성)에는 포함되지 않음.
A45: 42 | B45: 3. 공공조달의 특성 | C45: 2. 공공조달의 조달행위 특성 | D45: [상황] 어느 학자가 "공공조달은 단순 물품 조달에서 시작해 법령 준수, 예산의 효율적 사용, 책임성 확보를 거쳐 궁극적으로 비용 대비 가치(VFM) 실현으로 발전한다"는 단계적 발전 모델을 제시했다. 이 모델이 강조하는 핵심 내용으로 가장 적절한 것은? | E45: 공공조달의 핵심 목적은 기초적인 관련 법령과 규정을 준수하는 단계에 확고히 도달한 이후에는, 질적으로 더 이상 진화하거나 새로운 차원으로 발전하지 않고 정체된다. | F45: 공공조달의 목적은 발전 단계가 거듭될수록 점차 확대 및 심화되며, 궁극적으로는 비용 대비 가치(VFM) 실현이라는 가장 고도화된 정책적 목표를 향해 지속 나아간다. | G45: 해당 모델은 민간 기업의 단순 구매 관행을 설명하는 고전 이론으로, 복합적인 공공성을 지닌 정부의 공공조달 시스템이나 정책적 발전 과정과는 사실상 전혀 무관하다. | H45: 공공조달 시스템은 제도의 도입 초기부터 성숙 단계에 이르기까지, 어떠한 외부 환경 변화에도 항상 동일한 수준의 기초적인 단순 물품 확보 목적만을 지속적으로 추구한다. | I45: 2 | J45: * 정답 (②): 공공조달의 목적과 역할은 고정되어 있는 것이 아니라, 단순한 물품 확보라는 기초적 수준에서 출발해 규정 준수, 효율성, 책임성을 거쳐 최종적으로 '비용 대비 가치(VFM)'를 창출하는 심화된 수준으로 끊임없이 발전해 나간다는 점을 시사함.
A46: 43 | B46: 3. 공공조달의 특성 | C46: 2. 공공조달의 조달행위 특성 | D46: 사기업의 구매 부서와 달리, 국가나 공공기관의 조달 업무 담당자에게 고도의 윤리의식과 공공성, 그리고 무거운 책임성이 그 무엇보다 강하게 요구되는 가장 근본적인 이유는? | E46: 조달 사업에 투입되어 지출되는 모든 자금의 원천이 전적으로 국민이 피땀 흘려 납부한 신성한 세금(Tax)으로 조성된 공적 자금이기 때문이다. | F46: 공공조달 시장에서 연간 집행되는 전체 예산의 절대적인 규모와 그에 따른 경제적 파급력이 국가 거시 경제 지표에 막대한 영향을 미치기 때문이다. | G46: 세계무역기구 정부조달협정(WTO GPA) 가입국으로서 국제 사회가 요구하는 엄격하고 글로벌한 투명성 기준을 의무적으로 준수해야 하기 때문이다. | H46: 수요 파악부터 입찰 공고, 적격심사, 낙찰, 그리고 계약 해제 및 지체상금 부과에 이르는 관련 법령과 행정 절차가 사기업에 비해 매우 복잡하기 때문이다. | I46: 1 | J46: * 정답 (①): 조달 절차의 복잡성이나 경제적 파급력도 이유가 되지만, 조달 공무원에게 요구되는 청렴과 책임성의 가장 근원적인 잣대는 사용처의 재원이 '국민의 혈세'라는 점에 있습니다.
A47: 44 | B47: 3. 공공조달의 특성 | C47: 2. 공공조달의 조달행위 특성 | D47: 조달 업무의 실무적 흐름을 보여주는 전체 라이프사이클을 6단계로 도식화할 때, 다음 빈칸에 들어갈 가장 알맞은 단계 명칭은? [조달계획 수립] → [조달 실행(입찰/계약)] → [계약 이행(납품) 관리] → [ 빈칸 ] → [공급자 성과 평가] → [차기 계획 피드백] | E47: 외부 민간 시장에 해당 조달 건의 세부 과업 내역을 널리 알리고 역량 있는 다수 업체의 경쟁적 참여를 유도하는 입찰 공고 단계 | F47: 참여 업체의 재무 건전성, 과거 납품 실적, 기술 인력 보유 현황 등 적합한 기준을 갖추었는지 꼼꼼히 검증하는 적격 자격 심사 단계 | G47: 물품의 획득이나 서비스 제공 중 예기치 않게 발생하는 각종 하자에 대해 책임 소재를 명확히 묻고 이를 무상으로 보완하는 사후 보증 단계 | H47: 계약상대자의 최종 납품 검수를 무사히 통과하고 사전에 약정된 대금을 관계 법령에 따라 정산하여 지급을 완료하는 계약 완료 단계 | I47: 4 | J47: * 정답 (④): 계약 이행(물품 납품 및 용역 수행)이 마무리되면, 검사/검수를 거쳐 대금을 지급하는 '계약 완료(종결)' 단계로 이어집니다. 이후 해당 업체의 성과를 평가하여 다음 계획에 피드백합니다.
A48: 45 | B48: 3. 공공조달의 특성 | C48: 2. 공공조달의 조달행위 특성 | D48: 막대한 예산이 투입되는 공공조달 업무를 성공적으로 완수하고 예산 낭비를 막기 위해, 발주처인 조달기관이 가장 중점을 두고 통제 및 관리해야 할 핵심 사항은? | E48: 수요 부서의 최초 조달 요구사항 분석 및 기획부터 시작하여, 입찰 공고, 낙찰자 선정, 물품 납품(이행), 그리고 사후 하자 평가에 이르기까지 구매 전·중·후의 전 과정을 유기적인 생애주기로 묶어 총체적으로 관리한다. | F48: 공급자의 물품 납품 및 최초 설치가 정상적으로 완료된 이후에 발생하는 시스템 오류 및 유지보수 등 사후 영역은 전적으로 해당 물품을 쓰는 사용 부서의 책임이므로 조달 부서의 관리 대상에서 엄격히 제외한다. | G48: 국가 예산 절감이 그 무엇보다 가장 중요한 가치이므로, 초기 서류 심사나 입찰 단계를 대폭 간소화하고 오로지 낙찰자와의 최종 가격 협상 과정에만 기관의 행정력을 집중적으로 투입하여 가격을 깎는 데 주력한다. | H48: 계약이 최종적으로 체결되고 도장이 찍히는 시점의 법적 하자가 없는지가 향후 감사에서 가장 중요하게 다뤄지므로, 실제 이행 과정보다는 구매 및 계약이 성립하는 단일 행정 시점만을 중점적으로 서류상 관리한다. | I48: 1 | J48: * 정답 (①): 현대적 공공조달 관리는 특정 시점의 단편적인 구매 행위 중심에서 벗어나, 사업의 기획 단계부터 계약 종결 및 폐기/사후 평가에 이르는 전체 생애주기(Life-Cycle)를 통합 관리하는 것을 핵심으로 합니다.
A49: 46 | B49: 3. 공공조달의 특성 | C49: 2. 공공조달의 조달행위 특성 | D49: 국민의 세금을 재원으로 하는 공공계약의 고유한 행정적 특징으로 가장 올바른 것은? | E49: 규정 위반 시 대외적 효력이 전면 무효화된다. | F49: 최종 결과보다는 합법적 절차와 과정을 중시한다. | G49: 상업적 이윤을 투명성보다 우선시하는 경향이 있다. | H49: 법령의 모든 조문은 재량권이 배제된 강행규정이다. | I49: 2 | J49: * 정답 (②): 공공조달은 세금을 집행하므로 절차적 정당성(과정)을 매우 중시합니다. 훈시규정 위반 시 무조건 무효화되는 것은 아니며 재량규정도 존재합니다.
A50: 47 | B50: 4. 공공조달의 구성체계 | C50: 1. 조직적 구성체계 | D50: [상황] 공공조달의 구성요소를 '법적 근거', '이를 운영하는 조직', '실제 업무가 처리되는 수단'으로 나눠 설명하려 한다. 이 중 '실제 업무가 처리되는 수단'에 해당하는 것은? | E50: 국가 공공조달 업무의 실무적 집행을 총괄하는 중앙행정기관인 조달청 | F50: 국가계약제도의 핵심 정책 수립을 총괄 담당하는 재정경제부 계약정책과 | G50: 공공조달 제도의 기본적 법적 근거인 '국가를 당사자로 하는 계약에 관한 법률' | H50: 실제 조달 업무가 전산상으로 처리되는 국가종합전자조달시스템(나라장터) | I50: 4 | J50: * 정답 (④): 나라장터는 실제 조달 업무가 처리되는 운영적 수단이며, 국가계약법은 법적 근거, 재정경제부·조달청은 이를 운영하는 조직에 해당함.
A51: 48 | B51: 4. 공공조달의 구성체계 | C51: 1. 조직적 구성체계 | D51: [상황] 신임 실무자가 신규 사업 추진을 위해 공공조달 업무 프로세스를 정리하고 있다. 다음 중 공공조달의 표준적인 계약 추진 절차를 시간 흐름에 따라 가장 올바르게 나열한 것은? | E51: [개찰 및 심사] → [공식 입찰공고] → [사업 수요제기] → [낙찰자 선정] → [사전규격공개] → [입찰서류 제출] → [최종 계약체결] | F51: [공식 입찰공고] → [사업 수요제기] → [최종 계약체결] → [사전규격공개] → [입찰서류 제출] → [개찰 및 심사] → [낙찰자 선정] | G51: [사전규격공개] → [사업 수요제기] → [입찰서류 제출] → [개찰 및 심사] → [최종 계약체결] → [공식 입찰공고] → [낙찰자 선정] | H51: [사업 수요제기] → [사전규격공개] → [공식 입찰공고] → [입찰서류 제출] → [개찰 및 심사] → [낙찰자 선정] → [최종 계약체결] | I51: 4 | J51: * 정답 (④): 공공조달은 발주기관의 '수요제기'를 시작으로, 업계 의견 수렴을 위한 '사전규격공개'와 '입찰공고'를 거쳐, '입찰서 제출 및 개찰', 적격심사 등을 통한 '낙찰자 선정' 후 최종적으로 '계약 체결'에 이르는 일련의 흐름을 따릅니다.
A52: 49 | B52: 4. 공공조달의 구성체계 | C52: 1. 조직적 구성체계 | D52: [상황] 조달 담당자가 공급업체를 탐색해 적합한 후보군을 추리는 '소싱(Sourcing)' 단계를 막 끝냈다. 다음으로 진행해야 할 업무 단계로 가장 적절한 것은? | E52: 내부 조달수요를 다시 식별하는 단계로 되돌아간다 | F52: 곧바로 낙찰자를 선정하는 단계로 건너뛴다 | G52: 제출된 입찰서를 평가하는 단계로 곧바로 넘어간다(권유 절차 없이) | H52: 추린 후보군에게 입찰 참여를 권유하는 단계로 넘어간다 | I52: 4 | J52: * 정답 (④): 조달업무는 수요식별 → 공급업체탐색 → 소싱 → 입찰권유 → 입찰평가 순으로 이어지므로, 소싱 직후에는 입찰권유가 이루어짐.
A53: 50 | B53: 4. 공공조달의 구성체계 | C53: 1. 조직적 구성체계 | D53: [상황] 해외 선진 조달 행정 체계 벤치마킹을 위해 관련 자료를 수집하던 중, 각국의 조달 전담기관 운영 현황에 대해 실무자들이 나눈 대화 내용이다. 이 중 가장 타당한 설명은 무엇인가? | E53: 미국의 GSA나 영국의 CCS처럼 주요 선진국들은 대체로 국가 조달 정책을 수립하고 대규모 공동구매 사업을 총괄적으로 관리하는 별도의 전담 조달기관을 체계적으로 운영하고 있습니다. | F53: 조달 업무의 특수성으로 인해 해외 선진국들조차 정부 조달만을 전담하는 별도의 독립적인 국가 기관을 설립하여 운영하는 사례는 전 세계적으로 사실상 전혀 존재하지 않는 것으로 파악됩니다. | G53: 해외의 주요 조달기관들은 각 부처의 요구에 따라 단순한 물품 구매 대행 업무만을 기계적으로 수행할 뿐, 거시적인 조달 정책을 기획하거나 제도를 개선하는 권한은 전혀 보유하지 않습니다. | H53: 글로벌 공공행정 개혁의 흐름에 따라 주요 선진국들의 국가 조달 전담기관들은 모두 동일한 특정 연도에 일괄적으로 설립되어 완벽히 똑같은 행정 기능과 조직적 역할을 수행하고 있습니다. | I53: 1 | J53: * 정답 (①): 미국 GSA, 영국 CCS 등 주요 선진국은 범정부 차원의 조달 정책 수립 및 공동구매를 총괄하는 전담기관을 두고 있음. 단, 각 기관의 구체적인 설립 시기나 세부 기능은 국가별 행정 환경에 따라 상이함.
A54: 51 | B54: 4. 공공조달의 구성체계 | C54: 1. 조직적 구성체계 | D54: 대한민국 공공조달의 뼈대를 이루는 대표적인 계약 관련 법령인 「국가계약법」과 「지방계약법」을 실무적으로 구분하여 적용하는 가장 명확하고 절대적인 기준은? | E54: 수의계약, 일반경쟁입찰, 다수공급자계약(MAS), 협상에 의한 계약 등 해당 조달 목적을 구체적으로 달성하기 위해 발주처가 채택한 계약 체결 방식의 종류 | F54: 최초 과업 납품 요구 지시로부터 최종 검수 완료 및 대금 지급 시점까지 소요되는 전체 조달 사업의 물리적 계약 기간과 장기계속계약 여부 | G54: 조달청 나라장터 등에 입찰 공고를 내고 최종적으로 계약서에 날인하여 해당 사업 자금을 집행하고 책임을 지는 핵심 계약 주체(발주기관)의 행정적 성격 | H54: 해당 조달 건을 통해 집행되는 전체 사업 예산 규모가 재정경제부장관이 고시하는 특정 고시 금액을 초과하는지 여부 및 최종 계약 금액의 크기 | I54: 3 | J54: * 정답 (③): 중앙행정기관(국가기관)이 주체가 되면 국가계약법을, 지방자치단체나 지방교육행정기관이 주체가 되면 지방계약법을 우선 적용합니다. 즉, 계약 주체의 성격이 법령 적용의 기준입니다.
A55: 52 | B55: 4. 공공조달의 구성체계 | C55: 2. 감독 및 기능적 책임 | D55: [상황] 조달 업무 신임 실무자가 공공계약의 법적 체계를 이루는 법령과 소관 부처를 다음과 같이 정리하였다. [ㄱ. 국가계약법-재정경제부, ㄴ. 지방계약법-행정안전부, ㄷ. 판로지원법-중소벤처기업부, ㄹ. 민법-법무부] 이에 대한 평가로 가장 적절한 것은? | E55: 제시된 ㄱ, ㄴ, ㄷ, ㄹ의 조달 관련 주요 법령 및 계약의 일반법에 대한 각 소관 부처의 연결은 모두 법적으로 올바른 설명이다. | F55: 제시된 항목 중에서 ㄴ(지방계약법)과 ㄹ(민법)의 소관 중앙부처를 서로 연결하여 정리한 실무자의 설명은 현행 법령상 옳지 않다. | G55: 제시된 항목 중에서 ㄷ(판로지원법)과 ㄹ(민법)의 소관 중앙부처를 서로 연결하여 정리한 실무자의 설명은 현행 법령상 옳지 않다. | H55: 제시된 항목 중에서 ㄱ(국가계약법)과 ㄷ(판로지원법)의 소관 중앙부처를 서로 연결하여 정리한 실무자의 설명은 현행 법령상 옳지 않다. | I55: 1 | J55: * 정답 (①): 국가계약법은 재정경제부, 지방계약법은 행정안전부, 중소기업 제품 구매를 다루는 판로지원법은 중소벤처기업부, 공공계약의 기본 원리가 되는 민법은 법무부 소관으로 제시된 설명은 모두 옳음.
A56: 53 | B56: 4. 공공조달의 구성체계 | C56: 2. 감독 및 기능적 책임 | D56: 공공계약 관련 법규 및 제정 배경에 대한 설명으로 가장 옳은 것은? | E56: 지방계약법 하위 규정엔 시행령과 규칙만 있으며 별도 행안부 예규는 없다. | F56: 조달시장 개방 및 국제 규범 대응을 위해 국가계약법이 별도로 제정되었다. | G56: 국가계약법 하위 규정엔 시행령 등만 존재하며 재경부 계약예규는 제외된다. | H56: 공공계약은 사법상 계약이므로 특별법인 계약법보다 민법이 항상 우선된다. | I56: 2 | J56: 정답 (②) 1995년 GPA 가입 등에 대응해 예산회계법에서 분리 제정됨 / ①·③ 각종 예규 존재함 / ④ 특별법이 우선함 | K56: 「국가계약법(1995.1.5., 법률 제4868호)」 제정·개정이유
A57: 54 | B57: 4. 공공조달의 구성체계 | C57: 2. 감독 및 기능적 책임 | D57: 계약사무 위임 및 위탁에 대한 설명으로 가장 옳은 것은? | E57: 지자체의 장은 계약사무를 다른 지방자치단체나 전문기관에 위탁하는 것이 전면 금지된다. | F57: 지방계약법령상 계약사무를 위탁할 수 있는 전문기관에는 공기업과 준정부기관이 포함된다. | G57: 각 중앙관서의 장이나 지자체장은 소속 기관의 특정 관직 지정 방식으로 계약사무를 위임할 수 없다. | H57: 지자체가 국가기관에 계약사무를 위탁할 경우 수탁기관인 국가기관의 법령이 아닌 무조건 지방계약법을 적용한다. | I57: 2 | J57: 정답 (②) 지방계약법 시행령 제6조제2항제1호에 따라 공기업과 준정부기관이 전문기관에 명시적으로 포함됨 / ① 위임·위탁 자체는 허용됨 / ③ 관직 지정 방식의 위임 가능 / ④ 국가기관 위탁 시 국가계약법령을 따르는 것이 원칙 | K57: 지방계약법
A58: 55 | B58: 1. 공공조달의 정의 및 목적 | C58: 1. 공공조달의 정의 | D58: 공공조달의 정의 및 목적의 기본 개념/원칙으로 가장 적절한 것은? | E58: 기준·절차를 사전에 명확히 하고 동일하게 적용하여 공정성과 투명성을 확보한다. | F58: 상황에 따라 사후에 기준을 바꾸어도 무방하다. | G58: 구두 합의가 문서보다 우선한다. | H58: 담당자 편의에 따라 공개·기록을 생략할 수 있다. | I58: 1 | J58: * 정답 (①): 원칙(사전확정·공개·기록·동일적용)은 감사·분쟁 리스크를 줄이는 핵심이다. 공공조달은 법령에 따라 기준과 절차를 사전에 명확히 정하고, 모든 참가자에게 동일하게 적용함으로써 공정성과 투명성을 확보해야 한다. | M58: AAA
A59: 56 | B59: 1. 공공조달의 정의 및 목적 | C59: 1. 공공조달의 정의 | D59: 공공조달의 정의 및 목적 관련 실무통제(리스크 관리)로 가장 적절한 것은? | E59: 검수는 생략하고 하자 발생 시 추후 협의한다. | F59: 요구사항·평가기준·검수기준·변경절차를 문서화하고 이해관계자에게 사전 공유한다. | G59: 계약조건은 낙찰자와 구두로만 정한다. | H59: 평가기준은 입찰 마감 후 필요에 따라 조정한다. | I59: 2 | J59: * 정답 (②): 문서화+사전공유는 분쟁 예방, 성과관리, 책임소재 명확화에 가장 효과적이다. 공공조달은 문서 기반의 투명한 절차를 원칙으로 하며, 요구사항과 평가기준 등은 반드시 사전에 문서화하여 이해관계자에게 공유되어야 한다. | M59: AAA
A60: 57 | B60: 1. 공공조달의 정의 및 목적 | C60: 1. 공공조달의 정의 | D60: 공공조달의 정의 및 목적에 관한 설명으로 옳은 것은? | E60: 입찰·계약 단계에서 이해상충은 문제되지 않는다. | F60: 조달절차의 각 단계는 관련 규정에 따라 수행되며, 핵심 판단은 기록으로 남겨야 한다. | G60: 절차는 내부 방침만 따르면 되며 외부 기준은 고려하지 않는다. | H60: 사전공개는 원칙이 아니라 선택사항이다. | I60: 2 | J60: * 정답 (②): 절차 준수와 기록(근거)은 공공조달에서 필수 요건이다. 공공조달의 모든 단계는 「국가계약법」, 「지방계약법」 등 관련 규정에 따라 수행되어야 하며, 주요 의사결정은 반드시 기록으로 남겨 투명성과 책임성을 확보해야 한다. | M60: AAA
A61: 58 | B61: 1. 공공조달의 정의 및 목적 | C61: 1. 공공조달의 정의 | D61: 다음은 공공조달의 기본 원칙에 관한 설명이다. 옳은 것을 모두 고른 것은? ㄱ. 공공조달은 공정성과 투명성을 확보해야 한다. ㄴ. 입찰 기준은 입찰 마감 후 변경할 수 있다. ㄷ. 주요 의사결정 과정은 기록으로 남겨야 한다. ㄹ. 담당자의 재량에 따라 공개를 생략할 수 있다. | E61: ㄱ, ㄴ | F61: ㄱ, ㄷ | G61: ㄱ, ㄷ, ㄹ | H61: ㄱ, ㄴ, ㄷ | I61: 2 | J61: * 정답 (②): 공공조달은 공정성·투명성 확보와 의사결정 기록이 핵심 원칙이다. | M61: AAA
A62: 59 | B62: 1. 공공조달의 정의 및 목적 | C62: 1. 공공조달의 정의 | D62: 「국가계약법」에 따른 '국가를 당사자로 하는 계약'의 의미에 포함되지 않는 것은? | E62: 국가가 사인과 체결하는 물품구매계약 | F62: 국가기관이 체결하는 공사도급계약 | G62: 지방자치단체가 체결하는 용역계약 | H62: 중앙행정기관이 체결하는 임대차계약 | I62: 3 | J62: * 정답 (③): 지방자치단체가 체결하는 계약은 「지방계약법」의 적용을 받으며, 「국가계약법」은 국가(중앙행정기관 등)가 당사자인 계약에 적용된다. | M62: AAA
A63: 60 | B63: 1. 공공조달의 정의 및 목적 | C63: 2. 공공조달의 목적 | D63: 공공조달의 1차적 목적으로 가장 적절한 것은? | E63: 국내 기업 보호 및 지원 | F63: 행정 업무 수행에 필요한 물품·공사·용역의 적기 조달 | G63: 조달청의 수익 창출 | H63: 민간기업의 경쟁력 향상 | I63: 2 | J63: * 정답 (②): 공공조달의 1차적 목적은 행정기관이 업무를 수행하는 데 필요한 물품, 공사, 용역을 적시에, 적정 품질로, 적정 가격에 조달하는 것이다. | M63: AAA
A64: 61 | B64: 1. 공공조달의 정의 및 목적 | C64: 1. 공공조달의 정의 | D64: 「조달사업법」상 '조달'의 정의에서 '물자'에 해당하지 않는 것은? | E64: 수요기관이 필요로 하는 물품 | F64: 정부가 비축·관리하는 물자 | G64: 수요기관이 발주하는 시설 공사 | H64: 정부 창고에 보관 중인 물품 | I64: 3 | J64: * 정답 (③): 「조달사업법」에서 '물자'는 수요기관이 필요로 하거나 정부가 비축·관리하는 유형의 물품을 의미하며, 시설 공사(공사계약)는 별도로 구분한다. | M64: AAA
A65: 62 | B65: 1. 공공조달의 정의 및 목적 | C65: 3. 공공조달의 범위 | D65: 공공조달에서 '물품'과 '용역'을 구분하는 기준으로 가장 적절한 것은? | E65: 계약금액의 크기 | F65: 유형성(물리적 형태) 존재 여부 | G65: 계약 당사자의 규모 | H65: 납품 장소의 위치 | I65: 2 | J65: * 정답 (②): 물품은 물리적 형태를 지닌 유형의 동산이고, 용역은 무형의 서비스 활동으로 구분된다. 가장 핵심적인 구분 기준은 유형성 여부이다. | M65: AAA
A66: 63 | B66: 1. 공공조달의 정의 및 목적 | C66: 1. 공공조달의 정의 | D66: 공공조달과 민간구매의 차이에 대한 설명으로 옳지 않은 것은? | E66: 공공조달은 국민의 세금을 재원으로 한다. | F66: 공공조달은 법령에 따른 엄격한 절차가 요구된다. | G66: 공공조달은 사회적 가치 실현 목적이 포함될 수 있다. | H66: 공공조달은 민간구매보다 구매 의사결정이 자유롭다. | I66: 4 | J66: * 정답 (④): 공공조달은 법령에 따른 엄격한 절차·기준을 따라야 하므로 민간구매에 비해 의사결정의 자유도가 낮다. | M66: AAA
A67: 64 | B67: 1. 공공조달의 정의 및 목적 | C67: 3. 공공조달의 범위 | D67: 다음 중 공공조달 대상에 해당하지 않는 것은? | E67: 사무용 컴퓨터 구매 | F67: 청사 신축 공사 | G67: 법률 자문 용역 | H67: 공무원 급여 지급 | I67: 4 | J67: * 정답 (④): 공무원 급여는 공공조달의 대상이 아닌 인건비 지출로서, 물품·공사·용역 계약과는 구별된다. | M67: AAA
A68: 65 | B68: 1. 공공조달의 정의 및 목적 | C68: 1. 공공조달의 정의 | D68: 「지방계약법」에 따른 '지방자치단체를 당사자로 하는 계약'에 해당하는 것은? | E68: 교육부가 발주하는 교과서 인쇄·용역 | F68: 광역시가 발주하는 도로 포장 공사 | G68: 조달청이 체결하는 MAS 계약 | H68: 한국전력공사가 체결하는 전기 공급 계약 | I68: 2 | J68: * 정답 (②): 광역시는 지방자치단체에 해당하며, 광역시가 발주하는 공사 계약은 「지방계약법」의 적용 대상이다. | M68: AAA
A69: 66 | B69: 1. 공공조달의 정의 및 목적 | C69: 3. 공공조달의 범위 | D69: 공공조달에서 '공사'와 '용역'이 혼재하는 계약에서 적용 법령을 결정하는 기준은? | E69: 계약 금액이 더 큰 부분의 법령 적용 | F69: 공사 부분의 법령 항상 우선 적용 | G69: 용역 부분의 법령 항상 우선 적용 | H69: 수요기관이 임의로 선택 | I69: 1 | J69: * 정답 (①): 물품과 용역이 혼재하거나 공사와 용역이 혼재하는 경우, 금액 비중이 더 큰 부분의 계약 유형에 해당하는 법령을 적용하는 것이 원칙이다. | M69: AAA
... A116: 113 | B116: 4. 공공조달의 구성체계 | C116: 2. 감독 및 기능적 책임 | D116: 다음 중 성과감사(Performance Audit)의 주된 초점으로 옳은 것은? | E116: 법정 절차·기한·자격요건 등 규범의 충족 여부를 확인한다. | F116: 조달 활동이 정책 목표를 달성했는지, 비용 대비 가치(VFM)가 적정한지를 평가한다. | G116: 지출 기록의 정확성과 부패·횡령 등 금전적 비위 여부를 점검한다. | H116: 부패 사건·신규 시스템 도입 등 특정 사안에 초점을 맞추어 수시로 실시한다. | I116: 2 | J116: * 정답 (②): 성과감사는 조달 활동이 소기의 목적을 달성했는지, 투입 대비 산출이 적정한지를 평가하는 감사이다. '①'은 적법성 점검(규정준수 감사), '③'은 재정 건전성 점검(재무 감사), '④'는 목적 지향적 점검(특수목적 감사)에 해당한다. | M116: AAA
A117: 114 | B117: 4. 공공조달의 구성체계 | C117: 2. 감독 및 기능적 책임 | D117: UN, WTO, OECD, EU 등 주요 국제기구가 공공조달의 공통 기본원칙으로 제시하는 3가지를 올바르게 나열한 것은? | E117: 공정성, 효율성, 수익성 | F117: 경쟁, 차별금지·평등대우, 투명성 | G117: 경쟁, 신속성, 투명성 | H117: 공개성, 전문성, 안전성 | I117: 2 | J117: * 정답 (②): 국제기구들이 공통으로 제시하는 공공조달 3대 원칙은 '경쟁', '차별금지·평등대우', '투명성'이다. 감독은 이 원칙들이 현실에서 실제로 지켜지고 있는지를 검증하는 핵심 수단으로 기능한다. | L117: 260830 | M117: AAA
A118: 115 | B118: 4. 공공조달의 구성체계 | C118: 2. 감독 및 기능적 책임 | D118: 공공조달 규범의 계층 구조에 관한 설명으로 옳지 않은 것은? | E118: 헌법은 경제질서·기본권 조항을 통해 제도의 정당성 기반을 제공한다. | F118: 「국가계약법」과 「지방계약법」은 동일한 법률에 통합되어 운영된다. | G118: 시행령은 법률이 위임한 세부 요건·절차를 구체화한다. | H118: 계약예규·고시·훈령은 입찰·계약 실무의 상세 기준을 제공하는 행정규칙이다. | I118: 2 | J118: * 정답 (②): 「국가계약법」은 국가기관의 계약을 규율하고 「지방계약법」은 지방자치단체의 계약을 규율하는 별개 법률이다. 적용 주체와 소관 부처(재정경제부·행정안전부)도 다르다. | M118: AAA
A119: 116 | B119: 4. 공공조달의 구성체계 | C119: 2. 감독 및 기능적 책임 | D119: 공공조달 관련 법령의 소관 기관 연결로 옳지 않은 것은? | E119: 「국가계약법」 - 재정경제부 | F119: 「지방계약법」 - 행정안전부 | G119: 「조달사업법」 - 조달청 운영 근거/재정경제부 소속 | H119: 「전자조달법」 - 산업통상자원부 | I119: 4 | J119: * 정답 (④): 「전자조달법」은 전자적 방법에 의한 조달 절차의 법적 효력을 부여하는 법률로, 조달청이 운영 주체이며 재정경제부 소관이다. 산업통상자원부 소관이 아니다. | M119: AAA
A120: 117 | B120: 4. 공공조달의 구성체계 | C120: 1. 조직적 구성체계 | D120: 공공조달의 실행 주체와 역할에 관한 설명으로 옳지 않은 것은? | E120: 조달청은 일정 금액 이상의 물품·공사·용역에 대해 의무구매 대행 기능을 수행한다. | F120: 방위사업청은 무기체계와 군수물자의 조달을 전담한다. | G120: 조달청이 모든 공공조달을 독점적으로 처리하므로 수요기관의 자체 조달은 허용되지 않는다. | H120: 농수산식품유통공사는 공공급식 식재료 분야의 전자조달 플랫폼(NeaT)을 운영한다. | I120: 3 | J120: * 정답 (③): 소액 구매·기관 고유 사업·긴급 수요 등에서는 수요기관이 자체조달기관으로 기능하며, 적용 법령(「국가계약법」 또는 「지방계약법」)을 직접 준수해 입찰·계약 절차를 진행한다. | M120: AAA
A121: 118 | B121: 4. 공공조달의 구성체계 | C121: 1. 조직적 구성체계 | D121: 공공조달 운영 모델에 관한 설명으로 옳은 것은? | E121: 중앙집중형은 단일 또는 소수의 전문기관이 국가 전체의 조달 수요를 통합 처리하는 방식이다. | F121: 분산형은 모든 조달을 단일 기관이 처리하므로 절차 표준화 효과가 가장 크다. | G121: 혼합형은 국제적으로 채택 사례가 없는 이론적 모델이다. | H121: 한국은 완전한 분산형 모델을 채택하고 있다. | I121: 1 | J121: * 정답 (①): 중앙집중형은 통합 처리, 분산형은 개별 기관 처리, 혼합형은 양자 결합이다. 분산형은 표준화보다 기관 자율성에 강점이 있고, 한국은 중앙집중(조달청 의무구매 대행)과 분산(수요기관 자체 조달)이 결합된 혼합형에 해당한다. | M121: AAA
A122: 119 | B122: 4. 공공조달의 구성체계 | C122: 2. 감독 및 기능적 책임 | D122: 공공조달 구성체계에서 특별법 우선 원칙에 관한 설명으로 옳은 것은? | E122: 모든 공공조달 계약은 「국가계약법」이 다른 법률보다 우선하여 적용된다. | F122: 다른 법률에 특별한 규정이 있으면 그 법이 우선 적용된다. | G122: 행정규칙은 법률보다 우선 적용된다. | H122: 「조달사업법」은 「국가계약법」보다 항상 후순위로 적용된다. | I122: 2 | J122: * 정답 (②): 「국가계약법」 제3조는 다른 법률에 특별한 규정이 있으면 그 법이 우선 적용된다고 규정한다(특별법 우선 원칙). 따라서 「판로지원법」의 중소기업자 간 경쟁제품 등 특별 규정이 있는 경우에는 그 법이 우선한다. | M122: AAA

Sheet 1-2_원칙및방법
A2: 공공조달과 법제도 이해 - 2. 공공조달 원칙 및 방법
A3: 번호 | B3: 세부항목 | C3: 세세항목 | D3: 문제 내용 | E3: 보기① | F3: 보기② | G3: 보기③ | H3: 보기④ | I3: 정답 번호 | J3: 해설 및 오답노트 | K3: 출처 | L3: 개정일자 | M3: 숫자문제
A4: 1 | B4: 1. 공공조달 원칙 | C4: 1. 공공조달 기본 원칙 | D4: [상황] 한 강사가 공공조달의 5대 기본원칙을 설명하며 '투명성, 비용대비가치, 경쟁성, 차별금지 및 동등대우, 책임성'을 언급했다. 다음 중 이 목록에 포함될 가능성이 가장 낮은 개념은? | E4: 투명성(Transparency) | F4: 책임성(Accountability) | G4: 경쟁성(Competitiveness) | H4: 수익성(Profitability) | I4: 4 | J4: * 정답 (④): 수익성은 민간구매의 최우선 목표이며, 공공조달의 5대 기본원칙(투명성·VFM·경쟁성·차별금지동등대우·책임성)에는 포함되지 않음.
A5: 2 | B5: 1. 공공조달 원칙 | C5: 1. 공공조달 기본 원칙 | D5: [상황] 발주기관이 사무기기를 구매하면서 구매가격뿐 아니라 유지보수 비용, 소모품 비용, 폐기 비용까지 함께 비교해 선정했다. 이러한 접근방식이 구현하는 원칙은? | E5: 차별금지 및 동등대우 | F5: 비용 대비 가치(VFM) | G5: 책임성 | H5: 경쟁성 | I5: 2 | J5: * 정답 (②): 구매가격 외에 유지보수·폐기 등 총소유비용까지 종합 고려하는 것은 비용 대비 가치(VFM) 원칙의 구현임.
A6: 3 | B6: 1. 공공조달 원칙 | C6: 1. 공공조달 기본 원칙 | D6: [상황] 한 공공기관의 조달 담당자가 신규 장비 도입을 위해 TCO(총소유비용)를 산정하면서, '장비의 최초 취득부터 운영, 그리고 최종 폐기까지 우리 기관이 실제로 지출하게 될 모든 비용'을 합산하여 집계했다. 이러한 산정 방식에 대한 평가로 가장 적절한 것은? | E6: 틀린 산정 방식이다. TCO는 장비의 최초 취득과 운영 기간의 유지보수 비용만을 합산하는 재무 지표이므로, 수명이 종료된 이후의 최종 폐기 단계에서 발생하는 각종 처리 비용은 원칙적으로 전면 제외하고 계산해야 한다. | F6: 올바른 산정 방식이다. 하지만 향후 감사에 대비해 객관성을 완벽히 입증하려면, 우리 기관의 실제 지출 비용 외에 입찰에 참여했던 타 경쟁업체들의 평균 제시 가격까지도 TCO 산출 내역에 반드시 포함시켜야만 한다. | G6: 올바른 산정 방식이다. TCO(총소유비용)는 자산의 최초 취득 단계부터 정비 등의 운영 기간을 거쳐 최종 폐기에 이르기까지, 해당 자산과 관련해 실질적으로 발생하는 모든 비용을 온전히 포괄하는 개념이기 때문이다. | H6: 틀린 산정 방식이다. 공공조달에서 TCO는 당해 예산 집행을 위해 장비를 최초 도입할 때 지급하는 초기 구매 가격만을 의미하므로, 향후에 지속적으로 발생하게 될 장기적인 운영 비용 및 폐기 비용은 제외해야 한다. | I6: 3 | J6: * 정답 (③): TCO(Total Cost of Ownership, 총소유비용)는 자산을 획득하고 유지·보수하며 최종적으로 폐기하는 전체 수명 주기 동안 실제 발생하는 모든 지출 비용을 합산한 포괄적 개념임. 경쟁업체의 가격을 억지로 포함시킬 필요가 없으며, 단순 초기 구매 비용만을 의미하지도 않음.
A7: 4 | B7: 1. 공공조달 원칙 | C7: 1. 공공조달 기본 원칙 | D7: [상황] 한 공공기관의 계약담당자가 입찰 공고가 정식으로 게시되기 전에, 평소 친분이 있던 특정 업체에게만 과업지시서 등 입찰 관련 핵심 정보를 미리 제공했다. 이러한 담당자의 행위가 위반하고 있는 공공조달의 기본 원칙으로 가장 적절한 것은? | E7: 특정 업체에 유리한 입찰 환경을 조성했으므로 '경쟁성 원칙'만을 단편적으로 위반한 것이며, 공공조달의 다른 핵심적인 기본 원칙들과는 직접적인 연관성이 없다. | F7: 계약 공고 이전의 단순한 절차적 하자에 해당할 뿐이므로, 공공 예산 집행에 대해 국민에게 엄중히 책임을 져야 한다는 '책임성 원칙'과는 사실상 전혀 무관하다. | G7: 예산을 절감하여 경제적 효율성을 달성해야 한다는 '비용 대비 가치 원칙'만을 단독으로 훼손한 것이며, 공공조달의 절차적 공정성 문제로 치부하기는 매우 어렵다. | H7: 잠재적 입찰자 모두에게 동등하게 정보를 공개해야 한다는 '투명성 원칙' 및 특정 업체를 부당하게 우대해서는 안 되는 '차별금지·동등대우 원칙'에 정면으로 반한다. | I7: 4 | J7: * 정답 (④): 특정 업체에만 사전 정보를 제공하는 행위는 입찰 관련 정보를 모든 이해관계자에게 투명하게 공개해야 한다는 '투명성 원칙'과 특정인을 유리하게 대우하지 않아야 한다는 '차별금지 및 동등대우 원칙'을 심각하게 훼손하는 부정행위임.
A8: 5 | B8: 1. 공공조달 원칙 | C8: 1. 공공조달 기본 원칙 | D8: [상황] 한 신임 계약담당자가 "향후 감사를 대비하여 공공조달의 책임성을 확보하려면, 무조건 가장 낮은 입찰 가격을 제시한 최저가 업체를 낙찰자로 선정하는 것이 가장 확실한 방법이다"라고 주장했다. 이 주장의 핵심적인 문제점은 무엇인가? | E8: 단순 가격 중심의 무조건적인 최저가 낙찰 방식은 오히려 조달 목적물의 품질 저하를 초래하여 '비용 대비 가치(VFM)' 원칙을 심각하게 훼손할 우려가 크므로, 진정한 의미의 책임성 확보 방안이 될 수 없다. | F8: 책임성 원칙은 예산 집행 과정의 경제성과는 전혀 무관한 독립적 개념이므로, 입찰 업체의 가격 제안 수준이나 구체적인 낙찰자 선정 방식 등 재무적인 요소들을 억지로 결부시켜 책임성을 논의하는 것은 잘못된 접근이다. | G8: 공공조달에서 의미하는 책임성이란 사후 감사 기관의 지적 사항을 회피하기 위한 소극적인 방어 기제에만 전적으로 국한되므로, 초기 입찰 단계에서의 가격 산정 문제나 낙찰자 결정 방식과는 근본적으로 아무런 관련성이 없다. | H8: 해당 주장은 아무런 문제가 없다. 국민의 혈세를 집행하는 공공조달의 특성상, 예산을 최대한 절감할 수 있는 무조건적 최저가 선정이 곧 투명하고 공정한 업무 처리이자 책임성을 완벽하게 입증하는 가장 핵심적인 지표이다. | I8: 1 | J8: * 정답 (①): 무조건적인 최저가 선정은 장기적인 품질과 효율성을 따지는 VFM(비용 대비 가치) 원칙을 훼손할 수 있음. 공공조달의 책임성은 단순한 가격 인하가 아니라 합리적 의사결정 과정, 꼼꼼한 기록 보관, 투명한 성과평가 등을 통해 확보됨.
A9: 6 | B9: 1. 공공조달 원칙 | C9: 1. 공공조달 기본 원칙 | D9: [상황] 신입 직원이 '공공조달은 수의계약을 기본으로 하고 경쟁입찰은 특별한 경우에만 쓰는 것 아니냐'고 물었다. 이에 대한 올바른 답변은? | E9: 아니다. 제한경쟁이 원칙이며 나머지가 예외이다 | F9: 아니다. 일반경쟁이 원칙이며, 제한경쟁·지명경쟁·수의계약이 예외적으로 허용된다 | G9: 맞다. 지명경쟁이 원칙이고 나머지가 보조수단이다 | H9: 맞다. 수의계약이 원칙이고 경쟁입찰이 예외이다 | I9: 2 | J9: * 정답 (②): 국가계약법 제7조는 일반경쟁을 원칙으로 규정하며, 제한경쟁·지명경쟁·수의계약은 예외적 방법임. | K9: 국가계약법 제7조
A10: 7 | B10: 1. 공공조달 원칙 | C10: 1. 공공조달 기본 원칙 | D10: [상황] 적격심사제도를 처음 접한 직원이 '결국 가격만 보고 낙찰자를 정하는 것 아니냐'고 물었다. 이 질문에 대한 올바른 답변은? | E10: 아니다. 입찰가격과 함께 계약이행능력(수행능력·재무상태·신인도 등)을 종합 심사한다 | F10: 아니다. 오직 재무상태만으로 결정한다 | G10: 맞다. 수행능력만 보고 가격은 보지 않는다 | H10: 맞다. 오직 가격만으로 결정한다 | I10: 1 | J10: * 정답 (①): 적격심사제도는 가격뿐 아니라 수행능력·재무상태·신인도 등 계약이행능력을 종합적으로 심사하는 제도임.
A11: 8 | B11: 1. 공공조달 원칙 | C11: 1. 공공조달 기본 원칙 | D11: 국가계약법령 및 조달사업법령의 취지에 비추어 볼 때, 공공조달 업무 수행 시 요구되는 핵심 기본원칙에 해당하지 않는 것은? | E11: 조달 절차와 심사 기준을 외부로 투명하게 공개하여 조달 행정에 대한 국민적 신뢰를 확보하는 투명성 유지의 원칙 | F11: 다수의 유효한 공급자에게 입찰에 참여할 수 있는 동등한 기회를 부여하여 시장의 활력을 높이는 경쟁성 확보의 원칙 | G11: 특정 조달기업과의 장기적이고 반복적인 거래 관계를 우선적으로 보호하여 공급망을 고착화하는 지속성 유지의 원칙 | H11: 투입된 국가 예산 대비 최적의 품질과 효용을 추구하여 재정 지출의 효율성을 극대화하는 비용대비 가치 창출의 원칙 | I11: 3 | J11: * 정답 (③): 공공조달은 공정성과 경쟁성을 중시하므로, 특정 기업과의 거래를 고착화하여 기회균등을 저해하는 '지속성 유지'는 기본원칙이 될 수 없습니다.
A12: 9 | B12: 1. 공공조달 원칙 | C12: 1. 공공조달 기본 원칙 | D12: 국가계약법령의 기본 이념에 비추어 볼 때, 공공조달 제도를 운영함에 있어 반드시 지켜야 할 3대 원칙으로 볼 수 없는 것은? | E12: 합리적인 기준 없이 특정 기업에 부당한 특혜를 주거나 불이익을 강요하는 행위를 원천적으로 차단하는 차별금지의 원칙 | F12: 조달 사업 수행 과정에서 공공기관의 재무적 이익과 잉여금을 극대화하여 국고에 환수하도록 규정하는 수익 창출의 원칙 | G12: 공공 입찰과 관련된 모든 정보와 평가 기준을 외부로 명확하게 공개하여 절차적 정당성을 확보하는 투명성 유지의 원칙 | H12: 자격 요건을 갖춘 다수의 적격 공급자에게 입찰에 참여할 수 있는 동등한 기회를 균등하게 보장하는 경쟁 확보의 원칙 | I12: 2 | J12: * 정답 (②): 공공조달은 국가 예산을 재원으로 공공성을 실현하는 것이 목적이므로, 민간 기업처럼 조달 자체를 통한 '재무적 수익 창출'을 원칙으로 삼지 않습니다.
A13: 10 | B13: 1. 공공조달 원칙 | C13: 1. 공공조달 기본 원칙 | D13: 공공기관의 계약 및 지출 업무 담당자가 조달 업무 수행 시 원칙적으로 '경쟁적 조달 방법(경쟁입찰)'을 우선적으로 선택하여 설계해야 하는 가장 타당하고 중요한 법리적 근거는? | E13: 조달청의 적격심사 및 낙찰자 선정 과정이 시스템을 통해 완벽히 정형화되어 있어, 경험이 부족한 실무자의 행정 편의성과 업무 효율성이 수의계약 대비 대폭 향상되기 때문이다. | F13: 수의계약 시 발생할 수 있는 잦은 유찰의 위험이나 업체 간의 분쟁 소지가 적고, 궁극적으로 발주기관이 필요한 물자를 최종적으로 획득하는 데 걸리는 전체 조달 기간이 단축되기 때문이다. | G13: 오랜 기간 거래해 오며 제품의 품질이 이미 검증된 신뢰할 수 있는 특정 우수 조달기업의 몫을 확실히 챙겨주어 그들의 안정적 매출 규모를 정책적으로 보호해 줄 수 있기 때문이다. | H13: 국가 세금을 사용하는 조달 행정의 근간인 공공성 확보, 절차적 투명성 보장, 그리고 관련 업계의 기회균등이라는 공공조달 제도의 확고한 대원칙을 준수하기 위한 최우선 전제 조건이기 때문이다. | I13: 4 | J13: * 정답 (④): 조달의 기본 이념인 경쟁, 투명성, 차별금지를 공정하게 실현하는 가장 완벽하고 원칙적인 방법론이 바로 지정정보처리장치를 통한 공개 경쟁입찰입니다.
A14: 11 | B14: 1. 공공조달 원칙 | C14: 1. 공공조달 기본 원칙 | D14: 공공조달 제도를 공정하고 굳건하게 지탱하기 위해, 실무자와 기업이 가슴에 새기고 각종 법령에서 엄격하게 규정하고 있는 '3대 기본원칙(Core Principles)'을 가장 바르게 나열한 것은? | E14: 행정상 불필요한 비용을 과감히 단축하는 절차적 편의성의 원칙, 다양한 사회적 가치를 포괄적으로 실현하는 포용성의 원칙, 납품 결과에 끝까지 책임지는 사후관리 보장의 원칙 | F14: 장기간의 안정적이고 익숙한 거래를 유도하는 공급망 지속성의 원칙, 영세한 지역 중소기업을 무조건적으로 보호하는 상생협력의 원칙, 첨단 신기술을 우대하는 기술 혁신성의 원칙 | G14: 특정 자격 요건을 갖춘 자에게 참여 기회균등을 보장하는 경쟁의 원칙, 정당한 이유 없이 특정 업체를 배제하지 않는 차별금지 원칙, 심사 기준과 절차를 투명하게 공개하는 투명성의 원칙 | H14: 투입되는 국가 예산 대비 산출 효율을 무조건적으로 높이는 경제성 제일주의 원칙, 무역협정에도 불구하고 국내 기업을 무조건 우대하는 자국우대 원칙, 공정성을 중시하는 도덕적 책임의 원칙 | I14: 3 | J14: * 정답 (③): 공공조달의 흔들림 없는 3대 대원칙은 다수의 입찰을 유도하는 '경쟁', 국적이나 기업 규모를 이유로 한 부당한 진입 장벽을 없애는 '차별금지', 입찰 전 과정의 정보를 사전에 고지하는 '투명성'입니다.
A15: 12 | B15: 1. 공공조달 원칙 | C15: 2. 공공조달 실행 원칙 | D15: [상황] 어느 기관이 조달 계획을 예산 편성·재정 관리 계획과 긴밀히 연계하여 운영하기로 했다. 이러한 접근이 구현하는 실행원칙으로 가장 적절한 것은? | E15: 참여(Participation) | F15: 통합(Integration) | G15: 평가(Evaluation) | H15: 균형성(Balance) | I15: 2 | J15: * 정답 (②): 조달을 재정관리·예산편성이라는 더 큰 틀과 연계해 운영하는 것은 통합(Integration) 원칙의 구현임.
A16: 13 | B16: 1. 공공조달 원칙 | C16: 2. 공공조달 실행 원칙 | D16: [상황] 조달정책 담당자가 '중소기업이 서류 제출 부담 때문에 공공입찰 참여를 포기하는 사례가 많다'는 지적을 받고, 관련 행정절차를 간소화하기로 했다. 이 조치가 구현하는 실행원칙로 가장 적절한 것은? | E16: 참여(Participation) | F16: 통합(Integration) | G16: 균형성(Balance) | H16: 접근성(Access) | I16: 4 | J16: * 정답 (④): 중소기업 등의 시장 진입 장벽(행정 부담 등)을 낮추는 조치는 접근성(Access) 원칙의 구현임.
A17: 14 | B17: 1. 공공조달 원칙 | C17: 2. 공공조달 실행 원칙 | D17: [상황] 한 기관이 평가위원의 이해충돌 여부를 사전에 점검하고, 뇌물·향응 수수를 엄격히 금지하는 내부 규정을 강화했다. 이 조치가 구현하는 실행원칙로 가장 적절한 것은? | E17: 균형성(Balance) | F17: 청렴성(Integrity) | G17: 효율성(Efficiency) | H17: 참여(Participation) | I17: 2 | J17: * 정답 (②): 이해충돌 점검, 뇌물·향응 금지는 부패·사기를 예방하고 높은 윤리기준을 유지하는 청렴성(Integrity) 원칙의 구현임.
A18: 15 | B18: 1. 공공조달 원칙 | C18: 2. 공공조달 실행 원칙 | D18: 다음 설명이 공통적으로 가리키고 있는 공공조달의 5대 핵심 실행 원칙은? [설명] 공공기관이 조달 과정에서 단순히 최저가격을 추구하는 것을 넘어, 투입된 예산 대비 대상물의 품질, 내구성, 사후 유지비용 등을 종합적으로 고려하여 최적의 효용과 성과를 획득하는 것 | E18: 자격을 갖춘 다수의 공급자에게 동등하고 균등한 참여 기회를 폭넓게 제공하여 시장의 활력을 유도하는 경쟁성 확보의 원칙 | F18: 조달 행정의 최종 결과 및 절차적 정당성에 대해 담당자가 엄격한 책임을 지고 사후 검증을 수용하는 조달 책임성의 원칙 | G18: 입찰에 투입되는 한정된 국가 예산 대비 최적의 품질과 장기적 효용을 구하여 재정 효율성을 높이는 비용대비 가치의 원칙 | H18: 조달 과정 전반의 정보를 외부에 명확히 공개하여 공정성을 입증하고 정보의 비대칭성을 해소하는 투명성 유지의 원칙 | I18: 3 | J18: * 정답 (③): 가격 중심의 단편적 평가를 벗어나 생애주기비용(LCC)과 품질을 아울러 판단하는 것은 '비용대비 가치(Value for Money)' 원칙에 대한 설명입니다.
A19: 16 | B19: 1. 공공조달 원칙 | C19: 2. 공공조달 실행 원칙 | D19: 공공조달의 12대 원칙 중 시장에 대한 ‘참여(Participation)’ 원칙이 배제되거나 원활하게 작동하지 않을 때 우려되는 가장 치명적인 문제점은? | E19: 시장 진입 장벽이 인위적으로 높아짐에 따라 소수의 기존 공급자만이 조달 시장을 장악하는 폐쇄적인 독과점 구조가 고착화된다. | F19: 새로운 업체의 시장 진입 장벽이 지나치게 낮아져 자격 미달 업체의 난립 현상이 발생하고 계약 불이행 사태가 빈발하게 된다. | G19: 소수의 우량 업체 간 담합 횟수가 현저히 줄어들고 입찰 과정의 공정성과 투명성이 오히려 긍정적인 방향으로 강화되는 결과를 낳는다. | H19: 조달 시장에 참여하는 유효 경쟁 기업의 수가 줄어들어 조달청 등 발주기관의 계약 행정 업무 전문성이 과도하게 고도화된다. | I19: 1 | J19: * 정답 (①): 참여 기회가 차단되면 경쟁이 사라지고, 기존에 진입한 시장 지배적 사업자들만이 입찰을 독식하여 국가 예산의 낭비를 초래하게 됩니다.
A20: 17 | B20: 1. 공공조달 원칙 | C20: 2. 공공조달 실행 원칙 | D20: 공공조달의 선순환을 위한 ‘성과 평가(Evaluation)’ 기능이 제대로 작동하지 않을 경우 발생할 수 있는 행정적 위험 요소로 가장 거리가 먼 것은? | E20: 측정 가능한 객관적 핵심성과지표(KPI)가 부족하여 장기적인 관점에서 공공조달 시스템의 정책적 효과성 분석이 심각하게 제한된다. | F20: 과거 조달 사업에 대한 피드백 루프가 단절되어, 향후 유사한 사업의 조달 계획을 수립할 때 과거의 행정 오류가 그대로 반복될 수 있다. | G20: 분산된 조달 데이터가 일관되게 수집 및 정제되지 않아 통계의 신뢰성이 하락하고, 데이터 기반의 과학적인 의사결정에 활용하기 어렵다. | H20: 재정 지출 과정 전반에 대한 촘촘한 감시망이 소홀해져 횡령, 사기, 입찰 담합, 공적 자금 오남용 등 범죄 발생 위험이 직접적으로 증가한다. | I20: 4 | J20: * 정답 (④): 횡령, 자금 오남용 등의 부패 범죄는 사후적인 '성과 평가'의 부재라기보다는 내부 통제 및 '위험 관리(Risk Management)' 시스템이 미흡할 때 발생하는 직접적 위험 요소입니다.
A21: 18 | B21: 2. 공공조달 유형 | C21: 1. 중앙집중형 공공조달 | D21: 조달사업법령상 조달청에 원칙적으로 의무 구매를 요청해야 하는 '수요물자'의 품류에 해당하는 것은? | E21: 보관이 까다로운 각종 신선 식료품류 | F21: 관리가 필요한 살아있는 동·식물류 | G21: 행정 인프라에 쓰이는 일반 기계장치류 | H21: 기밀 유지가 필요한 무기 및 총포·화약류 | I21: 3 | J21: * 정답 (③): 식료품, 동·식물, 무기류는 특수성 탓에 조달청 의무 요청 대상에서 제외(자체 구매)되나, 기계장치류는 수요물자에 해당합니다.
... A23: 20 | B23: 2. 공공조달 유형 | C23: 2. 분산형 공공조달 | D23: 조달청장이 수요기관의 요청 물품을 해당 수요기관이 '직접 구매하도록 위임'할 수 있는 사유로 틀린 것은? | E23: 긴급한 재난 복구로 인해 조달청을 거치면 적기에 수요를 충족하기 어려운 경우 | F23: 조달청 내부 행정 절차상 수의계약을 체결하는 것이 매우 번거롭고 까다로운 경우 | G23: 시중 거래가 없는 신규 개발품으로 수요기관의 특수 기술과 전문성이 요구되는 경우 | H23: 국방·안보상의 사정 등으로 수요기관이 직접 구매하는 것이 국가에 명백히 유리한 경우 | I23: 2 | J23: * 정답 (②): 조달 위임은 긴급성, 안보 등 법적 사유가 있어야 하며, 단순히 조달청 입장에서 '수의계약 체결이 번거롭다'는 사유로 위임할 수 없습니다.
A24: 21 | B24: 3. 경쟁적 공공조달 방법 | C24: 1. 일반경쟁 | D24: [상황] 한 교육생이 '지명경쟁입찰이 국가계약법상 원칙적인 계약방법이고, 참가자격 제한이 없는 방식이 오히려 예외'라고 잘못 이해하고 있었다. 이 오해를 바로잡는 설명으로 가장 적절한 것은? | E24: 수의계약이 원칙이며 나머지가 예외이다 | F24: 그 이해가 맞다. 지명경쟁이 원칙이다 | G24: 참가자격 제한 없는 일반경쟁이 원칙이며, 지명경쟁은 예외적으로만 허용된다 | H24: 제한경쟁이 원칙이며 나머지가 예외이다 | I24: 3 | J24: * 정답 (③): 국가계약법상 원칙은 참가자격 제한이 없는 일반경쟁이며, 지명경쟁은 예외적 방법에 불과함. | K24: 국가계약법 제7조
A25: 22 | B25: 3. 경쟁적 공공조달 방법 | C25: 1. 일반경쟁 | D25: [상황] 발주기관이 인공위성 시스템처럼 기술적으로 매우 복잡해 사전에 완벽한 규격을 정하기 어려운 사업을 발주하려 한다. 먼저 가격을 제외한 기술제안서만 평가하고, 기술 적합 판정을 받은 업체만을 대상으로 이후 가격입찰을 실시해 낙찰자를 정하는 방식을 무엇이라 하는가? | E25: 적격심사낙찰제 | F25: 지명경쟁입찰 | G25: 협상에 의한 계약 | H25: 2단계 경쟁입찰 | I25: 4 | J25: * 정답 (④): 기술평가와 가격입찰을 단계적으로 분리해 진행하는 방식은 2단계 경쟁입찰이며, 기술 요구가 복잡해 사전 규격 확정이 어려운 사업에 활용됨.
A26: 23 | B26: 3. 경쟁적 공공조달 방법 | C26: 1. 일반경쟁 | D26: [상황] 발주기관이 대량의 표준 사무용품 구매에 2단계 경쟁입찰(기술평가+가격입찰 분리) 방식을 적용하려 한다. 이 선택에 대한 평가로 가장 적절한 것은? | E26: 적절하다. 표준화된 소모품 구매에도 항상 2단계 경쟁입찰을 적용해야 한다 | F26: 적절하다. 모든 물품 구매는 2단계 경쟁입찰이 원칙이다 | G26: 적절하지 않다. 표준 사무용품은 반드시 수의계약으로만 구매해야 한다 | H26: 적절하지 않다. 2단계 경쟁입찰은 기술적으로 복잡해 사전 규격 확정이 어려운 사업에 적합하며, 표준화된 사무용품에는 불필요한 절차 부담을 줄 수 있다 | I26: 4 | J26: * 정답 (④): 2단계 경쟁입찰은 기술 요구가 복잡해 사전 규격 확정이 어려운 사업에 적합하며, 표준화된 사무용품처럼 단순한 구매에는 오히려 불필요한 절차 부담을 줄 수 있음.
A27: 24 | B27: 3. 경쟁적 공공조달 방법 | C27: 1. 일반경쟁 | D27: [상황] 협상에 의한 계약에서 1순위 협상대상자와의 협상이 결렬되었다. 발주기관의 다음 조치로 가장 적절한 것은? | E27: 모든 절차를 처음부터 새로 시작해 재공고한다 | F27: 동일한 기준·절차에 따라 차순위 협상적격자와 협상을 이어간다 | G27: 1순위 업체와 가격만 다시 협상한다 | H27: 해당 사업을 자동으로 취소한다 | I27: 2 | J27: * 정답 (②): 협상에 의한 계약은 고득점자 순으로 순차 협상(연속협상)을 진행하며, 1순위와 결렬되면 차순위와 협상을 이어감.
A28: 25 | B28: 3. 경쟁적 공공조달 방법 | C28: 1. 일반경쟁 | D28: [상황] 전자역경매(ERA)를 도입한 기관에서 공급업체들의 납품 품질이 이전보다 다소 낮아졌다는 지적이 나왔다. 이 현상의 원인으로 가장 적절한 것은? | E28: 전자역경매는 담합을 조장하는 구조이기 때문이다 | F28: 전자역경매는 특정 업체에 대한 특혜를 유발하기 때문이다 | G28: 실시간 최저가 경쟁이 과열되면서 공급업체가 수익성 확보를 위해 품질을 낮출 유인이 생기기 때문이다 | H28: 전자역경매는 절차가 지나치게 복잡해 품질 관리가 어려워지기 때문이다 | I28: 3 | J28: * 정답 (③): 전자역경매는 실시간 최저가 발굴에는 효율적이지만, 과도한 가격 경쟁이 공급업체의 품질 저하·수익성 악화로 이어질 수 있다는 단점이 있음.
A29: 26 | B29: 3. 경쟁적 공공조달 방법 | C29: 1. 일반경쟁 | D29: 다수의 업체를 참여시키는 '경쟁입찰(Competitive Bidding)' 방식이 내포하고 있는 행정적 단점 또는 한계로 가장 적절한 것은? | E29: 까다로운 입찰 참가 자격 요건으로 인해 혁신적인 기술력을 갖춘 신생 조달기업의 입찰 참여 기회가 원천적으로 완벽히 차단된다. | F29: 법령에 정해진 표준화된 공개 절차와 공고 기간을 엄격히 준수해야 하므로 조달 물자의 최종 획득 완료까지 상당한 시간이 지연될 수 있다. | G29: 계약 체결 과정의 세부 평가 기준과 심사위원 명단 등 핵심 정보가 투명하게 공개되지 않아 절차적 공정성을 확보하기가 매우 어려워진다. | H29: 다수의 영세 업체가 무분별하게 참여함에 따라 업체 간의 기술 경쟁성이 과도하게 약화되어 최종 납품되는 대상물의 품질이 심각하게 저하된다. | I29: 2 | J29: * 정답 (②): 경쟁입찰은 공정성과 투명성을 담보하기 위해 사전 규격 공개, 공고 기간 준수, 서류 심사 등 엄격한 절차를 거치므로 필연적으로 조달 리드타임이 길어집니다.
A30: 27 | B30: 3. 경쟁적 공공조달 방법 | C30: 1. 일반경쟁 | D30: 우리나라의 국가계약법령 체계에서 명시적으로 규정하여 운영 중인 '3대 경쟁입찰 방식'을 가장 올바르게 묶은 것은? | E30: 불특정 다수를 대상으로 하는 공개경쟁입찰, 협상을 통해 낙찰자를 정하는 협상경쟁입찰, 종합 심사를 거치는 종합경쟁입찰 | F30: 가장 널리 쓰이는 일반경쟁입찰, 특정 조건을 갖춘 자로 제한하는 제한경쟁입찰, 발주자가 직접 업체를 지정하는 지명경쟁입찰 | G30: 특정 지역 업체로 한정하는 지역경쟁입찰, 지식재산권을 보호하기 위한 특허경쟁입찰, 다수의 공급자를 등록하는 다수공급자경쟁입찰 | H30: 예산 절감을 최우선으로 하는 최저가경쟁입찰, 물품의 규격을 심사하는 규격경쟁입찰, 협상 절차를 포함하는 복합경쟁입찰 | I30: 2 | J30: * 정답 (②): 법령상 경쟁입찰의 기본 형태는 참가 자격을 제한하지 않는 '일반경쟁'을 원칙으로 하며, 예외적인 요건을 충족할 경우 '제한경쟁' 및 '지명경쟁'을 허용하고 있습니다.
A31: 28 | B31: 3. 경쟁적 공공조달 방법 | C31: 1. 일반경쟁 | D31: 공공기관의 계약담당자가 특정 업체와의 수의계약 유혹을 뿌리치고 원칙에 따라 '경쟁입찰' 방식을 채택했을 때 실무적으로 얻을 수 있는 기대 효과와 가장 거리가 먼 것은? | E31: 발주기관의 재량권이 대폭 확대되어, 계약 체결 이후 상황 변화에 따라 과업지시서를 임의로 변경하거나 계약 조건을 발주자에게 유리하게 수정하는 등 계약변경의 자유가 완벽히 보장된다. | F31: 다수 업체의 치열한 투찰 가격 경쟁을 통해 시장의 합리적이고 객관적인 시장 가격(Market Price)이 자연스럽게 형성되고, 결과적으로 국고 예산이 눈에 띄게 절감된다. | G31: 다수의 예비 공급자 간의 선의의 기술 및 품질 경쟁을 유도하여, 더 뛰어난 기술력과 우수한 납품 역량을 갖춘 숨은 우량 공급자를 발굴하고 산업계 전반을 자극하고 촉진한다. | H31: 입찰 공고부터 적격심사, 최종 낙찰자 선정까지의 전 과정이 시스템을 통해 외부로 명명백백히 공개되므로 공공조달 행정 전반의 객관성과 대국민 투명성이 강력하게 강화된다. | I31: 1 | J31: * 정답 (①): 경쟁입찰은 사전에 확정하여 공고한 과업지시서와 계약 조건에 따라 투찰이 이루어지므로, 낙찰 후 기관이 임의로 과업을 변경하는 행위는 탈락한 타 업체의 기득권을 침해하는 위법 행위가 될 수 있어 오히려 계약 변경이 엄격히 통제됩니다.
A32: 29 | B32: 3. 경쟁적 공공조달 방법 | C32: 1. 일반경쟁 | D32: 누구나 참여할 수 있는 '일반경쟁입찰' 방식이 지니는 구조적 단점 및 위험 요소로 가장 타당한 것은? | E32: 기회균등 원칙 탓에 행정의 공평성이 심각하게 저해된다. | F32: 조달 절차가 투명하여 담당자의 통제력이 상실된다. | G32: 부실업체의 참여로 과당경쟁 및 품질 저하가 우려된다. | H32: 다수 업체 참여로 염가 계약이 체결되어 예산이 낭비된다. | I32: 3 | J32: * 정답 (③): 일반경쟁은 무분별한 부실업자 진입으로 인한 품질 저하 및 과당경쟁 위험이 가장 큰 단점으로 지적됩니다.
A33: 30 | B33: 3. 경쟁적 공공조달 방법 | C33: 1. 일반경쟁 | D33: 국가계약법령에 따라 발주기관이 선택할 수 있는 합법적인 정규 '경쟁입찰의 방법(방식)'에 해당하지 않는 것은? | E33: 능력이 검증된 5인 이상을 지명하는 지명경쟁입찰 | F33: 특정 객관적 실적으로 문턱을 높이는 제한경쟁입찰 | G33: 불특정 다수에게 기회를 개방하는 일반경쟁입찰 | H33: 온라인 경매로 실시간 최저가를 찾는 복수경쟁입찰 | I33: 4 | J33: * 정답 (④): 국가계약법상의 원칙적인 입찰 방식은 일반경쟁, 제한경쟁, 지명경쟁 등이며 '복수경쟁입찰'이라는 법적 분류는 존재하지 않습니다.
A34: 31 | B34: 3. 경쟁적 공공조달 방법 | C34: 1. 일반경쟁 | D34: 공공조달의 원칙적 방법인 '일반경쟁입찰'이 지니는 장단점에 대한 객관적 평가로 부적절하게 서술된 것은? | E34: 자격 미달 부실업체가 덤핑 투찰로 낙찰될 경우 심각한 계약 불이행 및 품질 저하 위험을 내포한다. | F34: 복잡한 적격자 선별 절차가 생략되어 공고부터 낙찰까지 행정 절차가 간소화되고 업무 부담이 준다. | G34: 다수 업체가 치열한 가격 경쟁을 벌여 예산 낭비를 막고 목적물을 염가에 구매할 가능성이 커진다. | H34: 모든 입찰 희망자에게 참가 자격을 폭넓게 부여하므로 공평성이 보장되고 대국민 신뢰도가 높아진다. | I34: 2 | J34: * 정답 (②): 일반경쟁은 제한이 없어 참가자가 폭증할 수 있으며, 이로 인해 제출된 서류 검토 및 심사 대상이 늘어나 오히려 행정 절차가 복잡해진다는 것이 큰 단점입니다.
A35: 32 | B35: 3. 경쟁적 공공조달 방법 | C35: 1. 일반경쟁 | D35: 공공계약의 일반 원칙 및 입찰 진행 절차에 대한 설명으로 가장 옳은 것은? | E35: 청렴계약을 위반한 경우 국가 안보 등과 무관하게 모든 계약을 해제해야 한다. | F35: 사업자등록증 등 고유번호증 서류 제출만으론 입찰참가자격이 자동 부여된다. | G35: 국가계약법령상 공공계약 체결 시 기본적으로 적용해야 하는 방식은 일반경쟁이다. | H35: 경쟁입찰은 단 1인의 유효한 입찰 참가자만 있어도 정상적으로 입찰이 성립된다. | I35: 3 | J35: 정답 (③) 일반경쟁입찰이 원칙임 / ① 국가안보 등 예외 시 유지 가능 / ② 추가 요건(면허 등) 필요 / ④ 2인 이상 유효입찰 필요 | K35: 계약법 제7조
A36: 33 | B36: 3. 경쟁적 공공조달 방법 | C36: 2. 제한경쟁 | D36: [상황] 계약담당공무원이 '평소 친분이 있는 업체와 계약하고 싶다'는 이유로 제한경쟁입찰의 참가자격을 좁게 설정하려 한다. 이 사유의 적법성에 대한 평가로 가장 적절한 것은? | E36: 적법 여부는 계약금액에 따라 달라진다 | F36: 적법하다. 담당자의 재량으로 자유롭게 정할 수 있다 | G36: 적법하지 않다. 개인적 선호는 제한경쟁의 적법한 사유가 될 수 없으며 공정성을 해치는 행위이다 | H36: 적법하다. 특수 기술 요건과 동일하게 취급된다 | I36: 3 | J36: * 정답 (③): 담당자의 개인적 선호는 제한경쟁의 적법한 사유가 될 수 없으며, 특수기술·설비 요구, 추정가격 기준 등 법령상 인정되는 사유만 정당함. | K36: 국가계약법 시행령 제21조
A37: 34 | B37: 3. 경쟁적 공공조달 방법 | C37: 2. 제한경쟁 | D37: 일반경쟁의 단점을 보완하기 위해 도입된 '제한경쟁입찰' 제도의 법적 기준과 운영 원칙에 대한 설명으로 올바른 것은? | E37: 중소기업 보호를 위해 고시금액 이하일 때만 영업소 소재지로 지역제한을 적용할 수 있다. | F37: 발주기관 임의로 2개 이상의 제한 기준(실적+지역 등)을 무제한으로 중복 적용할 수 있다. | G37: 일반경쟁의 부실업자 진입 단점을 보완하고 우량 업체의 경쟁을 유도하기 위한 제도이다. | H37: 특혜 시비를 차단하기 위해 실적 제한과 지역 제한을 동일 공고에 중복하는 것이 원칙이다. | I37: 3 | J37: * 정답 (③): 실적 및 지역 제한은 원칙적으로 중복 금지되며(특수 예외 있음), 지역제한은 고시금액 '미만(이하 아님)'일 경우에만 적용할 수 있습니다.
A38: 35 | B38: 3. 경쟁적 공공조달 방법 | C38: 2. 제한경쟁 | D38: 일반경쟁 단점을 보완하기 위해 고안된 '제한경쟁입찰' 제도의 법적·실무적 의의를 가장 정확하게 서술한 것은? | E38: 특정 업체 5인 이내만을 직접 지명하여 행정 소요일수를 획기적으로 단축하는 편의적 제도이다. | F38: 전국 단위로 개방하되 지역 업체의 투찰 금액을 일정 비율 할인해 주는 지역 상생 유인 제도이다. | G38: 신규 영세 업체의 진입을 유도하여 과당경쟁 부작용을 원천 해소하기 위한 특별 예외 제도이다. | H38: 부실업자 진입을 막고 우량 업체의 경쟁을 유도하는 일반과 지명경쟁의 중간적 보완 제도이다. | I38: 4 | J38: * 정답 (④): 제한경쟁입찰은 부실업체 진입(일반경쟁 단점)을 막고, 특혜 시비(지명경쟁 단점)를 줄이면서 일정 기준을 갖춘 다수의 경쟁을 유도하는 중간적 성격의 제도입니다.
A39: 36 | B39: 3. 경쟁적 공공조달 방법 | C39: 2. 제한경쟁 | D39: 지역제한 등 제한경쟁입찰의 적용 기준에 대한 설명으로 가장 옳은 것은? | E39: 국가기관의 지역제한은 고시금액 이상인 대규모 계약에 한정하여 엄격히 적용한다. | F39: 지자체가 물품제조실적으로 제한할 경우 그 기준은 행안부 고시금액 미만일 때이다. | G39: 지역제한 참가자는 입찰 공고일 하루만 해당 본점소재지를 유지하면 자격이 인정된다. | H39: 산업표준화법상 KS인증이나 우수단체표준인증 제품 등으로 입찰 참가자격을 제한할 수 있다. | I39: 4 | J39: 정답 (④) 품질 확보를 위해 인증 제품으로 제한 가능함 / ① 고시금액 미만 적용 / ② 고시금액 이상 / ③ 계약체결일까지 유지 | K39: 계약법 시행령
A40: 37 | B40: 3. 경쟁적 공공조달 방법 | C40: 2. 제한경쟁 | D40: 정부계약 제한경쟁입찰의 실적 및 자격 제한에 대한 설명으로 가장 옳은 것은? | E40: 국가기관이 실적으로 자격을 제한할 때는 계약목적물 규모의 1배 이내로 제한해야 한다. | F40: 농공단지 입주업체가 생산한 물품으로 참가자격을 제한하는 것은 법령상 전면 금지된다. | G40: 중소기업자간 제한경쟁 진행 시 타 법령에 명시된 제한 요건을 추가로 중복할 수 없다. | H40: 지역제한 대상자의 본점소재지는 입찰 당일에만 요건을 충족하면 유효하게 인정받는다. | I40: 1 | J40: 정답 (①) 과도한 진입장벽 방지를 위해 실적 제한은 1배 이내로 함 / ② 제한 가능 / ③ 중복 제한 가능 / ④ 계약일까지 유지 | K40: 계약법 시행령
A41: 38 | B41: 3. 경쟁적 공공조달 방법 | C41: 3. 지명경쟁 | D41: [상황] 한 담당자가 '지명경쟁입찰은 담당자가 신뢰하는 업체를 미리 골라 부르는 방식이라 오히려 공정성 시비가 적다'고 주장했다. 이 주장에 대한 평가로 가장 적절한 것은? | E41: 옳지 않다. 지명 과정에서 담당자의 주관이 개입될 소지가 있어 오히려 일반경쟁입찰보다 공정성 시비 가능성이 높다 | F41: 옳다. 지명경쟁은 원칙적 계약방법이라 문제되지 않는다 | G41: 지명경쟁과 공정성은 서로 무관한 개념이다 | H41: 옳다. 지명 절차가 있으므로 공정성 시비가 적다 | I41: 1 | J41: * 정답 (①): 지명 과정에서 담당자의 주관이 개입될 소지가 있어, 지명경쟁은 오히려 일반경쟁입찰보다 공정성 시비 가능성이 높음.
A42: 39 | B42: 3. 경쟁적 공공조달 방법 | C42: 3. 지명경쟁 | D42: 발주기관이 특정 업체를 직접 지정하는 '지명경쟁입찰' 제도의 특징과 주의사항에 대한 설명으로 틀린 것은? | E42: 유효 경쟁자가 10인 이내 소수일 경우 적용하는 등 제한경쟁입찰과는 뚜렷한 차이가 있다. | F42: 수의계약 대상이라도 특혜 시비를 줄이기 위해 지명경쟁입찰로 전환하여 집행할 수 있다. | G42: 특혜 시비를 없애기 위해 계약담당자는 사적 지인이 추천하는 업체를 우선적으로 지명해야 한다. | H42: 원칙적으로 5인 이상을 지명해야 하며, 최소 2인 이상이 참가해야 유효한 입찰로 성립된다. | I42: 3 | J42: * 정답 (③): 지명경쟁은 객관적인 기준과 협의를 통해 대상을 지명해야 하며, 사적 지인의 추천을 받아 지명하는 것은 심각한 특혜 및 유착 비리입니다. | K42: 국가계약법 시행령 제23조
A43: 40 | B43: 3. 경쟁적 공공조달 방법 | C43: 3. 지명경쟁 | D43: 지명경쟁입찰의 성립 요건 및 절차에 대한 설명으로 가장 옳은 것은? | E43: 지명경쟁입찰은 5인 이상 지명하되 실제 입찰참가신청은 단 1인만 있어도 성립한다. | F43: 수의계약 요건을 충족하는 대상 사업은 지명경쟁입찰 방식을 적용하는 것이 금지된다. | G43: 관련 요건에 해당할 경우 입찰대상자가 10인 이내일 때 지명경쟁입찰에 부칠 수 있다. | H43: 지명경쟁입찰로 체결한 모든 계약은 감사원에 대한 통지 의무가 완전히 면제되어 있다. | I43: 3 | J43: 정답 (③) 성질상 10인 이내인 경우 지명경쟁 가능 / ① 2인 이상 참가 필요 / ② 수의계약 대상도 지명 가능 / ④ 통지 의무 있음 | K43: 국가계약법 시행령 제23조 및 제24조
A44: 41 | B44: 4. 비경쟁적 공공조달 방법 | C44: 1. 수의계약 | D44: [상황] 예상치 못한 태풍으로 시설물이 붕괴되어 경쟁에 부칠 시간적 여유가 없이 즉시 복구가 필요한 상황이다. 이 경우 활용할 수 있는 계약방법으로 가장 적절한 것은? | E44: 수의계약 | F44: 일반경쟁입찰 | G44: 지명경쟁입찰 | H44: 2단계 경쟁입찰 | I44: 1 | J44: * 정답 (①): 천재지변 등으로 경쟁에 부칠 여유가 없는 긴급한 경우는 수의계약이 가능한 대표적 사유임. | K44: 국가계약법 시행령 제26조
A45: 42 | B45: 4. 비경쟁적 공공조달 방법 | C45: 1. 수의계약 | D45: 특허권 등 배타적 권리를 보유한 업체가 시장에 객관적으로 단 하나만 존재해 그 업체와 수의계약을 체결하는 경우를 가리키는 용어는? | E45: 단독공급원(Sole Source) 조달 | F45: 일반경쟁 조달 | G45: 제한경쟁 조달 | H45: 단일공급원(Single Source) 조달 | I45: 1 | J45: * 정답 (①): 단독공급원(Sole Source) 조달은 특허·저작권 등으로 공급 가능한 업체가 객관적으로 하나뿐인 경우를 말함.
A46: 43 | B46: 4. 비경쟁적 공공조달 방법 | C46: 1. 수의계약 | D46: [상황] 시장에 여러 경쟁업체가 존재함에도, 시간적 여유가 없는 긴급한 재해 복구를 이유로 그중 한 업체를 선정해 수의계약을 체결했다. 이러한 조달방식을 가리키는 용어는? | E46: 단일공급원(Single Source) 조달 | F46: 지명경쟁입찰 | G46: 단독공급원(Sole Source) 조달 | H46: 일반경쟁입찰 | I46: 1 | J46: * 정답 (①): 단일공급원(Single Source) 조달은 경쟁자가 존재함에도 긴급성 등 특별한 사유로 특정 업체 하나를 선택하는 경우를 말하며, 공급자 자체가 하나뿐인 단독공급원과 구분됨.
A47: 44 | B47: 4. 비경쟁적 공공조달 방법 | C47: 1. 수의계약 | D47: [상황] 발주기관이 '경쟁 절차 없이 특정 업체를 직접 선정해 계약을 체결'하려 한다. 이 방식이 속하는 범주로 옳은 것은? | E47: 경쟁적 조달 방법(일반경쟁의 일종) | F47: 경쟁적 조달 방법(제한경쟁의 일종) | G47: 비경쟁적 조달 방법(수의계약) | H47: 경쟁적 조달 방법(2단계 경쟁입찰의 일종) | I47: 3 | J47: * 정답 (③): 경쟁 절차 없이 특정 업체를 직접 선택하는 방식은 비경쟁적 조달 방법인 수의계약에 해당함.
A48: 45 | B48: 4. 비경쟁적 공공조달 방법 | C48: 1. 수의계약 | D48: [상황] 발주기관이 총 2억원 규모의 사업을 5천만원짜리 계약 4건으로 나누어, 각각 수의계약 가능 금액 이하로 맞춰 체결하려 한다. 이 계획에 대한 평가로 가장 적절한 것은? | E48: 적절하다. 기관장 승인만 받으면 항상 가능하다 | F48: 적절하다. 소액으로 나누면 예산 절감에 도움이 된다 | G48: 적절하지 않다. 수의계약 한도에 맞추기 위한 인위적 사업 분할은 관련 법령상 엄격히 금지된다 | H48: 적절하다. 소액 사업은 분할이 예외적으로 항상 허용된다 | I48: 3 | J48: * 정답 (③): 수의계약 제도 남용을 막기 위해, 사업을 인위적으로 분할해 수의계약 한도에 맞추는 행위는 법령상 엄격히 금지됨.
A49: 46 | B49: 4. 비경쟁적 공공조달 방법 | C49: 1. 수의계약 | D49: 국가계약법 시행령에 근거할 때, 원칙적인 경쟁입찰을 배제하고 예외적으로 '수의계약(Private Contract)'을 합법적으로 체결할 수 있는 사유에 해당하는 것은? | E49: 시중에서 쉽게 구할 수 있는 범용적이고 표준화된 규격의 일반 사무용품을 기관 운영을 위해 대량으로 일괄 구매하고자 하는 경우 | F49: 집중호우로 극심한 수해를 입은 지방자치단체가 이재민 구호와 무너진 제방의 긴급 복구를 위해 즉시 투입할 자재를 구매하는 경우 | G49: 규격과 품질이 확정된 단일 품목의 대규모 물량을 장기간에 걸쳐 정기적이고 반복적으로 특정 업체로부터 납품받아 구매해야 하는 경우 | H49: 조달 시장에 해당 품목을 전문적으로 취급하는 다수의 유력한 공급업체가 존재하여 업체 간 기술 및 가격 경쟁이 치열하게 벌어지는 경우 | I49: 2 | J49: * 정답 (②): 천재지변, 감염병 확산, 긴급 재난 복구 등 시간적 여유가 없어 입찰 공고를 거칠 수 없는 긴박한 상황은 수의계약의 대표적인 합법적 사유입니다.
A50: 47 | B50: 4. 비경쟁적 공공조달 방법 | C50: 1. 수의계약 | D50: 비경쟁적 공공조달 방식인 '수의계약'이 지니는 장점과 단점에 대한 설명으로 가장 논리적이지 않은 것은? | E50: 복잡한 입찰 공고 및 적격심사 절차가 생략되어 행정 소요 기간이 획기적으로 단축되므로, 국가적 비상사태 등 긴급한 상황에서 신속한 조달이 가능하다. | F50: 다수 업체의 치열한 경쟁을 원천적으로 배제하므로 시장 가격 변동에 따른 과도한 비용 지불 가능성과 특정 기업에 대한 특혜 시비가 필연적으로 발생할 수 있다. | G50: 다수의 유망한 예비 공급자 간의 기술 및 가격 경쟁을 자연스럽게 유도하여 공공서비스의 질을 단기간에 혁신적으로 대폭 끌어올릴 수 있는 긍정적 효과가 있다. | H50: 국가 안보 등 보안이 강하게 요구되는 민감한 사안에 대해 외부로의 정보 유출을 막고, 사전에 철저히 검증된 업체와 안정적인 거래 관계를 유지할 수 있다. | I50: 3 | J50: * 정답 (③): 다수 공급자 간의 기술 및 품질 경쟁을 유도하여 서비스의 질을 끌어올리는 것은 수의계약이 아닌 '경쟁입찰' 체제에서 기대할 수 있는 장점입니다.
A51: 48 | B51: 4. 비경쟁적 공공조달 방법 | C51: 1. 수의계약 | D51: 발주기관의 계약담당자가 경쟁입찰 대신 수의계약 방식으로 조달을 집행할 때, 훗날의 감사나 분쟁에 대비하여 법적·행정적으로 반드시 확보해 두어야 할 가장 중요한 사항은? | E51: 수의계약을 통해 체결된 계약 단가가 시장 평균가 대비 명백히 저렴하여 예산 절감에 기여했음을 증명할 수 있는 타사 대비 최저가격 입증 서류 | F51: 과업 수행에 필요한 계약 기간이 적정하게 산정되었는지, 그리고 해당 업체가 기한 내에 과업을 완수할 물리적 능력이 있는지를 증명하는 서류 | G51: 수의계약 대상자로 선정된 특정 공급자가 관련 산업 및 조달 시장 내에서 독보적인 기술력과 우월적 지위를 차지하고 있음을 보여주는 실적 증명 | H51: 해당 조달 건을 경쟁입찰에 부치지 못하고 부득이하게 수의계약으로 진행해야만 했던 합법적인 적용 사유에 대한 객관적인 근거 자료 및 내부 기록 | I51: 4 | J51: * 정답 (④): 수의계약은 원칙에 대한 중대한 예외 적용이므로, 반드시 해당 법령에 부합하는 명백한 사유와 객관적 증빙 서류를 남겨야 합니다.
A52: 49 | B52: 4. 비경쟁적 공공조달 방법 | C52: 1. 수의계약 | D52: 원칙적인 경쟁입찰의 틀을 깨고, 국가계약법 시행령에 근거하여 예외적으로 1인과의 '수의계약'을 합법적으로 집행할 수 있는 정당한 사유에 해당하지 않는 것은? | E52: 조달 업무 담당자의 과도한 행정적 서류 부담을 일거에 해소하고, 과거에 여러 차례 문제없이 거래해 오던 익숙한 특정 업체와의 원활하고 지속적인 우호 협력 관계를 유지하고자 수의계약을 맺는 경우 | F52: 특정 기업이 조달 대상물에 대한 원천 특허, 실용신안 등 배타적 지식재산권을 온전히 보유하고 있어, 현실적으로 다른 대체 업체로부터 동일한 물품이나 기술을 조달받는 것이 원천적으로 불가능한 경우 | G52: 태풍, 지진 등 천재지변이나 국가적 감염병 확산 등 초유의 긴급한 재난 상황이 발생하여, 국민의 생명과 안전을 지키기 위해 신속한 구호 및 복구 물자가 즉각적으로 필요한 경우 | H52: 해당 조달 대상물을 생산하거나 공급할 수 있는 자격을 갖춘 조달기업이 시장에 단 하나만 존재하거나, 고도의 국방 안보상 기밀 유지를 위해 특정 업체와 수의계약을 맺는 것이 국가에 명백히 유리하다고 판단되는 경우 | I52: 1 | J52: * 정답 (①): 담당자의 행정 편의주의나 특정 업체와의 친분, 거래 관행을 이유로 한 수의계약 체결은 관련 법규 위반이며 심각한 특혜 및 유착 비리로 처벌받을 수 있는 대표적 부적절 사례입니다.
A53: 50 | B53: 4. 비경쟁적 공공조달 방법 | C53: 1. 수의계약 | D53: 국가 재정을 집행함에 있어 수의계약 방식을 무리하게 적용하기에 가장 부적절하여, 훗날 특정 업체에 대한 감사 및 특혜 시비가 발생할 소지가 가장 다분한 사례는? | E53: 집중호우로 크게 유실된 하천 제방을 장마철이 본격적으로 시작되기 전 신속히 원상 복구하기 위해 불가피하게 투입되는 긴급 재난 구호 건설 공사 | F53: 국가정보원이나 국방부 등에서 국가 안보와 직결되어 세부 제원이나 수량이 외부 적대 세력에게 절대 유출되어서는 안 되는 고도의 특수 방산장비 구매 | G53: 시장에 대체품이 존재하고 다수 업체의 경쟁이 충분히 가능한 범용 품목임에도 불구하고, 단지 발주 편의를 위해 과거 거래 실적이 있는 특정 기업과 체결하는 반복적 계약 | H53: 기관 내부의 핵심 행정망 서버 교체 시 기존 구축된 데이터베이스 시스템과의 호환성 문제로 인해 대체 기술이나 호환 가능 소프트웨어가 전혀 없는 독점 전문 시스템의 도입 | I53: 3 | J53: * 정답 (③): 경쟁이 가능한 품목을 명확한 법적 사유 없이 행정 편의를 위해 특정 기업과 지속적으로 수의계약하는 것은 공정성을 크게 훼손하는 행위입니다.
A54: 51 | B54: 4. 비경쟁적 공공조달 방법 | C54: 1. 수의계약 | D54: 경쟁입찰을 실시하였으나 원활한 낙찰자가 선정되지 않아, 예외적으로 '수의계약'으로 전환할 수 있는 사유 중 틀린 것은? | E54: 낙찰자가 결정되었으나 정당한 사유 없이 기일 내에 계약을 체결하지 않아 사업이 지연되는 경우 | F54: 1차 입찰자가 1인뿐이며, 재공고 시에도 참가 자격을 갖춘 자가 1인뿐임이 명백히 인정되는 경우 | G54: 1순위자가 적격심사 점수 미달로 탈락할 경우, 차순위자 심사를 생략하고 즉시 수의계약으로 전환하는 경우 | H54: 재공고 입찰에 부친 경우로서 입찰에 참여한 자가 없거나 조건을 만족하는 유효한 낙찰자가 없는 경우 | I54: 3 | J54: * 정답 (③): 1순위자가 적격심사에서 탈락하면 즉시 수의계약으로 넘어가는 것이 아니라, 차순위자(2순위, 3순위 순)를 대상으로 적격심사를 계속 실시해야 합니다.
A55: 52 | B55: 4. 비경쟁적 공공조달 방법 | C55: 1. 수의계약 | D55: 국가계약법령에 따라 경쟁입찰의 예외로서 '수의계약'을 체결할 수 있는 법적 요건에 해당하지 않는 것은? | E55: 물품 제조·구매 시 사전에 적절한 규격이나 과업지시서 작성이 곤란한 경우 | F55: 긴급 상황 등으로 인해 경쟁에 부칠 여유가 없거나 목적 달성이 곤란한 경우 | G55: 특정인의 기술이 필요하거나 물품 생산자가 단 1인뿐이라 경쟁이 불가한 경우 | H55: 중소기업자가 직접 생산한 제품을 해당 기업으로부터 예외적으로 구매하는 경우 | I55: 1 | J55: * 정답 (①): '미리 적절한 규격 등의 작성이 곤란한 경우'는 수의계약이 아니라, 먼저 규격(제안)을 받아 심사하는 **'2단계 경쟁입찰'**의 적용 대상입니다. (나머지는 모두 수의계약 사유)
A56: 53 | B56: 4. 비경쟁적 공공조달 방법 | C56: 1. 수의계약 | D56: 수의계약 가능 대상 및 운영 규정에 대한 설명으로 가장 옳은 것은? | E56: 소프트웨어 품질인증(GS)을 받은 중소기업 제품은 원칙적으로 수의계약 대상이 아니다. | F56: 우수조달공동상표로 지정된 물품이라도 수의계약을 체결할 수 있는 금액 한도가 존재한다. | G56: 수의계약을 체결하려 할 때 반드시 사전 경쟁입찰을 먼저 진행하여 2회 유찰되어야 한다. | H56: 특허나 실용신안을 받은 물품은 별도 용도 검토 없이 무조건 수의계약으로만 체결한다. | I56: 2 | J56: 정답 (②) 지정 상표라도 금액 등에 따른 세부 제한이 있음 / ① GS인증 제품 수의 가능 / ③ 여유 없을 시 바로 가능 / ④ 대체 가능성 등 검토 필요 | K56: 국가계약법 시행령 제26조
A57: 54 | B57: 4. 비경쟁적 공공조달 방법 | C57: 1. 수의계약 | D57: 특정 물품 및 대상자에 대한 수의계약 적용 기준 중 가장 옳은 것은? | E57: 추정가격 1억 원 이하 물품 구매 시 소기업·소상공인 전용 수의계약을 진행할 수 있다. | F57: 신기술 인증 물품의 수의계약은 연장 신청 없이도 최초 지정 후 최장 6년까지 자동으로 유효하다. | G57: 국가유공자나 장애인 일자리 지원 목적의 계약은 수의계약 진행이 불가능하다. | H57: 수의계약으로 체결한 사안은 감사원 통지 의무가 항상 면제된다. | I57: 1 | J57: 정답 (①) 소기업·소상공인 대상 특례 수의계약 가능 / ② 자동 연장이 아니라 별도 절차로 연장해야 최대 6년까지 인정됨 / ③ 지원 목적 수의 가능 / ④ 통지 의무는 항상 면제되지 않음 | K57: 국가계약법 시행령 제26조
A58: 55 | B58: 4. 비경쟁적 공공조달 방법 | C58: 1. 수의계약 | D58: 유찰 등에 따른 수의계약 전환 요건으로 가장 옳은 것은? | E58: 재공고입찰이 유찰된 경우에는 반드시 한 번 더 재공고를 한 후 수의계약으로 전환한다. | F58: 경제위기 극복 특례 기간 내에는 최초 입찰에서 1인만 입찰한 경우에도 수의계약이 가능하다. | G58: 입찰 실시 후 수의계약으로 전환할 때 최초 입찰에 정한 모든 조건을 자유롭게 변경할 수 있다. | H58: 추정가격 1억 원 이하의 소액 수의계약은 사유서 등 수의계약 근거서류 비치 의무가 없다. | I58: 2 | J58: 정답 (②) 특례 적용 시 1인 입찰 단독 유찰이어도 재공고 없이 수의 전환 가능 / ① 재공고 유찰 시 바로 수의 가능 / ③ 조건 변경 금지 원칙 / ④ 근거 비치해야 함 | K58: 국가계약법 시행령 제27조
A59: 56 | B59: 4. 비경쟁적 공공조달 방법 | C59: 1. 수의계약 | D59: 재입찰이나 수의계약 전환 시 최초 입찰 조건 중 예외적으로 변경이 허용되는 것은? | E59: 과업 내용서 및 납품 일자 | F59: 입찰서 제출 기한 및 보증금 | G59: 입찰 참가 자격 면허 기준 | H59: 낙찰자 결정 및 평가 방식 | I59: 2 | J59: 정답 (②) 원칙적으로 조건 변경이 금지되나, 원활한 추진을 위해 '기한'과 '보증금'에 한해서만 변경이 허용됨 | K59: 국가계약법 시행령 제27조
A60: 57 | B60: 4. 비경쟁적 공공조달 방법 | C60: 2. 소액구매 | D60: [상황] 한 기관이 소모품 등 반복적인 소액 구매마다 정식 입찰 절차를 거치느라 행정 부담이 크다는 문제를 겪고 있다. 이 문제를 해결하기 위해 도입할 수 있는 제도로 가장 적절한 것은? | E60: 모든 구매를 국제입찰로 전환 | F60: 정부구매카드를 활용한 소액구매 절차 도입 | G60: 대규모 공사 발주 절차 강화 | H60: 특정 대기업과의 장기 전속계약 체결 | I60: 2 | J60: * 정답 (②): 정부구매카드를 활용한 소액구매 절차는 빈번한 소규모 구매의 행정비용·시간을 절감해 업무 효율성을 높이기 위해 도입됨.
A61: 58 | B61: 4. 비경쟁적 공공조달 방법 | C61: 2. 소액구매 | D61: 조달 행정의 효율성을 위해 운영되는 '소액수의계약' 제도의 구체적인 적용 기준 및 운영 방식에 대한 실무적 설명으로 가장 올바른 것은? | E61: 소액수의계약 제도는 행정의 남용을 막기 위해 대상 물품이나 일반 용역의 추정가격이 1억 원 미만으로 산정된 경우에 한정하여 매우 엄격히 예외적으로만 적용된다. | F61: 견적서 제출을 안내하는 공고문은 견적서 제출 마감일의 전일을 기준으로 기산하여 영업일 기준 최소 5일 이상 나라장터에 공고하여야 한다. | G61: 추정가격이 2천만 원 이상 1억 원 미만이라도 2인 이상의 견적을 받는 다자간 입찰 방식은 원칙적으로 금지된다. | H61: 대상 물품의 추정가격이 2천만 원 이하(특정 요건 충족 시 5천만 원 등 예외 있음)인 소액 조달 건의 경우에는, 지정정보처리장치를 통하지 않고 단일 공급자가 제출한 1인 수기 견적서만으로도 계약 체결이 가능하다. | I61: 4 | J61: * 정답 (④): 소액수의 대상 금액 기준은 추정가격 1억 원 '이하'입니다. 2천만 원 이하는 1인 견적이 가능하지만, 2천만 원 초과~1억 원 이하는 다자간 전자 견적을 원칙으로 합니다. 견적 제출 안내 공고는 최소 3일 이상입니다.
A62: 59 | B62: 4. 비경쟁적 공공조달 방법 | C62: 2. 소액구매 | D62: 조달청 및 공공기관의 내자 물품 '소액구매' 기준 및 약자 보호 절차에 대한 설명으로 올바르지 않은 것은? (추정가격 기준) | E62: 영세한 소액 조달(2천만 원 이하) 건은 공고 없이 1인 견적 수의계약이 허용된다. | F62: 2천만 원 초과 1억 원 이하인 경우 원칙적으로 다자간 전자 견적 공고를 실시한다. | G62: 간소화된 절차를 밟을 수 있는 소액구매 추정가격의 기본 범위는 1억 원 이하이다. | H62: 5천만 원 초과 1억 원 이하일 경우 여성기업 대상 1인 견적 특례가 무조건 적용된다. | I62: 4 | J62: * 정답 (④): 사회적 약자 기업(여성기업 등)에 대한 1인 견적 수의계약 특례 상한액은 추정가격 '5천만 원 이하'입니다. 초과 시 특례를 적용할 수 없습니다.
A63: 60 | B63: 4. 비경쟁적 공공조달 방법 | C63: 2. 소액구매 | D63: 소액수의계약 및 전자견적 제출 규정에 대한 설명으로 가장 옳은 것은? | E63: 소액수의계약을 진행할 때 견적서 제출 가능 업체를 지역 본점소재지로 제한할 수 없다. | F63: 수의계약은 입찰 절차가 아니므로 참가자들은 입찰참가 요건을 전혀 준용받지 않는다. | G63: 5천만 원 초과 계약도 전자조달시스템을 통하지 않고 임의로 직접 견적서를 수령한다. | H63: 장애인기업 등 특정 기업은 5천만 원 이하 계약 시 1인의 견적서 제출로 수의계약이 가능하다. | I63: 4 | J63: 정답 (④) 여성·장애인기업 등은 5천만 원 이하 1인 수의 가능 / ① 지역제한 가능 / ② 참가 요건 준용함 / ③ 2천만(또는 5천만) 초과 시 전자견적 의무 | K63: 국가계약법 시행령 제30조
A64: 61 | B64: 1. 공공조달 원칙 | C64: 1. 공공조달 기본 원칙 | D64: 공공조달 원칙의 기본 개념/원칙으로 가장 적절한 것은? | E64: 구두 합의가 문서보다 우선한다. | F64: 담당자 편의에 따라 공개·기록을 생략할 수 있다. | G64: 기준·절차를 사전에 명확히 하고 동일하게 적용하여 공정성과 투명성을 확보한다. | H64: 상황에 따라 사후에 기준을 바꾸어도 무방하다. | I64: 3 | J64: * 정답 (③): 원칙(사전확정·공개·기록·동일적용)은 감사·분쟁 리스크를 줄이는 핵심이다. | M64: AAA
A65: 62 | B65: 1. 공공조달 원칙 | C65: 1. 공공조달 기본 원칙 | D65: 다음 중 공공조달 원칙 관련 실무통제(리스크 관리)로 가장 적절한 것은? | E65: 평가기준은 입찰 마감 후 필요에 따라 조정한다. | F65: 계약조건은 낙찰자와 구두로만 정한다. | G65: 요구사항·평가기준·검수기준·변경절차를 문서화하고 이해관계자에게 사전 공유한다. | H65: 검수는 생략하고 하자 발생 시 추후 협의한다. | I65: 3 | J65: * 정답 (③): 문서화+사전공유는 분쟁 예방, 성과관리, 책임소재 명확화에 가장 효과적이다. | M65: AAA
A66: 63 | B66: 1. 공공조달 원칙 | C66: 1. 공공조달 기본 원칙 | D66: 다음 중 공공조달 원칙에 관한 설명으로 옳은 것은? | E66: 절차는 내부 방침만 따르면 되며 외부 기준은 고려하지 않는다. | F66: 입찰·계약 단계에서 이해상충은 문제되지 않는다. | G66: 사전공개는 원칙이 아니라 선택사항이다. | H66: 조달절차의 각 단계는 관련 규정에 따라 수행되며, 핵심 판단은 기록으로 남겨야 한다. | I66: 4 | J66: * 정답 (④): 절차 준수와 기록(근거)은 공공조달에서 필수 요건이다. | M66: AAA
A67: 64 | B67: 1. 공공조달 원칙 | C67: 1. 공공조달 기본 원칙 | D67: OECD 공공조달 12대 원칙 중 '기본원칙(5개)'에 해당하지 않는 것은? | E67: 투명성(Transparency) | F67: 비용 대비 가치(Value for Money) | G67: 경쟁(Competition) | H67: 청렴성(Integrity) | I67: 4 | J67: * 정답 (④): OECD 12대 원칙에서 기본원칙은 투명성·비용 대비 가치(VfM)·경쟁·차별금지 및 동등대우·책임성의 5가지이다. 청렴성(Integrity)은 기본원칙이 아닌 실행원칙 7개 중 하나에 해당한다. 실행원칙에는 청렴성 외에도 접근성·효율성·균형성·참여·전자조달·역량개발 등이 있다. | M67: AAA
A68: 65 | B68: 1. 공공조달 원칙 | C68: 1. 공공조달 기본 원칙 | D68: 투명성(Transparency) 원칙을 확보하는 가장 효과적인 수단으로 옳은 것은? | E68: 수의계약 방식의 적극적 활용 | F68: 입찰 참가자에게만 선별적으로 정보를 제공하는 절차 설계 | G68: 공개적이고 경쟁적인 입찰 절차의 실행 | H68: 평가 기준을 낙찰자 발표 후에 공개하여 이의 제기를 방지 | I68: 3 | J68: * 정답 (③): 공개적이고 경쟁적인 입찰 절차는 입찰 참여자 전원에게 동일한 정보를 동시에 제공하고 평가 기준과 결과를 사전·사후에 공개함으로써 투명성을 확보하는 가장 효과적인 수단이다. 이는 청렴성(Integrity) 향상에도 직접적으로 기여한다. | M68: AAA
A69: 66 | B69: 1. 공공조달 원칙 | C69: 1. 공공조달 기본 원칙 | D69: 비용 대비 가치(Value for Money) 원칙에 관한 설명으로 옳지 않은 것은? | E69: 최저가격이 반드시 최선의 선택은 아니다. | F69: 총소유비용(TCO)과 생애주기비용(LCC) 관점에서 운영·유지·폐기 비용까지 종합적으로 고려해야 한다. | G69: 공급자 역량, 정책 목표 달성 여부까지 포괄하여 판단한다. | H69: VFM 원칙에서는 품질이나 성과보다 조달 시점의 단가를 항상 최우선으로 고려해야 한다. | I69: 4 | J69: * 정답 (④): VFM은 비용·품질·기타 요소의 최적 조합을 확보하는 것으로, 단순히 구매 시점의 최저가를 추구하는 개념이 아니다. 총소유비용(TCO)·생애주기비용(LCC)을 고려하고, 공급자 역량·정책 목표까지 종합적으로 평가하여 진정한 가치를 추구해야 한다. | M69: AAA
A70: 67 | B70: 1. 공공조달 원칙 | C70: 1. 공공조달 기본 원칙 | D70: 경쟁(Competition) 원칙에 관한 설명으로 옳은 것은? | E70: 경쟁은 그 자체가 목적이며 다른 원칙들과 무관하게 독립적으로 기능한다. | F70: 경쟁은 투명성·책임성·공정성·청렴성을 동시에 구현하는 통합적 장치이다. | G70: 수의계약이 VFM 달성에 있어 공개경쟁입찰보다 일반적으로 더 효과적이다. | H70: 경쟁 절차에서 산출되는 입찰서·평가표 등의 기록은 감사에 활용할 수 없다. | I70: 2 | J70: * 정답 (②): 경쟁은 비용 대비 가치 확보를 위한 핵심 수단이면서, 동시에 투명성·책임성·공정성·청렴성을 구현하는 통합적 장치이다. 공개경쟁 절차를 통해 특정 업체에 대한 편향을 차단하고, 경쟁 과정에서 생성된 기록은 사후 감사와 이의 제기의 근거로 활용된다. | M70: AAA
A71: 68 | B71: 1. 공공조달 원칙 | C71: 1. 공공조달 기본 원칙 | D71: 차별금지·동등대우(Non-discrimination and Equal Treatment) 원칙에 관한 설명으로 옳지 않은 것은? | E71: 국적·출신지 등 조달 목적과 관련 없는 요소에 의한 참여 제한을 배제한다. | F71: 특정 업체 제품에만 부합하는 규격 설정은 이 원칙에 위배될 수 있다. | G71: WTO 정부조달협정(GPA), UN 모델법, EU 지침 등 국제기준에서 핵심 원칙으로 채택한다. | H71: 자국 산업 보호를 위해 외국 기업의 입찰 참가를 일반적으로 제한하는 것은 허용된다. | I71: 4 | J71: * 정답 (④): 차별금지·동등대우 원칙은 국적·출신지 등 조달 목적과 무관한 요소에 의한 참여 제한을 배제하는 것이다. 자유무역 체제하에서 자국 기업 보호를 이유로 외국 기업의 입찰을 일반적으로 제한하는 것은 WTO GPA·UN 모델법·OECD 권고 등 국제기준에 위배된다. | M71: AAA
A72: 69 | B72: 1. 공공조달 원칙 | C72: 1. 공공조달 기본 원칙 | D72: 책임성(Accountability) 원칙의 구현 방식에 관한 설명으로 옳지 않은 것은? | E72: 조달 활동의 기록과 결과를 이해관계자가 열람·확인할 수 있는 체계를 마련한다. | F72: 공급업체가 조달 절차에 대해 이의를 제기할 수 있는 공식 경로를 제공한다. | G72: 이해관계자가 제기한 문제에 대한 처리 결과를 공개적 방법으로 환류한다. | H72: 조달 담당자에게 완전한 재량을 부여하고 외부 검토 없이 의사결정을 집중시킨다. | I72: 4 | J72: * 정답 (④): 책임성은 의사결정과 결과에 대한 설명·달성 책임을 의미한다. 조달 담당자에게 무제한 재량을 부여하고 외부 검토를 배제하는 방식은 오히려 책임성을 약화시킨다. 책임성 구현을 위해서는 정보 접근 보장, 이의 제기 절차, 피드백 체계, 성과 보고의 4가지 요소가 갖추어져야 한다. | M72: AAA
A73: 70 | B73: 1. 공공조달 원칙 | C73: 1. 공공조달 기본 원칙 | D73: 공공조달 5대 기본원칙의 상호관계에 관한 설명으로 옳지 않은 것은? | E73: 투명성이 확보되어야 다수의 공급자가 참여하는 공정한 경쟁이 가능하다. | F73: 경쟁 환경이 형성되어야 가격·품질의 최적 조합인 VFM을 달성할 수 있다. | G73: 5개 기본원칙 중 하나가 약화되더라도 나머지 원칙들은 독립적으로 실효성을 유지한다. | H73: 차별금지 원칙은 공정한 경쟁의 전제 조건으로 전 단계에 걸쳐 공정성의 기반으로 작동한다. | I73: 3 | J73: * 정답 (③): 5개 기본원칙은 독립적으로 존재하는 것이 아니라 상호 보완하고 강화하는 유기적 관계를 형성한다. 어느 하나의 원칙이 무너지면 다른 원칙의 실효성도 함께 약화된다. 예컨대 투명성이 확보되지 않으면 경쟁과 책임성 모두 형해화될 수 있으므로, 5개 원칙은 동시에 충족되어야 한다. | M73: AAA
A74: 71 | B74: 1. 공공조달 원칙 | C74: 1. 공공조달 기본 원칙 | D74: 공공조달의 5대 기본 원칙에 관한 설명으로 옳지 않은 것은? | E74: 경제성 원칙 — 최소 비용으로 최대 가치를 실현해야 한다. | F74: 공정성 원칙 — 입찰 참가자에게 차별 없는 동등한 기회를 보장한다. | G74: 투명성 원칙 — 절차와 의사결정을 공개하고 추적 가능성을 확보한다. | H74: 비밀보장 원칙 — 모든 입찰·계약 정보는 절대 공개하지 않는 것이 원칙이다. | I74: 4 | J74: * 정답 (④): 공공조달은 투명성 원칙을 기본으로 하며, 입찰가 등 일부 정보는 개찰 전까지만 비밀이 유지된다. 모든 정보의 절대적 비공개는 투명성 원칙과 정면으로 충돌한다. | M74: AAA
A75: 72 | B75: 1. 공공조달 원칙 | C75: 1. 공공조달 기본 원칙 | D75: 효율성 원칙과 공정성 원칙이 충돌할 때의 조정 방향으로 옳은 것은? | E75: 효율성을 절대 기준으로 삼아 공정성을 후순위로 둔다. | F75: 공정성을 절대 기준으로 삼아 효율성을 무시한다. | G75: 두 원칙은 양립 불가능하므로 사안별로 한쪽만 선택한다. | H75: 두 원칙은 균형 있게 추구하되, 절차의 형식성을 통해 양자를 동시에 보장한다. | I75: 4 | J75: * 정답 (④): 공공조달의 5대 원칙은 상호 보완 관계로, 절차의 형식성(공고·공개·기록)을 통해 효율성과 공정성을 동시에 확보하는 것이 원칙이다. 한쪽 원칙의 절대적 우선은 인정되지 않는다. | M75: AAA
... A123: 120 | B123: 4. 비경쟁적 공공조달 방법 | C123: 1. 수의계약 | D123: 시범특례에 따른 계약 제도에 관한 설명으로 옳은 것은? | E123: 2022년 9월 15일부터 시행 중이며, 신기술·신산업 분야의 혁신적 제품을 적시 조달하기 위한 제도이다. | F123: 조달청장이 별도 심의 없이 단독으로 시범특례 적용 여부를 결정한다. | G123: 시범특례는 영구적으로 적용되며 별도의 기간 제한이 없다. | H123: 일반경쟁입찰 절차를 강화하는 추가적 통제 장치이다. | I123: 1 | J123: * 정답 (①): 시범특례는 기존 계약 방법으로는 신기술·신산업 분야 혁신적 제품을 조달시장에 적시 투입하기 어려운 문제를 해결하기 위해 도입된 제도이다. 재정경제부 장관이 공공조달제도개선위원회의 심의를 거쳐 한시적(2년 범위, 연장 가능)으로 별도의 기준·절차를 적용할 수 있도록 허용한다. | M123: AAA
A124: 121 | B124: 4. 비경쟁적 공공조달 방법 | C124: 1. 수의계약 | D124: 수의계약의 장점과 거리가 먼 것은? | E124: 절차 간소화 | F124: 신속한 계약 체결 | G124: 공정성 및 투명성 확보 | H124: 조달기관에 적합한 조달 대상물을 확보할 가능성 향상 | I124: 3 | J124: * 정답 (③): 수의계약은 특정 업체와 임의로 계약을 체결하는 방식이므로 신속성과 절차 간소화 등의 장점이 있으나, 경쟁입찰에 비해 공정성과 투명성 확보에는 불리하다. | K124: 공공조달관리사 수험자용 예제문제

Sheet 1-3_전자조달시스템
A2: 공공조달과 법제도 이해 - 3. 전자조달시스템
A3: 번호 | B3: 세부항목 | C3: 세세항목 | D3: 문제 내용 | E3: 보기① | F3: 보기② | G3: 보기③ | H3: 보기④ | I3: 정답 번호 | J3: 해설 및 오답노트 | K3: 출처 | L3: 개정일자 | M3: 숫자문제
A4: 1 | B4: 1. 전자조달시스템 개요 | C4: 1. 전자조달시스템 개념 | D4: [상황] 한 신입 직원이 '전자조달은 그냥 정부가 인터넷으로 물건 사는 거 아니냐'고 간단히 이해하고 있었다. 이 이해를 보완하는 정확한 설명으로 가장 적절한 것은? | E4: 전자조달은 ICT를 기반으로 조달 계획 수립부터 대금지급까지 전 과정을 온라인으로 처리해 공정성·투명성을 실현하는 시스템·방식이다 | F4: 전자조달은 계약은 오프라인, 대금지급만 온라인으로 이뤄지는 방식이다 | G4: 전자조달은 개인이 쇼핑몰에서 물건을 사는 것과 동일한 개념이다 | H4: 전자조달은 기업 간 상거래 전반을 가리키는 일반적 용어이다 | I4: 1 | J4: * 정답 (①): 전자조달은 ICT 기반으로 조달의 전 과정을 온라인화해 공정성·투명성 등 공공가치를 실현하는 시스템·방식임.
A5: 2 | B5: 1. 전자조달시스템 개요 | C5: 1. 전자조달시스템 개념 | D5: [상황] 한 수요기관이 경쟁입찰을 진행하면서 편의상 이메일로 입찰서를 접수받으려 했다. 이 방식이 전자조달법상 원칙에 부합하는지에 대한 평가로 가장 적절한 것은? | E5: 부합한다. 방문·우편·이메일 중 담당자가 자유롭게 선택할 수 있다 | F5: 부합한다. 이메일도 전자적 수단이므로 문제없다 | G5: 이 사안은 전자조달법의 규율 대상이 아니다 | H5: 부합하지 않는다. 경쟁입찰은 지정된 전자조달시스템을 이용한 전자입찰을 원칙으로 한다 | I5: 4 | J5: * 정답 (④): 경쟁입찰은 이메일이 아니라 지정된 전자조달시스템을 이용한 전자입찰을 원칙으로 함. | K5: 전자조달의 이용 및 촉진에 관한 법률 제9조
A6: 3 | B6: 1. 전자조달시스템 개요 | C6: 1. 전자조달시스템 개념 | D6: 국가전자조달시스템을 도입하여 조달 업무를 수행하는 가장 근본적이고 핵심적인 목적은 무엇인가? | E6: 예산 절감을 위해 민간 쇼핑몰보다 무조건 최저가로 구매하기 위함 | F6: 조달 행정의 투명성, 공정성, 효율성을 시스템으로 구현하기 위함 | G6: 실무자의 수기 결재를 줄이고 전산 장비 활용 능력을 배양하기 위함 | H6: 입찰 참여 업체의 수를 시스템으로 제한하여 행정 과부하를 막기 위함 | I6: 2 | J6: * 정답 (②): 전자조달의 궁극적 목적은 단순히 저렴하게 사는 것을 넘어, 공공조달의 3대 핵심 가치(효율, 공정, 투명)를 시스템적으로 확보하는 데 있습니다.
A7: 4 | B7: 1. 전자조달시스템 개요 | C7: 1. 전자조달시스템 개념 | D7: 수요기관과 조달업체 간의 조달 업무 전 과정을 전자적으로 1회 등록하여 모든 공공기관 입찰에 참여할 수 있게 해주는 '국가종합전자조달시스템'의 공식 약칭은? | E7: DAPA (Defense Acquisition Program Administration) | F7: NIPA (National IT Industry Promotion Agency) | G7: KONEPS (Korea On-line E-Procurement System) | H7: KOMSCO (Korea Minting and Security Printing Corporation) | I7: 3 | J7: * 정답 (③): 나라장터의 공식 영문 명칭은 Korea On-line E-Procurement System이며, 줄여서 KONEPS(코넵스)라고 부릅니다.
A8: 5 | B8: 1. 전자조달시스템 개요 | C8: 2. 전자조달시스템 유형 | D8: [상황] 조달 시스템의 발전 단계를 오프라인 처리, 내부 전산화, 온라인 정보교환, 온라인 거래처리, 통합 플랫폼 구축의 순서로 구분하는 이론이 있다고 하자. 조달 전 과정을 하나의 시스템에서 단일 창구로 처리하는 나라장터는 이 구분에서 어느 단계에 가장 가까운가? | E8: 중간 단계(내부 전산화) | F8: 이 구분과는 무관하다 | G8: 가장 발전된 단계(통합 플랫폼) | H8: 가장 초기 단계(오프라인 처리) | I8: 3 | J8: * 정답 (③): 조달 전 과정을 하나의 시스템에서 단일 창구로 통합 처리하는 나라장터는 통합 플랫폼 구축이라는 가장 발전된 단계에 해당하는 것으로 설명됨(구체적 단계 구분·명칭은 참고 문헌에 따라 다를 수 있음).
A9: 6 | B9: 1. 전자조달시스템 개요 | C9: 3. 전자조달시스템 운영환경 | D9: 투찰 시 입찰 대리인의 불법 대리 투찰을 막고 정확한 신원확인을 위해 도입된 인증 수단 중, 단독으로는 신원확인 효력이 없는 것은? | E9: 조달청이 제공하는 나라장터 스마트폰 전용 앱 인증 | F9: 블록체인 기술이 적용된 모바일 신분증 기반 본인 인증 | G9: 카카오, 네이버 등 민간 플랫폼 기반의 개인용 간편인증 | H9: 법인 및 개인사업자 명의로 발급된 기존 사업자용 공동인증서 | I9: 4 | J9: * 정답 (④): 사업자 범용 공동인증서(NPKI)는 기업 단위로 발급되어 파일 복사와 비밀번호 공유가 가능하므로, 단독으로는 투찰자를 특정할 수 없습니다. 과거 필수였던 지문인식 의무가 전면 폐지(2024.1.)됨에 따라, 현재는 모바일 간편인증이나 개인용 인증서 등을 필수적으로 병행해야 합니다.
A10: 7 | B10: 1. 전자조달시스템 개요 | C10: 3. 전자조달시스템 운영환경 | D10: 최근 개편된 차세대 나라장터 시스템의 통합로그인 체계에서, 사용자의 편의성과 보안을 위해 지원하는 인증 수단에 해당하지 않는 것은? | E10: 스마트폰 카메라를 이용한 안면 및 홍채 인식 생체 인증 | F10: 카카오, 네이버, 토스 등을 활용한 민간 개인용 간편 인증 | G10: 스마트폰에 발급받아 사용하는 국가 공인 모바일 신분증 | H10: 기업 범용 공동인증서(NPKI) 및 금융결제원 금융인증서 | I10: 1 | J10: * 정답 (①): 차세대 나라장터는 편의를 위해 간편인증, 모바일 신분증 등을 폭넓게 도입했으나, 기기 종속성이 강하고 오인식 우려가 있는 단독 '홍채 인식'은 공식 인증 수단으로 제공하지 않습니다.
A11: 8 | B11: 1. 전자조달시스템 개요 | C11: 4. 전자조달시스템 구성요소 | D11: [상황] 나라장터의 보안 체계를 소개하는 자료에서 '모든 입찰 과정이 예외 없이 블록체인으로만 처리된다'고 설명했다. 이 설명에 대한 평가로 가장 적절한 것은? | E11: 부정확하다. 나라장터는 보안체계 자체를 갖추고 있지 않다 | F11: 정확하다. 블록체인이 유일한 보안수단이다 | G11: 부정확하다. 나라장터는 지문인증·암호화·전자서명 등을 함께 활용하며, 모든 과정이 블록체인 기반인 것은 아니다 | H11: 정확하다. 나라장터의 모든 절차는 블록체인 기반이다 | I11: 3 | J11: * 정답 (③): 나라장터는 지문인증·암호화·전자서명 등으로 보안을 유지하며, 모든 입찰과정이 블록체인 기반으로 운영되는 것은 아님.
A12: 9 | B12: 1. 전자조달시스템 개요 | C12: 4. 전자조달시스템 구성요소 | D12: 전자문서 시스템의 정보보안 4대 핵심 요소와 이를 구현하기 위한 대표적인 기술적 수단이 서로 잘못 연결된 것은? | E12: 무결성 - 전자문서가 위변조되지 않았음을 증명하는 해시함수(Hash) 기술 적용 | F12: 기밀성 - 비인가자의 데이터 열람을 방지하기 위한 암호화 및 접근제어 | G12: 부인방지 - 비인가자의 문서 열람 및 정보 유출을 차단하는 데이터 암호화 기술 | H12: 가용성 - 정당한 사용자의 원활한 접근을 보장하는 시스템 이중화 및 백업 관리 | I12: 3 | J12: * 정답 (③): 비인가자의 데이터 열람 및 유출을 방지하는 '암호화 기술'은 부인방지가 아닌 '기밀성'을 확보하기 위한 수단이다. 송수신 사실을 사후에 부인하지 못하게 하는 '부인방지(Non-repudiation)'는 공인인증서 등 '전자서명' 기술을 통해 확보된다. | L12: 260830
A13: 10 | B13: 1. 전자조달시스템 개요 | C13: 5. 전자조달시스템 기능 | D13: [상황] A업체가 '나라장터에 등록만 하면 그 후로는 개별 기관마다 별도로 등록할 필요 없이 모든 입찰에 참여할 수 있다'는 말을 들었다. 이 특징을 가리키는 개념으로 가장 적절한 것은? | E13: 다중 접속 제한 기능 | F13: 단일 창구(Single Window) 기능 | G13: 일일 공고 제한 기능 | H13: 실시간 입찰가 공개 기능 | I13: 2 | J13: * 정답 (②): 한 번의 등록으로 모든 수요기관의 입찰에 참여할 수 있게 하는 것이 나라장터의 단일 창구(Single Window) 기능임.
A14: 11 | B14: 1. 전자조달시스템 개요 | C14: 5. 전자조달시스템 기능 | D14: 국가종합전자조달시스템(나라장터)이 수행하는 가장 핵심적인 기능과 역할로 올바른 것은? | E14: 공공기관 내부의 인사 및 재무 결재만을 전담 처리하는 폐쇄형 ERP 시스템 | F14: 민간 기업 간의 B2B 거래를 독려하기 위해 구축된 전용 영업 플랫폼 | G14: 물품 구매 시 오직 최저가 입찰만을 강제하기 위해 설계된 전자 카탈로그 | H14: 공고부터 투찰, 계약, 대금 지급까지 조달 전 과정을 전자적으로 처리하는 시스템 | I14: 4 | J14: * 정답 (④): 나라장터는 기관 내부 결재용이 아니라, 공공조달의 시작(공고)부터 끝(대금 지급)까지 전 과정을 원스톱으로 처리하는 통합 시스템입니다.
A15: 12 | B15: 1. 전자조달시스템 개요 | C15: 5. 전자조달시스템 기능 | D15: 공공조달에서 제공하는 '원스톱(One-Stop) 서비스'가 의미하는 실무적 개념으로 가장 적절한 것은? | E15: 하위 실무자 기안부터 최상위 기관장 결재까지의 내부 보고를 일사천리로 처리하는 것 | F15: 입찰 공고부터 시작하여 계약 체결, 보증 이행, 대금 지급까지 하나의 흐름으로 연결하는 것 | G15: 모든 공공기관의 입찰 서류를 오프라인으로 1회만 제출하면 온라인으로 스캔해주는 것 | H15: 업체의 입찰 참가 자격 등록부터 내부 재무제표 승인까지 조달청이 직접 대행하는 것 | I15: 2 | J15: * 정답 (②): 조달에서 원스톱 서비스란, 낙찰 이후 별도의 오프라인 서류 제출 없이 계약, 이행, 대금 지급까지 나라장터 내에서 매끄럽게 연결되는 것을 뜻합니다.
A16: 13 | B16: 1. 전자조달시스템 개요 | C16: 5. 전자조달시스템 기능 | D16: 일정 규모 이상 입찰 및 계약 처리를 위해 행안부가 지정·고시한 장치는? | E16: 국고보조금통합관리시스템 | F16: 국가종합전자조달시스템(나라장터) | G16: 지방재정관리시스템 | H16: 중소기업공공구매종합정보망 | I16: 2 | J16: 정답 (②) 조달 업무의 전자적 처리를 위해 국가 및 지자체 공통으로 '나라장터'를 지정정보처리장치로 활용함 | K16: 지방계약법 시행령
A17: 14 | B17: 1. 전자조달시스템 개요 | C17: 6. 전자조달시스템 도입 성과 | D17: [상황] 나라장터 도입 이후 조달업체들 사이에서 '여러 기관에 각각 서류를 낼 필요가 없어져서 행정 부담이 줄었다'는 반응이 나왔다. 이러한 변화와 가장 거리가 먼 평가는? | E17: 전국 단위 경쟁 확대로 예산 절감 효과가 있었다는 평가 | F17: 업무 처리시간이 단축되었다는 평가 | G17: 조달업체의 행정비용이 오히려 증가했다는 평가 | H17: 조달 행정의 투명성이 강화되었다는 평가 | I17: 3 | J17: * 정답 (③): 나라장터는 한 번의 등록으로 여러 기관 입찰에 참여하고 업무를 온라인화해 조달업체의 행정비용을 오히려 절감시켰음.
A18: 15 | B18: 1. 전자조달시스템 개요 | C18: 6. 전자조달시스템 도입 성과 | D18: [상황] 한 기관이 차세대 나라장터 도입을 앞두고 '기존 방식대로 모든 거래 기록을 종이로 뽑아 별도 보관하는 절차도 그대로 유지하자'고 제안했다. 이 제안이 차세대 시스템의 지향 방향과 부합하는지에 대한 평가로 가장 적절한 것은? | E18: 부합한다. 모든 전자시스템은 종이 기록을 병행해야 한다 | F18: 이 사안은 차세대 시스템의 방향성과 무관하다 | G18: 부합한다. 종이 이중보관이 차세대 시스템의 핵심이다 | H18: 부합하지 않는다. 차세대 시스템은 AI·빅데이터·클라우드 기반의 페이퍼리스 운영을 지향한다 | I18: 4 | J18: * 정답 (④): 차세대 나라장터는 AI·빅데이터·클라우드 기반의 페이퍼리스 업무환경을 지향하며 거래기록을 전자적으로 안전하게 보관함.
A19: 16 | B19: 1. 전자조달시스템 개요 | C19: 6. 전자조달시스템 도입 성과 | D19: [상황] 시민단체가 '예전에는 입찰이 어떻게 진행되는지 알기 어려웠는데, 요즘은 공고·평가기준·개찰결과까지 온라인에서 실시간으로 확인할 수 있다'고 평가했다. 이 변화가 보여주는 전자조달의 효과로 가장 적절한 것은? | E19: 투명성 강화를 통한 정보 비대칭 해소 효과 | F19: 전국 참여 확대 효과 | G19: 업무 처리시간 단축 효과 | H19: 종이 문서 비용 절감 효과 | I19: 1 | J19: * 정답 (①): 조달 전 과정이 온라인에 실시간 공개되어 정보 비대칭이 해소되는 것은 투명성 강화의 핵심 효과임.
A20: 17 | B20: 2. 국가종합전자조달시스템(나라장터) 연계 계약 관리 지원시스템 개요 | C20: 1. 종합쇼핑몰 이용절차 | D20: [상황] 한 수요기관 담당자가 '종합쇼핑몰이 있으니 모든 물품은 반드시 여기서만 구매해야 한다'고 주장했다. 이 주장에 대한 평가로 가장 적절한 것은? | E20: 옳다. 종합쇼핑몰 이용은 법적 의무이다 | F20: 옳지 않다. 종합쇼핑몰 이용은 의무가 아니며, 수요기관은 자체 판단에 따라 다른 방식으로도 구매할 수 있다 | G20: 이 주장은 MAS 제도와 무관한 이야기이다 | H20: 옳다. 종합쇼핑몰 외의 구매는 모두 불법이다 | I20: 2 | J20: * 정답 (②): 종합쇼핑몰 이용은 의무가 아니며, 수요기관은 자체 판단에 따라 일반 입찰 등 다른 방식으로도 물품을 구매할 수 있음.
A21: 18 | B21: 2. 국가종합전자조달시스템(나라장터) 연계 계약 관리 지원시스템 개요 | C21: 1. 종합쇼핑몰 이용절차 | D21: [상황] 수요기관이 종합쇼핑몰에서 일정 금액 이상의 물품을 구매하면서, 등록된 업체 2곳 이상에게 추가 제안을 받아 더 좋은 조건을 제시한 업체와 계약하려 한다. 이 절차의 명칭은? | E21: 수의계약 | F21: 지명경쟁 | G21: 1단계 경쟁 | H21: 2단계 경쟁 | I21: 4 | J21: * 정답 (④): MAS 2단계 경쟁은 일정 금액 이상 구매 시 등록업체 중 2개 이상으로부터 추가 제안을 받아 계약상대자를 정하는 절차임.
A22: 19 | B22: 2. 국가종합전자조달시스템(나라장터) 연계 계약 관리 지원시스템 개요 | C22: 1. 종합쇼핑몰 이용절차 | D22: [상황] MAS 계약업체 B사가 '계약기간 중에는 등록된 가격을 절대 바꿀 수 없다'고 알고 있었다. 이 이해에 대한 평가로 가장 적절한 것은? | E22: 정확하다. 가격 조정은 계약 종료 후에만 가능하다 | F22: 정확하다. MAS 등록가격은 계약기간 중 절대 불변이다 | G22: 이 사안은 MAS 제도와 무관하다 | H22: 부정확하다. 시장가격 변동이나 자발적 인하 제안 등에 따라 등록가격이 조정될 수 있다 | I22: 4 | J22: * 정답 (④): MAS 계약기간 중이라도 계약상대자의 가격 인하 제안이나 시장가격 변동에 따라 등록가격이 조정될 수 있음.
A23: 20 | B23: 2. 국가종합전자조달시스템(나라장터) 연계 계약 관리 지원시스템 개요 | C23: 1. 종합쇼핑몰 이용절차 | D23: MAS 2단계 경쟁 제도를 실시하는 근본적인 취지로 가장 적절한 것은? | E23: 쇼핑몰 등록가격을 기준으로 추가 경쟁을 유도해 더 유리한 가격·품질 조건을 확보하기 위해 | F23: 특정 업체에게 우선권을 부여하기 위해 | G23: 절차를 늘려 계약담당자의 업무 부담을 가중시키기 위해 | H23: 구매 절차를 의도적으로 지연시키기 위해 | I23: 1 | J23: * 정답 (①): 2단계 경쟁은 등록가격보다 더 유리한 가격·품질 조건을 이끌어내기 위해 공급업체 간 추가 경쟁을 유도하는 제도임.
A24: 21 | B24: 2. 국가종합전자조달시스템(나라장터) 연계 계약 관리 지원시스템 개요 | C24: 2. 혁신장터 활용 계약 | D24: [상황] 국가 R&D로 개발된 신기술 제품이 초기 판로를 확보하지 못해 사장될 위기에 처했다. 이 제품의 공공조달 연계와 판로 지원을 위해 활용할 수 있는 전용 시스템은? | E24: 디지털서비스몰 | F24: 종합쇼핑몰 | G24: 혁신장터 | H24: 이음장터 | I24: 3 | J24: * 정답 (③): 혁신장터는 혁신제품으로 지정된 제품의 초기 판로 지원을 위한 전용 시스템으로, 구매자 면책·수의계약 허용 등의 혜택이 제공됨.
A25: 22 | B25: 2. 국가종합전자조달시스템(나라장터) 연계 계약 관리 지원시스템 개요 | C25: 2. 혁신장터 활용 계약 | D25: [상황] 수요기관 담당자가 '혁신제품을 구매하면 구매금액의 절반을 정부가 대신 지원해준다'고 알고 있었다. 이 이해에 대한 평가로 가장 적절한 것은? | E25: 정확하다. 구매금액 50%를 정부가 보조한다 | F25: 부정확하다. 구매자 면책·수의계약 허용·구매목표제 실적 인정 등의 혜택은 있으나 구매금액을 직접 보조하는 제도는 없다 | G25: 이 사안은 혁신제품 제도와 무관하다 | H25: 정확하다. 다만 지원 비율은 기관마다 다르다 | I25: 2 | J25: * 정답 (②): 혁신제품 구매 시 구매자 면책·수의계약 허용·구매목표제 실적 인정 등의 혜택은 있으나, 구매금액을 정부가 직접 보조하는 제도는 없음.
A26: 23 | B26: 2. 국가종합전자조달시스템(나라장터) 연계 계약 관리 지원시스템 개요 | C26: 3. 벤처나라 활용 계약 | D26: [상황] 창업 2년차 스타트업이 기술력은 있지만 실적이 부족해 일반 공공입찰 진입이 어렵다는 고충을 토로했다. 이 기업에게 안내할 수 있는 전용 판로 지원 시스템은? | E26: 혁신장터 | F26: 종합쇼핑몰 | G26: 벤처나라 | H26: 디지털서비스몰 | I26: 3 | J26: * 정답 (③): 벤처나라는 벤처·창업기업의 초기 판로 지원을 위해 구축된 전용 쇼핑몰임.
A27: 24 | B27: 2. 국가종합전자조달시스템(나라장터) 연계 계약 관리 지원시스템 개요 | C27: 3. 벤처나라 활용 계약 | D27: [상황] 한 담당자가 '벤처나라는 중견기업의 해외 진출을 돕는 시스템'이라고 설명했다. 이 설명에 대한 평가로 가장 적절한 것은? | E27: 부정확하다. 벤처나라는 벤처·창업기업의 국내 공공조달시장 진입 및 초기 판로 지원을 위한 시스템이다 | F27: 정확하다. 벤처나라의 핵심 기능이 해외 수출 지원이다 | G27: 이 설명은 종합쇼핑몰에 대한 설명과 같다 | H27: 정확하다. 다만 중견기업 중 일부만 대상이다 | I27: 1 | J27: * 정답 (①): 벤처나라는 벤처·창업기업의 국내 공공조달시장 진입 및 초기 판로 지원을 위한 시스템이며, 중견기업의 해외 수출 지원과는 무관함.
A28: 25 | B28: 2. 국가종합전자조달시스템(나라장터) 연계 계약 관리 지원시스템 개요 | C28: 3. 벤처나라 활용 계약 | D28: 벤처나라 지정 신청 과정에서 조달청이 요구하는 공인 품질평가 증빙자료(시험성적서, KC인증 등)를 구비하지 못한 영세 기업이 이를 합법적으로 대체하기 위해 제출할 수 있는 문서는? | E28: 공공기관 대상 납품 내역을 증빙하는 납품실적증명서 | F28: 해당 제품에 적용된 기술적 차별성을 보여주는 특허등록증 | G28: 업체 자체적인 공정 통제 및 검수 방안을 담은 품질관리계획서 | H28: 기업의 사업 영위 목적과 업태를 보여주는 사업자등록증 | I28: 3 | J28: * 정답 (③): 벤처 및 창업기업의 인증 취득 부담을 완화하기 위해, 공인 인증서가 없다 하더라도 자체적인 품질 보증 방안을 체계적으로 서술한 '품질관리계획서' 양식을 제출하면 심사를 받을 수 있습니다. | K28: 벤처나라 등록 물품·서비스 지정 관리 규정 제21조 제6항
A29: 26 | B29: 2. 국가종합전자조달시스템(나라장터) 연계 계약 관리 지원시스템 개요 | C29: 3. 벤처나라 활용 계약 | D29: 조달업체가 조달청 벤처나라 지정 신청을 하기 위해 반드시 사전에 완료해 두어야 할 필수 준비 단계에 해당하지 않는 것은? | E29: 신청하려는 제품에 대해 부여받은 고유 물품식별번호 발급 완료 | F29: 나라장터 입찰 시스템에 입찰참가자격 사전 등록 완료 | G29: 심사 가점을 받기 위한 산업부 등 관련 공공기관의 추천서 발급 완료 | H29: 국가종합전자조달시스템(나라장터) 신규 이용자 회원가입 및 인증서 등록 | I29: 3 | J29: * 정답 (③): 유관 공공기관의 추천을 받으면 지정 심사 과정에서 면제 혜택이나 가점을 받을 수 있어 유리하지만, 추천서가 없어도 업체가 직접 온라인으로 벤처나라 지정 신청을 하는 데는 아무 제약이 없습니다.
A30: 27 | B30: 2. 국가종합전자조달시스템(나라장터) 연계 계약 관리 지원시스템 개요 | C30: 3. 벤처나라 활용 계약 | D30: 벤처나라 지정 물품을 보유한 업체가 수요 기관의 요구에 맞춰 기존 제품에 '규격 추가'를 신청하려 할 때, 법적으로 규격 추가가 승인될 수 없는 명백한 거절 사유는? | E30: 새 규격의 적용 기술과 품질 수준이 기존 지정 제품과 완전히 동등하다고 인정되는 경우 | F30: 새 규격 제품의 본질적인 세부품명 번호가 기존 지정 제품의 세부품명과 서로 다른 경우 | G30: 새 규격 제품의 세부품명 번호가 기존에 지정받았던 벤처나라 제품과 동일한 경우 | H30: 새 규격 제품의 외형 및 제원이 기존에 지정받았던 제품 규격과 매우 유사한 경우 | I30: 2 | J30: * 정답 (②): '규격 추가'는 말 그대로 기존 제품의 파생형 사이즈나 색상 등을 더하는 것입니다. 따라서 기존 제품과 아예 카테고리(세부품명)가 달라지면 규격 추가가 불가하며 신규 지정 신청을 처음부터 다시 해야 합니다.
A31: 28 | B31: 2. 국가종합전자조달시스템(나라장터) 연계 계약 관리 지원시스템 개요 | C31: 3. 벤처나라 활용 계약 | D31: 벤처나라에 상품을 등록한 업체가 관리 규정을 위반했을 때, 즉각적인 '이용정지'라는 중징계를 내리지 않고 혁신조달업무심의회를 거쳐 가벼운 '경고 조치'로 갈음할 수 있는 사유는? | E31: 벤처나라 기본 이용약관이나 단순 공급확약서 상의 의무 조항을 일부 위반한 사실이 적발된 경우 | F31: 타 입찰 건에서 뇌물수수 등으로 부정당업자 입찰참가자격 제한 처분을 확정받은 경우 | G31: 자사 상품의 주요 성능 스펙과 인증 정보를 명백히 허위로 기재하여 수요기관을 기만한 경우 | H31: 업체 규모나 제조 공장 현황 등 핵심 기업 정보를 조작하여 벤처나라 심사를 통과한 경우 | I31: 1 | J31: * 정답 (①): 허위 정보 기재나 부정당업자 제재 확정은 즉시 등록 취소 및 이용 정지가 되는 중대 사유이지만, 단순 약관 위반 등은 심의를 통해 개선을 요구하는 '경고'로 1차 조치할 수 있습니다.
A32: 29 | B32: 2. 국가종합전자조달시스템(나라장터) 연계 계약 관리 지원시스템 개요 | C32: 3. 벤처나라 활용 계약 | D32: 초기 창업 기업의 공공판로 개척을 지원하는 조달청 벤처나라 제도의 규정에 따르면, 벤처나라 지정 제품의 효력이 유지되는 기본 유효기간은 최초 지정일로부터 최대 몇 년인가? | E32: 최장 4년 | F32: 최장 6년 | G32: 최장 3년 | H32: 최장 5년 | I32: 2 | J32: * 정답 (②): 벤처나라 등록 물품·서비스 지정 관리규정 제15조에 명시된 바에 따라, 지정 취소 등 특별한 귀책사유가 없는 한 벤처나라 제품의 지정 유효기간은 지정일로부터 최장 '6년'으로 보장됩니다.
A33: 30 | B33: 2. 국가종합전자조달시스템(나라장터) 연계 계약 관리 지원시스템 개요 | C33: 4. 디지털서비스몰 활용 계약 | D33: [상황] 한 기관이 클라우드 기반 업무시스템 도입을 검토하며 관련 서비스를 전문적으로 취급하는 조달 플랫폼을 찾고 있다. 가장 적절한 시스템은? | E33: 디지털서비스몰 | F33: 벤처나라 | G33: 종합쇼핑몰 | H33: 혁신장터 | I33: 1 | J33: * 정답 (①): 디지털서비스몰은 클라우드·AI 등 디지털 기술 서비스를 전문적으로 취급하는 시스템임.
A34: 31 | B34: 2. 국가종합전자조달시스템(나라장터) 연계 계약 관리 지원시스템 개요 | C34: 5. 이음장터 활용 계약 | D34: [상황] 민간의 우수한 예약 플랫폼을 공공기관이 그대로 활용할 수 있도록 연계해주는 조달 시스템을 찾고 있다. 가장 적절한 것은? | E34: 벤처나라 | F34: 이음장터 | G34: 종합쇼핑몰 | H34: 혁신장터 | I34: 2 | J34: * 정답 (②): 이음장터는 민간의 혁신적인 플랫폼을 공공부문에 연계해 활용할 수 있도록 지원하는 시스템임.
A35: 32 | B35: 3. 목록정보시스템 개요 | C35: 1. 물품목록법령의 개요 | D35: 물품목록번호의 구성에 대한 설명으로 옳은 것은? | E35: 8자리 물품식별번호와 8자리 물품분류번호로 구성된 16자리 숫자이며, 분류번호가 상위개념이다 | F35: 물품목록번호는 국가마다 다른 자리수로 구성된다 | G35: 물품목록번호는 업체등록번호와 동일한 개념이다 | H35: 물품목록번호는 4자리 숫자로만 구성된다 | I35: 1 | J35: * 정답 (①): 물품목록번호는 상위개념인 8자리 물품분류번호와, 개별 제품을 특정하는 8자리 물품식별번호로 구성된 16자리 숫자임. | K35: 물품목록정보의 관리 및 이용에 관한 법률
A36: 33 | B36: 3. 목록정보시스템 개요 | C36: 1. 물품목록법령의 개요 | D36: [상황] 「물품목록정보의 관리 및 이용에 관한 법률」의 취지를 묻는 질문에 담당자가 '특정 업체에게 독점적 지위를 보장해주는 법'이라고 잘못 답했다. 올바른 취지로 가장 적절한 것은? | E36: 특정 기업에 대한 독점적 지위 보장 | F36: 공무원 개인의 업무 편의성 증대만을 위한 것 | G36: 조달업체의 이익 극대화 | H36: 물품 목록정보의 체계적 관리 및 효율적 이용을 통한 조달업무 효율화 | I36: 4 | J36: * 정답 (④): 이 법은 물품 목록정보를 체계적으로 관리·이용해 조달업무의 효율성을 높이는 것을 목적으로 함. | K36: 물품목록정보의 관리 및 이용에 관한 법률 제1조
A37: 34 | B37: 3. 목록정보시스템 개요 | C37: 2. 목록정보시스템 이용 일반절차 | D37: [상황] 신제품을 생산한 C사가 이 제품을 나라장터에서 거래되도록 조달청장에게 등재를 요청하려 한다. 이 절차를 가리키는 용어는? | E37: 목록화 요청 | F37: 품목 등록 취소 | G37: 식별번호 신청 | H37: 분류번호 문의 | I37: 1 | J37: * 정답 (①): 물품을 제조·수입·공급하는 자는 해당 물품의 목록화를 조달청장에게 요청할 수 있으며, 이를 목록화 요청이라 함. | K37: 물품목록정보의 관리 및 이용에 관한 법률 제9조
A38: 35 | B38: 3. 목록정보시스템 개요 | C38: 2. 목록정보시스템 이용 일반절차 | D38: 조달업체가 자사에서 취급하는 개별 품목에 대해 고유한 8자리 '물품식별번호' 발급을 신청하고자 할 때 접속해야 하는 시스템 플랫폼과 절차는? | E38: 나라장터 → 입찰정보 → 물품등록 | F38: 정부24 → 민원신청 → 조달청민원 | G38: 목록정보시스템 → 목록화요청 → 품목등록 | H38: 벤처나라 → 온라인신청 → 상품등록 | I38: 3 | J38: * 정답 (③): 물품식별번호 발급은 나라장터 메인 화면이 아닌, 물품의 속성 관리를 전담하는 별도의 조달청 목록정보시스템(goods.g2b.go.kr)에 접속하여 '목록화요청 → 품목등록' 메뉴를 통해 직접 신청해야 합니다.
A39: 36 | B39: 3. 목록정보시스템 개요 | C39: 2. 목록정보시스템 이용 일반절차 | D39: 대한민국 공공조달 전산망에서 개별 상품을 관리하기 위해 부여하는 총 16자리의 번호 체계 중, 제조사 및 모델·규격별로 고유하게 부여되는 뒤의 8자리 번호를 뜻하는 공식 명칭은? | E39: 세부품명번호 | F39: 물품목록번호 | G39: 물품식별번호 | H39: 국가물품분류번호 | I39: 3 | J39: * 정답 (③): 공공조달 물품 번호(총 16자리)는 카테고리 성격의 '물품분류번호(앞 8자리)'와 개별 상품 단위를 특정하는 '물품식별번호(뒤 8자리)'로 구성되며, 이 전체 16자리를 합쳐서 '물품목록번호'라고 통칭합니다.
A40: 37 | B40: 3. 목록정보시스템 개요 | C40: 2. 목록정보시스템 이용 일반절차 | D40: 조달청 국가종합전자조달시스템에서 공공기관이 물품을 취득하고 관리할 때 기준이 되는 번호로서, 8자리의 '물품분류번호'와 8자리의 '물품식별번호'가 결합된 총 16자리의 전체 고유 번호를 의미하는 공식 명칭은? | E40: 물품분류번호 | F40: 물품식별번호 | G40: 물품목록번호 | H40: 세부품명번호 | I40: 3 | J40: * 정답 (③): 조달 물품의 고유 번호 체계는 용도별 카테고리인 '물품분류번호(앞 8자리)'와 개별 상품 단위인 '물품식별번호(뒤 8자리)'로 구성되며, 이 두 가지가 결합된 전체 16자리의 번호를 통칭하여 '물품목록번호'라고 규정합니다.
A41: 38 | B41: 3. 목록정보시스템 개요 | C41: 3. 목록정보시스템 활용 목록화 절차 | D41: [상황] 담당자가 목록화 원칙을 정리하며 '가격이 가장 낮은 제품을 우선적으로 목록에 등재한다'는 원칙을 추가하려 했다. 이 제안에 대한 평가로 가장 적절한 것은? | E41: 타당하다. 저가 제품 우선 등재는 예산 절감에 직결된다 | F41: 타당하지 않다. 목록화는 1품목1번호·제조자규격우선·속성정보표준화 등을 원칙으로 하며, 가격은 목록화 단계의 고려요소가 아니다 | G41: 이 사안은 목록화 절차와 무관하다 | H41: 타당하다. 가격이 목록화의 핵심 원칙이다 | I41: 2 | J41: * 정답 (②): 목록화 원칙은 1품목1번호·제조자규격우선·속성정보표준화·국제표준분류체계준수 등이며, 가격은 고려요소가 아님.
A42: 39 | B42: 3. 목록정보시스템 개요 | C42: 4. 목록정보시스템 활용 분류·품명·품목 관리 절차 | D42: [상황] 동일한 노트북 모델이라도 색상·저장용량이 다르면 나라장터에서 서로 다른 물품식별번호를 부여받는다. 이 현상을 설명하는 원칙은? | E42: 국제표준분류체계 준수 원칙 | F42: 속성정보 표준화 원칙 | G42: 1품목 1번호 원칙 | H42: 제조자 규격 우선 원칙 | I42: 3 | J42: * 정답 (③): 1품목 1번호 원칙은 속성(규격·모델 등)이 다르면 서로 다른 물품으로 보아 각각 고유 번호를 부여하는 원칙임.
A43: 40 | B43: 3. 목록정보시스템 개요 | C43: 5. 목록정보시스템 활용 최신화 및 분류 정비 | D43: 물품목록법령상 '품명 신설'과 '품목 등록'을 비교한 설명으로 옳은 것은? | E43: 품목 등록은 새로운 물품분류번호 자체를 부여받는 절차이다 | F43: 품명 신설은 새로운 분류(세부품명)를 만드는 절차이고, 품목 등록은 기존 품명에 새로운 제품(물품식별번호)을 추가하는 절차이다 | G43: 품명 신설과 품목 등록은 완전히 동일한 절차이다 | H43: 신기술(NET/NEP) 인증 제품은 품명 신설 시 신속처리 대상에서 제외된다 | I43: 2 | J43: * 정답 (②): 품명 신설은 목록에 없던 새로운 품명(세부품명번호)을 만드는 절차이고, 품목 등록은 이미 있는 품명에 새로운 제품(물품식별번호)을 추가하는 절차로, 신기술 인증제품은 오히려 신속처리(Fast Track) 대상이 됨.
A44: 41 | B44: 3. 목록정보시스템 개요 | C44: 6. 목록정보시스템 활용 분류체계 국제 표준화 | D44: [상황] 해외 조달기관과의 물품 정보 호환을 위해 국내 물품분류번호가 국제 표준 코드체계를 따르도록 설계되었다. 이 국제 표준체계로 가장 적절한 것은? | E44: ISBN(도서 식별용 표준) | F44: ISO 9001(품질경영 인증 표준) | G44: GTIN(유통상품 식별용 코드) | H44: UNSPSC(유엔 표준 상품 및 서비스 분류 코드) | I44: 4 | J44: * 정답 (④): 물품분류번호는 국제적 호환성 확보를 위해 UNSPSC 등 국제표준 분류체계를 기반으로 부여됨.
A45: 42 | B45: 1. 전자조달시스템 개요 | C45: 1. 전자조달시스템 개념 | D45: 전자조달시스템 개요의 기본 개념으로 가장 적절한 것은? | E45: 기준·절차를 사전에 명확히 하고 동일하게 적용하여 공정성과 투명성을 확보한다. | F45: 구두 합의가 문서보다 우선한다. | G45: 담당자 편의에 따라 공개·기록을 생략할 수 있다. | H45: 상황에 따라 사후에 기준을 바꾸어도 무방하다. | I45: 1 | J45: * 정답 (①): 전자조달시스템의 핵심은 사전에 확정된 기준과 절차를 투명하게 공개하고 동일하게 적용하는 것이며, 이를 통해 감사·분쟁 리스크를 줄이는 것이 근본 원칙이다.
A46: 43 | B46: 1. 전자조달시스템 개요 | C46: 3. 전자조달시스템 운영환경 | D46: 전자조달시스템 운영환경의 지출 분석 4사분면 중 '전략적(Strategic) 지출 유형'에 해당하는 것은? | E46: 표준화된 소모품을 소량으로 반복 구매하는 환경 | F46: 기술적 진입장벽이 높아 소수 공급업체만 존재하지만 지출 규모는 작은 환경 | G46: 시장의 복잡성과 위험이 높으면서 동시에 대규모 예산이 투입되는 환경 | H46: 구매 사양이 단순하고 다수의 공급업체가 가격 경쟁을 벌이며 지출 규모가 큰 환경 | I46: 3 | J46: * 정답 (③): 전략적 지출 유형은 높은 시장 복잡성·위험성과 높은 지출 규모가 결합된 영역으로, 개별 사업에 맞춘 고객화(Customization) 절차가 요구되며, 전자입찰(e-Tendering)을 중심으로 시스템이 구현된다. A는 인수(Acquisition) 유형, B는 기술적(Technical) 유형, D는 레버리지(Leverage) 유형에 해당한다.
A47: 44 | B47: 1. 전자조달시스템 개요 | C47: 6. 전자조달시스템 도입 성과 | D47: 전자조달시스템 도입 성과에 관한 설명으로 옳은 것은? | E47: 조달절차의 각 단계는 관련 규정에 따라 수행되며, 핵심 판단은 기록으로 남겨야 한다. | F47: 전자조달시스템은 입찰 단계에만 한정되므로 공급업체 관리와는 무관하다. | G47: 절차는 내부 방침만 따르면 되며 외부 기준은 고려하지 않는다. | H47: 전자조달시스템의 데이터 생성 기능은 보고 목적에만 활용되며 의사결정 지원과는 관련이 없다. | I47: 1 | J47: * 정답 (①): 전자조달시스템의 핵심 성과 중 하나는 조달 프로세 전 과정에서 생산되는 데이터와 문서를 체계적으로 기록·관리함으로써 투명성과 책임성을 확보하는 것이다. 각 단계별 판단 근거를 기록으로 남기는 것은 사후 감사·분쟁 대응의 기본 요건이다.
A48: 45 | B48: 1. 전자조달시스템 개요 | C48: 5. 전자조달시스템 기능 | D48: e-Sourcing(전자적 소싱)의 주요 기능에 해당하지 않는 것은? | E48: 공급업체 데이터베이스(DB) 관리 및 전자입찰(e-Tendering) | F48: 온라인 평가(e-Evaluation) 및 전자협상(e-Negotiation) | G48: 전자카탈로그를 통한 구매 주문 처리 및 전자지불(e-Payment) | H48: 전자경매(e-Auction) 및 계약관리(Contract Management) | I48: 3 | J48: * 정답 (③): e-Sourcing은 적격 공급업체의 탐색·평가·선정 과정을 디지털화하는 것이 핵심 목적으로, 공급업체 DB 관리·전자입찰·온라인 평가·전자협상이 주요 기능이다. 전자카탈로그를 통한 구매 주문 처리와 전자지불은 구매·대금 처리 효율화에 초점을 두는 e-Purchasing의 기능에 해당한다.
A49: 46 | B49: 1. 전자조달시스템 개요 | C49: 1. 전자조달시스템 개념 | D49: UN(2006)이 제시한 전자조달시스템 발전 5단계 중 '인터넷 기반 도구와 통합 플랫폼으로 기존 종이 기반 절차를 전면 대체하는 단계'에 해당하는 것은? | E49: 1단계: 종이 기반 업무처리 | F49: 2단계: 전자적 업무지원(EDI·ERP 활용) | G49: 4단계: 인터넷 도구·플랫폼 보완 | H49: 5단계: 인터넷 도구·플랫폼 대체 | I49: 4 | J49: * 정답 (④): 발전 5단계는 ① 종이 기반 → ② EDI·ERP 등 전자시스템 보조 → ③ 인터넷 커뮤니케이션 도입 → ④ 인터넷 도구 보완(전자카탈로그·웹 EDI 병행) → ⑤ 통합 플랫폼으로 전면 대체 순이다. 한국의 나라장터(KONEPS)처럼 조달 전 과정을 하나의 디지털 플랫폼에서 처리하는 것이 5단계에 해당한다.
... A94: 91 | B94: 3. 목록정보시스템 개요 | C94: 3. 목록정보시스템 활용 목록화 절차 | D94: 목록화의 4대 원칙에 해당하지 않는 것은? | E94: 단일화 — 동일한 분류 대상은 하나의 분류 체계로 통일 | F94: 표준화 — 분류·식별 기준을 표준화하여 일관성 확보 | G94: 정확성 — 목록 정보의 정확성을 확보하고 검증 절차를 운영 | H94: 경쟁성 — 복수의 분류체계를 경쟁적으로 운영하여 효율 확보 | I94: 4 | J94: * 정답 (④): 목록화의 4대 원칙은 단일화·표준화·정확성·최신화이다. '경쟁성'은 분류체계 운영 원칙에 해당하지 않으며, 오히려 분류체계는 단일화·표준화가 핵심이다.

Sheet 1-4_전략적공공조달
A2: 공공조달과 법제도 이해 - 4. 전략적 공공조달
A3: 번호 | B3: 세부항목 | C3: 세세항목 | D3: 문제 내용 | E3: 보기① | F3: 보기② | G3: 보기③ | H3: 보기④ | I3: 정답 번호 | J3: 해설 및 오답노트 | K3: 출처 | L3: 개정일자 | M3: 숫자문제
A4: 1 | B4: 1. 중소기업지원 조달 | C4: 2. 중소기업자간 경쟁제도 이해 | D4: [상황] 공무원 A가 중소기업자간 경쟁제도의 근거를 찾으며 국가계약법, 조달사업법, 판로지원법, 여성기업지원법 중 하나를 확인하려 한다. 직접적인 근거 법률로 옳은 것은? | E4: 여성기업지원에 관한 법률 | F4: 국가를 당사자로 하는 계약에 관한 법률 | G4: 조달사업에 관한 법률 | H4: 중소기업제품 구매촉진 및 판로지원에 관한 법률 | I4: 4 | J4: * 정답 (④): 중소기업자간 경쟁제도는 판로지원법에 근거함. | K4: 중소기업제품 구매촉진 및 판로지원에 관한 법률 제4조
A5: 2 | B5: 1. 중소기업지원 조달 | C5: 2. 중소기업자간 경쟁제도 이해 | D5: [상황] 제조업체가 아닌 순수 유통업체 A사가 중소기업자간 경쟁제품 입찰에 참가하려 한다. 이 경우 필요한 서류로 가장 적절한 것은? | E5: 벤처기업 확인서만 있으면 된다 | F5: 아무 서류 없이 참가 가능하다 | G5: 우수조달물품 지정서만 있으면 된다 | H5: 해당 제품의 직접생산확인증명서가 필요하다 | I5: 4 | J5: * 정답 (④): 페이퍼컴퍼니 난립을 방지하기 위해 중소기업자간 경쟁입찰은 직접생산확인증명서를 보유한 업체만 참가할 수 있음. | K5: 중소기업제품 구매촉진 및 판로지원에 관한 법률
A6: 3 | B6: 1. 중소기업지원 조달 | C6: 2. 중소기업자간 경쟁제도 이해 | D6: [상황] 중소벤처기업부가 특정 품목을 경쟁제품으로 지정한 지 2년이 다가온다. 다음 조치로 가장 적절한 것은? | E6: 매년 새로 지정 여부를 재검토한다 | F6: 지정을 영구히 유지하고 재검토하지 않는다 | G6: 지정 주기에 맞춰 재지정 여부를 검토·공고한다 | H6: 3년 주기로만 재검토한다 | I6: 3 | J6: * 정답 (③): 중소벤처기업부장관은 경쟁제품을 지정하고 2년마다 이를 재검토·공고해야 함. | K6: 중소기업제품 구매촉진 및 판로지원에 관한 법률 제4조
A7: 4 | B7: 1. 중소기업지원 조달 | C7: 2. 중소기업자간 경쟁제도 이해 | D7: [상황] B사가 발급받은 직접생산확인증명서의 진위를 확인하려 관련 기관에 조회하려 한다. 이 증명서를 발급한 기관으로 가장 적절한 것은? | E7: 중소벤처기업부장관(또는 위임기관) | F7: 환경부장관 | G7: 조달청장 | H7: 고용노동부장관 | I7: 1 | J7: * 정답 (①): 직접생산확인증명서는 중소벤처기업부장관(위임기관 포함)이 발급함. | K7: 중소기업제품 구매촉진 및 판로지원에 관한 법률
A8: 5 | B8: 1. 중소기업지원 조달 | C8: 3. 공사용자재 직접구매제도 이해 | D8: [상황] 발주기관이 공사에 필요한 철근·시멘트 등 주요 자재를 직접 구매해 시공업체에 공급하기로 했다. 이 방식이 하도급 부조리 방지와 중소기업 판로 지원에 기여하는 이유로 가장 적절한 것은? | E8: 조달청이 모든 자재를 독점 판매하기 때문이다 | F8: 발주기관이 직접 구매함으로써 중소 자재업체가 원도급-하도급 관계를 거치지 않고 직접 공급기회를 얻을 수 있기 때문이다 | G8: 시공업체가 자재 선택권을 완전히 상실하기 때문이다 | H8: 이 제도는 중소기업 지원과 무관하기 때문이다 | I8: 2 | J8: * 정답 (②): 발주기관의 직접구매는 중소 자재업체가 하도급 단계를 거치지 않고 직접 공급기회를 얻게 해 판로를 지원하고 하도급 부조리를 방지함.
A9: 6 | B9: 2. 녹색조달 | C9: 2. 녹색제품 우선구매제도 이해 | D9: [상황] 조달담당자가 NEP(신제품) 인증제품을 녹색제품으로 분류해 실적에 반영하려 했다. 이 분류가 정확한지에 대한 평가로 가장 적절한 것은? | E9: 정확하지 않다. NEP는 기술개발제품에 해당하며, 녹색제품에는 환경표지·GR·환경성적표지 인증제품 등이 포함된다 | F9: 정확하다. 신제품은 모두 친환경 제품으로 간주된다 | G9: 이 사안은 분류와 무관하다 | H9: 정확하다. NEP는 대표적인 녹색제품이다 | I9: 1 | J9: * 정답 (①): NEP(신제품) 인증제품은 기술개발제품이며, 녹색제품에는 환경표지·GR·환경성적표지 인증제품 등이 해당함. | K9: 녹색제품 구매촉진에 관한 법률
A10: 7 | B10: 2. 녹색조달 | C10: 2. 녹색제품 우선구매제도 이해 | D10: [상황] 녹색제품 관련 민원을 어느 부처에 제기해야 하는지 문의가 들어왔다. 담당 주무 부처로 가장 적절한 것은? | E10: 중소벤처기업부 | F10: 산업통상자원부 | G10: 재정경제부 | H10: 환경부 | I10: 4 | J10: * 정답 (④): 녹색제품 우선구매 제도는 녹색제품 구매촉진에 관한 법률에 근거하며, 환경부가 주무 부처임. | K10: 녹색제품 구매촉진에 관한 법률
A11: 8 | B11: 2. 녹색조달 | C11: 3. 생애주기비용을 고려한 공공조달 제도 이해 | D11: [상황] 담당자가 LCC를 산정하며 '경쟁업체가 이 제품을 얼마에 파는지도 우리 제품의 LCC에 포함해야 한다'고 주장했다. 이 주장에 대한 평가로 가장 적절한 것은? | E11: 이 사안은 LCC와 무관하다 | F11: 타당하지 않다. LCC는 구매·운영·폐기 등 해당 자산과 관련해 실제 발생하는 비용을 포함하며, 경쟁사 가격은 포함되지 않는다 | G11: 타당하다. 경쟁사 가격이 LCC의 핵심 요소이다 | H11: 타당하다. 비교를 위해서는 반드시 필요하다 | I11: 2 | J11: * 정답 (②): LCC는 구매·운영(유지보수 등)·폐기까지 해당 자산과 관련해 실제 발생하는 비용을 포함하며, 경쟁사 가격은 포함되지 않음.
A12: 9 | B12: 2. 녹색조달 | C12: 3. 생애주기비용을 고려한 공공조달 제도 이해 | D12: [상황] 두 제품 중 A는 초기가가 낮지만 유지보수 비용이 매우 크고, B는 초기가가 높지만 장기 운영비가 훨씬 적다. 이런 상황에서 LCC 평가를 도입하는 이유로 가장 적절한 것은? | E12: 입찰 절차 자체를 생략하기 위해 | F12: 총소유비용 관점에서 장기적으로 더 경제적인 선택(이 경우 B일 수 있음)을 하도록 돕기 위해 | G12: 특정 기업의 시장 진입을 막기 위해 | H12: 항상 초기가가 낮은 A를 선택하도록 유도하기 위해 | I12: 2 | J12: * 정답 (②): LCC 평가는 초기비용뿐 아니라 유지보수·폐기 등 총소유비용을 종합 고려해 장기적으로 경제적인 선택을 하도록 돕기 위해 도입됨.
A13: 10 | B13: 3. 혁신·기술개발 촉진조달 | C13: 1. 중소기업 기술개발제품 우선구매제도 이해 | D13: [상황] 담당자가 환경표지 인증제품을 기술개발제품 실적에 포함시키려 했다. 이 처리에 대한 평가로 가장 적절한 것은? | E13: 옳지 않다. 환경표지 인증제품은 녹색제품이며, 기술개발제품은 NEP·NET·성능인증제품 등이다 | F13: 이 사안은 실적 관리와 무관하다 | G13: 옳다. 모든 인증제품은 기술개발제품으로 통합 관리된다 | H13: 옳다. 환경표지 인증도 기술개발제품에 포함된다 | I13: 1 | J13: * 정답 (①): 환경표지 인증제품은 녹색제품에 해당하며, 기술개발제품에는 NEP·NET·성능인증제품·우수조달물품 등이 포함됨. | K13: 중소기업제품 구매촉진 및 판로지원에 관한 법률
A14: 11 | B14: 3. 혁신·기술개발 촉진조달 | C14: 1. 중소기업 기술개발제품 우선구매제도 이해 | D14: [상황] 한 기관의 중소기업 물품 구매액이 100억원이었다. 기술개발제품 우선구매 목표를 충족하려면 최소 얼마 이상을 기술개발제품으로 구매해야 하는가? | E14: 20억원 | F14: 5억원 | G14: 15억원 | H14: 10억원 | I14: 3 | J14: * 정답 (③): 공공기관은 중소기업 물품 구매액의 15% 이상을 기술개발제품으로 구매해야 하므로, 100억원의 15%인 15억원 이상이 목표가 됨. | K14: 중소기업제품 구매촉진 및 판로지원에 관한 법률
A15: 12 | B15: 3. 혁신·기술개발 촉진조달 | C15: 1. 중소기업 기술개발제품 우선구매제도 이해 | D15: 중소기업 기술 개발 촉진을 위해 수의계약 체결이 예외적으로 허용되는 '기술 인증 제품'의 종류가 아닌 것은? | E15: 조달청장이 심사하여 기술력과 품질을 공식 지정하고 고시한 우수조달물품 인증 제품 | F15: 한국산업기술진흥협회가 국내 최초 신기술 적용을 공식 인증하여 부여하는 NEP 인증 제품 | G15: 공공서비스 개선 혁신성을 인정받아 기재부장관 등이 시범 구매용으로 지정한 혁신제품 | H15: 한국산업기술시험원이 공산품 품질을 임의로 평가하여 일정 기준을 보증하는 K마크 지정제품 | I15: 4 | J15: * 정답 (④): K마크는 공산품의 품질을 평가하는 임의 인증제도일 뿐, 우수조달물품이나 혁신제품처럼 법령상 수의계약 특례가 허용되는 대상 기술 인증에 포함되지 않습니다.
A16: 13 | B16: 3. 혁신·기술개발 촉진조달 | C16: 2. 우수조달물품 지정제도의 이해 | D16: [상황] 대기업 C사가 우수조달물품 지정을 신청하려 하자, 담당자가 '중소기업만 신청할 수 있다'며 거부했다. 이 처리에 대한 평가로 가장 적절한 것은? | E16: 옳지 않다. 대기업도 신청할 수 있으며, 다만 중소기업 제품이 우대받는 경우가 많다 | F16: 옳다. 대기업은 어떤 조달 우대제도도 이용할 수 없다 | G16: 이 사안은 신청 자격과 무관하다 | H16: 옳다. 우수조달물품은 중소기업 전용 제도이다 | I16: 1 | J16: * 정답 (①): 우수조달물품은 중소기업뿐 아니라 대기업도 신청할 수 있으며, 다만 심사 과정에서 중소기업 제품이 우대받는 경우가 많음.
A17: 14 | B17: 3. 혁신·기술개발 촉진조달 | C17: 3. 혁신제품 지정제도의 이해 | D17: [상황] 공무원 D가 혁신제품을 구매했으나 성과가 기대에 미치지 못했다. 이때 D가 고의로 부적합 제품임을 알고도 구매를 강행한 사실이 확인되었다면, 구매자 면책 적용 여부로 가장 적절한 것은? | E17: 성과가 낮으면 무조건 면책된다 | F17: 고의·중대한 과실이 있는 경우 면책되지 않는다 | G17: 면책 여부는 구매금액에 따라 결정된다 | H17: 고의가 있어도 항상 면책된다 | I17: 2 | J17: * 정답 (②): 구매자 면책은 고의·중대한 과실이 없는 경우에만 적용되며, 고의가 있으면 면책되지 않음.
A18: 15 | B18: 3. 혁신·기술개발 촉진조달 | C18: 3. 혁신제품 지정제도의 이해 | D18: [상황] 국가 R&D로 개발한 신기술을 상용화하려는 스타트업이 초기 판로 확보와 조달 구매 기관의 감사 부담 경감을 동시에 요구하고 있다. 이 업체에게 안내할 가장 적합한 조달 제도는? | E18: 「혁신제품 지정 제도」를 통해 혁신장터에 등록하고, 수의계약 체결 및 구매 공무원의 감사 면책 혜택을 활용하도록 안내한다. | F18: 「우수조달물품 제도」를 통해 종합쇼핑몰에 우선 등록하고, 구매기관의 감사 면책은 별도의 심사위원회를 추가로 거치도록 안내한다. | G18: 「벤처나라 등록 제도」를 통해 창업기업 전용몰로 판로를 개척하되, R&D 제품 상용화에 따른 법정 구매면책은 적용되지 않음을 안내한다. | H18: 「신제품(NEP) 인증 제도」를 통해 기술력을 공식 입증받고, 별도 면책 없이 일반경쟁입찰에서 기술 가점을 받아 경쟁하도록 안내한다. | I18: 1 | J18: * 정답 (①): 「혁신제품 지정 제도」는 국가 R&D 성과물 등 혁신 기술의 초기 판로를 지원하기 위해 도입되었다. 혁신장터를 통한 수의계약이 가능하며, 적극행정의 일환으로 구매 공무원에게 법정 구매면책 혜택을 부여하여 조달 도입 시의 감사 부담을 경감시켜 준다. | K18: 조달사업에 관한 법률 | L18: 260830
A19: 16 | B19: 3. 혁신·기술개발 촉진조달 | C19: 3. 혁신제품 지정제도의 이해 | D19: [상황] 신입 직원이 '혁신제품 우선구매도 중소기업기본법에 근거한 제도 아니냐'고 물었다. 올바른 답변은? | E19: 맞다. 여성기업지원에 관한 법률이 근거이다 | F19: 아니다. 혁신제품 우선구매는 조달사업에 관한 법률에 근거하며, 중소기업기본법은 중소기업의 정의·범위를 정하는 기본법일 뿐이다 | G19: 이 제도는 법적 근거가 필요 없다 | H19: 맞다. 중소기업기본법이 근거이다 | I19: 2 | J19: * 정답 (②): 혁신제품 우선구매는 조달사업에 관한 법률에 근거하며, 중소기업기본법은 근거법이 아님. | K19: 조달사업에 관한 법률
A20: 17 | B20: 3. 혁신·기술개발 촉진조달 | C20: 3. 혁신제품 지정제도의 이해 | D20: 아직 시장에 출시되지 않은 상용화 이전 단계의 우수 기술을 '혁신시제품(유형Ⅱ)'으로 지정받기 위해 조달청이 최소 조건으로 요구하는 '기술개발단계(TRL)' 기준은? | E20: 기초 이론 정립 및 실험실 규모의 초기 검증이 진행 중인 TRL 1~3단계 | F20: 대량 생산 라인 구축 및 본격적인 시장 사업화가 궤도에 오른 TRL 10단계 이상 | G20: 핵심 요소 기술이 확보되고 성능 평가용 시작품을 막 제작한 TRL 4~6단계 | H20: 신뢰성 평가를 마치고 실제 현장 적용이 가능한 시제품이 완성된 TRL 7~9단계 | I20: 4 | J20: * 정답 (④): 혁신시제품은 아이디어 수준(1~6단계)을 넘어, 당장 공공 현장에 시범 적용하여 성능을 테스트할 수 있는 실체화된 시제품 상태여야 하므로 상용화 직전인 TRL 7~9단계 솔루션을 요구합니다.
A21: 18 | B21: 3. 혁신·기술개발 촉진조달 | C21: 3. 혁신제품 지정제도의 이해 | D21: 조달청의 엄격한 '혁신시제품 지정 절차' 5대 단계를 시간의 흐름과 논리적 순서에 맞게 가장 정확히 나열한 것은? | E21: 사전 등록 → 추가서류 제출 → 온라인 신청 → 혁신성평가 → 지정 심의 | F21: 온라인 신청 → 사전 등록 → 혁신성평가 → 추가서류 제출 → 지정 심의 | G21: 사전 등록 → 온라인 신청 → 혁신성평가(통과 시) → 추가서류 제출 → 지정 심의 | H21: 사전 등록 → 온라인 신청 → 지정 심의 → 혁신성평가 → 추가서류 제출 | I21: 3 | J21: * 정답 (③): 시스템 [사전등록] 후 [온라인 신청]을 마치면, 1차로 공공성 평가를 하고 이를 통과한 업체에 한해 [혁신성 평가]를 진행하며, 이후 규격서 등 [추가서류]를 검토한 뒤 최종 [지정심의] 위원회를 엽니다.
A22: 19 | B22: 3. 혁신·기술개발 촉진조달 | C22: 3. 혁신제품 지정제도의 이해 | D22: 혁신시제품 지정 신청 시 핵심 요건인 '지식재산권 및 신기술 인증' 종류별로 요구되는 최초 등록(지정)일 기준 법정 유효 기한으로 올바른 것은? | E22: 실용신안: 등록일로부터 5년 이내 | F22: NET(신기술인증): 최초 지정일로부터 1년 이내 | G22: 특허: 등록일로부터 7년 이내 | H22: NEP(신제품인증): 최초 지정일로부터 7년 이내 | I22: 3 | J22: * 정답 (③): 혁신시제품 신청 요건으로 적용된 핵심 기술의 특허는 등록일 기준 7년 이내, 실용신안은 3년 이내여야 유효하며, 신제품(NEP) 및 신기술(NET) 인증은 공통적으로 3년 이내여야 합니다.
A23: 20 | B23: 3. 혁신·기술개발 촉진조달 | C23: 3. 혁신제품 지정제도의 이해 | D23: 조달청 혁신제품 구매운영 규정에 따른 '혁신제품 심사 및 지정 제외(탈락) 대상'에 대한 설명 중 법적으로 틀린 것은? | E23: 이전에 우수조달물품으로 지정되었던 낡은 핵심 기술이라도 다른 세부품명으로 바꾸기만 하면 얼마든지 신규 혁신제품 신청이 가능하다. | F23: 동일한 세부품명과 특정 핵심기술을 바탕으로 평가에서 통산 4회 이상 탈락한 이력이 있으면 향후 심사 대상에서 영구 제외된다. | G23: 시스템 지식재산권 중복 조회 결과, 동일 세부품명과 완전히 똑같은 특허번호가 이미 존재하면 규격 추가 외에 신규 절차는 진행할 수 없다. | H23: 이미 혁신제품으로 지정된 제품과 신청 제품의 핵심 기술 및 세부품명이 100% 동일할 경우 신규 심사 대상에서 배제될 수 있다. | I23: 1 | J23: * 정답 (①): 혁신제품 제도의 취지는 새로운 기술의 발굴이므로, 이미 '우수조달물품'으로 지정되어 시장에서 검증이 끝난 낡은 핵심 기술이라면 단순히 품명만 바꾼다고 해서 신규 혁신제품으로 심사받을 수 없습니다.
A24: 21 | B24: 4. 사회적가치 지원 조달 | C24: 1. 장애인기업 우선구매제도 이해 | D24: [상황] 한 공공기관의 연간 총 구매액이 1,000억원이다. 장애인기업 우선구매 목표를 충족하려면 최소 얼마 이상을 장애인기업 제품으로 구매해야 하는가? | E24: 10억원 | F24: 50억원 | G24: 30억원 | H24: 100억원 | I24: 1 | J24: * 정답 (①): 장애인기업활동 촉진법에 따라 총 구매액의 1% 이상을 장애인기업 제품으로 구매해야 하므로, 1,000억원의 1%인 10억원 이상이 목표가 됨. | K24: 장애인기업활동 촉진법
A25: 22 | B25: 4. 사회적가치 지원 조달 | C25: 2. 중증장애인생산품 우선구매제도 이해 | D25: [상황] 담당자가 '중증장애인생산품 우선구매와 장애인기업 우선구매는 같은 제도이니 하나만 관리하면 된다'고 말했다. 이 발언에 대한 평가로 가장 적절한 것은? | E25: 옳다. 두 제도는 동일하다 | F25: 옳지 않다. 두 제도는 근거 법령과 목표 대상이 달라 별도로 관리해야 한다 | G25: 옳다. 두 제도 모두 5% 목표를 공유한다 | H25: 옳다. 장애인기업활동 촉진법 하나로 모두 규율된다 | I25: 2 | J25: * 정답 (②): 중증장애인생산품 우선구매(중증장애인생산품 우선구매 특별법, 1%)와 장애인기업 우선구매(장애인기업활동 촉진법, 1%)는 근거 법령과 대상이 다른 별도의 제도임. | K25: 중증장애인생산품 우선구매 특별법
A26: 23 | B26: 4. 사회적가치 지원 조달 | C26: 3. 여성기업 우선구매제도 이해 | D26: [상황] 한 기관이 물품·용역 구매액 200억원, 공사 구매액 100억원을 집행할 예정이다. 여성기업 우선구매 목표에 따라 물품·용역과 공사 각각 최소 얼마를 여성기업 제품으로 구매해야 하는가? | E26: 물품·용역 4억원, 공사 1억원 | F26: 물품·용역 2억원, 공사 10억원 | G26: 물품·용역 20억원, 공사 5억원 | H26: 물품·용역 10억원, 공사 3억원 | I26: 4 | J26: * 정답 (④): 여성기업 우선구매는 물품·용역 5% 이상, 공사 3% 이상이므로 200억원의 5%인 10억원, 100억원의 3%인 3억원이 최소 목표금액이 됨. | K26: 여성기업지원에 관한 법률 제9조, 같은 법 시행령 제7조
A27: 24 | B27: 4. 사회적가치 지원 조달 | C27: 3. 여성기업 우선구매제도 이해 | D27: 다음 [보기]의 (A), (B)에 들어갈 의무 구매목표 비율 숫자를 합한 값은? [보기] - 여성기업 우선구매(물품·용역): ( A )% - 장애인기업 우선구매: ( B )% | E27: 2 | F27: 4 | G27: 6 | H27: 8 | I27: 3 | J27: * 정답 (③): 여성기업 우선구매(물품·용역)의 의무 구매목표 비율은 5%(A)이며, 장애인기업 우선구매 비율은 1%(B)임. 따라서 두 숫자의 합(5 + 1)은 6임. | L27: 260830 | M27: NUM
A28: 25 | B28: 4. 사회적가치 지원 조달 | C28: 4. 사회적기업제품 우선구매제도 이해 | D28: [상황] 고용노동부 소관 법령을 근거로 판로를 지원받는 기업 유형을 묻는 질문에, 담당자가 '중소기업기본법이 근거'라고 잘못 답했다. 올바른 근거 법률은? | E28: 중소기업제품 구매촉진 및 판로지원에 관한 법률 | F28: 협동조합기본법 | G28: 중소기업기본법 | H28: 사회적기업 육성법 | I28: 4 | J28: * 정답 (④): 사회적기업 제품 우선구매는 사회적기업 육성법에 근거하며, 주무부처는 고용노동부임. | K28: 사회적기업 육성법
A29: 26 | B29: 4. 사회적가치 지원 조달 | C29: 5. 공공조달과 사회적가치 및 이에스지(ESG) | D29: [상황] ESG 보고서를 작성하던 직원이 'S'를 'Safety(안전)'로 잘못 표기했다. 올바른 의미는? | E29: Sustainability(지속가능성) | F29: Standard(표준) | G29: Social(사회) | H29: Safety(안전) | I29: 3 | J29: * 정답 (③): ESG는 환경(E)·사회(S)·지배구조(G)의 약자이며, S는 Social(사회)을 의미함.
A30: 27 | B30: 4. 사회적가치 지원 조달 | C30: 5. 공공조달과 사회적가치 및 이에스지(ESG) | D30: [상황] 한 기관장이 '우리 기관의 조달 정책 목표는 오직 예산 절감 하나뿐이어야 한다'고 지시했다. 이 지시가 전략적 공공조달의 취지에 부합하는지에 대한 평가로 가장 적절한 것은? | E30: 부합한다. 다른 목표는 부차적이다 | F30: 부합한다. 비용 최소화가 유일한 목표여야 한다 | G30: 이 지시는 전략적 조달과 무관한 사안이다 | H30: 부합하지 않는다. 전략적 공공조달은 비용 절감뿐 아니라 중소기업 지원·환경보호·사회적 가치 실현 등을 함께 추구한다 | I30: 4 | J30: * 정답 (④): 전략적 공공조달은 비용 최소화만이 아니라 중소기업 지원·환경보호·사회적 가치 실현·기술혁신 등 다양한 목표를 동시에 추구함.
A31: 28 | B31: 4. 사회적가치 지원 조달 | C31: 5. 공공조달과 사회적가치 및 이에스지(ESG) | D31: [상황] 공공기관이 검토 중인 B제품은 장애인기업이 생산했고 우수재활용(GR) 인증도 받았지만, 기술개발제품 인증은 받지 못했다. 이 경우 적용 가능한 우선구매 제도를 모두 고르면? (ㄱ. 장애인기업 제품 우선구매 ㄴ. 녹색제품 우선구매 ㄷ. 기술개발제품 우선구매) | E31: ㄱ, ㄴ, ㄷ 모두 적용 가능하다 | F31: ㄱ, ㄷ만 적용 가능하다 | G31: ㄱ, ㄴ만 적용 가능하다 | H31: ㄴ, ㄷ만 적용 가능하다 | I31: 3 | J31: * 정답 (③): B제품은 장애인기업 제품(ㄱ)이자 GR인증 녹색제품(ㄴ)에 해당하지만, 기술개발제품 인증을 받지 못했으므로 ㄷ은 적용되지 않음.
A32: 29 | B32: 4. 사회적가치 지원 조달 | C32: 5. 공공조달과 사회적가치 및 이에스지(ESG) | D32: [상황] 발표자가 '혁신 촉진 정책은 ESG 중 지배구조(G)와 직접 관련이 크다'고 설명했다. 이 설명에 대한 평가로 가장 적절한 것은? | E32: 옳다. 지배구조만이 혁신의 유일한 동력이다 | F32: 옳다. 혁신 촉진은 ESG 요소와 전혀 무관하다 | G32: 옳지 않다. 혁신 촉진은 경제·사회적 가치와 관련되며, 지배구조(G)는 오히려 공정성·반부패 등과 관련이 크다 | H32: 옳다. 혁신은 지배구조 개선과 직결된다 | I32: 3 | J32: * 정답 (③): 혁신 촉진은 경제적·사회적 가치와 관련되며, 지배구조(G)는 투명성·공정성·반부패 등과 관련되어 혁신 촉진과 직접적 연관성은 낮음.
A33: 30 | B33: 4. 사회적가치 지원 조달 | C33: 5. 공공조달과 사회적가치 및 이에스지(ESG) | D33: [상황] 신입 직원이 다음 세 가지를 헷갈려 한다: 직접생산확인증명서 발급기관, 우수조달물품 지정기관, 혁신제품 구매자 면책의 적용범위. 이 중 옳게 정리된 것은? | E33: 두 서류 모두 중소벤처기업부장관이 담당하며, 면책 제도는 존재하지 않는다 | F33: 직접생산확인증명서는 중소벤처기업부장관이, 우수조달물품은 조달청장이 지정하며, 면책은 고의·중과실이 없을 때만 적용된다 | G33: 두 서류 모두 조달청장이 발급·지정하며, 면책은 모든 경우에 적용된다 | H33: 직접생산확인증명서는 조달청장이, 우수조달물품은 중소벤처기업부장관이 담당하며, 면책은 고의가 있어도 적용된다 | I33: 2 | J33: * 정답 (②): 직접생산확인증명서는 중소벤처기업부장관, 우수조달물품은 조달청장이 각각 발급·지정하며, 혁신제품 구매자 면책은 고의·중과실이 없는 경우에만 적용됨.
A34: 31 | B34: 4. 사회적가치 지원 조달 | C34: 5. 공공조달과 사회적가치 및 이에스지(ESG) | D34: [상황] 한 정책연구원이 '전략적 공공조달의 궁극적 지향점은 결국 대기업의 시장 지배력 확대'라고 주장했다. 이 주장에 대한 평가로 가장 적절한 것은? | E34: 옳지 않다. 전략적 공공조달은 경제·사회·환경적 가치를 동시에 실현하는 것을 궁극적 목표로 한다 | F34: 옳다. 조달 비용의 절대적 최소화가 유일한 목표이다 | G34: 옳다. 해외 기업 유치가 궁극적 목표이다 | H34: 옳다. 대기업 지배력 확대가 목표이다 | I34: 1 | J34: * 정답 (①): 전략적 공공조달은 단순 비용 절감을 넘어 중소기업 지원·사회적 가치·녹색성장·기술혁신 등 경제·사회·환경적 가치를 동시에 달성하는 것을 목표로 함.
A35: 32 | B35: 4. 사회적가치 지원 조달 | C35: 5. 공공조달과 사회적가치 및 이에스지(ESG) | D35: 연간 수십조 원에 달하는 공공조달의 거대한 막강한 구매력을 전략적으로 활용하여 우리 사회의 지속 가능한 '사회적 가치(Social Value)'를 실현하는 대표적인 실무 사례로 가장 적절한 것은? | E35: 특정 재난 상황에서 물품의 신속하고 정확한 납품을 유도하기 위해 계약서상에 명시된 납품 이행 기간을 기존 관례보다 대폭 단축하여 업체를 압박하는 행위 | F35: 유찰 발생 시 수반되는 불필요한 행정 비용을 줄이고 조달 업무를 빠르게 종결짓기 위해 의도적으로 법정 입찰 공고 횟수를 인위적으로 축소하는 행위 | G35: 중증 장애인 표준사업장, 사회적기업, 여성 기업 등이 생산한 제품이나 용역을 관련 법령에 근거하여 정부 기관의 목표액만큼 우선적으로 배정하여 구매하는 행위 | H35: 기업의 기술력이나 과거 납품 품질 실적 등에 상관없이 오로지 가장 낮은 투찰 가격을 제시한 영세 업체를 기계적으로 최종 낙찰자로 선정하여 예산을 아끼는 행위 | I35: 3 | J35: * 정답 (③): 사회적 가치 실현 조달(Social Public Procurement)이란 취약계층 일자리 창출 보장, 환경 보호, 지역 상생 등 경제적 효율성(최저가) 이외의 공익적 요소를 조달 과정에 적극 반영하여 사회적 기업 등을 우대하는 정책을 뜻합니다.
A36: 33 | B36: 1. 중소기업지원 조달 | C36: 1. 중소기업과 공공구매제도 이해 | D36: 전략적 공공조달의 기본 개념/원칙으로 가장 적절한 것은? | E36: 구두 합의가 문서보다 우선한다. | F36: 기준·절차를 사전에 명확히 하고 동일하게 적용하여 공정성과 투명성을 확보한다. | G36: 상황에 따라 사후에 기준을 바꾸어도 무방하다. | H36: 담당자 편의에 따라 공개·기록을 생략할 수 있다. | I36: 2 | J36: * 정답 (②): 원칙(사전확정·공개·기록·동일적용)은 감사·분쟁 리스크를 줄이는 핵심이다.
A37: 34 | B37: 1. 중소기업지원 조달 | C37: 1. 중소기업과 공공구매제도 이해 | D37: 전략적 공공조달 관련 실무통제(리스크 관리)로 가장 적절한 것은? | E37: 검수는 생략하고 하자 발생 시 추후 협의한다. | F37: 요구사항·평가기준·검수기준·변경절차를 문서화하고 이해관계자에게 사전 공유한다. | G37: 계약조건은 낙찰자와 구두로만 정한다. | H37: 평가기준은 입찰 마감 후 필요에 따라 조정한다. | I37: 2 | J37: * 정답 (②): 문서화+사전공유는 분쟁 예방, 성과관리, 책임소재 명확화에 가장 효과적이다.
A38: 35 | B38: 1. 중소기업지원 조달 | C38: 1. 중소기업과 공공구매제도 이해 | D38: 전략적 공공조달에 관한 설명으로 옳은 것은? | E38: 사전공개는 원칙이 아니라 선택사항이다. | F38: 조달절차의 각 단계는 관련 규정에 따라 수행되며, 핵심 판단은 기록으로 남겨야 한다. | G38: 입찰·계약 단계에서 이해상충은 문제되지 않는다. | H38: 절차는 내부 방침만 따르면 되며 외부 기준은 고려하지 않는다. | I38: 2 | J38: * 정답 (②): 절차 준수와 기록(근거)은 공공조달에서 필수 요건이다.
A39: 36 | B39: 1. 중소기업지원 조달 | C39: 1. 중소기업과 공공구매제도 이해 | D39: 중소기업지원 조달의 기본 개념/원칙으로 가장 적절한 것은? | E39: 기준·절차를 사전에 명확히 하고 동일하게 적용하여 공정성과 투명성을 확보한다. | F39: 담당자 편의에 따라 공개·기록을 생략할 수 있다. | G39: 상황에 따라 사후에 기준을 바꾸어도 무방하다. | H39: 구두 합의가 문서보다 우선한다. | I39: 1 | J39: * 정답 (①): 원칙(사전확정·공개·기록·동일적용)은 감사·분쟁 리스크를 줄이는 핵심이다.
A40: 37 | B40: 1. 중소기업지원 조달 | C40: 2. 중소기업자간 경쟁제도 이해 | D40: 중소기업자 간 경쟁제품으로 지정되기 위한 기본요건으로 옳은 것은? | E40: 국내에서 직접 생산·납품하는 중소기업이 10개 이상이고, 공공기관의 연간 구매 수요가 10억 원 이상이어야 한다. | F40: 국내에서 직접 생산·납품하는 중소기업이 20개 이상이고, 공공기관의 연간 구매 수요가 20억 원 이상이어야 한다. | G40: 국내에서 직접 생산·납품하는 중소기업이 30개 이상이고, 공공기관의 연간 구매 수요가 30억 원 이상이어야 한다. | H40: 국내에서 직접 생산·납품하는 중소기업이 50개 이상이고, 공공기관의 연간 구매 수요가 50억 원 이상이어야 한다. | I40: 2 | J40: * 정답 (②): 「판로지원법 시행령」에 따라 경쟁제품 지정 기본요건은 직접 생산·납품 중소기업 20개 이상, 연간 구매 수요 20억 원 이상이다.
A41: 38 | B41: 1. 중소기업지원 조달 | C41: 2. 중소기업자간 경쟁제도 이해 | D41: 직접생산확인증명서에 관한 설명으로 옳은 것은? | E41: 조달청장이 발급하며 유효기간은 2년이다. | F41: 중소벤처기업부 장관이 발급하며 유효기간은 1년이다. | G41: 중소벤처기업부 장관이 발급하며 유효기간은 3년이다. | H41: 재정경제부 장관이 발급하며 유효기간은 5년이다. | I41: 3 | J41: * 정답 (③): 직접생산확인증명서는 중소벤처기업부 장관(중소기업유통센터에 위탁)이 발급하며, 유효기간은 3년(갱신 가능)이다.
A42: 39 | B42: 1. 중소기업지원 조달 | C42: 3. 공사용자재 직접구매제도 이해 | D42: 공사용 자재 직접구매제도의 종합공사 적용 기준으로 옳은 것은? | E42: 추정가격 20억 원 이상의 종합공사에서 대상 품목의 추정가격이 2,000만 원 이상인 경우 | F42: 추정가격 30억 원 이상의 종합공사에서 대상 품목의 추정가격이 3,000만 원 이상인 경우 | G42: 추정가격 40억 원 이상의 종합공사에서 대상 품목의 추정가격이 4,000만 원 이상인 경우 | H42: 추정가격 50억 원 이상의 종합공사에서 대상 품목의 추정가격이 5,000만 원 이상인 경우 | I42: 3 | J42: * 정답 (③): 종합공사(「건설산업기본법」)의 경우 추정가격 40억 원 이상이며, 직접 구매 대상 품목의 추정가격이 4,000만 원 이상인 경우 직접구매제도가 적용된다. | K42: 판로지원법 시행령 제11조
A43: 40 | B43: 3. 혁신·기술개발 촉진조달 | C43: 1. 중소기업 기술개발제품 우선구매제도 이해 | D43: 기술개발제품 구매목표비율의 변천 과정으로 옳은 것은? | E43: 2006년 5% → 2009년 5% → 2016년 10% → 2020년 15% 이상 | F43: 2006년 5% → 2009년 10% → 2016년 10% 이상 → 2020년 15% 이상 | G43: 2006년 10% → 2009년 10% → 2016년 15% → 2020년 20% 이상 | H43: 2006년 5% → 2009년 10% → 2016년 15% → 2020년 20% 이상 | I43: 2 | J43: * 정답 (②): 기술개발제품 구매목표비율은 2006년 5%(권장)에서 2009년 10%(권장)로 상향되었으며, 2016년부터 10% 이상 구매가 법정 의무사항으로 전환되었습니다. 이후 2020년 2월 법령 개정을 통해 의무 비율이 15% 이상으로 강화되었고, 해당 기준은 공공기관 구매계획 수립 일정에 따라 2021년부터 실제 의무 달성 비율로 적용 중입니다.
A44: 41 | B44: 1. 중소기업지원 조달 | C44: 3. 공사용자재 직접구매제도 이해 | D44: 공사용 자재 직접 구매 예외 사유로 옳지 않은 것은? | E44: 「재난 및 안전관리기본법」 제3조에 따른 재난 관련 공사로 발주가 시급한 경우 | F44: 공사용 자재의 직접 구매로 국방·국가안보가 저해될 우려가 있다고 인정되는 공사 | G44: 공공기관의 장과 관할 지방중소벤처기업청장이 협의하여 직접 구매가 곤란하다고 인정한 경우 | H44: 발주기관의 예산 절감이 필요하다고 담당자가 판단하는 경우 | I44: 4 | J44: * 정답 (④): 직접 구매 예외 사유는 ① 재난 관련 시급 공사, ② 국방·국가안보 저해 우려, ③ 공공기관의 장과 지방중소벤처기업청장의 협의(도서·벽지 등)이다. 예산 절감을 이유로 한 임의 판단은 예외 사유에 해당하지 않는다.
A45: 42 | B45: 1. 중소기업지원 조달 | C45: 2. 중소기업자간 경쟁제도 이해 | D45: 중소기업자 간 경쟁제품의 지정 유효기간 및 지정 주체로 옳은 것은? | E45: 유효기간 1년, 조달청장이 지정·고시 | F45: 유효기간 3년, 중소벤처기업부 장관이 지정·고시 | G45: 유효기간 5년, 재정경제부 장관이 지정·고시 | H45: 유효기간 3년, 조달청장이 지정·고시 | I45: 2 | J45: * 정답 (②): 중소기업자 간 경쟁제품은 중소벤처기업부 장관이 지정·고시하며, 지정 유효기간은 3년이다. 매년 실태조사를 통해 신규 지정·추가·해제가 가능하다.
A46: 43 | B46: 1. 중소기업지원 조달 | C46: 1. 중소기업과 공공구매제도 이해 | D46: 「판로지원법」상 공공기관 구매목표비율 제도에 관한 설명으로 옳지 않은 것은? | E46: 공공기관은 매년 구매 계획을 수립하고 구매 실적은 중소벤처기업부에 보고해야 한다. | F46: 물품·용역의 전체 중소기업 구매비율은 50% 이상이다. | G46: 중소기업자 간 경쟁제품의 구매비율은 해당 품목의 80% 이상이다. | H46: 기술개발제품 구매목표비율은 물품 구매액의 5% 이상이다. | I46: 4 | J46: * 정답 (④): 기술개발제품 구매목표비율은 2006년 5%에서 시작해 단계적으로 상향되어, 현재는 물품 구매액의 15% 이상 의무 달성으로 적용된다.
A47: 44 | B47: 1. 중소기업지원 조달 | C47: 3. 공사용자재 직접구매제도 이해 | D47: 공사용 자재 직접구매(분리발주) 제도에 관한 설명으로 옳은 것은? | E47: 자재 조달 주체가 시공업체에서 발주기관으로 바뀌는 구조이다. | F47: 시공업체가 자재업체와 직접 계약하는 일반 방식과 동일하다. | G47: 모든 공사 규모에 일률적으로 적용된다. | H47: 직접구매 대상 품목은 일반경쟁입찰로만 진행된다. | I47: 1 | J47: * 정답 (①): 직접구매는 발주기관이 자재를 별도 계약으로 확보한 후 시공사에 인도하는 분리발주 방식이다. 시공업체의 하도급 자재업체에 대한 부당한 단가 인하·조건 강요를 구조적으로 차단한다. 직접구매 대상 품목은 중소기업 간 제한경쟁 또는 지명경쟁으로 입찰이 진행된다.
A48: 45 | B48: 1. 중소기업지원 조달 | C48: 2. 중소기업자간 경쟁제도 이해 | D48: 중소기업자 간 경쟁제품 입찰 참가에 필요한 자격 요건으로 옳은 것은? | E48: 직접생산확인증명서와 중소기업확인서를 모두 갖추어야 한다. | F48: 중소기업확인서만 있으면 직접생산확인증명서는 면제된다. | G48: 대기업도 일정 조건을 충족하면 입찰에 참가할 수 있다. | H48: 자격 요건 없이 누구나 입찰에 참가할 수 있다. | I48: 1 | J48: * 정답 (①): 중소기업자 간 경쟁제품에 입찰하려면 ① 직접생산확인증명서(실제 생산 능력 확인) + ② 중소기업확인서(중소기업 자격 확인)를 모두 보유해야 한다. 무자격 입찰을 방지하기 위한 이중 확인 장치이다.
A49: 46 | B49: 4. 사회적가치 지원 조달 | C49: 5. 공공조달과 사회적가치 및 이에스지(ESG) | D49: 여성기업·장애인기업의 공공구매 지원에 관한 설명으로 옳지 않은 것은? | E49: 여성기업 구매목표비율은 물품·용역 구매총액의 5% 이상이다. | F49: 여성기업 공사 구매목표비율은 공사구매총액의 3% 이상이다. | G49: 「판로지원법」 제5조에 근거한 의무 비율로 운영된다. | H49: 장애인기업 구매목표비율은 별도로 설정되지 않는다. | I49: 4 | J49: * 정답 (④): 장애인기업 구매목표비율은 구매총액의 1% 이상으로 별도로 설정되어 있다. 여성기업·장애인기업 모두 정책 대상 기업으로 별도 의무 비율이 적용된다.
A50: 47 | B50: 1. 중소기업지원 조달 | C50: 2. 중소기업자간 경쟁제도 이해 | D50: 중소기업자 간 경쟁제품 입찰의 낙찰자 결정 방식에 관한 설명으로 옳은 것은? | E50: 일반 낙찰 기준이 그대로 적용된다. | F50: 계약이행능력심사기준을 별도 제정·적용한다. | G50: 가격 입찰가만으로 낙찰자를 결정한다. | H50: 낙찰자 결정 시 중소기업 자격은 고려하지 않는다. | I50: 2 | J50: * 정답 (②): 중소기업자 간 경쟁제품 입찰은 일반 낙찰 기준이 아닌 '계약이행능력심사기준'을 별도 제정·적용하여 낙찰자를 결정한다. 이는 가격뿐만 아니라 계약 이행 능력(생산 능력, 경영 안정성 등)을 종합 평가하는 방식이다.
A51: 48 | B51: 2. 녹색조달 | C51: 1. 공공조달의 환경적 지속가능성 개요 | D51: 녹색조달에 관한 설명으로 옳은 것은? | E51: 사전공개는 원칙이 아니라 선택사항이다. | F51: 절차는 내부 방침만 따르면 되며 외부 기준은 고려하지 않는다. | G51: 입찰·계약 단계에서 이해상충은 문제되지 않는다. | H51: 조달절차의 각 단계는 관련 규정에 따라 수행되며, 핵심 판단은 기록으로 남겨야 한다. | I51: 4 | J51: * 정답 (④): 절차 준수와 기록(근거)은 공공조달에서 필수 요건이다.
A52: 49 | B52: 2. 녹색조달 | C52: 2. 녹색제품 우선구매제도 이해 | D52: 「녹색제품 구매촉진에 관한 법률」상 녹색제품의 3가지 유형으로 올바르게 짝지어진 것은? | E52: 환경표지제품, 저탄소제품, 에너지절약제품 | F52: 환경표지제품, 저탄소제품, 우수재활용제품 | G52: 친환경제품, 저탄소제품, 우수재활용제품 | H52: 환경표지제품, 탄소중립제품, 우수재활용제품 | I52: 2 | J52: * 정답 (②): 「녹색구매법」 제2조에 따라 녹색제품은 환경표지제품, 저탄소제품, 우수재활용제품의 3가지 유형으로 구성된다.
A53: 50 | B53: 2. 녹색조달 | C53: 3. 생애주기비용을 고려한 공공조달 제도 이해 | D53: 조달청이 운영하는 종합낙찰제의 평가 비율로 옳은 것은? | E53: 가격 60%, 품질 20%, 환경우월성(탄소배출량) 20% | F53: 가격 40%, 품질 40%, 환경우월성(탄소배출량) 20% | G53: 가격 40%, 품질 20%, 환경우월성(탄소배출량) 40% | H53: 가격 50%, 품질 30%, 환경우월성(탄소배출량) 20% | I53: 3 | J53: * 정답 (③): 종합낙찰제 평가공식은 G = 0.4×(입찰가격 점수) + 0.2×(품질 점수) + 0.4×(탄소배출량 점수)로, 가격 40%·품질 20%·환경우월성 40%이다.
A54: 51 | B54: 2. 녹색조달 | C54: 1. 공공조달의 환경적 지속가능성 개요 | D54: 녹색공공조달(GPP)에 관한 설명으로 옳지 않은 것은? | E54: 한국은 「녹색제품 구매촉진에 관한 법률」에 따라 공공기관의 녹색제품 의무구매제도를 운영하고 있다. | F54: EU는 전체 입찰의 50% 이상에 녹색 공공조달기준(GPP Criteria) 적용을 목표로 하고 있다. | G54: 해당 품목에 녹색제품이 존재하더라도 가격 차이가 크면 일반 제품을 구매할 수 있다. | H54: OECD 국가를 중심으로 GDP의 12 ~ 15%에 달하는 공공조달의 구매력을 환경보호에 활용한다. | I54: 3 | J54: * 정답 (③): 「녹색구매법」에 따라 해당 품목에 녹색제품이 존재하거나 대체 가능한 경우 반드시 녹색제품을 우선 구매해야 한다. 가격 차이를 이유로 일반 제품을 선택하는 것은 허용되지 않는다.
... A95: 92 | B95: 4. 사회적가치 지원 조달 | C95: 2. 중증장애인생산품 우선구매제도 이해 | D95: 이음장터의 운영 목적으로 가장 적절한 것은? | E95: 사회적기업·여성기업·장애인기업 등 사회적 가치 실현 기업의 제품 거래 플랫폼 운영 | F95: 외국 기업의 한국 시장 진출 지원 | G95: 대기업 제품의 우선구매 지원 | H95: 군수물자 전용 거래 시스템 | I95: 1 | J95: * 정답 (①): 이음장터는 사회적기업·여성기업·장애인기업·중증장애인생산품 시설 등 사회적 가치 실현 기업의 제품을 공공기관이 수의계약 방식으로 손쉽게 구매할 수 있도록 지원하는 플랫폼이다.
A98: 93 | B98: 3. 혁신·기술개발 촉진조달 | C98: 3. 혁신제품 지정제도의 이해 | D98: [상황] 국가 R&D로 개발한 신기술을 상용화하려는 스타트업이 초기 판로 확보와 조달 구매 기관의 감사 부담 경감을 동시에 요구하고 있다. 이 업체에게 안내할 가장 적합한 조달 제도는? | E98: 「혁신제품 지정 제도」를 통해 혁신장터에 등록하고, 수의계약 체결 및 구매 공무원의 감사 면책 혜택을 활용하도록 안내한다. | F98: 「우수조달물품 제도」를 통해 종합쇼핑몰에 우선 등록하고, 구매기관의 감사 면책은 별도의 심사위원회를 추가로 거치도록 안내한다. | G98: 「벤처나라 등록 제도」를 통해 창업기업 전용몰로 판로를 개척하되, R&D 제품 상용화에 따른 법정 구매면책은 적용되지 않음을 안내한다. | H98: 「신제품(NEP) 인증 제도」를 통해 기술력을 공식 입증받고, 별도 면책 없이 일반경쟁입찰에서 기술 가점을 받아 경쟁하도록 안내한다. | I98: 1 | J98: * 정답 (①): 「혁신제품 지정 제도」는 국가 R&D 성과물 등 혁신 기술의 초기 판로를 지원하기 위해 도입되었다. 혁신장터를 통한 수의계약이 가능하며, 적극행정의 일환으로 구매 공무원에게 법정 구매면책 혜택을 부여하여 조달 도입 시의 감사 부담을 경감시켜 준다. | K98: (출처)
A99: 94 | B99: 1. 중소기업지원 조달 | C99: 1. 중소기업과 공공구매제도 이해 | D99: [상황] A 국가기관은 추정가격 1억 5천만 원의 일반 물품을 구매하기 위해 입찰을 준비 중이다. 판로지원법령에 따른 올바른 입찰참가자격 제한 방법은? | E99: 2.3억 미만이므로 소기업·소상공인 대상 제한경쟁입찰 실시 | F99: 1억 이상이므로 중기업 포함 중소기업자 대상 제한경쟁입찰 실시 | G99: 지정 경쟁제품이 아니므로 기업 규모 무관 일반경쟁입찰 적용 | H99: 조달청 고시금액 미만이므로 실적 보유업체 대상 지명경쟁 적용 | I99: 2 | J99: * 정답 (②): 1억 원 미만은 '소기업·소상공인', 1억 원 이상~고시금액(약 2.3억) 미만은 '중소기업자(중기업 포함)' 간 제한경쟁을 실시하는 것이 원칙입니다. 일반 물품이라도 이 금액 구간에서는 적용됩니다. | K99: 판로지원법 시행령 제2조의2 | L99: 260904 | M99: NUM
A100: 95 | B100: 1. 중소기업지원 조달 | C100: 1. 중소기업과 공공구매제도 이해 | D100: 공공조달시장에서 운영되는 '중소기업자간 경쟁제도'의 세부 운영 기준에 대한 설명으로 가장 옳지 않은 것은? | E100: 직접생산 중소기업자만 대상으로 경쟁입찰을 실시해야 한다 | F100: 직접생산 미확인 유통업체는 참여가 엄격히 제한된다 | G100: 가격 출혈경쟁 방지 위해 별도 낙찰자결정기준을 따른다 | H100: 직접생산확인증명서는 낙찰자 결정 전까지 발급받아 제출하면 된다 | I100: 4 | J100: * 정답 (④): 직접생산 확인증명서는 원칙적으로 '입찰서 제출 마감일 전일'까지 발급된 것으로 유효기간 내에 있어야 입찰참가자격이 인정됩니다. 낙찰자 결정 전 사후 발급은 인정되지 않습니다. | K100: 판로지원법 제9조, 동법 시행령 제10조, 국가계약법 시행령 제36조 제4의2 | L100: 260904
A101: 96 | B101: 1. 중소기업지원 조달 | C101: 1. 중소기업과 공공구매제도 이해 | D101: [상황] C기관은 당해 연도 구매계획을 수립하며 중소기업제품 의무구매비율을 검토 중이다. 판로지원법령상 기준 및 제재 조치로 가장 옳은 것은? | E101: 총구매액의 30% 이상을 중소기업제품으로 우선구매 목표를 설정한다 | F101: 중소기업 물품구매액의 15% 이상을 기술개발제품으로 구매 목표를 설정한다 | G101: 시설·건설공사 계약금액은 총구매액 산정 기준에서 제외된다 | H101: 비율 미달 기관장은 차년도 기본경비 예산이 10% 삭감된다 | I101: 2 | J101: * 정답 (②): 판로지원법령에 따라 공공기관은 총구매액의 50% 이상을 중소기업제품으로, 중소기업 물품 구매액의 15% 이상을 기술개발제품으로 구매해야 합니다. (공사 금액도 포함되며, 예산 삭감 규정은 없습니다) | K101: 판로지원법 시행령 제3조, 제4조, 제12조 | L101: 260904 | M101: NUM
A102: 97 | B102: 2. 녹색조달 | C102: 1. 공공조달의 환경적 지속가능성 개요 | D102: 『녹색제품 구매촉진에 관한 법률』에 따른 공공기관의 녹색제품 의무구매 예외 사유로 법령에 명시되지 않은 것은? | E102: 예산 부족으로 타 의무비율 달성이 구조적으로 불가능한 경우 | F102: 재고 부족 등으로 기한 내 정상 납품이 불가능한 경우 | G102: 품질이 사업 목적 달성에 현저히 미달하는 경우 | H102: 긴급 구호·천재지변으로 조달할 시간 여유가 없는 경우 | I102: 1 | J102: * 정답 (①): 예산 부족이나 타 의무구매 비율 달성 곤란 등의 행정적 사유는 법정 의무구매 예외 사유에 명시되어 있지 않습니다. 예외가 되려면 현저한 품질 미달, 긴급 수요, 재고 부족 등 요건을 갖춰야 합니다. | K102: 녹색제품 구매촉진에 관한 법률 제6조 | L102: 260904
A103: 98 | B103: 2. 녹색조달 | C103: 1. 공공조달의 환경적 지속가능성 개요 | D103: 다음 중 관련 법령에 의해 공공기관이 의무적으로 우선 구매해야 하는 법정 '녹색제품'의 범주에 포함되지 않는 것은? | E103: 기후에너지환경부장관의 환경표지(마크) 인증을 획득한 제품 | F103: 산업통상부장관의 우수재활용(GR) 인증을 획득한 제품 | G103: 기후에너지환경부 고시 저탄소 인증 기준을 통과한 제품 | H103: 중소벤처기업부의 기술개발제품 성능인증(EPC)을 획득한 제품 | I103: 4 | J103: * 정답 (④): 중소기업 기술개발제품(성능인증 등)은 판로지원 대상일 뿐, 그 자체로 『녹색제품 구매촉진에 관한 법률』에서 정의하는 '녹색제품(환경표지, GR마크, 저탄소인증)'에 자동 포함되는 것은 아닙니다. | K103: 녹색제품 구매촉진에 관한 법률 제2조의2 | L103: 260904
A104: 99 | B104: 2. 녹색조달 | C104: 1. 공공조달의 환경적 지속가능성 개요 | D104: 녹색조달을 도입함으로써 발생하는 '생애주기비용(LCC)' 관점의 경제적 효과에 대한 설명으로 가장 타당한 것은? | E104: 내용연수 단축으로 감가상각비를 줄이는 회계 기법이다 | F104: 단가·유지보수비 상승으로 총비용이 일반 제품보다 높게 나타난다 | G104: 초기 단가는 높아도 장기적인 총소유비용(LCC)은 절감된다 | H104: 미래 운영·폐기 비용은 평가 지표에서 배제된다 | I104: 3 | J104: * 정답 (③): 녹색제품은 친환경 소재 및 고효율 기술 적용으로 초기 단가는 높을 수 있으나, 에너지 절감과 폐기 시 처리 비용 감소 등으로 전체 생애주기비용(LCC)은 낮아지는 것이 기대효과입니다. | L104: 260904

Sheet 1-5_공공조달법률이해
A2: 공공조달과 법제도 이해 - 5. 공공조달법률 이해
A3: 번호 | B3: 세부항목 | C3: 세세항목 | D3: 문제 내용 | E3: 보기① | F3: 보기② | G3: 보기③ | H3: 보기④ | I3: 정답 번호 | J3: 해설 및 오답노트 | K3: 출처 | L3: 개정일자 | M3: 숫자문제
A4: 1 | B4: 1. 공공계약 관련 민법 규정의 이해 | C4: 1. 계약의 성립 관련 규정 | D4: [상황] 한 시민이 '공공계약은 국가가 우월한 지위에서 일방적으로 명령하는 행정처분 아니냐'고 물었다. 이 질문에 대한 올바른 답변은? | E4: 맞다. 민법의 원리는 전혀 적용되지 않는다 | F4: 맞다. 공공계약은 행정처분의 일종이다 | G4: 아니다. 국가계약법이 민법보다 상위의 일반법이다 | H4: 아니다. 공공계약은 국가가 사경제 주체로서 상대방과 대등한 지위에서 체결하는 사법상 계약이다 | I4: 4 | J4: * 정답 (④): 판례에 따르면 공공계약은 국가가 사경제 주체로서 상대방과 대등한 지위에서 체결하는 사법상 계약이며, 국가계약법은 민법의 특별법적 지위를 가짐.
A5: 2 | B5: 1. 공공계약 관련 민법 규정의 이해 | C5: 1. 계약의 성립 관련 규정 | D5: [상황] 발주기관이 입찰공고를 낸 뒤 조달기업이 이에 응해 입찰서를 제출했다. 이 단계에서 발주기관의 낙찰자 결정이 '승낙'에 해당한다면, '청약'에 해당하는 행위는 무엇인가? | E5: 조달기업의 입찰서 제출 | F5: 발주기관의 계약서 작성 요청 | G5: 발주기관의 입찰공고 | H5: 조달기업의 계약이행 착수 | I5: 1 | J5: * 정답 (①): 입찰공고는 청약의 유인이며, 이에 응해 조달기업이 제출하는 입찰서가 구체적인 청약에 해당함.
A6: 3 | B6: 1. 공공계약 관련 민법 규정의 이해 | C6: 1. 계약의 성립 관련 규정 | D6: [상황] 두 회사가 구두로 물품 공급에 합의했으나 아직 정식 계약서를 작성하지 않았다. 민법상 이 합의의 계약 성립 여부에 대한 설명으로 가장 적절한 것은? | E6: 계약서 작성만이 유일한 계약 성립 요건이다 | F6: 청약과 승낙의 의사표시가 합치했다면 계약서 작성 여부와 무관하게 원칙적으로 계약이 성립한다 | G6: 계약서를 작성하지 않았으므로 어떠한 경우에도 계약이 성립하지 않는다 | H6: 구두 합의는 법적으로 아무 의미가 없다 | I6: 2 | J6: * 정답 (②): 민법상 계약은 청약과 승낙의 의사표시 합치만으로 성립하는 낙성계약이 원칙이며, 계약서 작성은 증거일 뿐 필수 성립요건은 아님(다만 개별 법령이 별도로 요구하는 경우는 예외).
A7: 4 | B7: 1. 공공계약 관련 민법 규정의 이해 | C7: 1. 계약의 성립 관련 규정 | D7: 국가기관이 대등한 사경제 주체로서 맺는 '정부계약'에 적용되는 민법상 기본 원칙이 아닌 것은? | E7: 자유롭게 합의하는 계약자유의 원칙 | F7: 상황 변화를 반영하는 사정변경의 원칙 | G7: 행정 절차를 규율하는 공정·투명의 원칙 | H7: 상호 신뢰를 바탕으로 한 신의성실의 원칙 | I7: 3 | J7: * 정답 (③): '공정·투명의 원칙'은 조달 행정 및 공법상의 원칙이며, 계약 당사자 관계를 규율하는 민법상(사법상) 원칙에 해당하지 않습니다.
A8: 5 | B8: 1. 공공계약 관련 민법 규정의 이해 | C8: 1. 계약의 성립 관련 규정 | D8: 국가계약법령상 정부계약의 의의와 법적 성질에 대한 설명으로 가장 올바르지 않은 것은? | E8: 행정 목적을 위한 사법상 계약이다. | F8: 대가적 의미를 지니는 쌍무계약이다. | G8: 우월적 지위에서 맺는 편무계약이다. | H8: 예산 범위 내의 공법적 제약을 받는다. | I8: 3 | J8: * 정답 (③): 정부계약은 당사자가 서로 대가적 의미를 지니는 의무를 부담하는 '쌍무계약'이며, 공권력을 통한 '편무계약'이 아닙니다.
A9: 6 | B9: 1. 공공계약 관련 민법 규정의 이해 | C9: 2. 계약의 효력 관련 규정 | D9: [상황] 계약 상대방을 착각해 잘못된 상대와 계약을 체결하거나, 상대방의 협박에 못 이겨 계약서에 서명한 경우가 있다. 이러한 사례들이 공통적으로 속하는 민법상 개념은? | E9: 계약의 해제 | F9: 채무불이행 | G9: 의사표시의 하자 | H9: 부당이득 | I9: 3 | J9: * 정답 (③): 착오, 사기·강박에 의한 의사표시는 비진의 의사표시·통정허위표시와 함께 민법상 의사표시의 하자에 해당함. | K9: 민법 제107조~제110조
A10: 7 | B10: 1. 공공계약 관련 민법 규정의 이해 | C10: 3. 계약의 해제·해지에 관한 규정 | D10: [상황] 임대차 계약을 중도에 끝내는 경우와, 매매계약을 처음부터 없었던 것으로 되돌리는 경우가 있다. 전자와 후자에 각각 해당하는 개념을 옳게 짝지은 것은? | E10: 전자=해지, 후자=해제 | F10: 전자=해제, 후자=해지 | G10: 전자·후자 모두 해지 | H10: 전자·후자 모두 해제 | I10: 1 | J10: * 정답 (①): 임대차처럼 계속적 계약을 장래에 향해 끝내는 것은 해지, 매매처럼 계약을 소급해 처음부터 무효화하는 것은 해제임. | K10: 민법 제543조~제550조
A11: 8 | B11: 1. 공공계약 관련 민법 규정의 이해 | C11: 4. 도급·위임에 관한 규정 | D11: [상황] 건설사가 건물 완공을 목표로 계약을 체결했고, 완공 후 하자가 발견되면 보수 책임을 진다는 조항이 있다. 이 계약의 유형으로 가장 적절한 것은? | E11: 임치 | F11: 화해 | G11: 위임 | H11: 도급 | I11: 4 | J11: * 정답 (④): 일의 완성을 목적으로 하고 완성물의 하자에 대해 담보책임을 지는 계약은 도급이며, 사무처리 자체를 목적으로 하는 위임과 구분됨. | K11: 민법 제664조·제667조
A12: 9 | B12: 2. 공공계약(국가 및 지방) 법령의 이해 | C12: 1. 추정가격 및 예정가격 결정 | D12: [상황] 담당자가 개찰이 끝나기 전 낙찰 예정업체에게 '예정가격을 미리 알려달라'는 요청을 받았다. 이 요청에 응해도 되는지에 대한 설명으로 가장 적절한 것은? | E12: 응해도 된다. 예정가격은 추정가격과 달리 사전 공개가 원칙이다 | F12: 예정가격은 부가가치세를 제외해 산정하므로 공개해도 무방하다 | G12: 응해도 된다. 예정가격은 낙찰자 결정과 무관한 참고자료일 뿐이다 | H12: 응하면 안 된다. 예정가격은 개찰 전까지 공개되지 않으며 낙찰자·계약금액 결정의 기준이 되므로 사전 유출은 부정행위이다 | I12: 4 | J12: * 정답 (④): 예정가격은 개찰 전까지 비공개이며 낙찰자·계약금액 결정의 기준이 되므로, 사전 유출 요청에 응하는 것은 부정행위에 해당함. | K12: 국가계약법 시행령 제2조·제7조의2
A13: 10 | B13: 2. 공공계약(국가 및 지방) 법령의 이해 | C13: 1. 추정가격 및 예정가격 결정 | D13: [상황] 한 담당자가 복수예비가격 제도의 목적을 '절차를 빠르게 끝내기 위한 것'이라고 설명했다. 이 설명에 대한 평가로 가장 적절한 것은? | E13: 이 제도는 목적 자체가 정해져 있지 않다 | F13: 옳지 않다. 이 제도는 특정인이 사전에 예정가격을 알 수 없도록 해 입찰의 공정성을 확보하는 데 주된 목적이 있다 | G13: 옳다. 신속성과 공정성은 동일한 개념이다 | H13: 옳다. 신속성이 유일한 목적이다 | I13: 2 | J13: * 정답 (②): 복수예비가격 제도는 신속성보다 예정가격 사전 유출을 막아 공정성을 확보하는 데 주된 목적이 있음. | K13: 국가계약법 시행령 제7조의2
A14: 11 | B14: 2. 공공계약(국가 및 지방) 법령의 이해 | C14: 1. 추정가격 및 예정가격 결정 | D14: 예정가격 결정 전, 예산에 계상된 금액 등을 기준으로 부가세 및 관급자재 대금을 제외하고 산정한 가격은? | E14: 고시금액 | F14: 기초금액 | G14: 예정가격 | H14: 추정가격 | I14: 4 | J14: * 정답 (④): 부가세 등을 제외한 순수 사업 예산 기준액은 '추정가격'입니다. (기초금액, 예정가격 등과 엄격히 구별됨)
A15: 12 | B15: 2. 공공계약(국가 및 지방) 법령의 이해 | C15: 1. 추정가격 및 예정가격 결정 | D15: 국가계약법령상 입찰 및 계약방법을 결정하는 '추정가격' 기준에 대한 설명으로 올바르지 않은 것은? | E15: 국제입찰 의무 대상은 추정가격이 고시금액 이상인 경우이다. | F15: 지역제한경쟁입찰은 추정가격이 고시금액 미만일 때 적용된다. | G15: 일반적인 물품 소액수의계약 한도는 추정가격 1억 원 이하이다. | H15: 물품 제조·구매 지명경쟁입찰은 추정가격 1억 원 미만으로 제한된다. | I15: 4 | J15: * 정답 (④): 특수물품 제조 및 구매에 대한 지명경쟁입찰은 추정가격 1억 원 미만이 아니라 '1억 원 이하'인 경우에 가능합니다.
A16: 13 | B16: 2. 공공계약(국가 및 지방) 법령의 이해 | C16: 1. 추정가격 및 예정가격 결정 | D16: 전자입찰의 전체 진행 절차 중, 기초금액을 바탕으로 생성된 '예정가격'이 실질적인 효력을 발휘하여 결정되는 단계는? | E16: 개찰 단계 | F16: 공고 단계 | G16: 투찰 단계 | H16: 계약 단계 | I16: 1 | J16: * 정답 (①): 투찰 시점에는 업체와 발주기관 모두 최종 예정가격을 알 수 없으며, 투찰 마감 후 '개찰'을 진행할 때 난수 추첨 등을 통해 예정가격이 확정되어 낙찰 기준이 됩니다.
A17: 14 | B17: 2. 공공계약(국가 및 지방) 법령의 이해 | C17: 1. 추정가격 및 예정가격 결정 | D17: 예산을 확정하기 어렵거나 긴급한 사유로 1인 견적구매, 계산계약, 기술제안입찰, 일괄입찰 등을 진행할 때 예외적으로 적용하는 예정가격 결정 방식은? | E17: 시스템 난수 추첨을 통해 결정하는 복수예가 | F17: 가장 낮은 견적서를 제출한 업체의 최저가격 | G17: 기초금액 자체를 예가로 확정 짓는 단일예가 | H17: 예정가격을 아예 작성하지 않고 진행하는 비예가 | I17: 4 | J17: * 정답 (④): 일괄입찰(턴키), 대안입찰, 협상에 의한 계약 등 업체가 가격과 기술을 자율적으로 제안해야 하는 특수한 형태의 계약에서는 예정가격을 생략하는 '비예가' 방식을 씁니다.
A18: 15 | B18: 2. 공공계약(국가 및 지방) 법령의 이해 | C18: 1. 추정가격 및 예정가격 결정 | D18: 입찰 참가 업체들이 투찰 금액을 결정하는 절대적 기준이 되는 '기초금액'의 법정 공개 시점으로 가장 원칙적이고 올바른 것은? | E18: 업체의 철저한 비밀 유지를 위해 개찰이 완료되기 전까지는 시스템상 절대 공개하지 않는다. | F18: 투찰의 기준이 되므로 입찰공고와 동시에, 또는 늦어도 입찰서 접수 개시일 5일 전까지는 공개해야 한다. | G18: 입찰의 공정성을 확보하기 위해 개찰을 완료하고 낙찰예정자를 선정한 직후에 즉시 공개한다. | H18: 개찰 후 적격심사 대상자로 선정된 1~3순위 업체가 심사 서류를 제출할 때에만 한정하여 공개한다. | I18: 2 | J18: * 정답 (②): 기초금액은 업체들이 예가를 유추하고 투찰 금액을 산정하는 기준표이므로, 투찰 시작 전(접수 개시일 5일 전)에 미리 공개하여 분석할 시간을 주어야 합니다. | K18: 조달청 내자구매업무 처리규정 제30조
A19: 16 | B19: 2. 공공계약(국가 및 지방) 법령의 이해 | C19: 1. 추정가격 및 예정가격 결정 | D19: 기초금액이 1억 원으로 산정된 일반용역 입찰에서, 해당 기관의 복수예비가격 산출 범위가 '98% ~ 102%'로 설정되었다면 복수예비가격이 생성되는 최소값과 최대값은? | E19: 9,900만 원 / 1억 1백만 원 | F19: 1억 원 / 1억 2백만 원 | G19: 9,000만 원 / 1억 1천만 원 | H19: 9,800만 원 / 1억 2백만 원 | I19: 4 | J19: * 정답 (④): 1억 원의 98%는 9,800만 원, 102%는 1억 200만 원(1억 2백만 원)이므로 이 범위 내에서 15개의 복수예비가격이 무작위로 생성됩니다.
A20: 17 | B20: 2. 공공계약(국가 및 지방) 법령의 이해 | C20: 1. 추정가격 및 예정가격 결정 | D20: 국가계약법령상 공공조달 계약 업무에 적용되는 여러 금액 기준 중, '추정가격'에 대한 올바른 법적·실무적 정의는? | E20: 낙찰자 및 계약금액 결정의 기준으로 삼기 위해 발주기관이 사전에 미리 산정하여 비치해 두는 금액 | F20: 복수예비가격을 산정하기 위한 기준이 되며 입찰서 접수 개시 전에 전자조달시스템에 공개하는 금액 | G20: 국제입찰 대상 여부 판단 등의 기준으로 삼기 위해 예정가격 결정 전에 산정하는 부가가치세 제외 금액 | H20: 계약 목적물 완성에 필요한 총 사업비로서 산정된 금액에 부가가치세와 관급자재대가를 모두 합산한 금액 | I20: 3 | J20: * 정답 (③): 「국가를 당사자로 하는 계약에 관한 법률 시행령」 제2조 제1호 및 제7조에 따라 '추정가격'은 국제입찰 대상 여부를 판단하는 기준 등으로 삼기 위해 산정된 가격을 말하며, 실무적으로 부가가치세와 관급자재대가를 제외한 순수 금액을 의미합니다. (①은 예정가격, ②는 기초금액, ④는 추정금액에 대한 설명입니다.)
A21: 18 | B21: 2. 공공계약(국가 및 지방) 법령의 이해 | C21: 1. 추정가격 및 예정가격 결정 | D21: 국가계약 및 지방계약 주요 용어 정의에 대한 설명으로 가장 옳은 것은? | E21: 예정가격 결정 이후에 비로소 산정되는 기준 금액을 추정가격이라 칭한다. | F21: 국제입찰 적용 대상 기준 금액은 조달청장이 단독으로 정하여 고시한다. | G21: 지방계약법상 교육·과학·체육 사항은 행안부장관을 교육부장관으로 간주한다. | H21: 계약체결 전 전체 예산 규모를 뜻하는 예산액은 예정가격과 항상 동일하다. | I21: 3 | J21: 정답 (③) 지방계약법 제3조에 따라 교육 등은 교육부장관 소관임 / ① 추정가격은 예가 결정 전 가격임 / ② 재경부·행안부장관 고시 | K21: 지방계약법
A22: 19 | B22: 2. 공공계약(국가 및 지방) 법령의 이해 | C22: 1. 추정가격 및 예정가격 결정 | D22: 원가계산 시 일반관리비 산정 기준 금액에 대한 설명으로 가장 옳은 것은? | E22: 일반관리비를 산정하기 위한 기준 합계 금액에는 이윤 비목도 포함된다. | F22: 일반관리비는 재료비, 노무비, 경비 합계액을 기준으로 일정 비율을 곱한다. | G22: 계약목적물 제조에 소요되는 직접 노무비는 일반관리비 기준에서 제외된다. | H22: 계약목적물 제조에 소요되는 모든 제반 경비는 일반관리비 대상이 아니다. | I22: 2 | J22: 정답 (②) 일반관리비는 (재료비+노무비+경비) 합계에 요율을 곱함 / ① 이윤은 제외됨 | K22: 예정가격작성
A23: 20 | B23: 2. 공공계약(국가 및 지방) 법령의 이해 | C23: 1. 추정가격 및 예정가격 결정 | D23: 예정가격 결정을 위해 우선적으로 적용하는 가격 산정 기준 순서로 가장 옳은 것은? | E23: 원가계산가격 - 거래실례가격 - 표준시장단가 - 견적가격 - 감정가격 | F23: 감정가격 - 유사 거래실례가격 - 견적가격 - 거래실례가격 - 원가계산 | G23: 거래실례가격 - 원가계산가격 - 감정가격 및 유사 거래실례가격 - 견적가격 | H23: 거래실례가격 - 감정가격 - 원가계산가격 - 유사 거래실례가격 - 견적가격 | I23: 3 | J23: 정답 (③) 1. 거래실례, 2. 원가계산, 3. 감정가·유사거래·견적가 순임 | K23: 국가계약법 시행령 제9조
A24: 21 | B24: 2. 공공계약(국가 및 지방) 법령의 이해 | C24: 1. 추정가격 및 예정가격 결정 | D24: 공공계약 예정가격 결정 시 원칙적인 산출 기준 단위로 가장 적절한 것은? | E24: 계약목적물 전체 단가 평균 | F24: 월별 단위 환산 납품 가액 | G24: 계약목적물 전체에 대한 총액 | H24: 시장 표준 기준 시중 실례 단가 | I24: 3 | J24: 정답 (③) 원칙적으로 계약목적물 가격의 '총액'에 대하여 예정가격을 결정함 | K24: 국가계약법 시행령 제8조
A25: 22 | B25: 2. 공공계약(국가 및 지방) 법령의 이해 | C25: 1. 추정가격 및 예정가격 결정 | D25: 일정 기간 계속하여 제조·구매하는 계약의 경우, 예정가격 결정 시 예외적으로 적용할 수 있는 산출 기준은? | E25: 총사업비의 합산 금액 | F25: 계약목적물의 단가 | G25: 분기별 산정 추정가격 | H25: 조달청장의 고시 금액 | I25: 2 | J25: 정답 (②) 국가계약법 제8조 단서에 따라 일정 기간 계속되는 제조·공사·수리·가공·매매·공급·임차 등 계약은 예외적으로 '단가'에 대해 예정가격을 결정할 수 있음(단가계약) | K25: 국가계약법 시행령 제8조
A26: 23 | B26: 2. 공공계약(국가 및 지방) 법령의 이해 | C26: 1. 추정가격 및 예정가격 결정 | D26: 다음 중 국가계약법령상 예정가격의 작성을 생략할 수 있는 경우로 가장 옳지 않은 것은? | E26: 국가기관이나 지방자치단체와 계약을 체결하는 경우 | F26: 협상에 의한 계약이나 경쟁적 대화에 의한 계약 | G26: 원가계산이 곤란하여 개산계약을 체결하는 경우 | H26: 전자조달시스템을 통해 견적서를 제출받는 수의계약 | I26: 4 | J26: 정답 (④) 견적서를 제출하게 하는 수의계약은 예정가격 생략 대상에서 제외되므로 원칙대로 작성해야 함 / ①·②·③은 모두 예정가격 작성 생략 가능 사유임 | K26: 국가계약법 시행령 제7조의2
A27: 24 | B27: 2. 공공계약(국가 및 지방) 법령의 이해 | C27: 2. 계약의 방법에 관한 규정 | D27: [상황] 지방자치단체가 지역경제 활성화를 위해 관내 업체에 입찰 참가 우대 조건을 부여했다. 이 조치가 가능한 근거로 가장 적절한 것은? | E27: 지역업체 우대는 모든 공공기관에 동일하게 적용되는 국가계약법 조항이다 | F27: 국가계약법과 지방계약법은 완전히 동일해 이런 우대가 불가능하다 | G27: 지방자치단체는 어떠한 법령의 적용도 받지 않는다 | H27: 지방계약법은 국가계약법과 기본 골격은 유사하되, 지역제한입찰 등 지역업체 우대 규정을 별도로 두고 있다 | I27: 4 | J27: * 정답 (④): 지방계약법은 국가계약법과 기본 골격은 유사하지만, 지역경제 활성화를 위한 지역제한입찰 등 지역업체 우대 규정을 별도로 두고 있음. | K27: 국가계약법, 지방계약법 비교
A28: 25 | B28: 2. 공공계약(국가 및 지방) 법령의 이해 | C28: 2. 계약의 방법에 관한 규정 | D28: [상황] 발주기관이 차세대 정보시스템 구축 용역을 발주하면서, 가격뿐 아니라 시스템 성능·안정성·개발사의 기술력 등을 종합 평가해 계약상대자를 정하려 한다. 가장 적합한 계약방법은? | E28: 일반 물품 구매 방식의 지명경쟁 | F28: 협상에 의한 계약 | G28: 단순 최저가 경쟁입찰 | H28: 단순 수의계약 | I28: 2 | J28: * 정답 (②): 협상에 의한 계약은 기술성·전문성 평가가 중요한 계약에 적용되며, 정보시스템 구축처럼 비가격적 요소가 중요한 사업에 적합함.
A29: 26 | B29: 2. 공공계약(국가 및 지방) 법령의 이해 | C29: 2. 계약의 방법에 관한 규정 | D29: 정부계약의 실무적·학술적 분류 기준에 해당하지 않는 것은? | E29: 재정의 수입 또는 지출 여부에 따른 분류 | F29: 조달 목적물이 무엇인가에 따른 세부 분류 | G29: 입찰 전 계약금액의 확정 여부에 따른 분류 | H29: 조달청 내부의 전자 결재 방식에 따른 분류 | I29: 4 | J29: * 정답 (④): 기관 내부의 전자 결재 방식이나 문서 양식 등은 정부계약을 구분하는 학술적·법적 분류 기준이 아닙니다.
A30: 27 | B30: 2. 공공계약(국가 및 지방) 법령의 이해 | C30: 2. 계약의 방법에 관한 규정 | D30: 정부계약을 다양한 실무적 기준에 따라 분류할 때, 오직 '계약체결의 형태'에 속하는 항목으로만 올바르게 나열된 것은? | E30: 사전에 금액을 고정하는 확정계약, 여러 업체가 참여하는 공동계약, 수년간 이행하는 장기계속계약 | F30: 미리 단가만 정해두는 단가계약, 전체 대가를 고정하는 총액계약, 무형의 기술을 제공받는 용역계약 | G30: 사후에 실비를 정산하는 개산계약, 단일 업체가 수행하는 단독계약, 참가 자격을 제한하는 제한경쟁 | H30: 국회 의결을 받아두는 계속비계약, 경쟁을 배제하고 맺는 수의계약, 건축물을 신축하는 시설공사계약 | I30: 1 | J30: * 정답 (①): 계약체결 형태에는 금액(확정/개산), 수량(총액/단가), 당사자 수(단독/공동), 이행 기간(장기계속/계속비) 기준이 모두 포함됩니다. 반면 용역계약과 시설공사는 '목적물', 제한경쟁과 수의계약은 '계약(입찰) 방법'에 해당하여 오답입니다.
A31: 28 | B31: 2. 공공계약(국가 및 지방) 법령의 이해 | C31: 2. 계약의 방법에 관한 규정 | D31: 계약 대상이 되는 '목적물의 성질'에 따른 공공계약의 분류로 볼 수 없는 것은? | E31: 무형의 가치를 제공받는 각종 용역계약 | F31: 유형의 재화를 획득하는 물품구매계약 | G31: 수년에 걸쳐 예산을 나누는 장기계속계약 | H31: 건축물이나 토목을 수행하는 시설공사계약 | I31: 3 | J31: * 정답 (③): 장기계속계약은 조달 목적물이 아니라 '계약체결 형태(기간 장단 및 예산 확보 방식)'에 따른 분류입니다.
A32: 29 | B32: 2. 공공계약(국가 및 지방) 법령의 이해 | C32: 2. 계약의 방법에 관한 규정 | D32: 공공계약을 실무적으로 분류하는 정식 체계 중에서, 일반적으로 통용되지 않는 분류 기준은? | E32: 최종 계약금액이 사전에 확정적으로 결정되어 있는지에 따른 금액 확정 여부 분류 | F32: 최종 납품 및 인도가 이루어지는 지리적 장소가 결정되었는지에 따른 장소 확정 여부 분류 | G32: 목적물의 납품 수량이 체결 시점에 미리 특정되어 있는지에 따른 물량 확정 여부 분류 | H32: 사업 이행에 필요한 시일이 회계 연도를 넘기는지에 따른 이행 기간 장단 여부 분류 | I32: 2 | J32: * 정답 (②): 계약의 금액, 수량, 이행기간 확정 여부는 공식적인 정부계약 분류 기준이나, '장소의 물리적 확정 여부'는 정식 분류 체계가 아닙니다.
A33: 30 | B33: 2. 공공계약(국가 및 지방) 법령의 이해 | C33: 2. 계약의 방법에 관한 규정 | D33: 상용화되지 않은 개발시제품 제조나 긴급한 재난 복구 등 사전에 원가를 정확히 계산할 수 없을 때 적용하는 계약은? | E33: 낙찰 금액을 사전에 고정하는 확정계약 | F33: 이행 후 실비를 사후 정산하는 개산계약 | G33: 단가만 합의하여 계속 수급하는 단가계약 | H33: 일부 비목별로만 사후 정산하는 조건부계약 | I33: 2 | J33: * 정답 (②): 긴급복구나 개발시제품 등 사전에 예정가격을 도저히 정할 수 없는 경우에는 정산조건부인 '개산계약' 방식으로 우선 추진합니다.
A34: 31 | B34: 2. 공공계약(국가 및 지방) 법령의 이해 | C34: 2. 계약의 방법에 관한 규정 | D34: '계약 목적물에 대한 수량의 확정 여부'를 기준으로 한 계약 분류 체계에 속하지 않는 제도는 무엇인가? | E34: 품질이 유사한 다수 업체를 등록시켜 선택권을 부여하는 다수공급자계약 | F34: 연도별로 예산을 분할하여 차수계약 형식으로 맺는 장기계속계약 | G34: 공통 규격 품목을 대상으로 단가만 미리 정해두는 제3자를 위한 단가계약 | H34: 소모성 물품에 대해 수량을 고정하지 않고 개별 단가만 합의하는 단가계약 | I34: 2 | J34: * 정답 (②): 장기계속계약은 수량의 확정 여부가 아니라 '계약이행기간의 장단' 및 당해 연도 예산 반영 방식에 따른 분류입니다.
A35: 32 | B35: 2. 공공계약(국가 및 지방) 법령의 이해 | C35: 2. 계약의 방법에 관한 규정 | D35: 수년에 걸쳐 이행되는 대규모 국가 사업에 적용되는 '장기계속계약'과 '계속비계약'의 차이점으로 가장 바른 것은? | E35: 두 계약 모두 사업 완료 마지막 연도에 대금을 일괄 지급하는 공통점이 있다. | F35: 계속비계약은 예산 한도 내에서만 차수별로 계약하는 매우 유연한 방식이다. | G35: 장기계속계약은 당해 연도 예산으로 차수계약하고, 계속비는 총액으로 연속 이행한다. | H35: 장기계속계약은 사업 총액과 연부액을 국회의 의결을 거쳐 미리 엄격히 확정한다. | I35: 3 | J35: * 정답 (③): 장기계속계약은 당해 연도 확보 예산만으로 연도별 차수계약을 맺지만, 계속비계약은 국회 의결을 받아 연부액에 따라 끊김 없이 이행합니다.
A36: 33 | B36: 2. 공공계약(국가 및 지방) 법령의 이해 | C36: 2. 계약의 방법에 관한 규정 | D36: 다수의 업체가 상호 협력하여 대형 조달 사업을 수행하는 '공동계약' 제도에 대한 설명 중 사실과 명백히 다른 것은? | E36: 계약 목적물 성질상 부적절한 경우 외에는 중소기업 보호를 위해 원칙적으로 허용한다. | F36: 분담이행방식은 각자의 출자비율에 따라 자본을 섞어 연대하여 이행하는 방식을 말한다. | G36: 책임 소재를 명확히 하기 위해 공동이행방식의 공동수급체 구성원은 5인 이하로 제한된다. | H36: 공동계약의 유형은 크게 자본을 섞는 공동이행방식과 과업(공종)을 분담하는 분담이행이 있다. | I36: 2 | J36: * 정답 (②): 출자비율에 따라 '연대하여' 이행하는 방식은 '공동이행방식'입니다. '분담이행방식'은 면허나 공종에 따라 각자 과업을 분담하여 독립적으로 책임지는 방식입니다.
A37: 34 | B37: 2. 공공계약(국가 및 지방) 법령의 이해 | C37: 2. 계약의 방법에 관한 규정 | D37: 대형 사업을 다수가 수행하는 공동계약 유형 중 '공동이행방식'과 '분담이행방식'의 차이를 명확히 구분한 것은? | E37: 공동이행은 공사 구역을 엄격히 나누고, 분담이행은 지분율에 따라 손익을 연대 책임지는 방식이다. | F37: 공동이행은 대표사가 모든 하도급 책임을 지고, 분담이행은 구성원 전원이 직접 시공하는 방식이다. | G37: 공동이행은 대표사 1인만 무한 책임을 지고, 분담이행은 각 지분율로 발주처와 개별 계약하는 방식이다. | H37: 공동이행은 자본을 섞어 출자비율로 연대 이행하며, 분담이행은 분담 내용을 각자 독립 이행하는 방식이다. | I37: 4 | J37: * 정답 (④): 공동이행은 구성원 전원이 출자비율에 따라 '연대책임'을 지는 방식이며, 분담이행은 각자가 맡은 공종만 독립적으로 책임지고 이행하여 연대책임이 없는 방식입니다.
A38: 35 | B38: 2. 공공계약(국가 및 지방) 법령의 이해 | C38: 2. 계약의 방법에 관한 규정 | D38: 공공계약을 실무적으로 세분화할 때, '계약금액의 사전 확정 여부'를 기준으로 분류하는 방식에 해당하지 않는 것은? | E38: 원가 계산을 통해 예정가격 내에서 낙찰 금액을 확정 지어 체결하는 가장 통상적인 확정계약 | F38: 정확한 원가 산정이 불가능하여 대략 체결 후 이행 완료 시점에 실비로 사후 정산하는 개산계약 | G38: 기술 능력과 가격을 종합 심층 평가하여 가장 유리한 조건을 제시한 자와 맺는 협상에 의한 계약 | H38: 일부 비목별 금액을 결정할 수 없어 일단 체결 후 이행 뒤 해당 비목만 정산하는 조건부계약 | I38: 3 | J38: * 정답 (③): 확정, 개산, 조건부계약은 '금액의 확정 여부'에 따른 분류이나, '협상에 의한 계약'은 계약 체결 형태가 아닌 '낙찰자를 선정하는 방식(결정 기준)'의 종류입니다.
A39: 36 | B39: 2. 공공계약(국가 및 지방) 법령의 이해 | C39: 2. 계약의 방법에 관한 규정 | D39: 정부계약의 유형 및 회계연도 예산 집행 특성에 대한 설명으로 가장 올바른 것은? | E39: 장기계속계약은 사업 총액으로 입찰하는 것이 불가능하므로, 각 회계연도 예산 범위 내에서 매년 별도의 새로운 단가 입찰을 실시해야 한다. | F39: 단일공사로서 설계서 등에 의해 전체 사업내용이 확정된 공사는 지역 업체 참여 확대를 위해 가급적 잘게 분할하여 계약하는 것이 원칙이다. | G39: 성질상 중단할 수 없는 상시 용역 계약이라도 예산 배정 문제로 반드시 해당 회계연도가 공식 시작된 이후에만 계약을 체결해야 한다. | H39: '개산계약(槪算契約)'은 계약 체결 시점에 목적물의 금액을 확정할 수 없을 때 맺는 방식이며, 이행 완료 후 반드시 사후정산 절차를 거쳐야 한다. | I39: 4 | J39: * 정답 (④): 개발 시제품 제작 등 사전에 원가를 확정할 수 없는 경우 개산계약을 체결하며, 이는 사후 원가 검토를 통한 정산이 필수적입니다. (오답 노트: ① 장기계속계약은 총액으로 입찰 집행, ② 단일공사 분할계약 금지 원칙(시행령 제68조), ③ 임차·운송 등 성질상 중단할 수 없는 계약은 회계연도 개시 전이라도 미리 체결 가능(법 제20조)) | K39: 「국가계약법」 제23조 및 동법 시행령 제70조
A40: 37 | B40: 2. 공공계약(국가 및 지방) 법령의 이해 | C40: 2. 계약의 방법에 관한 규정 | D40: 공동수급체를 구성하여 입찰에 참여하는 공동계약 제도에 대한 설명으로 가장 올바른 것은? | E40: 공동수급체의 구성원은 계약 이행에 필요한 면허, 등록 등의 자격요건을 대표사 1인만 갖추고 있으면 나머지 구성원은 자격이 없어도 무방하다. | F40: 건설업 등의 균형발전을 위해 공동계약을 체결할 때, 담합 방지를 위해 반드시 공사현장 관할 구역 외의 업체를 대표사로 지정해야 한다. | G40: 국가계약법령상 공동계약은 강제 규정이 아니며, 발주기관이 목적과 성질을 고려하여 필요하다고 인정할 때 재량으로 채택할 수 있다. | H40: 광역시·도는 관할구역 내 기관의 공통 필요 물자에 대해 타 지자체와의 형평성을 이유로 제3자를 위한 단가계약을 체결할 권한이 없다. | I40: 3 | J40: * 정답 (③): 법령상 "공동계약에 의할 수 있다"라고 규정되어 있어, 목적과 성질상 부적합한 경우 단독 계약으로 진행할 수 있는 발주기관의 재량 사항입니다. (① 구성원 각자가 요건 충족 필요) | K40: 「국가계약법」 제25조
A41: 38 | B41: 2. 공공계약(국가 및 지방) 법령의 이해 | C41: 2. 계약의 방법에 관한 규정 | D41: 정부는 계속적인 제조, 수리, 공급 등을 요하는 물품에 대하여 일정 기간 동안 단가만을 정하여 계약을 맺고, 납품 요구 시마다 수량에 따라 대금을 지급하는 형태의 계약을 체결할 수 있습니다. 이 계약 방식의 명칭으로 올바른 것은? | E41: 개산계약 | F41: 희망수량경쟁계약 | G41: 단가계약 | H41: 사후정산조건부계약 | I41: 3 | J41: * 정답 (③): 일정 기간 계속하여 제조나 공급이 필요한 경우 총 수량을 확정하지 않고 '단가(Unit Price)'에 대해서만 경쟁하여 체결하는 방식을 단가계약이라 합니다. 다수공급자계약(MAS)의 기본 형태입니다. | K41: 「국가계약법」 제22조
A42: 39 | B42: 2. 공공계약(국가 및 지방) 법령의 이해 | C42: 2. 계약의 방법에 관한 규정 | D42: 입찰 전에 예정가격을 구성하는 일부 비목별 금액을 명확히 결정할 수 없는 경우 예외적으로 채택하는 ( ㉮ )계약 방식과, 계약 이행 완료 후 실제 투입된 비용을 검토하여 최종 금액을 ( ㉯ )하는 후속 절차를 바르게 짝지은 것은? | E42: ㉮ 총액계약 - ㉯ 감액 | F42: ㉮ 사후원가검토조건부계약(개산계약) - ㉯ 정산 | G42: ㉮ 단가계약 - ㉯ 설계변경 | H42: ㉮ 희망수량계약 - ㉯ 확정 | I42: 2 | J42: * 정답 (②): 신제품 개발 등 사전에 원가 산정이 곤란한 경우 일부 비목을 사후에 원가검토 조건으로 맺는 '개산계약(사후원가검토조건부계약)'을 체결하며, 완료 후 원가계산기관의 검토를 거쳐 대금을 '정산'해야 합니다. | K42: 「국가계약법 시행령」 제9조 및 제73조
A43: 40 | B43: 2. 공공계약(국가 및 지방) 법령의 이해 | C43: 3. 입찰 및 낙찰 절차 규정 | D43: [상황] A기관이 B기업을 낙찰자로 통지했으나, B기업이 사정을 이유로 계약체결을 거부했다. B기업이 주장할 수 없는 것으로 가장 적절한 것은? | E43: 낙찰자 결정은 본계약의 예약 성립으로 볼 수 있다는 이해 | F43: 정당한 이유 없이 거부했으므로 입찰보증금이 귀속될 수 있다는 점에 대한 이의 | G43: 아직 본계약이 성립하지 않았으므로 이행을 강제당하지 않는다는 주장 | H43: 예약상 채무불이행에 대한 책임을 질 수 있다는 점 | I43: 2 | J43: * 정답 (②): B기업 입장에서는 오히려 입찰보증금 귀속에 이의를 제기하기 어려우며, 정당한 이유 없는 계약체결 거부는 예약상 채무불이행이 되어 입찰보증금이 귀속될 수 있음.
A44: 41 | B44: 2. 공공계약(국가 및 지방) 법령의 이해 | C44: 3. 입찰 및 낙찰 절차 규정 | D44: [상황] 신입 직원이 '적격심사낙찰제는 기술제안서를 평가해 순위를 매기는 방식이 핵심'이라고 잘못 이해하고 있었다. 올바른 설명은? | E44: 입찰가격 점수만으로 결정하는 방식이다 | F44: 최저가 입찰자부터 순서대로 계약이행능력을 심사해 종합평점이 기준 이상인 최초 통과자를 낙찰자로 정하는 방식이다 | G44: 기술제안서 평가가 핵심이다 | H44: 모든 공공계약에 예외 없이 적용되는 유일한 방식이다 | I44: 2 | J44: * 정답 (②): 적격심사낙찰제는 최저가 입찰자부터 순차적으로 계약이행능력(시공경험·재무상태 등)을 심사해 기준 이상인 최초 통과자를 낙찰자로 정하는 방식임.
A45: 42 | B45: 2. 공공계약(국가 및 지방) 법령의 이해 | C45: 3. 입찰 및 낙찰 절차 규정 | D45: [상황] 신입 직원이 경쟁입찰 흐름을 '낙찰자결정 → 입찰공고 → 예정가격결정 → 입찰서제출' 순서로 잘못 외우고 있었다. 올바른 순서는? | E45: 입찰공고 → 입찰서제출 → 예정가격결정 → 낙찰자결정 | F45: 입찰서제출 → 입찰공고 → 예정가격결정 → 낙찰자결정 | G45: 낙찰자결정 → 예정가격결정 → 입찰공고 → 입찰서제출 | H45: 예정가격결정 → 입찰공고 → 입찰서제출 → 낙찰자결정 | I45: 1 | J45: * 정답 (①): 일반적인 경쟁입찰은 입찰공고 → 입찰서 제출 → 예정가격 결정 → 낙찰자 결정 순으로 진행됨.
A46: 43 | B46: 2. 공공계약(국가 및 지방) 법령의 이해 | C46: 4. 계약의 체결 및 이행 규정 | D46: [상황] 계약담당공무원과 계약상대자가 계약서 초안까지 주고받았지만 아직 서로 기명·날인하지 않았다. 국가계약법상 이 시점에서 계약이 성립했다고 볼 수 있는가? | E46: 성립했다. 낙찰자 결정 통지 시점에 이미 확정되었다 | F46: 성립 여부는 계약보증금 납부 시점에 좌우된다 | G46: 성립하지 않았다. 계약은 계약서에 양 당사자가 기명·날인함으로써 확정된다 | H46: 성립했다. 초안 송부만으로 계약이 확정된다 | I46: 3 | J46: * 정답 (③): 국가계약법은 계약담당공무원과 계약상대자가 계약서를 작성하고 기명·날인함으로써 계약이 확정된다고 규정함. | K46: 국가계약법 제11조
A47: 44 | B47: 2. 공공계약(국가 및 지방) 법령의 이해 | C47: 4. 계약의 체결 및 이행 규정 | D47: [상황] 계약상대자가 '계약보증금은 입찰 참가를 위해 내는 돈 아니냐'고 물었다. 올바른 설명은? | E47: 아니다. 그것은 입찰보증금이며, 계약보증금은 계약금액의 10% 이상을 계약체결 시 납부해 이행을 담보하는 것으로 정상 이행 시 반환된다 | F47: 맞다. 계약을 이행해도 반환되지 않는다 | G47: 아니다. 계약보증금은 5% 이상만 내면 된다 | H47: 맞다. 입찰 참가 시 납부하는 것이다 | I47: 1 | J47: * 정답 (①): 계약보증금은 계약체결 시 계약이행을 담보하기 위해 납부하는 것(계약금액 10% 이상)으로, 입찰 참가를 위한 입찰보증금과 구분되며 정상 이행 시 반환됨. | K47: 국가계약법 시행령 제50조·제51조
A48: 45 | B48: 2. 공공계약(국가 및 지방) 법령의 이해 | C48: 4. 계약의 체결 및 이행 규정 | D48: [상황] 계약체결 후 65일이 지난 시점에 원자재 가격이 4% 상승해, 계약상대자가 물가변동에 따른 계약금액 조정을 신청했다. 이 신청의 인정 여부로 가장 적절한 것은? | E48: 물가변동 조정 신청은 애초에 법령상 허용되지 않는다 | F48: 등락률 요건은 충족했으나 기간 요건(90일 이상)을 충족하지 못해 조정 대상이 아니다 | G48: 기간과 무관하게 등락률만 넘으면 항상 인정된다 | H48: 기간과 등락률 요건을 모두 충족했으므로 인정된다 | I48: 2 | J48: * 정답 (②): 물가변동으로 인한 계약금액 조정은 계약체결 후 90일 이상 경과와 등락률(품목조정률·지수조정률) 3% 이상을 모두 충족해야 하므로, 65일 경과만으로는 요건 미충족임. | K48: 국가계약법 시행령 제64조
A49: 46 | B49: 2. 공공계약(국가 및 지방) 법령의 이해 | C49: 4. 계약의 체결 및 이행 규정 | D49: [상황] 담당자가 건축물 주요구조체(기둥·보·내력벽 등)의 하자담보책임기간을 5년으로 잘못 기재했다. 올바른 기간은? | E49: 10년 | F49: 1년 | G49: 3년 | H49: 5년 | I49: 1 | J49: * 정답 (①): 건축물 주요구조체의 하자담보책임기간은 5년이 아니라 10년임(부위별로 1~10년 범위에서 차등 적용). | K49: 건설산업기본법 시행령 [별표4]
A50: 47 | B50: 2. 공공계약(국가 및 지방) 법령의 이해 | C50: 4. 계약의 체결 및 이행 규정 | D50: [상황] 담당자가 지체상금 산정 원리를 '천재지변으로 지연되었어도 예외 없이 부과해야 한다'고 잘못 설명했다. 옳게 고친 설명은? | E50: 천재지변 등 불가항력적 사유로 인한 지체에는 지체상금을 부과하지 않는다 | F50: 지체상금은 손해배상과 전혀 무관한 별개의 벌금이다 | G50: 지체상금은 지체일수와 관계없이 정액으로 부과된다 | H50: 천재지변 여부와 무관하게 항상 지체상금을 부과한다 | I50: 1 | J50: * 정답 (①): 천재지변 등 불가항력적 사유로 인한 이행지체는 정당한 사유로 인정되어 지체상금이 부과되지 않음. | K50: 국가계약법 시행령 제74조
A51: 48 | B51: 2. 공공계약(국가 및 지방) 법령의 이해 | C51: 4. 계약의 체결 및 이행 규정 | D51: 정부계약의 체결 과정 및 계약보증금 제도에 대한 설명으로 가장 올바른 것은? | E51: 장기계속공사 등은 당해 연도의 1차 계약금액이 아닌 사업 전체 규모인 총공사금액을 기준으로 계약보증금을 산정해야 한다. | F51: 지방자치단체는 시스템 장애 대비를 위해 수기 문서로 계약서를 작성하는 것을 원칙으로 한다. | G51: 계약보증금 납부를 예외적으로 면제할 때에는 별도 서류 없이 구두 지급각서로 갈음할 수 있다. | H51: 계약담당자와 계약상대자가 구두로 최종 합의한 시점에 즉각적으로 계약이 확정된다. | I51: 1 | J51: * 정답 (①): 장기계속계약은 전체 사업 규모에 대한 책임을 담보하기 위해, 1차 계약 체결 시 해당 연도 계약액이 아닌 '총공사(계약)금액'의 10% 이상을 보증금으로 납부해야 합니다. (오답 노트: ④ 서명/날인 필수, ② 전자문서 원칙, ③ 서면 지급각서 필수) | K51: 「국가계약법 시행령」 제50조
A52: 49 | B52: 2. 공공계약(국가 및 지방) 법령의 이해 | C52: 4. 계약의 체결 및 이행 규정 | D52: 정부 공사계약에 있어서 계약상대자의 이행보증 방법에 대한 설명으로 가장 올바른 것은? | E52: 공사계약의 이행보증 방법은 현금 등을 납부하는 계약보증금 납부 방식 한 가지로만 엄격히 제한된다. | F52: 발주기관은 계약상대자가 계약이행보증방법의 변경을 요청하는 경우, 관련 법령에 따라 1회에 한하여 이를 변경하게 할 수 있다. | G52: 발주기관은 공사계약의 특성과 무관하게 항상 계약상대자가 두 가지 이행보증 방법 중 하나를 자유롭게 선택하도록 보장해야 한다. | H52: 계약이행 보증 후 계약상대자가 계약이행보증방법의 변경을 요청하는 경우, 발주기관은 정당한 사유만 있다면 횟수 제한 없이 여러 번 변경하게 할 수 있다. | I52: 2 | J52: * 정답 (②): 「국가계약법 시행령」 제52조 제2항에 따라, 계약이행보증방법의 변경 요청이 있는 경우 발주기관은 '1회에 한하여' 변경하게 할 수 있습니다. (오답 노트: ① 보증금 납부와 이행보증서 제출 두 가지가 있음, ③ 동조 제1항 단서에 따라 공사 특성상 필요한 경우 보증서 제출 방식으로 한정할 수 있으므로 항상 자유로운 것은 아님, ④ 1회 제한 규정 존재) | K52: 「국가계약법 시행령」 제52조
A53: 50 | B53: 2. 공공계약(국가 및 지방) 법령의 이해 | C53: 5. 이의신청과 분쟁조정 | D53: [상황] 계약상대자가 '분쟁조정위원회의 조정안은 그 자체로 법원 판결과 동일하다'고 알고 있었다. 이 이해에 대한 평가로 가장 적절한 것은? | E53: 정확하다. 조정안 자체가 확정판결과 동일한 효력을 갖는다 | F53: 정확하다. 조정 신청만으로 곧바로 확정된다 | G53: 이 위원회의 조정안은 어떤 경우에도 법적 효력이 없다 | H53: 부정확하다. 조정안은 권고적 효력을 가지며, 당사자가 수락하거나 일정 기간 이의를 제기하지 않을 때 비로소 재판상 화해와 같은 효력이 발생한다 | I53: 4 | J53: * 정답 (④): 조정안 자체는 권고적 효력을 가질 뿐이며, 당사자 수락 또는 일정 기간 이의 미제기 시 재판상 화해와 동일한 효력이 발생함. | K53: 국가계약법 제29조
A54: 51 | B54: 2. 공공계약(국가 및 지방) 법령의 이해 | C54: 5. 이의신청과 분쟁조정 | D54: [상황] A업체는 국가기관에 납품을 완료하여 2021년 3월 1일에 1억 원의 대금청구권이 발생하였다. 발주기관은 예산 부족을 이유로 지급을 미루다가, 3년이 지난 2024년 3월 1일에 대금의 일부인 2천만 원을 우선 지급하였다. 나머지 8천만 원에 대한 A업체의 대금청구권 소멸시효는 언제 최종 완성되는가? (단, 국가재정법상 시효를 적용하며, 이후 추가적인 시효 중단 사유는 없다고 가정한다.) | E54: 2026년 3월 1일 (최초 발생일로부터 5년) | F54: 2027년 3월 1일 (일부 지급일로부터 3년) | G54: 2029년 3월 1일 (일부 지급일로부터 5년 새로 기산) | H54: 2031년 3월 1일 (최초 발생일로부터 10년) | I54: 3 | J54: * 정답 (③): 「국가재정법」 제96조에 따라 국가에 대한 금전채권은 5년의 소멸시효가 적용된다. 그러나 채무자인 국가가 대금의 일부를 지급한 것은 「민법」상 '채무의 승인'에 해당하여 진행 중이던 소멸시효가 중단된다(국가재정법 제97조 및 민법 제168조). 시효가 중단된 경우, 해당 시점(일부 지급일인 2024년 3월 1일)부터 5년의 소멸시효가 새롭게 기산되므로 최종 시효 완성일은 2029년 3월 1일이 된다. | K54: 국가재정법 제96조
A55: 52 | B55: 3. 조달사업법령의 이해 | C55: 3. 대금지급 규정 | D55: [상황] 계약상대자가 '선금은 최대한 많이 받을수록 좋으니 계약금액 전액을 요청해도 된다'고 생각했다. 이 이해에 대한 평가로 가장 적절한 것은? | E55: 옳다. 선금은 계약금액 100%까지 지급 가능하다 | F55: 옳다. 선금은 기성대가와 무관하게 별도로 지급된다 | G55: 옳지 않다. 선금은 계약금액의 일정 상한(통상 100분의 70 이내) 범위에서 지급되며, 기성대가 지급 시 정산된다 | H55: 옳지 않다. 선금 제도 자체가 존재하지 않는다 | I55: 3 | J55: * 정답 (③): 선금은 계약금액 전액이 아니라 일정 상한(계약예규상 100분의 70 이내) 범위에서 지급되며, 기성대가 지급 시마다 정산됨. | K55: 계약예규(정부 입찰·계약 집행기준)
A56: 53 | B56: 3. 조달사업법령의 이해 | C56: 3. 대금지급 규정 | D56: 조달청이 사업을 대행하며 수요기관으로부터 징수하는 '구매수수료'에 대한 법적 설명으로 가장 옳지 않은 것은? | E56: 징수되는 수수료 및 감면 비율은 납품 대금 총액의 100분의 20을 초과할 수 없다. | F56: 수수료의 감면 및 세부 요율은 조달청장이 단독으로 임의 결정하여 즉시 고시한다. | G56: 미리 대금을 지급받은 등 특정 요건 충족 시 조달청 내부 기준에 따라 감면할 수 있다. | H56: 조달수수료는 조달특별회계의 세입으로 편입되며 재정경제부 장관과 협의하여 고시한다. | I56: 2 | J56: * 정답 (②): 조달수수료율 및 감면 사항은 조달청장이 단독으로 결정하는 것이 아니라, 반드시 재정경제부 장관과 사전 협의를 거쳐야 합니다. (2026년 조직 개편에 따른 소관 부처 변경 반영)
A57: 54 | B57: 3. 조달사업법령의 이해 | C57: 3. 대금지급 규정 | D57: 조달청 총액계약 및 단가계약의 금액 구간별 '조달수수료율 산정 방식'으로 올바르게 연결된 것은? | E57: 5천만 원 초과 1억 원 이하 총액계약: 일괄적으로 75만 원의 정액 수수료 고정 부과 | F57: 1억 원을 초과하는 대형 총액계약: 납품 금액이 클수록 수수료율이 높아지는 할증제 적용 | G57: 5천만 원 이하의 소액 총액계약: 계약 금액의 1.07%를 일괄 적용하는 세밀한 정률제 방식 | H57: 10억 원 이하의 단가계약: 0.54%의 정률제 적용 후 금액이 커질수록 초과분 체감 방식 적용 | I57: 4 | J57: * 정답 (④): 단가계약은 10억 원까지 0.54%의 정률제를 적용하며, 그 이상은 '초과분 체감방식(예: 10억 초과~100억까지 0.47%)'을 적용합니다. [오답노트] ① 5천만 원 초과 1억 원 이하 총액계약은 정액제가 아닌 '1.07% 정률제'를 적용합니다. ② 1억 원을 초과하는 총액계약은 할증제가 아니라, 반대로 납품 금액이 클수록 적용 요율이 낮아지는 '초과분 체감방식'을 적용합니다. ③ 5천만 원 이하 총액계약은 정률제가 아닌 '구간별 정액제'를 적용합니다(2천만 원 이하 21만 원, 2천만~5천만 원 53만 원). | K57: 조달수수료 고시
A58: 55 | B58: 3. 조달사업법령의 이해 | C58: 3. 대금지급 규정 | D58: 조달사업법령상 수요기관에 부과하는 '조달수수료'를 예외적으로 면제(감면)할 수 있는 법정 사유에 해당하지 않는 것은? | E58: 국가 정책적 보호를 목적으로 전통공예품, 전통주 및 전통식품 등을 조달청을 통해 구매하여 조달사업을 확대하는 경우 | F58: 조달청이 직접 계약을 체결하고 관리하는 공사 건에 대하여 추후 총사업비 물가변동 검토만을 조달청에 별도 요청하는 경우 | G58: 행정 지연 탓에 표준행정소요일수를 명백히 초과하여 단가계약을 지연 체결함으로써 수요기관 조달 일정에 차질이 생긴 경우 | H58: 수요기관이 납품 대금을 직접 지불하는 조달 건 중에서 산정된 조달수수료 총액이 천 원 미만의 소액 건으로 최종 확인된 경우 | I58: 3 | J58: * 정답 (③): 조달사업법 제16조에 따라 조달청 귀책으로 표준행정소요일수를 초과하여 계약을 체결할 경우 수수료가 면제되나, 단서 조항에 따라 **'단가계약' 및 '장기계속계약의 1차 계약'은 지연되더라도 면제 대상에서 엄격히 제외(부과 대상)**됩니다. | K58: 조달사업법 제16조 및 조달사업법 시행령 제20조
A59: 56 | B59: 4. 전자조달법령의 이해 | C59: 1. 전자적 공고의 방법 및 시기 | D59: [상황] 조달업체 담당자가 '전자조달법은 조달업체의 이윤을 정부가 보장해주기 위한 법'이라고 오해하고 있었다. 이 오해를 바로잡는 설명으로 가장 적절한 것은? | E59: 옳지 않다. 전자조달법은 조달업무의 투명성·공정성·효율성을 높여 국민경제 발전에 이바지하는 것을 목적으로 하며, 업체 수익 보장은 직접적 목적이 아니다 | F59: 이 법은 조달업체와 무관한 내부 행정 규정일 뿐이다 | G59: 옳다. 다만 대기업에만 해당된다 | H59: 옳다. 조달업체의 수익 보장이 핵심 목적이다 | I59: 1 | J59: * 정답 (①): 전자조달법은 투명성·공정성·효율성 제고와 국민경제 발전을 목적으로 하며, 조달업체의 수익성 보장은 직접적 목적이 아님. | K59: 전자조달의 이용 및 촉진에 관한 법률 제1조
A60: 57 | B60: 4. 전자조달법령의 이해 | C60: 1. 전자적 공고의 방법 및 시기 | D60: [상황] 한 기관이 전자조달 원칙을 소개하며 '신속한 처리를 위해 가급적 서면으로 처리하는 것을 원칙으로 한다'고 안내했다. 이 안내에 대한 평가로 가장 적절한 것은? | E60: 옳다. 서면과 전자처리는 동등하게 원칙으로 취급된다 | F60: 옳다. 서면 처리가 전자조달의 기본원칙이다 | G60: 이 사안은 전자조달 원칙과 무관하다 | H60: 옳지 않다. 전자조달의 기본원칙은 공개·공정경쟁, 전자적 처리, 문서형식 최소화, 정보보호·보안이며, 서면 처리는 오히려 취지에 반한다 | I60: 4 | J60: * 정답 (④): 전자조달의 기본원칙은 공개·공정경쟁, 전자적 처리, 문서형식 최소화, 정보보호·보안이며, '서면 처리'는 전자조달의 취지에 반하는 개념임. | K60: 전자조달의 이용 및 촉진에 관한 법률 제4조
A61: 58 | B61: 4. 전자조달법령의 이해 | C61: 1. 전자적 공고의 방법 및 시기 | D61: 관련 법령에 따라 모든 공공기관이 나라장터를 의무적으로 이용해야 하는 핵심 업무에 해당하는 것은? | E61: 민간 쇼핑몰을 통한 사무용품 자체 구매 | F61: 기관 내부의 수기 결재 문서 전자화 작업 | G61: 조달청 발주 외의 자체 입찰공고 및 집행 | H61: 임직원 직무 역량 강화를 위한 교육 수강 | I61: 3 | J61: * 정답 (③): 법령상 모든 공공기관은 예외적인 사유가 없는 한 국가종합전자조달시스템(나라장터)을 이용하여 입찰을 공고하고 집행할 의무가 있습니다.
A62: 59 | B62: 4. 전자조달법령의 이해 | C62: 1. 전자적 공고의 방법 및 시기 | D62: 조달청 전자입찰에서 업체의 충분한 입찰서 작성 시간을 보장하기 위해 '입찰서 접수 개시부터 마감까지' 필수적으로 부여해야 하는 최소 시간은? | E62: 최소 24시간 이상 보장 | F62: 최소 48시간 이상 보장 | G62: 최소 60시간 이상 보장 | H62: 최소 72시간 이상 보장 | I62: 2 | J62: * 정답 (②): 전자조달법 시행규칙 제2조에 따라, 전자입찰서 제출 마감일은 접수 개시일로부터 최소 '48시간' 이상이 지나도록 설정해야만 유효한 공고가 됩니다. | K62: 전자조달법 시행규칙 제2조
A63: 60 | B63: 4. 전자조달법령의 이해 | C63: 1. 전자적 공고의 방법 및 시기 | D63: 전자입찰을 집행할 때 입찰서를 개봉하는 '개찰 일시'는 법적 기준에 따라 전자입찰서 제출 마감 일시로부터 최소 얼마의 물리적 시간이 지난 후로 설정해야 하는가? | E63: 마감 후 최소 24시간 이후 | F63: 마감 후 최소 6시간 이후 | G63: 마감 후 최소 1시간 이후 | H63: 마감 후 즉시 (0시간) | I63: 3 | J63: * 정답 (③): 입찰서 마감 직후 트래픽 과부하나 전산망 오류 등을 점검하고 안정적으로 암호를 해독하기 위해 마감 시점으로부터 최소 '1시간' 이후에 개찰하도록 법으로 규정하고 있습니다. | K63: 전자조달법 시행규칙 제2조
A64: 61 | B64: 4. 전자조달법령의 이해 | C64: 2. 전자적 형태의 입찰서 제출 | D64: [상황] 한 업체가 마감시간 5분 전에 발송 버튼을 눌렀으나, 실제로 전자조달시스템에 데이터가 입력된 시점은 마감시간을 1분 넘긴 뒤였다. 이 입찰서의 제출 시점 판단으로 가장 적절한 것은? | E64: 발신자와 수신자가 협의해 임의로 시점을 정할 수 있다 | F64: 발송 버튼을 누른 시점을 기준으로 마감 전 제출로 인정된다 | G64: 전자조달시스템에 실제 입력된 시점을 기준으로 판단하므로 마감시간을 넘긴 것으로 처리될 수 있다 | H64: 수신자가 이를 열어본 시점을 기준으로 판단한다 | I64: 3 | J64: * 정답 (③): 전자문서는 전자조달시스템에 입력된 때 송신된 것으로 보므로, 발송 버튼을 누른 시점이 아니라 실제 시스템 입력 시점이 기준이 됨. | K64: 전자조달의 이용 및 촉진에 관한 법률 제11조
A65: 62 | B65: 4. 전자조달법령의 이해 | C65: 2. 전자적 형태의 입찰서 제출 | D65: 전자입찰 시스템에서 입찰서 제출 시 공개키와 개인키를 활용한 '암호화' 기술을 필수적으로 적용하는 주된 이유는? | E65: 계약담당자가 사전에 투찰액을 열람하여 예가를 조정할 수 있도록 권한을 부여하기 위해 | F65: 마감 시간 이전에 입찰서가 열람되어 입찰의 공정성이 훼손되는 것을 원천 차단하기 위해 | G65: 입찰서의 용량을 압축하여 나라장터 서버의 데이터 처리 속도를 획기적으로 높이기 위해 | H65: 투찰 가격이 예정가격을 초과할 경우 시스템이 자동으로 가격을 하향 조정하도록 하기 위해 | I65: 2 | J65: * 정답 (②): 입찰서는 개찰 일시 이전(마감 전)에 누군가 미리 열람하게 되면 심각한 부정행위가 발생하므로, 이를 막기 위해 암호화하여 전송 및 보관합니다.
A66: 63 | B66: 4. 전자조달법령의 이해 | C66: 2. 전자적 형태의 입찰서 제출 | D66: 국가종합전자조달시스템(나라장터)의 입찰 공정성 확보를 위해 도입된 '전자입찰 암호화 키 관리 원칙'에 대한 설명으로 가장 올바르지 않은 것은? | E66: 입찰 데이터의 독립적인 보안성을 철저히 보장하기 위하여, 기존 키를 재사용하지 않고 개별 입찰 공고 건마다 완전히 새로운 암호화 키 쌍을 생성한다. | F66: 관리적 보안 통제를 극대화하고 책임 소재를 명확히 규명하기 위하여, 암복호화에 사용되는 모든 핵심 키를 조달청 내부망 메인 데이터베이스에 중앙집중식으로 저장한다. | G66: 사전 유출 및 결탁 비리를 원천 차단하기 위하여, 개찰 전까지 암호를 해독할 수 있는 권한인 '개인키'는 조달청 내부가 아닌 제3의 클라우드 서버에 분할 보관한다. | H66: 입찰 참가 업체가 시스템을 통해 입찰서(투찰 금액 등)를 제출할 때는, 해당 입찰 건에 매칭된 '공개키'를 활용하여 데이터를 안전하게 암호화한 후 서버로 전송한다. | I66: 2 | J66: * 정답 (②): 내부자 결탁이나 해킹에 의한 사전 개찰(정보 유출)을 완벽히 차단하기 위해, 암호를 푸는 '개인키'는 조달청 내부 DB에 중앙집중식으로 저장하지 않고 완전히 분리된 '제3자 클라우드 시스템'에 분산 보관하는 것이 핵심 원칙입니다.
A67: 64 | B67: 4. 전자조달법령의 이해 | C67: 5. 전자조달시스템 이용·활용 제한 | D67: [상황] 조달청 직원 C가 직무상 알게 된 입찰 관련 비밀정보를 지인에게 누설해 부당하게 활용하도록 했다. 이 행위에 적용될 수 있는 벌칙으로 가장 적절한 것은? | E67: 3년 이하의 징역 또는 3천만원 이하의 벌금 | F67: 벌칙 규정이 없어 처벌할 수 없다 | G67: 2년 이하의 징역 또는 2천만원 이하의 벌금 | H67: 1년 이하의 징역 또는 1천만원 이하의 벌금 | I67: 3 | J67: * 정답 (③): 전자조달법은 직무상 알게 된 정보의 누설·부정사용에 대해 2년 이하의 징역 또는 2천만원 이하의 벌금에 처하도록 규정함. | K67: 전자조달의 이용 및 촉진에 관한 법률(벌칙 규정)
A68: 65 | B68: 5. 공기업·준정부기관 계약사무규칙 | C68: 1. 국제입찰 대상 공공조달계약 범위 | D68: WTO 정부조달협정(GPA)에 따라 2025~2026년도 기준, 중앙행정기관이 발주하는 물품 및 용역 분야의 국제입찰 대상 고시금액(추정가격) 기준은? | E68: 2억 3천만 원 이상 (2.3억 원) | F68: 3억 5천만 원 이상 (3.5억 원) | G68: 5억 2천만 원 이상 (5.2억 원) | H68: 7억 4천만 원 이상 (7.4억 원) | I68: 1 | J68: * 정답 (①): 재정경제부 고시에 따라 25~26년도 국가기관 물품/용역 국제입찰 하한선은 13만 SDR에 해당하는 '2억 3천만 원(2.3억)'으로 적용됩니다. (환율에 따라 2년마다 갱신됨)
A69: 66 | B69: 5. 공기업·준정부기관 계약사무규칙 | C69: 1. 국제입찰 대상 공공조달계약 범위 | D69: 정부조달협정(GPA)에 따른 국제입찰 대상 여부에 대한 설명으로 가장 옳은 것은? | E69: 농·수·축산물 구매나 재판매용 조달은 모두 예외 없이 국제입찰 대상이다. | F69: 정부조달협정 기준 요건에 부합하지 않는 계약도 원칙은 국제입찰을 한다. | G69: 국제입찰 범위에 해당하지 않는 공공계약의 경우 원칙적으로 국내입찰을 실시한다. | H69: 중소기업제품 구매촉진 관련 법령에 따른 조달도 반드시 국제입찰을 거친다. | I69: 3 | J69: 정답 (③) 국제입찰 대상 기준금액 미만이거나 예외 조항(농산물, 재판매, 중소기업 등)에 해당하면 국내입찰로 진행함 | K69: 특정조달 특례
A70: 67 | B70: 5. 공기업·준정부기관 계약사무규칙 | C70: 3. 수의계약 규정 | D70: 「공공기관의 운영에 관한 법률」을 적용받는 공기업 및 준정부기관의 계약 특례에 대한 설명으로 가장 올바른 것은? | E70: 「공기업·준정부기관 계약사무규칙」에서 명시적으로 규정하지 않은 계약 운영 사항은 상위 법령인 「국가를 당사자로 하는 계약에 관한 법령」을 준용하여 처리한다. | F70: 공기업·준정부기관은 퇴직자가 임원으로 취업한 법인과 수의계약을 맺을 때 유착 방지를 위한 별도의 기간 제한 없이 자유롭게 계약을 체결할 수 있다. | G70: 공기업 및 준정부기관은 정부조달협정에 따른 국제입찰 공표 사항을 별도의 공식 출판물 없이 자사 홈페이지에만 단순 게시하면 족하다. | H70: 소속 단위부서 임직원이 계약 사무와 관련하여 뇌물수수 등 범죄 혐의로 기소되더라도 해당 부서의 계약 사무를 조달청장에게 강제 위탁할 법적 근거는 없다. | I70: 1 | J70: 정답 (①) 동 규칙 제2조에 따라 규정되지 않은 사항은 국가계약법령을 준용함 / ② 퇴직자 임원 취업 법인과는 퇴직일로부터 2년간 수의계약 체결 금지 / ③ 정부조달협정 등에서 정한 공식 출판물 등에 공고 필요 / ④ 뇌물 기소·중징계 시 조달청장 위탁 의무 규정(원스트라이크 아웃제) 존재 | K70: 「공기업·준정부기관 계약사무규칙」 제2조 및 제7조
A71: 68 | B71: 1. 공공계약 관련 민법 규정의 이해 | C71: 1. 계약의 성립 관련 규정 | D71: 공공조달 절차에서 입찰공고, 입찰(투찰), 낙찰 결정, 계약서 작성에 대한 「민법」상 성격으로 옳은 것은? | E71: 입찰공고는 '청약'이므로 발주기관에 계약 체결 의무가 발생한다. | F71: 낙찰 결정으로 본계약이 성립하며 별도의 계약서 작성은 불필요하다. | G71: 입찰(투찰)은 '청약'에 해당하며 「민법」 제527조에 따라 철회할 수 없다. | H71: 승낙기간이 경과해 연착된 승낙은 어떠한 경우에도 효력이 없다. | I71: 3 | J71: * 정답 (③): 입찰공고는 '청약의 유인'(구속력 없음), 낙찰은 '계약의 예약'(본계약 아님)이다. 연착된 승낙은 「민법」 제530조에 따라 새 청약으로 볼 수 있다. 입찰서 제출은 구속력 있는 청약으로서 제527조에 의해 철회가 불가하다. | M71: AAA
A72: 69 | B72: 1. 공공계약 관련 민법 규정의 이해 | C72: 2. 계약의 효력 관련 규정 | D72: 쌍무계약의 효력에 관한 설명으로 옳은 것은? | E72: 편무계약에서도 동시이행 항변권이 동일하게 발생한다. | F72: 채무자위험부담주의에 따라 쌍방 무과실 이행불능 시에도 채무자는 반대급부를 청구할 수 있다. | G72: 쌍무계약의 당사자 일방은 상대방이 채무이행을 제공할 때까지 자기의 채무이행을 거절할 수 있다. | H72: 제3자를 위한 계약에서 제3자는 채무자에게 직접 이행을 청구할 수 없다. | I72: 3 | J72: * 정답 (③): 「민법」 제536조(동시이행 항변권)는 쌍무계약에서만 발생한다. 제537조에 따르면 쌍방 무과실 이행불능 시 채무자는 반대급부를 청구하지 못한다(② 오류). 제539조에 따라 제3자는 직접 이행 청구가 가능하다(④ 오류). | M72: AAA
A73: 70 | B73: 1. 공공계약 관련 민법 규정의 이해 | C73: 3. 계약의 해제·해지에 관한 규정 | D73: 「민법」상 계약의 해제와 해지에 관한 설명으로 옳지 않은 것은? | E73: 해제는 소급적 효력, 해지는 장래적 효력을 가진다. | F73: 해제 시 원상회복 의무가 발생하며, 해지 시 이미 이행된 부분은 유효하다. | G73: 해제·해지를 하면 손해배상 청구권도 함께 소멸한다. | H73: 해제·해지의 의사표시는 철회할 수 없다. | I73: 3 | J73: * 정답 (③): 「민법」 제551조에 따라 해지·해제는 손해배상 청구에 영향을 미치지 않는다. 따라서 해제·해지 후에도 손해배상 청구는 별도로 가능하다. | M73: AAA
A74: 71 | B74: 1. 공공계약 관련 민법 규정의 이해 | C74: 4. 도급·위임에 관한 규정 | D74: 「민법」상 도급과 위임에 관한 설명으로 옳은 것은? | E74: 도급계약에서 수급인은 일이 완성되기 전이라도 보수 전액을 청구할 수 있다. | F74: 위임계약은 각 당사자가 언제든지 해지할 수 있다. | G74: 공공조달의 공사계약은 위임계약에 해당한다. | H74: 수급인의 하자담보책임 존속기간은 모든 목적물에 대해 동일하게 5년이다. | I74: 2 | J74: * 정답 (②): 「민법」 제689조에 따라 위임계약은 각 당사자가 언제든지 해지할 수 있다. 도급의 보수는 완성 후 지급이 원칙(① 오류), 공사계약은 도급(③ 오류), 하자담보 기간은 1년/5년/10년으로 상이(④ 오류)하다. | M74: AAA
A75: 72 | B75: 1. 공공계약 관련 민법 규정의 이해 | C75: 5. 화해에 관한 규정 | D75: 「민법」상 화해에 관한 설명으로 옳지 않은 것은? | E75: 화해는 당사자가 상호 양보하여 분쟁을 종지할 것을 약정함으로써 효력이 생긴다. | F75: 화해계약은 창설적 효력이 있어 양보한 권리는 소멸되고 새 권리가 발생한다. | G75: 화해계약은 언제든지 착오를 이유로 취소할 수 있다. | H75: 공공조달에서 화해 관련 규정은 「국가계약법」 제28조의2에 반영되어 있다. | I75: 3 | J75: * 정답 (③): 「민법」 제733조에 따라 화해계약은 착오를 이유로 취소하지 못하는 것이 원칙이다. 예외적으로 당사자의 자격 또는 분쟁 이외의 사항에 착오가 있는 때에만 취소 가능하다. | M75: AAA
A76: 73 | B76: 1. 공공계약 관련 민법 규정의 이해 | C76: 1. 계약의 성립 관련 규정 | D76: 공공계약 관련 「민법」 규정의 이해에 관한 기본 원칙으로 가장 적절한 것은? | E76: 상황에 따라 사후에 기준을 바꾸어도 무방하다. | F76: 담당자 편의에 따라 공개·기록을 생략할 수 있다. | G76: 구두 합의가 문서보다 우선한다. | H76: 기준·절차를 사전에 명확히 하고 동일하게 적용하여 공정성과 투명성을 확보한다. | I76: 4 | J76: * 정답 (④): 사전확정·공개·기록·동일적용은 감사·분쟁 리스크를 줄이는 핵심 원칙이다. | M76: AAA
A77: 74 | B77: 1. 공공계약 관련 민법 규정의 이해 | C77: 1. 계약의 성립 관련 규정 | D77: 공공계약 관련 「민법」 규정의 이해에 관한 실무통제(리스크 관리)로 가장 적절한 것은? | E77: 요구사항·평가기준·검수기준·변경절차를 문서화하고 이해관계자에게 사전 공유한다. | F77: 검수는 생략하고 하자 발생 시 추후 협의한다. | G77: 계약조건은 낙찰자와 구두로만 정한다. | H77: 평가기준은 입찰 마감 후 필요에 따라 조정한다. | I77: 1 | J77: * 정답 (①): 문서화+사전공유는 분쟁 예방, 성과관리, 책임소재 명확화에 가장 효과적이다. | M77: AAA
A78: 75 | B78: 1. 공공계약 관련 민법 규정의 이해 | C78: 2. 계약의 효력 관련 규정 | D78: 「민법」상 신의성실 원칙이 공공계약에 적용되는 양상에 관한 설명으로 옳지 않은 것은? | E78: 발주기관과 계약상대자 모두 신의에 따라 권리를 행사하고 의무를 이행해야 한다. | F78: 신의성실 원칙은 「민법」 제2조의 일반 조항으로 공공계약에도 적용된다. | G78: 신의성실 위반은 권리남용 금지 원칙과 결합하여 부당한 권리행사를 통제한다. | H78: 신의성실 원칙은 사인 간 계약에만 적용되고 공공계약에는 적용되지 않는다. | I78: 4 | J78: * 정답 (④): 신의성실 원칙은 「민법」 제2조 일반 조항으로 사인 간 계약뿐 아니라 공공계약에도 적용되며, 발주기관의 우월적 지위 남용 통제와 계약상대자의 성실한 이행 의무 모두에 적용한다. | M78: AAA
A79: 76 | B79: 1. 공공계약 관련 민법 규정의 이해 | C79: 1. 계약의 성립 관련 규정 | D79: 「민법」상 청약과 승낙에 관한 설명으로 옳은 것은? | E79: 청약은 일방적 의사표시이며 상대방의 승낙으로 계약이 성립한다. | F79: 청약은 상대방에게 도달하기 전에는 효력이 발생하지 않는다. | G79: 공공조달의 입찰공고는 청약의 유인에 해당하고, 입찰서 제출이 청약, 낙찰자 결정이 승낙에 해당한다. | H79: ①, ②, ③ 모두 옳다. | I79: 4 | J79: * 정답 (④): 「민법」상 청약은 도달주의에 따라 효력이 발생하며, 승낙으로 계약이 성립한다. 공공조달에서는 입찰공고가 청약의 유인, 입찰서 제출이 청약, 낙찰자 결정이 승낙에 해당하는 구조로 이해된다. | M79: AAA
A80: 77 | B80: 1. 공공계약 관련 민법 규정의 이해 | C80: 2. 계약의 효력 관련 규정 | D80: 채무불이행의 유형에 관한 설명으로 옳지 않은 것은? | E80: 이행지체 — 이행기가 도래했음에도 이행하지 않는 경우 | F80: 이행불능 — 채무 이행이 객관적으로 불가능하게 된 경우 | G80: 불완전이행 — 이행을 했으나 본래 채무 내용에 미치지 못하는 경우 | H80: 채무불이행은 「민법」상 단일 유형으로만 규정되어 구분이 없다. | I80: 4 | J80: * 정답 (④): 채무불이행은 「민법」상 ① 이행지체, ② 이행불능, ③ 불완전이행의 3가지 유형으로 구분되며, 각 유형별로 손해배상·계약해제 등의 구제 수단이 차등 적용된다. | M80: AAA
A81: 78 | B81: 1. 공공계약 관련 민법 규정의 이해 | C81: 2. 계약의 효력 관련 규정 | D81: 「민법」상 손해배상의 범위에 관한 설명으로 옳은 것은? | E81: 통상의 손해를 한도로 하며, 특별한 사정으로 인한 손해는 채무자가 그 사정을 알았거나 알 수 있었을 때에 한해 배상 책임이 있다. | F81: 모든 손해를 무제한으로 배상해야 한다. | G81: 손해배상은 위자료에 한정되며 재산상 손해는 배상 대상이 아니다. | H81: 손해배상의 범위는 채권자가 자유롭게 결정할 수 있다. | I81: 1 | J81: * 정답 (①): 「민법」 제393조는 통상손해와 특별손해의 구분을 통해 손해배상의 범위를 제한한다. 특별손해는 예견가능성 원칙에 따라 채무자가 그 사정을 알았거나 알 수 있었을 때에 한해 배상 책임이 있다. | M81: AAA
A82: 79 | B82: 1. 공공계약 관련 민법 규정의 이해 | C82: 1. 계약의 성립 관련 규정 | D82: 공공계약과 「민법」의 관계에 관한 설명으로 옳지 않은 것은? | E82: 「국가계약법」 등 공공계약 관련 법령에 특별한 규정이 없는 사항은 「민법」이 적용된다. | F82: 「민법」의 일반 원칙(신의성실, 권리남용 금지 등)은 공공계약에도 적용된다. | G82: 공공계약은 사적 계약과 본질적으로 같으므로 모든 면에서 「민법」이 우선 적용된다. | H82: 공공계약은 「민법」의 일반 원리 위에 공익적 통제(절차의 형식성, 공정성 의무 등)가 추가된 구조이다. | I82: 3 | J82: * 정답 (③): 공공계약은 사적 계약의 본질을 가지나, 공공자금 사용·공정성 의무 등 공익적 통제가 추가된 특수 영역이다. 「국가계약법」 등 특별 규정이 우선 적용되고, 그 보충으로 「민법」이 적용된다. 모든 면에서 「민법」이 우선 적용되는 것이 아니다. | M82: AAA
A83: 80 | B83: 2. 공공계약(국가 및 지방) 법령의 이해 | C83: 1. 추정가격 및 예정가격 결정 | D83: 공공계약(국가 및 지방) 법령의 이해의 기본 개념/원칙으로 가장 적절한 것은? | E83: 상황에 따라 사후에 기준을 바꾸어도 무방하다. | F83: 기준·절차를 사전에 명확히 하고 동일하게 적용하여 공정성과 투명성을 확보한다. | G83: 담당자 편의에 따라 공개·기록을 생략할 수 있다. | H83: 구두 합의가 문서보다 우선한다. | I83: 2 | J83: * 정답 (②): 원칙(사전확정·공개·기록·동일적용)은 감사·분쟁 리스크를 줄이는 핵심이다.
A84: 81 | B84: 2. 공공계약(국가 및 지방) 법령의 이해 | C84: 1. 추정가격 및 예정가격 결정 | D84: 다음 중 공공계약(국가 및 지방) 법령의 이해 관련 실무통제(리스크 관리)로 가장 적절한 것은? | E84: 계약조건은 낙찰자와 구두로만 정한다. | F84: 평가기준은 입찰 마감 후 필요에 따라 조정한다. | G84: 요구사항·평가기준·검수기준·변경절차를 문서화하고 이해관계자에게 사전 공유한다. | H84: 검수는 생략하고 하자 발생 시 추후 협의한다. | I84: 3 | J84: * 정답 (③): 문서화+사전공유는 분쟁 예방, 성과관리, 책임소재 명확화에 가장 효과적이다.
A85: 82 | B85: 2. 공공계약(국가 및 지방) 법령의 이해 | C85: 1. 추정가격 및 예정가격 결정 | D85: 다음 중 공공계약(국가 및 지방) 법령의 이해에 관한 설명으로 옳은 것은? | E85: 사전공개는 원칙이 아니라 선택사항이다. | F85: 조달절차의 각 단계는 관련 규정에 따라 수행되며, 핵심 판단은 기록으로 남겨야 한다. | G85: 절차는 내부 방침만 따르면 되며 외부 기준은 고려하지 않는다. | H85: 입찰·계약 단계에서 이해상충은 문제되지 않는다. | I85: 2 | J85: * 정답 (②): 절차 준수와 기록(근거)은 공공조달에서 필수 요건이다.
A86: 83 | B86: 2. 공공계약(국가 및 지방) 법령의 이해 | C86: 1. 추정가격 및 예정가격 결정 | D86: 「국가계약법 시행령」에 따른 추정가격에 관한 설명으로 옳은 것은? | E86: 추정가격은 부가가치세를 포함한 금액이다. | F86: 추정가격은 예정가격을 산정하기 위한 기초금액이다. | G86: 추정가격은 부가가치세를 제외한 금액으로 계약 방법을 결정하는 기준이다. | H86: 추정가격은 입찰 당일 공개하는 가격이다. | I86: 3 | J86: * 정답 (③): 추정가격은 부가세를 제외한 금액이며, 경쟁/수의계약 등 계약 방법 결정의 기준이다(시행령 제7조 제1항). 기초금액과는 다른 개념이다.
A87: 84 | B87: 2. 공공계약(국가 및 지방) 법령의 이해 | C87: 3. 입찰 및 낙찰 절차 규정 | D87: 경쟁입찰에서 계약이행능력을 갖추고 최저가격으로 입찰한 자를 낙찰자로 선정하는 제도는? | E87: 종합심사낙찰제 | F87: 적격심사낙찰제 | G87: 협상에 의한 계약 | H87: 경쟁적 대화에 의한 계약 | I87: 2 | J87: * 정답 (②): 적격심사낙찰제는 예정가격 이하 최저가 순으로 이행능력을 심사하여 기준점수 이상인 자를 낙찰자로 결정하는 가장 광범위하게 적용되는 제도이다(시행령 제42조 제1항·제5항).
A88: 85 | B88: 2. 공공계약(국가 및 지방) 법령의 이해 | C88: 4. 계약의 체결 및 이행 규정 | D88: 「국가계약법」 제11조에 따른 계약서의 필수 기재사항이 아닌 것은? | E88: 계약의 목적 | F88: 계약보증금 | G88: 하도급 계획 | H88: 지체상금(遲滯償金) | I88: 3 | J88: * 정답 (③): 계약서의 필수 기재사항 7개는 ① 목적 ② 금액 ③ 이행기간 ④ 계약보증금 ⑤ 위험부담 ⑥ 지체상금 ⑦ 기타 필요사항이다. 하도급 계획은 별도 관리 사항이다.
A89: 86 | B89: 2. 공공계약(국가 및 지방) 법령의 이해 | C89: 5. 이의신청과 분쟁조정 | D89: 국가계약분쟁조정위원회의 조정 결과에 대해 15일 이내에 이의를 제기하지 않은 경우의 효력은? | E89: 행정명령과 동일한 효력 | F89: 행정심판 결과와 동일한 효력 | G89: 재판상 '화해'와 동일한 효력 | H89: 확정판결과 동일한 효력 | I89: 3 | J89: * 정답 (③): 국가계약분쟁조정위원회의 조정에 대해 15일 이내 이의를 제기하지 않으면 재판상 '화해'와 동일한 효력이 발생한다(「국가계약법」 제31조).
A90: 87 | B90: 2. 공공계약(국가 및 지방) 법령의 이해 | C90: 4. 계약의 체결 및 이행 규정 | D90: 물가변동에 따른 계약금액 조정이 가능하기 위한 조건으로 옳은 것은? | E90: 계약 체결 후 60일 이상 경과, 품목조정률 또는 지수조정률 5% 이상 증감 | F90: 계약 체결 후 90일 이상 경과, 품목조정률 또는 지수조정률 3% 이상 증감 | G90: 계약 체결 후 90일 이상 경과, 품목조정률 또는 지수조정률 5% 이상 증감 | H90: 계약 체결 후 120일 이상 경과, 품목조정률 또는 지수조정률 3% 이상 증감 | I90: 2 | J90: * 정답 (②): 물가변동 조정은 계약 체결 후 90일 이상 경과하고, 조정기준인 품목조정률 또는 지수조정률이 100분의 3 이상 증감된 경우에 가능하다(시행령 제64조 제1항).
A91: 88 | B91: 2. 공공계약(국가 및 지방) 법령의 이해 | C91: 1. 추정가격 및 예정가격 결정 | D91: 「지방계약법」의 주요 적용 대상으로 옳은 것은? | E91: 중앙행정기관이 발주하는 공사 | F91: 지방자치단체(시·도·시·군·구)가 체결하는 계약 | G91: 공기업이 체결하는 MAS 계약 | H91: 조달청이 체결하는 중앙조달 | I91: 2 | J91: * 정답 (②): 「지방계약법」은 지방자치단체를 당사자로 하는 계약에 적용되며, 중앙행정기관은 「국가계약법」 적용 대상이다.
A92: 89 | B92: 2. 공공계약(국가 및 지방) 법령의 이해 | C92: 1. 추정가격 및 예정가격 결정 | D92: 「국가계약법」과 「지방계약법」의 공통 원칙으로 옳은 것은? | E92: 수의계약이 원칙이다. | F92: 공개경쟁입찰 원칙과 예정가격 제도가 공통으로 적용된다. | G92: 적용 범위가 동일하다. | H92: 감독 기관이 동일하다. | I92: 2 | J92: * 정답 (②): 두 법률 모두 공개경쟁입찰을 원칙으로 하고, 예정가격 제도를 통한 낙찰자 결정 구조가 유사하다.
A93: 90 | B93: 2. 공공계약(국가 및 지방) 법령의 이해 | C93: 1. 추정가격 및 예정가격 결정 | D93: 「국가계약법」과 「지방계약법」의 비교에 관한 설명으로 옳지 않은 것은? | E93: 「국가계약법」은 재정경제부, 「지방계약법」은 행정안전부가 소관한다. | F93: 두 법은 적용 주체(국가 / 지방자치단체)만 다를 뿐 기본 체계는 유사하다. | G93: 두 법은 동일한 시행령·시행규칙을 공유한다. | H93: 두 법 모두 일반경쟁입찰을 원칙으로 하며 동일한 예외 구조를 갖는다. | I93: 3 | J93: * 정답 (③): 「국가계약법」과 「지방계약법」은 별개의 법률로 각각 별도의 시행령(대통령령)·시행규칙(부령)을 가진다. 시행규칙은 「국가계약법」은 재정경제부령, 「지방계약법」은 행정안전부령으로 차이가 있다.
A94: 91 | B94: 2. 공공계약(국가 및 지방) 법령의 이해 | C94: 1. 추정가격 및 예정가격 결정 | D94: 「국가계약법」 제3조의 특별법 우선 원칙에 관한 설명으로 옳은 것은? | E94: 다른 법률에 특별한 규정이 있으면 그 법이 「국가계약법」에 우선 적용된다. | F94: 「국가계약법」은 모든 공공조달 관련 법률 중 항상 최우선 적용된다. | G94: 특별법 우선 원칙은 행정규칙에는 적용되지 않는다. | H94: 특별법 우선 원칙은 「민법」과의 관계에서만 적용된다. | I94: 1 | J94: * 정답 (①): 「국가계약법」 제3조는 다른 법률에 특별한 규정이 있는 경우 그 법이 우선 적용됨을 규정한다. 따라서 「판로지원법」의 중소기업자 간 경쟁제품 등 특별 규정이 있는 경우 그 법이 「국가계약법」보다 우선 적용된다.
... A134: 131 | B134: 5. 공기업·준정부기관 계약사무규칙 | C134: 1. 국제입찰 대상 공공조달계약 범위 | D134: 공기업·준정부기관 계약 사무 운영의 일반 원칙에 관한 설명으로 옳은 것은? | E134: 공기업·준정부기관도 공정성·투명성·경제성·효율성·책임성의 5대 원칙을 준수해야 한다. | F134: 공공기관은 민간기업이므로 공공조달 원칙은 적용되지 않는다. | G134: 공기업·준정부기관은 자체 규정만 따르면 되고 일반 원칙 준수 의무는 없다. | H134: 공기업·준정부기관 계약사무는 모든 정보를 비공개로 유지해야 한다. | I134: 1 | J134: * 정답 (①): 공기업·준정부기관도 공공조달의 일반 원칙(공정성·투명성·경제성·효율성·책임성)을 준수해야 하며, 「공공기관의 운영에 관한 법률」과 「공기업·준정부기관 계약사무규칙」은 이러한 원칙을 구체화하는 규범이다.
A135: 132 | B135: 1. 공공계약 관련 민법 규정의 이해 | C135: 3. 계약의 해제·해지에 관한 규정 | D135: 당사자 일방의 의사표시에 의하여 유효하게 성립된 계약의 효력을 장래에 대하여 소멸시키는 행위는? | E135: 해제 | F135: 해지 | G135: 철회 | H135: 취소 | I135: 2 | J135: * 정답 (②): 유효하게 성립한 계속적 계약의 효력을 '장래'에 향하여 소멸시키는 것은 '해지'이다. 반면 '해제'는 계약의 효력을 '소급'하여 소멸시키는 것을 의미한다. | K135: 공공조달관리사 수험자용 예제문제
A136: 133 | B136: 1. 공공계약 관련 민법 규정의 이해 | C136: 5. 화해에 관한 규정 | D136: [상황] 조달 분쟁 중 법원의 조정에 따라 양측이 상호 양보하는 민법상 '화해' 계약을 체결하였다. 이 계약의 효력에 대한 설명으로 옳은 것은? | E136: 진정한 권리관계와 다름이 입증되면 소급하여 무효가 된다 | F136: 종전 법률관계는 소멸하고 새 관계가 창설되어 재이의가 불가하다 | G136: 공공계약은 화해계약 효력을 상실하고 행정소송으로 전환된다 | H136: 행정지도에 불과하므로 계약상대자가 언제든 임의 취소할 수 있다 | I136: 2 | J136: * 정답 (②): 민법 제732조에 따라 화해계약은 당사자가 상호 양보하여 분쟁을 끝내는 계약이며, 화해가 성립하면 이전의 법률관계는 소멸하고 새로운 관계가 창설되는 효력(창설적 효력)을 가져 종전 주장을 되풀이할 수 없습니다. | K136: 민법 제732조 | L136: 260904
A137: 134 | B137: 1. 공공계약 관련 민법 규정의 이해 | C137: 5. 화해에 관한 규정 | D137: 민법 제733조에 따른 화해계약의 '착오를 이유로 한 취소'에 대한 예외적 허용 규정 및 법적 해석으로 가장 올바른 것은? | E137: 착오를 이유로 한 취소는 어떤 경우에도 전면 금지된다 | F137: 분쟁 사항 자체에 계산 착오가 있으면 소급 취소할 수 있다 | G137: 당사자 자격 등 분쟁 이외 사항의 착오는 예외적 취소가 가능하다 | H137: 법령 개정으로 내용이 불리해진 경우 동기 착오로 즉각 취소된다 | I137: 3 | J137: * 정답 (③): 민법 제733조에 따르면 화해계약은 원칙적으로 착오를 이유로 취소하지 못하지만, '화해 당사자의 자격' 또는 '화해의 목적인 분쟁 이외의 사항'에 착오가 있는 때에는 예외적으로 취소가 가능하도록 규정하고 있습니다. | K137: 민법 제733조 | L137: 260904
A138: 135 | B138: 1. 공공계약 관련 민법 규정의 이해 | C138: 5. 화해에 관한 규정 | D138: 조달계약 분쟁 해결을 위해 민법상 화해 규정을 적용할 때 법적 성질 및 실무상 유의점으로 가장 거리가 먼 것은? | E138: 정당한 근거 없는 권리 포기는 공무원 배임 문제가 될 수 있다 | F138: 유보 약정이 없으면 종전 하자담보책임 등은 모두 소멸된다 | G138: 반드시 서면 작성과 법원 확정판결을 거쳐야만 성립한다 | H138: 사기·강박에 의해 체결된 화해계약은 적법하게 취소할 수 있다 | I138: 3 | J138: * 정답 (③): 민법상 화해는 당사자 간의 의사 합치만으로 성립하는 '불요식 계약'이며, 반드시 서면으로 작성하거나 법원의 확정판결(재판상 화해)을 거쳐야만 효력이 발생하는 것은 아닙니다. | K138: 민법 제731조 (일반원칙) | L138: 260904
A139: 136 | B139: 3. 조달사업법령의 이해 | C139: 1. 공공조달의 정책기반 | D139: 공공조달의 기본원칙에 해당하지 않는 가치는 무엇인가? | E139: 공정하고 투명한 경쟁을 촉진해 조달 신뢰성을 제고한다 | F139: 수요기관 조달권한을 확대해 조달청 집중구매를 해소한다 | G139: 혁신성장과 환경친화 조달로 다양한 사회적 가치를 실현한다 | H139: 조달물자와 공공 시설물의 품질과 국민 안전을 확보한다 | I139: 2 | J139: * 정답 (②): 공공조달의 기본원칙에는 투명성, 품질/안전, 효율성, 사회적 가치 실현, 혁신성장 지원 등이 포함되나, '수요기관 조달 권한 확대를 통한 조달청 집중 구매의 해소'는 기본원칙에 명시된 가치가 아닙니다. | L139: 260904
A140: 137 | B140: 3. 조달사업법령의 이해 | C140: 1. 공공조달의 정책기반 | D140: 조달사업법령상 조달청장이 관장하는 '조달사업'의 구체적 범위에 명시적으로 포함되지 않는 업무는? | E140: 각종 조달물자의 구매·공급 및 체계적 관리 업무 | F140: 대규모 시설공사 및 감리·설계 용역의 계약체결 업무 | G140: 유휴 행정재산의 민간 매각·교환·대부 등 관리 업무 | H140: 비상사태·수급 불안 대비 비축 물자의 구매 및 관리 업무 | I140: 3 | J140: * 정답 (③): 행정재산 등 국유재산의 관리를 총괄하는 것은 국유재산법에 따른 재정경제부 소관 업무이며, 조달사업법상 '조달사업'의 직접적인 정의 범위(물자 조달, 비축, 시설공사 계약 등)에 해당하지 않습니다. | K140: 조달사업법 제2조, 제3조, 제29조 | L140: 260904
...

Sheet Temp
A3: 번호 | B3: 세부항목 | C3: 세세항목 | D3: 문제 내용 | E3: 보기① | F3: 보기② | G3: 보기③ | H3: 보기④ | I3: 정답 번호 | J3: 해설 및 오답노트 | K3: 출처 | L3: 구분

Sheet 2-1_공공조달계획
A2: 2-1. 공공조달계획
A3: 번호 | B3: 세부항목 | C3: 세세항목 | D3: 문제 내용 | E3: 보기① | F3: 보기② | G3: 보기③ | H3: 보기④ | I3: 정답 번호 | J3: 해설 및 오답노트 | K3: 출처 | L3: 개정일자 | M3: 숫자문제
A4: 1 | B4: 1. 공공조달 수요 분석 및 계획 | C4: 1. 공급 대상물 수요정보 식별 | D4: 과거 데이터 없이 전문가의 주관적 판단이나 의견에 의존하는 수요예측 기법에 해당하지 않는 것은? | E4: 회귀분석 | F4: 델파이 기법 | G4: 시장 조사법 | H4: 전문가 의견법 | I4: 1 | J4: * 정답 (①): 회귀분석은 과거 데이터의 인과관계를 통계적으로 분석하는 정량적 예측기법이며, 나머지는 전문가의 주관적 판단에 의존하는 정성적 기법임.
A5: 2 | B5: 1. 공공조달 수요 분석 및 계획 | C5: 1. 공급 대상물 수요정보 식별 | D5: [상황] 과거 3년간 월별 수요 데이터가 풍부하고 계절적 패턴이 안정적인 소모품이 있다. 이 품목의 수요예측에 가장 적합한 기법은? | E5: 이동평균법 | F5: 델파이 기법 | G5: 시나리오 분석법 | H5: 전문가 의견법 | I5: 1 | J5: * 정답 (①): 데이터가 풍부하고 패턴이 안정적인 경우 시계열 분석 기법인 이동평균법 등 정량적 기법이 적합함.
A6: 3 | B6: 1. 공공조달 수요 분석 및 계획 | C6: 3. 공급계획 및 일정 수립 | D6: 조달전략계획에 통상 포함되는 주제로 가장 거리가 먼 것은? | E6: 위험 관리 방안 | F6: 조달 배경 및 목적 | G6: 경쟁 업체의 내부 경영전략 | H6: 시장조사 결과 | I6: 3 | J6: * 정답 (③): 조달전략계획은 배경·범위·일정·예산·계약유형·시장조사·평가기준·위험관리 등을 포함하나, 경쟁업체의 내부 경영전략처럼 외부에서 알 수 없는 정보는 포함 대상이 아님.
A7: 4 | B7: 1. 공공조달 수요 분석 및 계획 | C7: 3. 공급계획 및 일정 수립 | D7: 국가계약법령에 따라 발주기관이 해당 연도 초에 업체들에게 미리 공개해야 하는 연간 '발주계획' 내역에 포함되지 않는 항목은? | E7: 특정 조달 건을 수주할 1순위 낙찰예정자의 상호 및 주소 | F7: 조달 사업의 공식 명칭 및 전체 예상 발주 물량 | G7: 해당 사업을 진행할 구체적인 입찰 방식 및 계약 방법 | H7: 분기별 등 대략적으로 예정된 조달 사업의 발주 시기 | I7: 1 | J7: * 정답 (①): 발주계획은 '앞으로 이런 사업을 공고할 예정이니 미리 준비하라'는 취지이므로, 아직 입찰도 진행되지 않은 시점이라 낙찰자 정보를 알 수 없습니다.
A8: 5 | B8: 1. 공공조달 수요 분석 및 계획 | C8: 3. 공급계획 및 일정 수립 | D8: 연초에 수요기관이 조달청 및 나라장터를 통해 공고하는 연간 '발주계획'을 조회하기 위한 올바른 나라장터 메뉴 이동 경로는? | E8: 입찰 → 입찰공고 → 발주계획 | F8: 발주 → 발주목록 → 발주계획 | G8: 공고 → 발주목록 → 발주계획 | H8: 이용자관리 → 발주관리 → 발주계획 | I8: 2 | J8: * 정답 (②): 나라장터 조달 프로세스 흐름에 따라 수요기관의 연간 발주 내역을 조회하려면, 메인 메뉴인 [발주] 탭을 클릭한 후 하위 메뉴인 [발주목록] → [발주계획] 순으로 진입해야 합니다.
A9: 6 | B9: 2. 공공조달 적정성 분석 | C9: 1. 공급방법 적정성 분석 | D9: 다음 중 다수공급자계약(MAS)에 대한 설명으로 옳은 것은? | E9: 수요기관은 납품업체를 선정할 때 반드시 최저가로 응찰한 업체를 선택해야 한다. | F9: 공공기관의 수요를 충족시키기 위해 오직 단일 공급업체와 독점 계약을 체결하는 방식이다. | G9: 2단계경쟁 제도를 통해 가격 외에도 품질, 납기, 사후관리 등을 종합적으로 평가하여 업체를 선정할 수 있다. | H9: 수요기관은 종합쇼핑몰을 통하지 않고 각 업체와 개별적으로 수의계약을 맺어야 한다. | I9: 3 | J9: * 정답 (③): MAS 계약은 다수의 공급업체와 계약을 체결(② 틀림)하고, 수요기관은 종합쇼핑몰에서 규격 및 가격을 비교(④ 틀림)할 수 있습니다. 또한, 가격 외에 품질이나 납기 등을 종합적으로 고려하여 업체를 선택할 수 있으므로 반드시 최저가 업체를 선택해야 하는 것은 아닙니다(① 틀림). | K9: 물품 다수공급자계약 업무처리규정
A10: 7 | B10: 2. 공공조달 적정성 분석 | C10: 1. 공급방법 적정성 분석 | D10: 다수공급자계약(MAS)을 통해 물품을 구매하려는 수요기관 담당자의 판단으로 가장 적절한 것은? | E10: "여러 업체의 물품을 비교해보고 싶지만, MAS 제도는 한 가지 물품당 하나의 업체만 등록되어 있어 비교할 수 없겠군." | F10: "우리 기관은 예산 절감이 최우선이니, 종합쇼핑몰에 등록된 업체 중 품질과 상관없이 무조건 최저가 업체에 납품을 요구해야겠어." | G10: "구매하려는 품목이 일정 금액 이상이니, 등록된 업체들을 대상으로 2단계경쟁을 실시하여 추가적인 조건 협상을 진행해봐야겠군." | H10: "MAS 계약 품목은 종합쇼핑몰에 이미 단가가 고정되어 있으므로, 어떠한 경우에도 추가적인 가격 협상이나 경쟁은 불가능해." | I10: 3 | J10: * 정답 (③): MAS 제도는 수요기관이 종합쇼핑몰에서 여러 업체의 동종·유사 물품을 비교할 수 있으며(① 틀림), 2단계경쟁을 통해 추가적인 가격 협상이 가능합니다(④ 틀림). 또한 최저가 업체만 고집할 필요 없이 납기나 사후관리 등 종합적인 조건을 고려할 수 있습니다(② 틀림). | K10: 물품 다수공급자계약 업무처리규정
A11: 8 | B11: 2. 공공조달 적정성 분석 | C11: 1. 공급방법 적정성 분석 | D11: 다음 빈칸 (A), (B)에 들어갈 말로 가장 바르게 짝지어진 것은? "다수공급자계약(MAS)은 공공기관의 다양한 수요를 충족하기 위하여 품질, 성능, 효율 등에서 ( A ) 물품에 대해 ( B ) 공급업체와 계약을 체결하여 종합쇼핑몰을 통해 공급하는 제도이다." | E11: (A) 완전히 동일한 - (B) 1개의 지정된 | F11: (A) 동종·유사 - (B) 1개의 지정된 | G11: (A) 완전히 동일한 - (B) 다수의 | H11: (A) 동종·유사 - (B) 다수의 | I11: 4 | J11: * 정답 (④): MAS(Multiple Award Schedule)라는 명칭에서 알 수 있듯이, 수요기관의 선택권을 넓히기 위해 '동종·유사' 물품에 대해 '다수'의 공급업체와 계약을 체결하는 것이 이 제도의 핵심입니다. | K11: 물품 다수공급자계약 업무처리규정
A12: 9 | B12: 2. 공공조달 적정성 분석 | C12: 1. 공급방법 적정성 분석 | D12: 다음 중 공공기관의 우선(의무)구매 제도에 대한 설명으로 가장 옳지 않은 것은? | E12: 중소기업제품의 구매목표비율은 해당 기관 구매총액의 50% 이상이어야 한다. | F12: 장애인기업제품은 해당 기관 구매총액의 1% 이상을 구매해야 한다. | G12: 여성기업제품은 공사 구매액의 경우 3% 이상을 구매해야 한다. | H12: 중소기업 기술개발제품은 중소기업 물품 구매액의 50% 이상을 의무적으로 구매해야 한다. | I12: 4 | J12: * 정답 (④): 중소기업 기술개발제품의 의무구매비율은 중소기업 물품 구매액의 15% 이상(과거 10%에서 상향)입니다. 50%는 중소기업제품 전체에 대한 의무구매비율입니다. (※ 여성기업제품: 물품/용역 5%, 공사 3%) | K12: 판로지원법 시행령 제4조, 12조, 여성기업법 시행령 제7조, 장애인기업법 시행령 제7조의2
A13: 10 | B13: 2. 공공조달 적정성 분석 | C13: 1. 공급방법 적정성 분석 | D13: 현행 법령상 공공기관의 '중소기업제품 구매목표비율'은 해당 기관이 해당 연도에 구매할 제품의 구매총액 대비 최소 얼마 이상으로 의무 규정되어 있는가? | E13: 15% | F13: 30% | G13: 50% | H13: 70% | I13: 3 | J13: * 정답 (③): 관련 법령에 따라 공공기관은 당해 연도 제품 구매총액의 50% 이상을 중소기업제품으로 의무 구매해야 합니다. | K13: 판로지원법 시행령 제4조
A14: 11 | B14: 2. 공공조달 적정성 분석 | C14: 3. 공급 대상물 조달시장 분석 | D14: ABC 분석에서 A등급 품목의 특성으로 옳은 것은? | E14: 품목 수와 구매금액 비중이 모두 낮다 | F14: 품목 수는 전체의 10~20% 수준이지만 구매금액 비중은 70~80%에 이른다 | G14: 품목 수와 구매금액 비중이 모두 중간 수준이다 | H14: 품목 수가 가장 많고 구매금액 비중은 가장 낮다 | I14: 2 | J14: * 정답 (②): ABC 분석의 A등급은 소수의 품목(약 10~20%)이 전체 구매금액의 대부분(약 70~80%)을 차지하는 핵심 관리대상 품목임.
A15: 12 | B15: 2. 공공조달 적정성 분석 | C15: 3. 공급 대상물 조달시장 분석 | D15: 시장조사 절차에서 가장 먼저 수행해야 하는 단계는? | E15: 기존 자료 검토 | F15: 가격 정보 수집 | G15: 잠재적 공급업체 식별 | H15: 조사의 목적과 범위 설정 | I15: 4 | J15: * 정답 (④): 시장조사는 먼저 조사의 목적과 범위를 명확히 설정한 뒤, 기존 정보 검토·시장구조 분석·업체 식별 등의 순서로 진행하는 것이 원칙임.
A16: 13 | B16: 3. 공공조달 비용 적정성 분석 | C16: 1. 공급 의사결정을 위한 비용분석 | D16: 다음 중 조달절차에서의 '경제성 평가'에 대한 설명으로 가장 옳지 않은 것은? | E16: 경제성 평가 항목에는 가격뿐만 아니라 운송비, 운영비, 초기 비용, 총소유비용(TCO) 등 다양한 요소를 포함할 수 있다. | F16: 서비스나 공사의 계약에서는 입찰자의 자유로운 서식 작성을 위해 물량내역서(BOQ) 등 비용내역서 제출 양식(템플릿)을 제공하지 않는다. | G16: 경제적 측면에서 입찰서 등의 내용이 해당 조달사업에서 확보한 예산 범위 내에 있는지 여부를 반드시 확인해야 한다. | H16: 경제성 평가 측면에서 검토·평가한 결과는 보고서에 정리해야 하며, 조달 담당자 또는 평가위원회가 이에 서명해야 한다. | I16: 2 | J16: * 정답 (②): 서비스나 공사의 경우, 공사별 물량내역서(BOQ)와 같이 비용내역서를 제공하는 양식(템플릿)을 반드시 제공하여야 합니다. | K16: 표준교재 2권 p.76
A17: 14 | B17: 3. 공공조달 비용 적정성 분석 | C17: 1. 공급 의사결정을 위한 비용분석 | D17: 조달사업의 '경제성 평가'를 수행할 때 고려해야 할 사항으로 가장 적절하지 않은 것은? | E17: 입찰공고 문서에 평가요소로 포함될 경제성 평가 항목과 평가기준을 명확하게 제시해야 한다. | F17: 시장 상황을 고려하여 경제성 측면에서 적정성을 분석하고, 가격 및 비용 요소가 합리적인지 검토해야 한다. | G17: 재정 기준의 가중치는 모든 조달 사업에서 변함없이 고정된 비율로 일정하게 적용해야 한다. | H17: 제안서의 재무평가는 입찰공고문에 명시된 재무적, 상업적 요건과 제안서를 비교하는 방식을 포함한다. | I17: 3 | J17: * 정답 (③): 재정제안은 중요한 평가기준이지만, 재정 기준의 가중치는 고정된 것이 아니라 선택한 평가 방법에 따라 달라질 수 있습니다. | K17: 표준교재 2권 p.76
A18: 15 | B18: 3. 공공조달 비용 적정성 분석 | C18: 2. 적정 공급비용 산정 | D18: 추정가격과 예정가격을 비교한 설명으로 가장 옳은 것은? | E18: 두 개념은 동일하며 구분할 실익이 없다 | F18: 예정가격은 계획 단계에서, 추정가격은 입찰 직전에 산정한다 | G18: 추정가격은 조달계획 단계의 개략적 추정치이고, 예정가격은 입찰 전 정밀 산정을 거쳐 법적 구속력을 갖는다 | H18: 추정가격이 예정가격보다 법적 구속력이 강하다 | I18: 3 | J18: * 정답 (③): 추정가격은 계획 단계의 개략적 추정(부가가치세 미포함)이고, 예정가격은 입찰 전 정밀하게 산정(부가가치세 포함)해 낙찰자·계약금액 결정의 법적 기준이 됨. | K18: 국가계약법 시행령 제2조·제7조의2
A19: 16 | B19: 3. 공공조달 비용 적정성 분석 | C19: 2. 적정 공급비용 산정 | D19: 예정가격 작성 시 원가계산 방식에서 '이윤'을 산정하기 위한 기준 금액 요소로 가장 옳은 것은? | E19: 재료비 + 노무비 + 경비 | F19: 노무비 + 경비 + 일반관리비 | G19: 재료비 + 일반관리비 | H19: 재료비 + 노무비 + 경비 + 일반관리비 | I19: 2 | J19: * 정답 (②): 원가계산 시 이윤은 (노무비 + 경비 + 일반관리비)의 합계액에 정해진 이윤율을 곱하여 산정합니다. 기술적·원가적 특성상 '재료비'는 이윤 산정 대상 금액에서 제외됩니다. | K19: 예정가격작성기준 제14조, 제21조
A20: 17 | B20: 3. 공공조달 비용 적정성 분석 | C20: 2. 적정 공급비용 산정 | D20: 정부계약 원가계산 방식의 각 비목별 산정 기준에 대한 설명으로 가장 옳지 않은 것은? | E20: 순원가(제조원가)는 재료비, 노무비, 경비의 합계액으로 구성된다. | F20: 일반관리비는 순원가(재료비·노무비·경비 합계액)에 일반관리비율을 곱하여 산정한다. | G20: 이윤은 재료비를 포함한 총원가 전체 금액에 이윤율을 곱하여 산정한다. | H20: 원가계산에 의한 예정가격 산정 시 관련 법령에서 정한 비목별 승율(비율) 상한을 초과할 수 없다. | I20: 3 | J20: * 정답 (③): 이윤 산정 시 '재료비'는 포함되지 않습니다. 이윤은 총원가가 아닌 (노무비 + 경비 + 일반관리비)의 합계액을 기준으로 계산합니다. | K20: 예정가격작성기준 제14조, 제21조
A21: 18 | B21: 3. 공공조달 비용 적정성 분석 | C21: 2. 적정 공급비용 산정 | D21: 원가계산에 의한 예정가격 산정 구조에서 재료비, 노무비, 경비를 모두 합한 금액을 의미하는 용어는? | E21: 총원가 | F21: 일반관리비 | G21: 순제조원가 | H21: 추정가격 | I21: 3 | J21: * 정답 (③): 재료비, 노무비, 경비의 합계는 '순제조원가'에 해당합니다. 여기에 일반관리비를 더하면 '총원가', 총원가에 이윤과 부가가치세를 더하면 최종 원가계산 가격이 산출됩니다. | K21: 표준교재 2권 p.121
A22: 19 | B22: 4. 기타 적정성 분석 | C22: 3. 공급관리 및 위험분석 | D22: 다음 중 조달 과정에서 발생할 수 있는 납품 지연(Late delivery) 위험의 '발생 가능성 완화 방안'에 해당하는 것은? | E22: 지연배상금(Liquidated damage) 부과 | F22: 비상계획(Contingency plan) 수립 | G22: 적정한 계획(Proper planning) 마련 | H22: 여유분(버퍼) 및 비상재고 유지 | I22: 1 | J22: * 정답 (①): 지연배상금과 선제적 계약관리는 납품 지연의 '발생 가능성을 완화'하기 위한 사전 방안입니다. 반면 ②, ③, ④는 납품 지연 사태가 발생했을 때 그 '결과나 영향을 완화'하기 위한 방안에 해당합니다. | K22: 표준교재 2권 p.263
A23: 20 | B23: 4. 기타 적정성 분석 | C23: 3. 공급관리 및 위험분석 | D23: [상황] 계약담당자가 계약상대자의 이행 실패 위험에 대비해, 그 손실 부담을 보험사 등 제3자가 나누어 지도록 하는 조치를 취했다. 이러한 위험 대응 전략은? | E23: 위험 수용(별도 조치 없이 감수) | F23: 위험 전가(이행보증보험 가입 요구) | G23: 위험 분산(공급선 다변화) | H23: 위험 회피(사업 자체 취소) | I23: 2 | J23: * 정답 (②): 이행보증보험 가입 요구처럼 위험의 재무적 결과를 제3자(보험사)에게 이전하는 전략을 위험의 전가(Transfer)라 함. | K23: 표준교재 2권 p.262
A24: 21 | B24: 4. 기타 적정성 분석 | C24: 3. 공급관리 및 위험분석 | D24: 위험관리매트릭스에서 발생 확률과 영향도가 모두 높게 평가된 위험의 등급으로 옳은 것은? | E24: 낮음 | F24: 결정적 | G24: 높음 | H24: 중간 | I24: 2 | J24: * 정답 (②): 발생확률·영향도가 모두 높은 위험은 결정적(Critical)으로 분류 | K24: 표준교재 2권 p.260
A25: 22 | B25: 1. 공공조달 수요 분석 및 계획 | C25: 1. 공급 대상물 수요정보 식별 | D25: 공공조달 수요 분석 및 공급계획의 기본 개념/원칙으로 가장 적절한 것은? | E25: 상황에 따라 사후에 기준을 바꾸어도 무방하다. | F25: 구두 합의가 문서보다 우선한다. | G25: 담당자 편의에 따라 공개·기록을 생략할 수 있다. | H25: 기준·절차를 사전에 명확히 하고 동일하게 적용하여 공정성과 투명성을 확보한다. | I25: 4 | J25: * 정답 (④): 공공조달의 기본 원칙은 사전확정·공개·기록·동일적용이다. 이를 통해 공정성과 투명성을 확보하고, 감사·분쟁 리스크를 줄일 수 있다(출처: 조달청 교재 단원별 문제구성).
A26: 23 | B26: 1. 공공조달 수요 분석 및 계획 | C26: 1. 공급 대상물 수요정보 식별 | D26: 공공조달 수요 분석 및 공급계획 관련 실무통제(리스크 관리)로 가장 적절한 것은? | E26: 계약조건은 낙찰자와 구두로만 정한다. | F26: 검수는 생략하고 하자 발생 시 추후 협의한다. | G26: 평가기준은 입찰 마감 후 필요에 따라 조정한다. | H26: 요구사항·평가기준·검수기준·변경절차를 문서화하고 이해관계자에게 사전 공유한다. | I26: 4 | J26: * 정답 (④): 문서화와 사전공유는 분쟁 예방, 성과관리, 책임소재 명확화에 가장 효과적인 실무통제 방법이다(출처: 조달청 교재 단원별 문제구성).
A27: 24 | B27: 1. 공공조달 수요 분석 및 계획 | C27: 1. 공급 대상물 수요정보 식별 | D27: 공공조달 수요 분석 및 공급계획에 관한 설명으로 옳은 것은? | E27: 조달절차의 각 단계는 관련 규정에 따라 수행되며, 핵심 판단은 기록으로 남겨야 한다. | F27: 사전공개는 원칙이 아니라 선택사항이다. | G27: 절차는 내부 방침만 따르면 되며 외부 기준은 고려하지 않는다. | H27: 입찰·계약 단계에서 이해상충은 문제되지 않는다. | I27: 1 | J27: * 정답 (①): 절차 준수와 기록(근거)은 공공조달에서 필수 요건이다. 모든 핵심 판단은 관련 규정에 따라 수행되고, 그 과정과 결과가 기록으로 남아야 사후 감사와 분쟁에 대응할 수 있다(출처: 조달청 교재 단원별 문제구성).
A28: 25 | B28: 1. 공공조달 수요 분석 및 계획 | C28: 1. 공급 대상물 수요정보 식별 | D28: 공급업체가 공공조달 수요정보를 수집할 수 있는 채널로 적절하지 않은 것은? | E28: 나라장터(g2b.go.kr)의 발주계획 및 입찰공고 | F28: 조달데이터허브(data.g2b.go.kr)의 계약 실적 통계 | G28: 수요기관 담당자의 비공식 사전 정보 제공 | H28: 각 지방자치단체의 전자조달시스템 | I28: 3 | J28: * 정답 (③): 공공조달의 수요정보는 공식적인 전자조달 플랫폼(나라장터, 조달데이터허브, 지자체 시스템)을 통해 수집해야 한다. 담당자의 비공식 사전 정보 제공은 공정성을 저해하는 행위에 해당할 수 있어 적절한 수요정보 수집 채널이 아니다.
A29: 26 | B29: 1. 공공조달 수요 분석 및 계획 | C29: 3. 공급계획 및 일정 수립 | D29: 5단계 공급계획 수립 절차를 올바른 순서로 나열한 것은? | E29: 수요 분석 → 수요정보 수집 → 입찰전략 수립 → 공급역량 평가 → 실행계획 확정 | F29: 수요정보 수집 → 수요 분석 → 공급역량 평가 → 입찰전략 수립 → 실행계획 확정 | G29: 공급역량 평가 → 수요정보 수집 → 수요 분석 → 실행계획 확정 → 입찰전략 수립 | H29: 입찰전략 수립 → 수요 분석 → 수요정보 수집 → 공급역량 평가 → 실행계획 확정 | I29: 2 | J29: * 정답 (②): 5단계 공급계획 수립은 ① 수요정보 수집 → ② 수요 분석 → ③ 공급역량 평가 → ④ 입찰전략 수립 → ⑤ 실행계획 확정의 순서로 진행된다. 수요정보를 먼저 수집·분석한 후, 자사 역량을 평가하고 전략을 수립하는 논리적 흐름을 따른다.
A30: 27 | B30: 2. 공공조달 적정성 분석 | C30: 3. 공급 대상물 조달시장 분석 | D30: 입찰혼잡도에 대한 설명으로 옳은 것은? | E30: 발주기관이 공고한 입찰의 예산 규모를 나타내는 지표이다. | F30: 특정 입찰에 참여하는 업체 수(경쟁 강도)를 나타내는 지표이다. | G30: 낙찰자 결정에 소요되는 기간을 측정하는 지표이다. | H30: 입찰 무효율(무효 입찰 비율)을 산정하는 지표이다. | I30: 2 | J30: * 정답 (②): 입찰혼잡도는 특정 입찰에 참여하는 업체 수, 즉 경쟁 강도를 나타내는 지표이다. 혼잡도가 높을수록 경쟁이 심화되어 낙찰 확률이 낮아지므로, 공급업체의 입찰 참여 의사결정에 중요한 참고지표가 된다.
A31: 28 | B31: 1. 공공조달 수요 분석 및 계획 | C31: 4. 비상 공급계획 수립 | D31: 비상 공급계획에 포함되어야 할 내용으로 가장 거리가 먼 것은? | E31: 원자재 공급 차질 시 대체 공급선 확보 방안 | F31: 생산 지연 발생 시 협력업체 긴급 지원 체계 | G31: 경쟁업체의 입찰가격 정보 수집 방안 | H31: 외부 환경 변화(자연재해 등)에 대한 사업 연속성 계획 | I31: 3 | J31: * 정답 (③): 비상 공급계획은 공급 차질에 대한 대안적 대응 체계를 다루는 것이다. 경쟁업체의 입찰가격 정보 수집은 비상계획과 무관하며, 나아가 공정경쟁 질서를 저해하는 행위에 해당할 수 있다.
A32: 29 | B32: 1. 공공조달 수요 분석 및 계획 | C32: 1. 공급 대상물 수요정보 식별 | D32: 공공조달 수요정보 수집의 4대 채널에 해당하지 않는 것은? | E32: 나라장터(g2b.go.kr) — 발주계획·사전규격 공개·입찰공고 | F32: 지자체 전자조달시스템 — 지자체별 발주계획·수의계약 정보 | G32: 조달데이터허브(data.g2b.go.kr) — 조달 통계·계약실적 | H32: 한국은행 경제통계시스템 — 거시경제 지표 | I32: 4 | J32: * 정답 (④): 공공조달 수요정보 수집의 4대 채널은 ① 나라장터, ② 지자체 전자조달시스템, ③ 조달데이터허브, ④ 정책정보(재정경제부·각 부처 홈페이지)이다. 한국은행 경제통계시스템은 거시경제 지표 제공으로 공공조달 수요정보의 직접 채널이 아니다.
A33: 30 | B33: 1. 공공조달 수요 분석 및 계획 | C33: 2. 수요정보 평가와 요구사항 분석 | D33: 공공조달 수요정보의 3가지 유형에 관한 설명으로 옳은 것은? | E33: 발주예정정보(사전 공개) → 입찰공고정보(공식 공고) → 계약실적정보(사후 데이터)의 시간 순서로 구분된다. | F33: 모든 수요정보는 입찰공고와 동시에 공개된다. | G33: 계약실적정보는 향후 수요예측에 활용할 수 없다. | H33: 발주예정정보는 입찰공고 후 사후 공개되는 정보이다. | I33: 1 | J33: * 정답 (①): 수요정보는 시간 순서대로 ① 발주예정정보(사전 공개) → ② 입찰공고정보(공식 공고) → ③ 계약실적정보(사후 데이터)로 구분되며, 공급업체는 단기·중장기 전략 수립에 모두 활용한다.
A34: 31 | B34: 2. 공공조달 적정성 분석 | C34: 3. 공급 대상물 조달시장 분석 | D34: 입찰혼잡도(Bidder Density) 개념에 관한 설명으로 옳지 않은 것은? | E34: 특정 입찰에 참여하는 업체 수를 나타내는 경쟁 강도 지표이다. | F34: 입찰혼잡도가 높을수록 낙찰 가능성은 일반적으로 낮아진다. | G34: 공급업체가 입찰 참여 의사결정에 활용하는 지표이다. | H34: 입찰혼잡도는 발주 규모와 비례하며 사업 규모가 클수록 항상 높다. | I34: 4 | J34: * 정답 (④): 입찰혼잡도는 발주 규모와 직접 비례하지 않는다. 사업 특수성·진입장벽·시장 경쟁 구조 등 복합 요인에 따라 결정되며, 큰 사업이라도 진입장벽이 높으면 혼잡도가 낮을 수 있다.
A35: 32 | B35: 1. 공공조달 수요 분석 및 계획 | C35: 3. 공급계획 및 일정 수립 | D35: 공급업체 관점의 5단계 공급계획 수립 절차로 옳은 것은? | E35: 수요정보 수집 → 수요 분석 → 공급역량 평가 → 입찰전략 수립 → 실행계획 확정 | F35: 입찰전략 수립 → 수요정보 수집 → 실행계획 확정 → 수요 분석 → 공급역량 평가 | G35: 수요 분석 → 수요정보 수집 → 입찰전략 수립 → 공급역량 평가 → 실행계획 확정 | H35: 공급역량 평가 → 실행계획 확정 → 수요정보 수집 → 입찰전략 수립 → 수요 분석 | I35: 1 | J35: * 정답 (①): 공급업체의 5단계 공급계획은 ① 수요정보 수집(채널 다변화) → ② 수요 분석(시장규모·경쟁현황) → ③ 공급역량 평가(Go/No-Go 기준) → ④ 입찰전략 수립(목표·방법·일정) → ⑤ 실행계획 확정 순서이다.
A36: 33 | B36: 1. 공공조달 수요 분석 및 계획 | C36: 2. 수요정보 평가와 요구사항 분석 | D36: 조달데이터허브를 활용한 수요 분석 차원에 해당하지 않는 것은? | E36: 조달유형별 분석 — 물품·용역·공사별 계약 규모·건수 추이 | F36: 계약방법별 분석 — 일반경쟁·제한경쟁·수의계약 비중 변화 | G36: 품목별 분석 — 세부품명 단위 계약금액·건수·단가 | H36: 입찰자 학력별 분석 — 응찰 담당자의 학위 분포 | I36: 4 | J36: * 정답 (④): 조달데이터허브의 분석 차원은 ① 조달유형별, ② 계약방법별, ③ 품목별, ④ 기관별 분석이다. 입찰자 담당자 학력 분포는 분석 차원에 해당하지 않으며, 정보 자체가 공개되지도 않는다.
... A81: 78 | B81: 4. 기타 적정성 분석 | C81: 3. 공급관리 및 위험분석 | D81: 공급자 선호 매트릭스(Supplier Preference Matrix)에 관한 설명으로 옳은 것은? | E81: 수요기관이 공급업체를 평가하는 주관적 선호도 분석 도구이다. | F81: 공급업체 관점에서 수요기관을 매력도·경쟁력 두 축으로 분류하여 차별화된 관계 전략을 수립하는 도구이다. | G81: 모든 공급업체와 동일한 거래 관계를 유지해야 한다는 원칙이다. | H81: 입찰가격 결정에만 사용되는 단일 목적 분석 도구이다. | I81: 2 | J81: * 정답 (②): 공급자 선호 매트릭스는 공급업체 관점에서 수요기관을 매력도(거래 가치)·경쟁력(자사 강점) 두 축으로 분류하여, 핵심 수요기관·일반 수요기관 등에 차별화된 관계 전략을 수립하는 포트폴리오 분석 도구이다.

Sheet 2-2_조달요구응대및제안
A2: 2-2. 조달요구 응대 및 제안
A3: 번호 | B3: 세부항목 | C3: 세세항목 | D3: 문제 내용 | E3: 보기① | F3: 보기② | G3: 보기③ | H3: 보기④ | I3: 정답 번호 | J3: 해설 및 오답노트 | K3: 출처 | L3: 개정일자 | M3: 숫자문제
A4: 1 | B4: 1. 조달요구 대처 절차 | C4: 1. 경쟁입찰참가자격 등록 | D4: 공공입찰 참여를 위해 가장 먼저 해야 할 절차는? | E4: 사전규격공개 의견 제출 | F4: 입찰보증금 납부 | G4: 제안서 작성 | H4: 나라장터 경쟁입찰참가자격 등록 | I4: 4 | J4: * 정답 (④): 공공입찰 참여를 위해서는 먼저 나라장터(KONEPS)에 경쟁입찰참가자격을 등록해야 함.
A5: 2 | B5: 1. 조달요구 대처 절차 | C5: 1. 경쟁입찰참가자격 등록 | D5: [상황] A사는 특정 물품의 '공급업체'로만 나라장터에 등록되어 있다. 해당 물품 입찰이 '제조입찰'로 참가자격이 제한된 경우 A사의 참가 가능 여부는? | E5: 참가 가능 | F5: 참가 불가 | G5: 발주기관 승인 시 참가 가능 | H5: 조건부 참가 가능 | I5: 2 | J5: * 정답 (②): 제조입찰로 참가자격이 제한된 경우 해당 물품의 제조업체로 등록해야만 참가 가능함.
A6: 3 | B6: 1. 조달요구 대처 절차 | C6: 1. 경쟁입찰참가자격 등록 | D6: 나라장터 등록정보(대표자 등) 변경 후 갱신하지 않고 입찰에 참가한 경우 발생할 수 있는 불이익은? | E6: 해당 입찰의 무효 처리 | F6: 과태료 부과 | G6: 형사처벌 | H6: 영업정지 | I6: 1 | J6: * 정답 (①): 등록정보 변경신고 없이 입찰서를 제출한 입찰은 무효 사유에 해당함.
A7: 4 | B7: 1. 조달요구 대처 절차 | C7: 1. 경쟁입찰참가자격 등록 | D7: 중소기업자간 경쟁제품에 해당하는 물품 입찰에 참가하기 위해 반드시 갖춰야 하는 것을 모두 고르면? (ㄱ.중소기업확인서 ㄴ.직접생산확인증명서 ㄷ.우수조달물품 지정서) | E7: ㄱ,ㄴ | F7: ㄱ,ㄴ,ㄷ | G7: ㄱ | H7: ㄴ,ㄷ | I7: 1 | J7: * 정답 (①): 중소기업자간 경쟁제품 입찰 참가에는 중소기업확인서와 직접생산확인증명서가 필요하며, 우수조달물품 지정서는 별도 제도로 필수 요건이 아님.
A8: 5 | B8: 1. 조달요구 대처 절차 | C8: 1. 경쟁입찰참가자격 등록 | D8: 공동수급체에 대한 설명으로 옳지 않은 것은? | E8: 공동수급협정서는 입찰마감 전일까지 제출해야 한다 | F8: 분담이행방식도 구성원 전원이 전체 계약에 연대책임을 진다 | G8: 공동이행방식은 구성원 전원이 연대책임을 진다 | H8: 2개 이상 사업자가 공동입찰을 위해 결성한 조직이다 | I8: 2 | J8: * 정답 (②): 분담이행방식은 각 구성원이 분담 내용에 따라 자기 책임하에 이행하며, 전체 계약에 대한 연대책임은 공동이행방식의 특징임. | K8: 공동계약 운용요령
A9: 6 | B9: 1. 조달요구 대처 절차 | C9: 1. 경쟁입찰참가자격 등록 | D9: 공동이행방식 공동수급체에 대한 설명으로 옳은 것은? | E9: 각 구성원이 분담한 부분만 책임진다 | F9: 주로 복합공종 사업에 활용된다 | G9: 구성원이 공동으로 자본·인력을 투자해 계약을 이행하고 손익도 공동 계산한다 | H9: 대표사 출자비율에 최소요건이 없다 | I9: 3 | J9: * 정답 (③): 공동이행방식은 구성원이 공동으로 자본·인력을 투자해 이행하고 손익도 공동 계산함. ①④는 분담이행방식의 특징. | K9: 공동계약 운용요령
A10: 7 | B10: 1. 조달요구 대처 절차 | C10: 1. 경쟁입찰참가자격 등록 | D10: 나라장터 등록정보 중 대표자가 변경됐음에도 갱신하지 않고 입찰서를 제출한 경우의 효력은? | E10: 발주기관 재량으로 결정된다 | F10: 계약체결 시 갱신하면 유효하다 | G10: 입찰 무효 사유에 해당한다 | H10: 과태료만 부과되고 입찰은 유효하다 | I10: 3 | J10: * 정답 (③): 등록사항 변경신고를 하지 않고 한 입찰은 무효 사유에 해당함. | K10: 국가계약법 시행규칙 제44조제1항제5호
A11: 8 | B11: 1. 조달요구 대처 절차 | C11: 1. 경쟁입찰참가자격 등록 | D11: 공동수급체 구성원 중 1인이 입찰참가자격을 갖추지 못한 경우에 대한 설명으로 옳은 것은? | E11: 해당 구성원만 제외하고 나머지로 진행 가능하다 | F11: 구성원 전원이 자격을 갖춰야 하므로, 전체 입찰이 무효 처리될 수 있다 | G11: 대표사만 자격을 갖췄으면 유효하다 | H11: 출자비율만 조정하면 된다 | I11: 2 | J11: * 정답 (②): 공동수급체의 모든 구성원은 각각 입찰참가자격을 갖추어야 하며, 한 구성원이라도 미달이면 전체 입찰이 무효 처리될 수 있음. | K11: 국가계약법 시행규칙 제44조
A12: 9 | B12: 1. 조달요구 대처 절차 | C12: 1. 경쟁입찰참가자격 등록 | D12: 「국가를 당사자로 하는 계약에 관한 법률」상 계약 체결 방식에 대한 설명으로 가장 옳지 않은 것은? | E12: 공공계약은 원칙적으로 일반경쟁입찰에 붙여야 한다. | F12: 제한경쟁입찰, 지명경쟁입찰, 수의계약은 법령이 정한 특별한 사유가 있는 경우에만 예외적으로 허용된다. | G12: 계약담당공무원은 업무 편의성을 위해 법령 규정과 상관없이 수의계약을 원칙으로 채택할 수 있다. | H12: 경쟁입찰에 부칠 때 입찰 참가 자격을 특정한 기준(실적, 기술 등)으로 제한하는 것은 제한경쟁입찰에 해당한다. | I12: 3 | J12: * 정답 (③): 국가계약법 제7조에 따라 공공조달은 일반경쟁이 원칙입니다. 계약담당공무원이 임의로 수의계약을 원칙으로 채택할 수 없으며, 수의계약은 법령에 명시된 특수 사유(소액, 천재지변, 국가안보 등)에 한해서만 제한적으로 적용됩니다. | K12: 국가계약법 제7조
A13: 10 | B13: 1. 조달요구 대처 절차 | C13: 1. 경쟁입찰참가자격 등록 | D13: 공공계약 방식 중 법률에 명시된 예외적 사유(천재지변, 국가안보, 재공고입찰 유찰, 소액계약 등)가 발생했을 때 경쟁 입찰 절차를 거치지 않고 특정 공급자와 직접 계약을 체결하는 방식은? | E13: 일반경쟁 | F13: 수의계약 | G13: 지명경쟁 | H13: 제한경쟁 | I13: 2 | J13: * 정답 (②): 수의계약은 경쟁을 거치지 않고 특정한 자를 지정하여 계약을 체결하는 예외적 방식입니다. | K13: 국가계약법 제7조 및 시행령 제26조
A14: 11 | B14: 1. 조달요구 대처 절차 | C14: 1. 경쟁입찰참가자격 등록 | D14: 「국가계약법」상 경쟁입찰의 종류 및 계약 방식에 관한 설명으로 가장 옳은 것은? | E14: 지명경쟁은 불특정 다수의 모든 업체가 제한 없이 자유롭게 참여하는 기본 방식이다. | F14: 수의계약은 공공조달 계약에서 가장 우선적으로 적용해야 하는 원칙적인 방식이다. | G14: 제한경쟁은 시공능력, 유사실적, 기술자격 등 법령이 정한 요건을 갖춘 자로 입찰 자격을 제한하여 경쟁시키는 방식이다. | H14: 일반경쟁은 특정한 신용이나 실적을 갖춘 특정 인원만을 지정하여 입찰에 참가시키는 방식이다. | I14: 3 | J14: * 정답 (③): 제한경쟁은 사업장 소재지, 실적, 기술 자격 등으로 입찰 참가 자격을 제한하는 경쟁 방식입니다. ①은 일반경쟁, ②는 수의계약이 아닌 일반경쟁이 원칙, ④는 지명경쟁에 대한 설명입니다. | K14: 국가계약법 제7조
A15: 12 | B15: 1. 조달요구 대처 절차 | C15: 1. 경쟁입찰참가자격 등록 | D15: 입찰참가자격 등록 절차 및 필요 서류에 관한 설명으로 가장 옳은 것은? | E15: 매각 등 세입 원인이 되는 계약에 입찰 참가 시에는 조달청 자격 등록이 면제된다. | F15: 물품 제조 입찰에서는 참가자격을 증명하기 위해 공장등록증이나 직접생산증명서가 필요하다. | G15: 지정정보처리장치를 통한 전자입찰 등록 시 인감증명서는 모든 업종에서 필수 제출서류이다. | H15: 공사 입찰과 용역 입찰에서 참가자격을 증명하기 위해 요구되는 기본 면허 서류는 동일하다. | I15: 2 | J15: 정답 (②) 제조업체 확인을 위해 필수임 / ① 세입 원인도 등록 필요 / ③ 인감증명서는 본인서명사실확인서 등으로 대체 가능하여 모든 업종 필수는 아님 / ④ 업종별 면허 서류가 다름 | K15: 입찰등록규정
A16: 13 | B16: 1. 조달요구 대처 절차 | C16: 2. 수요기관의 정보요청(규격, 과업 및 예산 등)에 대한 문서 작성 및 제출 | D16: RFI(정보제공요청서)에 대한 설명으로 옳지 않은 것은? | E16: 시장 기술수준·가격동향 파악이 목적이다 | F16: 공급자가 자사 역량을 알릴 기회가 된다 | G16: 사업 기획 초기 단계에 활용된다 | H16: 응답업체에 계약체결 의무가 발생한다 | I16: 4 | J16: * 정답 (④): RFI는 비구속적 문서로 응답업체에 계약체결 의무를 부과하지 않음.
A17: 14 | B17: 1. 조달요구 대처 절차 | C17: 2. 수요기관의 정보요청(규격, 과업 및 예산 등)에 대한 문서 작성 및 제출 | D17: 사업 진행 순서로 옳은 것은? | E17: RFI→RFQ→RFP | F17: RFP→RFI→RFQ | G17: RFQ→RFI→RFP | H17: RFI→RFP→RFQ | I17: 1 | J17: * 정답 (①): 시장정보수집(RFI)→가격확인(RFQ)→종합제안요청(RFP) 순으로 진행됨.
A18: 15 | B18: 1. 조달요구 대처 절차 | C18: 2. 수요기관의 정보요청(규격, 과업 및 예산 등)에 대한 문서 작성 및 제출 | D18: 발주기관이 조달 초기 단계에서 시장 정보를 수집하기 위해 활용하는 문서로, 응답업체에 입찰참가 의무를 부과하지 않는 것은? | E18: RFP(제안요청서) | F18: RFI(정보요청서) | G18: 입찰공고문 | H18: RFQ(견적요청서) | I18: 2 | J18: * 정답 (②): RFI(Request for Information)는 사업 초기 시장 동향·기술 수준·예산 추정 등을 파악하기 위해 활용되는 비구속적 문서로, 응답업체에 입찰참가 의무를 부여하지 않습니다. | K18: 표준교재 2권 p.17
A19: 16 | B19: 1. 조달요구 대처 절차 | C19: 2. 수요기관의 정보요청(규격, 과업 및 예산 등)에 대한 문서 작성 및 제출 | D19: 조달청에 계약 체결을 위탁하는 '중앙조달요청' 문서를 새롭게 작성하기 위해 나라장터(수요기관용) 시스템에서 거쳐야 하는 올바른 메뉴 이동 경로는? | E19: 계약 → 계약서작성 → 신규 | F19: 공고 → 입찰공고 → 신규 | G19: 발주 → 발주목록 → 신규 | H19: 물품 → 견적요청 → 신규 | I19: 3 | J19: * 정답 (③): 수요기관이 조달청에 계약을 의뢰(발주)하는 것이므로, 나라장터 메인 메뉴의 [발주] → [발주목록] → [신규] 순으로 진입하여 작성해야 합니다.
A20: 17 | B20: 1. 조달요구 대처 절차 | C20: 3. 조달관련 입법·행정예고 검색 및 의견제시 | D20: 조달 관련 법령(시행령·시행규칙 등)의 제·개정에 대해 의견을 제시하려 할 때, 관련 법제업무 운영규정상 입법예고 기간의 원칙으로 옳은 것은? | E20: 30일 이상 | F20: 60일 이상 | G20: 20일 이상 | H20: 40일 이상 | I20: 4 | J20: * 정답 (④): 조달담당자는 관련 법령의 입법예고 내용을 검색해 필요시 의견을 제시할 수 있으며, 법제업무 운영규정상 입법예고 기간은 원칙적으로 40일 이상(행정예고는 20일 이상)임. | K20: 법제업무 운영규정 제18조
A21: 18 | B21: 2. 사전규격공개 분석 | C21: 1. 과업내용 적정성 검토 | D21: 사전규격 검토 시 확인하는 핵심사항이 아닌 것은? | E21: 예산 적정성 | F21: 관련 법규 준수 여부 | G21: 입찰참가 예정업체의 재무상태 | H21: 특정 상표·규격으로 인한 경쟁제한 여부 | I21: 3 | J21: * 정답 (③): 입찰참가 예정업체의 재무상태는 적격심사 단계에서 확인하는 사항으로, 사전규격 검토 사항이 아님.
A22: 19 | B22: 2. 사전규격공개 분석 | C22: 1. 과업내용 적정성 검토 | D22: 사전규격공개 제도의 주된 목적으로 가장 적절한 것은? | E22: 특정 업체에 대한 사전 통보 | F22: 예산 절감 | G22: 입찰 절차의 신속한 진행 | H22: 경쟁 제한 방지 및 다양한 의견 반영을 통한 공정한 규격 확정 | I22: 4 | J22: * 정답 (④): 사전규격공개는 경쟁 제한 방지와 다양한 공급자 의견 반영을 통해 공정한 규격을 확정하는 것이 목적임.
A23: 20 | B23: 2. 사전규격공개 분석 | C23: 1. 과업내용 적정성 검토 | D23: 규격서 작성 방식 중, 제품이 어떻게 만들어져야 하는지가 아니라 달성해야 할 결과와 기능을 중심으로 기술하는 방식은? | E23: 상표규격(특정 업체 기술표준 기준) | F23: 모델규격(특정 모델·사양 명시) | G23: 성능규격(Performance Specification) | H23: 설계규격(제조방법 상세 지정) | I23: 3 | J23: * 정답 (③): 성능규격은 '무엇을' 달성해야 하는지, 즉 요구되는 성능·기능을 결과 중심으로 기술하는 방식으로, 다양한 업체의 참여와 혁신적 대안을 유도함.
A24: 21 | B24: 2. 사전규격공개 분석 | C24: 1. 과업내용 적정성 검토 | D24: 다음 중 구매사양서 작성의 SMART 원칙에 대한 설명으로 가장 옳지 않은 것은? | E24: S (Specific): 요구하는 물품이나 서비스의 특성을 구체적이고 명확하게 기술해야 한다. | F24: M (Measurable): 검수 및 평가가 가능하도록 정량적 지표나 측정 가능한 기준을 제시해야 한다. | G24: A (Achievable): 시장의 기술 수준과 관계없이 발주기관이 원하는 최상의 성능만을 무조건 요구해야 한다. | H24: T (Time-bound): 납기, 이행 일정 또는 추적 가능성(Traceable)을 명확히 설정해야 한다. | I24: 3 | J24: * 정답 (③): A는 Achievable(달성가능성)로, 해당 산업 및 시장에서 기술적으로 실행 가능한 요구사항을 제시해야 함을 의미합니다. 현실적으로 이행 불가능한 과도한 사양 설정은 유찰이나 부실 이행을 초래할 수 있습니다. | K24: 표준교재 2권 p.24
A25: 22 | B25: 2. 사전규격공개 분석 | C25: 1. 과업내용 적정성 검토 | D25: 구매사양서 작성 시 "납품된 물품의 성능이나 품질이 계약 기준에 부합하는지 정량적으로 검증 및 평가할 수 있도록 객관적 기준을 제시해야 한다"는 SMART 원칙 요소는? | E25: S (Specific) | F25: M (Measurable) | G25: R (Relevant) | H25: T (Time-bound) | I25: 2 | J25: * 정답 (②): 정량적 수치나 객관적 측정 기준을 제시하여 납품 후 검수 및 평가를 가능하게 하는 것은 M(Measurable, 측정가능성)에 해당합니다. | K25: 표준교재 2권 p.24
A26: 23 | B26: 2. 사전규격공개 분석 | C26: 1. 과업내용 적정성 검토 | D26: 구매사양서 작성의 SMART 원칙 구성 요소와 영문 구성의 연결이 올바르지 않은 것은? | E26: S - Specific (구체성) | F26: M - Measurable (측정가능성) | G26: R - Reasonable (합리적인 가격) | H26: T - Time-bound (기한성) | I26: 3 | J26: * 정답 (③): SMART 원칙에서 R은 Realistic(현실성)을 의미합니다. 해당 조달 사업의 목적과 직접 연관되고 현실적이어야 함을 뜻하며, 합리적인 가격(Reasonable)을 의미하지 않습니다. | K26: 표준교재 2권 p.24
A27: 24 | B27: 2. 사전규격공개 분석 | C27: 1. 과업내용 적정성 검토 | D27: 조달 요구사항(Procurement Requirement) 정의 및 과업명세서 작성 시 고려하는 항목과 세부 질문의 연결로 가장 옳지 않은 것은? | E27: 조달 배경 및 목표 - 상품, 서비스 및 공사가 필요한 이유는 무엇인가? | F27: 이행 장소 및 방법 - 배송지(수행/시공장소)는 어디이며 어떻게 수행되는가? | G27: 의사결정 체계 - 제안서 평가위원회의 개별 평가위원 명단은 누구인가? | H27: 스펙 및 요구량 - 어떤 구체적인 품질 또는 수량 요구 사항을 고려해야 하는가? | I27: 3 | J27: * 정답 (③): 조달 요구사항 정의 시 승인 요소(8번)는 '조달요구 실행을 위해 필요한 주요 승인 및 승인권자(내부 의사결정 절차)'를 의미합니다. 평가위원 명단은 보안 사항이자 별도 평가 절차 관리 항목으로 조달 요구사항 정의 및 SOW 항목에 해당하지 않습니다. | K27: 표준교재 2권 p.23
A28: 25 | B28: 2. 사전규격공개 분석 | C28: 1. 과업내용 적정성 검토 | D28: 다음 중 조달 요구사항을 분석하고 명확히 하기 위한 주요 확인 항목에 대한 설명으로 가장 적절하지 않은 것은? | E28: 조달 대상이 충족해야 하는 핵심 기능을 정의하여 불필요한 과도한 스펙 설정을 방지한다. | F28: 구체적인 품질 및 수량 요구사항은 계약 이행 후 정산 단계에서 결정하므로 초기 작성 시 생략할 수 있다. | G28: 배송지, 수행 장소, 배송 방식을 사전에 명확히 하여 물류 및 이행상의 차질을 예방한다. | H28: 구매에 영향을 미치는 외부·내부 요인 및 필요한 승인권자를 식별하여 조달 위험을 관리한다. | I28: 2 | J28: * 정답 (②): 어떤 구체적인 품질 또는 수량 요구사항을 고려해야 하는지(9번)는 계약 체결 전 조달 요구사항 정의 단계에서 반드시 명확히 검토되어 반영되어야 적정한 예산 산정 및 검수가 가능해집니다. | K28: 표준교재 2권 p.23
A29: 26 | B29: 2. 사전규격공개 분석 | C29: 3. 당해 규격공개 관련 법규 준수 및 부합여부 검토 | D29: 사전규격공개의 일반적인 공개 기간에 대한 설명으로 가장 적절한 것은? | E29: 통상 수일(3~7일 수준)이며, 긴급 시 더 짧게, 대형 SW사업은 더 길게 운영된다 | F29: 예외 없이 항상 10일이다 | G29: 공개 기간이라는 개념 자체가 없다 | H29: 30일이 원칙이다 | I29: 1 | J29: * 정답 (①): 사전규격공개 기간은 기관·사업유형별로 상이하며 통상 수일 수준으로 운영됨.
A30: 27 | B30: 2. 사전규격공개 분석 | C30: 3. 당해 규격공개 관련 법규 준수 및 부합여부 검토 | D30: 조달청 소프트웨어사업(사업규모 5억원 이상)의 사전규격공개 기간에 대한 설명으로 가장 적절한 것은? | E30: 긴급 시에도 동일하게 운영된다 | F30: 공개 자체가 면제된다 | G30: 일반 물품과 동일하게 운영된다 | H30: 일반 규격보다 더 긴 기간(10일 수준)으로 운영된다 | I30: 4 | J30: * 정답 (④): 조달청 SW사업(5억원 이상)은 일반 규격보다 더 긴 기간(10일 수준)으로 사전규격을 공개함.
A31: 28 | B31: 2. 사전규격공개 분석 | C31: 3. 당해 규격공개 관련 법규 준수 및 부합여부 검토 | D31: 규격을 외부에 투명하게 검증받기 위한 '구매규격 사전공개' 절차의 예외적 생략 사유로 어긋나는 것은? | E31: 구매 예상 예산이 1억 원 이하인 내자 물품 소액 구매의 경우 전면 생략할 수 있다. | F31: 안보와 직결된 비밀물자나 수요가 매우 긴급한 구매 건의 경우 생략할 수 있다. | G31: 당해 연도에 이미 1회 이상 동일한 규격으로 사전공개를 실시한 경우 생략할 수 있다. | H31: 시급한 재난 복구 등 특정 목적 달성을 위한 수의계약 대상 물품인 경우 생략할 수 있다. | I31: 1 | J31: * 정답 (①): 내자 물품 소액 구매의 경우, 규격 사전공개를 생략할 수 있는 예산 기준은 1억 원 '이하'가 아니라 '미만'으로 엄격히 규정되어 있습니다.
A32: 29 | B32: 2. 사전규격공개 분석 | C32: 3. 당해 규격공개 관련 법규 준수 및 부합여부 검토 | D32: 입찰 공고를 내기 전, 수요기관이 구매하려는 물품의 세부 규격이나 과업지시서를 나라장터에 미리 '사전규격공개' 하는 가장 주된 이유는? | E32: 행정 절차 지연 시 입찰서 제출 기한을 합법적으로 연장할 수 있는 근거를 마련하기 위해 | F32: 특정 업체에 유리한 독소 조항이 있는지 미리 의견을 수렴하여 공정성 논란을 줄이기 위해 | G32: 입찰 경쟁률을 낮추기 위해 불특정 다수의 접근을 막고 제한된 업체에만 정보를 제공하기 위해 | H32: 사전 공개 기간 동안 업체들이 제출한 단가 정보를 취합하여 예정가격을 낮게 산정하기 위해 | I32: 2 | J32: * 정답 (②): 발주기관이 특정 규격을 '알박기'하여 특정 업체에 특혜를 주는 것을 방지하고, 입찰 참여 희망 업체들의 이의제기 및 의견을 미리 수렴하여 조달 행정의 투명성과 공정성을 확보하기 위한 제도입니다. | K32: 정부 입찰·계약 집행기준 제77조
A33: 30 | B33: 2. 사전규격공개 분석 | C33: 3. 당해 규격공개 관련 법규 준수 및 부합여부 검토 | D33: 정식 입찰 공고를 내기 전에, 국가종합전자조달시스템을 통해 구매하려는 품목의 세부 사양이나 과업지시서를 일정 기간 동안 업체들에게 미리 공개하여 이의를 제기할 수 있게 하는 제도는? | E33: 실적증명 사전발급 | F33: 입찰참가자격 사전심사(PQ) | G33: 구매 규격 사전공개 | H33: 지명경쟁 대상자 사전예고 | I33: 3 | J33: * 정답 (③): 특정 업체에 유리한 스펙(규격 알박기)이 포함되는 것을 막고, 다수 업체의 의견을 들어 공정한 경쟁을 유도하기 위해 필수적으로 거쳐야 하는 '사전규격공개' 제도입니다. | K33: 정부 입찰·계약 집행기준 제77조
A34: 31 | B34: 2. 사전규격공개 분석 | C34: 4. 개선보완 필요사항에 대한 의견 제시 및 처리 | D34: 사전규격공개 후 의견이 접수된 경우 계약담당자의 대응으로 가장 옳은 것은? | E34: 조달사업의 목적을 저해하지 않는 한 적극적으로 검토해 반영 여부를 결정한다 | F34: 제출자에게 통보할 의무는 없다 | G34: 의견을 무시해도 무방하다 | H34: 모든 의견을 반드시 수용해야 한다 | I34: 1 | J34: * 정답 (①): 계약담당자는 조달사업의 목적·취지를 저해하지 않는 한 적극적으로 의견을 수렴해 구매규격에 반영 여부를 결정해야 함.
A35: 32 | B35: 2. 사전규격공개 분석 | C35: 3. 당해 규격공개 관련 법규 준수 및 부합여부 검토 | D35: 사전규격공개 면제 대상에 해당하지 않는 것은? | E35: 비밀 구매가 필요한 용역 | F35: 추정가격 1억원 이상 물품 | G35: 해당 연도 1회 이상 사전공개 실시 물품 | H35: 추정가격 5천만원 미만 물품 | I35: 2 | J35: * 정답 (②): 추정가격 1억원 이상 물품은 면제 대상이 아니라 오히려 사전규격공개가 필요한 대상임.
A36: 33 | B36: 3. 입찰공고문 분석 | C36: 1. 공고 내용 중 오류 및 법령 위반 사안으로 정정 필요성 검토 | D36: 입찰공고 내용에 법령위반 사항이 발견되어 정정공고를 하는 경우, 남은 공고기간에 추가로 확보해야 하는 최소 기간은? | E36: 3일 이상 | F36: 7일 이상 | G36: 추가 기간 없이 즉시 정정 가능 | H36: 5일 이상 | I36: 4 | J36: * 정답 (④): 입찰공고 내용에 오류·법령위반이 있어 정정이 필요한 경우, 남은 공고기간에 5일 이상을 더하여 공고해야 함. | K36: 국가계약법 시행령 제33조제2항
A37: 34 | B37: 3. 입찰공고문 분석 | C37: 1. 공고 내용 중 오류 및 법령 위반 사안으로 정정 필요성 검토 | D37: 입찰공고 및 정정 절차에 대한 설명으로 가장 옳은 것은? | E37: 국가계약법 시행령상 입찰공고 내용에 오류나 법령위반사항이 발견되어 정정공고할 경우 남은 공고기간에 5일 이상을 더한다. | F37: 물품 및 용역의 구매규격은 특정 업체와의 유착을 방지하기 위해 입찰공고 전 사전공개가 원칙적으로 금지된다. | G37: 입찰공고는 긴급한 재해예방·복구 등 특별한 사유가 있더라도 예외 없이 반드시 입찰서 제출마감일 전일부터 7일 전에 공고해야 한다. | H37: 지정정보처리장치의 게시 내용과 첨부된 입찰공고문 내용이 다르면 게시된 내용이 우선한다. | I37: 1 | J37: 정답 (①) 국가계약법 시행령 제33조제2항: 오류·법령위반 시 남은 공고기간에 5일 이상 가산 / ② 시행령 제32조의2에 따라 사전공개가 오히려 원칙(의무)임 / ③ 시행령 제35조제4항에 따라 긴급 시 5일 전 공고 가능한 예외가 있어 "예외 없이"는 틀림 / ④ 지방계약법 시행규칙 제36조 본문에 따라 게시 내용이 아닌 "공고문" 내용이 우선함 | K37: 국가계약법 시행령 및 지방계약법 시행령
A38: 35 | B38: 3. 입찰공고문 분석 | C38: 2. 입찰공고 내용 검토 및 분석 | D38: 입찰공고에 반드시 포함되어야 하는 사항이 아닌 것은? | E38: 입찰참가자격에 관한 사항 | F38: 입찰에 부치는 사항 | G38: 낙찰자 결정방법 | H38: 낙찰자의 재무제표 | I38: 4 | J38: * 정답 (④): 낙찰자의 재무제표는 입찰공고 필수 포함사항이 아님. | K38: 국가계약법 시행령 제36조
A39: 36 | B39: 3. 입찰공고문 분석 | C39: 2. 입찰공고 내용 검토 및 분석 | D39: 국가계약법 적용 입찰에서 예정가격 산정(복수예비가격) 범위로 옳은 것은? | E39: 기초금액 ±5% | F39: 기초금액 ±2% | G39: 기초금액 ±1% | H39: 기초금액 ±3% | I39: 2 | J39: * 정답 (②): 국가계약법 적용기관은 기초금액 ±2% 범위에서 복수예비가격을 작성함(지방계약법은 ±3%). | K39: 조달청 내자구매업무처리규정
A40: 37 | B40: 3. 입찰공고문 분석 | C40: 2. 입찰공고 내용 검토 및 분석 | D40: 제한경쟁입찰의 참가자격 제한 사유로 보기 어려운 것은? | E40: 동일 물품 공급실적 | F40: 특수 기술·공법 보유 | G40: 대표자의 학력 | H40: 시공능력평가액 | I40: 3 | J40: * 정답 (③): 대표자의 학력은 제한경쟁입찰의 참가자격 제한 사유에 해당하지 않음. | K40: 국가계약법 시행령 제21조
A41: 38 | B41: 3. 입찰공고문 분석 | C41: 2. 입찰공고 내용 검토 및 분석 | D41: 다음 중 입찰공고 필수 포함사항을 모두 고르면? (ㄱ.입찰에 부치는 사항 ㄴ.낙찰자결정방법 ㄷ.입찰참가자 신용등급 ㄹ.입찰보증금 관련사항) | E41: ㄱ,ㄷ,ㄹ | F41: ㄱ,ㄴ,ㄹ | G41: ㄴ,ㄷ,ㄹ | H41: ㄱ,ㄴ,ㄷ | I41: 2 | J41: * 정답 (②): 입찰에 부치는 사항, 낙찰자결정방법, 입찰보증금 관련사항이 필수 포함사항이며, 입찰참가자 신용등급은 아님. | K41: 국가계약법 시행령 제36조
